Workbook

Sheet TD
A1: TOMADOR | B1: (Vários itens)
A3: MODALIDADE | B3: Contagem de FUNCIONÁRIO | C3: Soma de TOTAL BRUTO + PF
A4: CLT | B4: 61 | C4: 327445.06
A5: ESTÁGIO | B5: 4 | C5: 6056.62
A6: PF | B6: 1 | C6: 9879.83
A7: PJ | B7: 9 | C7: 102840.78
A8: Total Geral | B8: 75 | C8: 446222.29

Sheet Custo_Fopag (2)
A1: FUNCIONARIO | B1: COMPETENCIA | C1: MODALIDADE | D1: EMPRESA | E1: CNPJ | F1: SETOR | G1: SECAO | H1: TOMADOR | I1: ADMISSAO | J1: DEMISSAO | K1: C CUSTO | L1: FUNCAO | M1: SAL. BASE | N1: SAL. PAGO | O1: ATESTADO | P1: SAL.PAGO + ATESTADO | Q1: AUX.MATERNID | R1: FERIAS | S1: ABONO PEC | T1: AD. FUNCAO | U1: AD. INSALUB | V1: AD. PERICUL | W1: GRAT FUNÇÃO 40% | X1: GRAT(ADRIANA) | Y1: ADICTPOSERV | Z1: ADIC NOTURNO | AA1: HRS EXTRAS | AB1: DSR HRS EXTRAS | AC1: COMISSOES | AD1: DSR COMISSOES | AE1: DIF CONVENCAO | AF1: QUEBRA CAIXA | AG1: TT EV TRIB (INSS/IRRF/FGTS) | AH1: P. GRAT G3S | AI1: P.PRODUCAO | AJ1: P.CHECKLIST | AK1: P.PRENSA | AL1: P.PORTA | AM1: P.CONTAINER | AN1: P.OPERADORES | AO1: P.V.UNIDADES | AP1: PREMIOS | AQ1: P ANUAL SETCESP | AR1: TT EV EXCL IRRF | AS1: ESTAGIARIOS | AT1: AJ DE CUSTO | AU1: CESTA BASICA R$ | AV1: DIARIA REF | AW1: DIARIA DIFER | AX1: SAL FAMILIA | AY1: PLANO SAUDE | AZ1: AB EVENTUAL | BA1: PLR | BB1: AJ. ALUGUEL | BC1: P.PROD(ANT) | BD1: P.BON(ANT) | BE1: TT EVENT Ñ TRIBUT | BF1: LIQ RESCISAO | BG1: GUIA RESCISAO | BH1: TOTAL RESCISAO | BI1: TOTAL BRUTO | BJ1: TOTAL DESC | BK1: TOTAL LIQUIDO | BL1: FGTS | BM1: INSS EMPRESA | BN1: RAT | BO1: TERCEIROS | BP1: TOTAL ENCARGOS | BQ1: CUSTO
A2: KAMYLA FERNANDA FORIM | B2: 46082 | C2: Empregado – Geral | D2: G3S FL 08 - LONDRINA | E2: 20.947.332/0008-61 | F2: ADMINISTRATIVO | G2: ATENDIMENTO | H2: SELETIVA LONDRINA | I2: 43903 | K2: 1.2.3.1 ADMINISTRATIVO | L2: AUX ADMINISTRATIVO SENIOR | M2: 2950 | N2: 2950 | O2: 0 | P2: =N2+O2 -> 2950 | Q2: 0 | R2: 0 | S2: 0 | T2: 0 | U2: 0 | V2: 0 | W2: 0 | X2: 0 | Y2: 0 | Z2: 0 | AA2: 311.13 | AB2: 59.83 | AC2: 0 | AD2: 0 | AE2: 0 | AF2: 295 | AG2: 3615.96 | AH2: 0 | AI2: 0 | AJ2: 0 | AK2: 0 | AL2: 0 | AM2: 0 | AN2: 0 | AO2: 529.48 | AP2: 0 | AQ2: 0 | AR2: 529.48 | AS2: 0 | AT2: 0 | AU2: 0 | AV2: 0 | AW2: 0 | AX2: 0 | AY2: 0 | AZ2: 0 | BA2: 0 | BB2: 0 | BC2: 0 | BD2: 0 | BE2: 0 | BF2: 0 | BG2: 0 | BH2: 0 | BI2: 4145.44 | BJ2: 1502.5 | BK2: 2642.94 | BL2: 289.27 | BM2: 723.19 | BN2: 206.32 | BO2: 209.72 | BP2: 1428.5 | BQ2: 5573.94
A3: PAULO VITOR TOOKUNI DE LIMA | B3: 46082 | C3: Empregado – Geral | D3: G3S FL 08 - LONDRINA | E3: 20.947.332/0008-61 | F3: OPERACIONAL | G3: PATIO | H3: SELETIVA LONDRINA | I3: 45027 | K3: 1.2.3.3 OPERACIONAL | L3: GERENTE DE PATIO SENIOR | M3: 3679.83 | N3: 1226.61 | O3: 0 | P3: =N3+O3 -> 1226.61 | Q3: 0 | R3: 5497.23 | S3: 2748.61 | T3: 245.32 | U3: 0 | V3: 367.98 | W3: 0 | X3: 0 | Y3: 0 | Z3: 0 | AA3: 0 | AB3: 0 | AC3: 0 | AD3: 0 | AE3: 0 | AF3: 0 | AG3: 10085.75 | AH3: 0 | AI3: 0 | AJ3: 0 | AK3: 0 | AL3: 0 | AM3: 0 | AN3: 0 | AO3: 529.48 | AP3: 0 | AQ3: 0 | AR3: 529.48 | AS3: 0 | AT3: 0 | AU3: 0 | AV3: 0 | AW3: 0 | AX3: 0 | AY3: 0 | AZ3: 0 | BA3: 0 | BB3: 0 | BC3: 0 | BD3: 0 | BE3: 0 | BF3: 0 | BG3: 0 | BH3: 0 | BI3: 10615.23 | BJ3: 257.59 | BK3: 2111.8 | BL3: 586.97 | BM3: 2017.15 | BN3: 575.49 | BO3: 584.97 | BP3: 3764.58 | BQ3: 14379.81
A4: HERALDO CARVALHO DE SOUZA | B4: 46082 | C4: Empregado – Geral | D4: G3S FL 08 - LONDRINA | E4: 20.947.332/0008-61 | F4: OPERACIONAL | G4: PATIO | H4: SELETIVA LONDRINA | I4: 42205 | L4: OPERADOR MANTENEDOR | M4: 1828 | N4: 0 | O4: 0 | P4: =N4+O4 -> 0 | Q4: 0 | R4: 0 | S4: 0 | T4: 0 | U4: 0 | V4: 0 | W4: 0 | X4: 0 | Y4: 0 | Z4: 0 | AA4: 0 | AB4: 0 | AC4: 0 | AD4: 0 | AE4: 0 | AF4: 0 | AG4: 0 | AH4: 0 | AI4: 0 | AJ4: 0 | AK4: 0 | AL4: 0 | AM4: 0 | AN4: 0 | AO4: 0 | AP4: 0 | AQ4: 0 | AR4: 0 | AS4: 0 | AT4: 0 | AU4: 0 | AV4: 0 | AW4: 0 | AX4: 0 | AY4: 0 | AZ4: 0 | BA4: 0 | BB4: 0 | BC4: 0 | BD4: 0 | BE4: 0 | BF4: 0 | BG4: 0 | BH4: 0 | BI4: 0 | BJ4: 0 | BK4: 0 | BL4: 0 | BM4: 0 | BN4: 0 | BO4: 0 | BP4: 0 | BQ4: 0
A5: LUIS DO CARMO PEREIRA | B5: 46082 | C5: Empregado – Geral | D5: G S MATRIZ - PRES PRUD | E5: 20.504.237/0001-17 | F5: LOGISTICA | G5: TRANSPORTE | H5: SELETIVA PRESIDENTE PRUDENTE | I5: 41883 | L5: MOTORISTA CARRETEIRO | M5: 1710 | N5: 0 | O5: 0 | P5: =N5+O5 -> 0 | Q5: 0 | R5: 0 | S5: 0 | T5: 0 | U5: 0 | V5: 0 | W5: 0 | X5: 0 | Y5: 0 | Z5: 0 | AA5: 0 | AB5: 0 | AC5: 0 | AD5: 0 | AE5: 0 | AF5: 0 | AG5: 0 | AH5: 0 | AI5: 0 | AJ5: 0 | AK5: 0 | AL5: 0 | AM5: 0 | AN5: 0 | AO5: 0 | AP5: 0 | AQ5: 0 | AR5: 0 | AS5: 0 | AT5: 0 | AU5: 0 | AV5: 0 | AW5: 0 | AX5: 0 | AY5: 0 | AZ5: 0 | BA5: 0 | BB5: 0 | BC5: 0 | BD5: 0 | BE5: 0 | BF5: 0 | BG5: 0 | BH5: 0 | BI5: 0 | BJ5: 0 | BK5: 0 | BL5: 0 | BM5: 0 | BN5: 0 | BO5: 0 | BP5: 0 | BQ5: 0
A6: CELIO MATEUS | B6: 46082 | C6: Empregado – Geral | D6: G S MATRIZ - PRES PRUD | E6: 20.504.237/0001-17 | F6: OPERACIONAL | G6: PATIO | H6: SELETIVA PRESIDENTE PRUDENTE | I6: 40269 | K6: 1.2.5.3 OPERACIONAL | L6: OPERADOR MANTENEDOR JR | M6: 2610 | N6: 870 | O6: 0 | P6: =N6+O6 -> 870 | Q6: 0 | R6: 3784.63 | S6: 1892.32 | T6: 174 | U6: 0 | V6: 0 | W6: 0 | X6: 0 | Y6: 43.5 | Z6: 0 | AA6: 88.98 | AB6: 19.77 | AC6: 0 | AD6: 0 | AE6: 0 | AF6: 0 | AG6: 6873.2 | AH6: 0 | AI6: 0 | AJ6: 0 | AK6: 0 | AL6: 0 | AM6: 0 | AN6: 0 | AO6: 579.34 | AP6: 0 | AQ6: 0 | AR6: 579.34 | AS6: 0 | AT6: 0 | AU6: 0 | AV6: 2520 | AW6: 0 | AX6: 0 | AY6: 0 | AZ6: 2175 | BA6: 0 | BB6: 0 | BC6: 0 | BD6: 0 | BE6: 0 | BF6: 0 | BG6: 0 | BH6: 0 | BI6: 12147.54 | BJ6: 3755.32 | BK6: 2715.27 | BL6: 398.47 | BM6: 1374.64 | BN6: 103.09 | BO6: 398.64 | BP6: 2274.84 | BQ6: 14422.38
A7: MARCIO AFONSO | B7: 46082 | C7: Empregado – Geral | D7: G S MATRIZ - PRES PRUD | E7: 20.504.237/0001-17 | F7: LOGISTICA | G7: TRANSPORTE | H7: SELETIVA PRESIDENTE PRUDENTE | I7: 44153 | K7: 1.7.8.4 LOGISTICA | L7: MOTORISTA CARRETEIRO MANTENEDOR SENIOR III | M7: 3287.33 | N7: 3287.33 | O7: 0 | P7: =N7+O7 -> 3287.33 | Q7: 0 | R7: 0 | S7: 0 | T7: 657.47 | U7: 0 | V7: 0 | W7: 0 | X7: 0 | Y7: 164.37 | Z7: 0 | AA7: 834.91 | AB7: 160.56 | AC7: 0 | AD7: 0 | AE7: 0 | AF7: 0 | AG7: 5104.64 | AH7: 0 | AI7: 0 | AJ7: 906.92 | AK7: 0 | AL7: 0 | AM7: 0 | AN7: 0 | AO7: 579.34 | AP7: 0 | AQ7: 0 | AR7: 1486.26 | AS7: 0 | AT7: 0 | AU7: 0 | AV7: 1452 | AW7: 0 | AX7: 0 | AY7: 0 | AZ7: 0 | BA7: 0 | BB7: 0 | BC7: 0 | BD7: 0 | BE7: 0 | BF7: 0 | BG7: 0 | BH7: 0 | BI7: 8042.9 | BJ7: 2052.61 | BK7: 5990.29 | BL7: 408.37 | BM7: 1020.93 | BN7: 76.56 | BO7: 296.06 | BP7: 1801.92 | BQ7: 9844.82
A8: JULIANO VIEIRA DE SANTANA | B8: 46082 | C8: Empregado – Geral | D8: G S MATRIZ - PRES PRUD | E8: 20.504.237/0001-17 | F8: LOGISTICA | G8: TRANSPORTE | H8: SELETIVA CORPORATIVO SUCATA | I8: 42217 | K8: 1.7.8.4 LOGISTICA | L8: MOTORISTA CARRETEIRO MANTENEDOR SENIOR III | M8: 3287.33 | N8: 3287.33 | O8: 0 | P8: =N8+O8 -> 3287.33 | Q8: 0 | R8: 0 | S8: 0 | T8: 657.47 | U8: 0 | V8: 0 | W8: 0 | X8: 0 | Y8: 164.37 | Z8: 0 | AA8: 812.5 | AB8: 156.25 | AC8: 0 | AD8: 0 | AE8: 0 | AF8: 0 | AG8: 5077.92 | AH8: 0 | AI8: 0 | AJ8: 0 | AK8: 0 | AL8: 0 | AM8: 0 | AN8: 0 | AO8: 579.34 | AP8: 0 | AQ8: 0 | AR8: 579.34 | AS8: 0 | AT8: 0 | AU8: 0 | AV8: 2205 | AW8: 0 | AX8: 0 | AY8: 0 | AZ8: 0 | BA8: 0 | BB8: 0 | BC8: 0 | BD8: 0 | BE8: 0 | BF8: 0 | BG8: 0 | BH8: 0 | BI8: 7862.26 | BJ8: 785.37 | BK8: 7076.89 | BL8: 406.23 | BM8: 1015.58 | BN8: 76.16 | BO8: 294.51 | BP8: 1792.48 | BQ8: 9654.74
A9: MONIQUE ISABELE DE LIMA | B9: 46082 | C9: Empregado – Geral | D9: G S MATRIZ - PRES PRUD | E9: 20.504.237/0001-17 | F9: TRANSMOVE | G9: ADMINISTRATIVO | H9: TRANSMOVE GSL | I9: 44274 | K9: 1.4.1.2 ADMINISTRATIVO | L9: ANALISTA ADMINISTRATIVO SENIOR | M9: 2950 | N9: 2950 | O9: 0 | P9: =N9+O9 -> 2950 | Q9: 0 | R9: 0 | S9: 0 | T9: 0 | U9: 0 | V9: 0 | W9: 0 | X9: 0 | Y9: 147.5 | Z9: 0 | AA9: 577.61 | AB9: 111.08 | AC9: 0 | AD9: 0 | AE9: 0 | AF9: 0 | AG9: 3786.19 | AH9: 0 | AI9: 808 | AJ9: 0 | AK9: 0 | AL9: 0 | AM9: 0 | AN9: 0 | AO9: 0 | AP9: 150 | AQ9: 0 | AR9: 958 | AS9: 0 | AT9: 0 | AU9: 0 | AV9: 0 | AW9: 0 | AX9: 0 | AY9: 0 | AZ9: 0 | BA9: 0 | BB9: 0 | BC9: 0 | BD9: 0 | BE9: 0 | BF9: 0 | BG9: 0 | BH9: 0 | BI9: 4744.19 | BJ9: 2203.05 | BK9: 2541.14 | BL9: 302.14 | BM9: 757.24 | BN9: 56.79 | BO9: 219.59 | BP9: 1335.76 | BQ9: 6079.95
A10: THAIS SILVA ROCHA | B10: 46082 | C10: Empregado – Geral | D10: G S MATRIZ - PRES PRUD | E10: 20.504.237/0001-17 | F10: INTRA-LOGISTICA | G10: ADMINISTRATIVO | H10: EKIPA LOCACOES E SERV G&S | I10: 45931 | K10: 1.7.1.1 APOIO | L10: ANALISTA ADMINISTRATIVO OPERACIONAL JUNIOR | M10: 2500 | N10: 2416.67 | O10: 83.33 | P10: =N10+O10 -> 2500 | Q10: 0 | R10: 0 | S10: 0 | T10: 0 | U10: 0 | V10: 0 | W10: 0 | X10: 0 | Y10: 0 | Z10: 0 | AA10: 0 | AB10: 0 | AC10: 0 | AD10: 0 | AE10: 0 | AF10: 0 | AG10: 2500 | AH10: 0 | AI10: 0 | AJ10: 0 | AK10: 0 | AL10: 0 | AM10: 0 | AN10: 0 | AO10: 0 | AP10: 0 | AQ10: 0 | AR10: 0 | AS10: 0 | AT10: 0 | AU10: 0 | AV10: 0 | AW10: 0 | AX10: 0 | AY10: 0 | AZ10: 0 | BA10: 0 | BB10: 0 | BC10: 0 | BD10: 0 | BE10: 0 | BF10: 0 | BG10: 0 | BH10: 0 | BI10: 2500 | BJ10: 225.68 | BK10: 2274.32 | BL10: 200 | BM10: 500 | BN10: 37.5 | BO10: 145 | BP10: 882.5 | BQ10: 3382.5
A11: MARCELO VITOR | B11: 46082 | C11: Empregado – Geral | D11: G S MATRIZ - PRES PRUD | E11: 20.504.237/0001-17 | F11: OPERACIONAL | G11: PATIO | H11: SELETIVA PRESIDENTE PRUDENTE | I11: 43790 | K11: 1.2.5.5 PRENSA FIXA JCG800 | L11: OPERADOR MANTENEDOR SENIOR | M11: 3158.66 | N11: 3158.66 | O11: 0 | P11: =N11+O11 -> 3158.66 | Q11: 0 | R11: 0 | S11: 0 | T11: 631.73 | U11: 0 | V11: 0 | W11: 0 | X11: 0 | Y11: 157.93 | Z11: 0 | AA11: 2010.05 | AB11: 386.55 | AC11: 0 | AD11: 0 | AE11: 0 | AF11: 0 | AG11: 6344.92 | AH11: 0 | AI11: 424.21 | AJ11: 0 | AK11: 0 | AL11: 0 | AM11: 0 | AN11: 0 | AO11: 579.34 | AP11: 0 | AQ11: 0 | AR11: 1003.55 | AS11: 0 | AT11: 0 | AU11: 0 | AV11: 2016 | AW11: 0 | AX11: 0 | AY11: 0 | AZ11: 0 | BA11: 0 | BB11: 0 | BC11: 0 | BD11: 0 | BE11: 0 | BF11: 0 | BG11: 0 | BH11: 0 | BI11: 9364.47 | BJ11: 4366.59 | BK11: 4997.88 | BL11: 507.59 | BM11: 1268.98 | BN11: 95.17 | BO11: 368 | BP11: 2239.74 | BQ11: 11604.21
A12: EDILEUSA PEREIRA LISBOA | B12: 46082 | C12: Empregado – Geral | D12: G S MATRIZ - PRES PRUD | E12: 20.504.237/0001-17 | F12: OPERACIONAL | G12: PATIO | H12: SELETIVA PRESIDENTE PRUDENTE | I12: 46043 | K12: 1.2.5.3 OPERACIONAL | L12: OPERADOR MANTENEDOR JR | M12: 2610 | N12: 2610 | O12: 0 | P12: =N12+O12 -> 2610 | Q12: 0 | R12: 0 | S12: 0 | T12: 522 | U12: 0 | V12: 0 | W12: 0 | X12: 0 | Y12: 0 | Z12: 0 | AA12: 750.61 | AB12: 144.35 | AC12: 0 | AD12: 0 | AE12: 0 | AF12: 0 | AG12: 4026.96 | AH12: 0 | AI12: 0 | AJ12: 0 | AK12: 0 | AL12: 0 | AM12: 0 | AN12: 0 | AO12: 579.34 | AP12: 0 | AQ12: 0 | AR12: 579.34 | AS12: 0 | AT12: 0 | AU12: 0 | AV12: 0 | AW12: 0 | AX12: 0 | AY12: 0 | AZ12: 0 | BA12: 0 | BB12: 0 | BC12: 0 | BD12: 0 | BE12: 0 | BF12: 0 | BG12: 0 | BH12: 0 | BI12: 4606.3 | BJ12: 1451.06 | BK12: 3155.24 | BL12: 322.15 | BM12: 805.39 | BN12: 60.4 | BO12: 233.56 | BP12: 1421.5 | BQ12: 6027.8
A13: MURILO BONI CANDIDO | B13: 46082 | C13: Bolsista - Estagiário | D13: G S MATRIZ - PRES PRUD | E13: 20.504.237/0001-17 | F13: INTRA-LOGISTICA | G13: ADMINISTRATIVO | H13: EKIPA LOCACOES E SERV G&S | I13: 46083 | K13: 1.7.2.1 ADMINISTRATIVO | L13: AUXILIAR DE MARKETING - ESTAGIARIO | M13: 1000 | N13: 0 | O13: 0 | P13: =N13+O13 -> 0 | Q13: 0 | R13: 0 | S13: 0 | T13: 0 | U13: 0 | V13: 0 | W13: 0 | X13: 0 | Y13: 0 | Z13: 0 | AA13: 0 | AB13: 0 | AC13: 0 | AD13: 0 | AE13: 0 | AF13: 0 | AG13: 0 | AH13: 0 | AI13: 0 | AJ13: 0 | AK13: 0 | AL13: 0 | AM13: 0 | AN13: 0 | AO13: 0 | AP13: 0 | AQ13: 0 | AR13: 0 | AS13: 1500 | AT13: 0 | AU13: 0 | AV13: 0 | AW13: 0 | AX13: 0 | AY13: 0 | AZ13: 0 | BA13: 0 | BB13: 0 | BC13: 0 | BD13: 0 | BE13: 0 | BF13: 0 | BG13: 0 | BH13: 0 | BI13: 1500 | BJ13: 250 | BK13: 1250 | BL13: 0 | BM13: 0 | BN13: 0 | BO13: 0 | BP13: 0 | BQ13: 1500
A14: FERNANDO THALLES SOUZA OLIVEIRA | B14: 46082 | C14: Bolsista - Estagiário | D14: G S MATRIZ - PRES PRUD | E14: 20.504.237/0001-17 | F14: INTRA-LOGISTICA | G14: ADMINISTRATIVO | H14: EKIPA LOCACOES E SERV G&S | I14: 46083 | K14: 1.7.2.1 ADMINISTRATIVO | L14: AUXILIAR DE ENGENHARIA - ESTAGIARIO | M14: 1000 | N14: 0 | O14: 0 | P14: =N14+O14 -> 0 | Q14: 0 | R14: 0 | S14: 0 | T14: 0 | U14: 0 | V14: 0 | W14: 0 | X14: 0 | Y14: 0 | Z14: 0 | AA14: 0 | AB14: 0 | AC14: 0 | AD14: 0 | AE14: 0 | AF14: 0 | AG14: 0 | AH14: 0 | AI14: 0 | AJ14: 0 | AK14: 0 | AL14: 0 | AM14: 0 | AN14: 0 | AO14: 0 | AP14: 0 | AQ14: 0 | AR14: 0 | AS14: 1500 | AT14: 0 | AU14: 0 | AV14: 0 | AW14: 0 | AX14: 0 | AY14: 0 | AZ14: 0 | BA14: 0 | BB14: 0 | BC14: 0 | BD14: 0 | BE14: 0 | BF14: 0 | BG14: 0 | BH14: 0 | BI14: 1500 | BJ14: 250 | BK14: 1250 | BL14: 0 | BM14: 0 | BN14: 0 | BO14: 0 | BP14: 0 | BQ14: 1500
A15: PATRICIO SANTANA DA SILVA THEODORO | B15: 46082 | C15: Empregado – Geral | D15: G S FL 04 - MARINGA | E15: 20.504.237/0004-60 | F15: OPERACIONAL | G15: PATIO | H15: SELETIVA MARINGA DISTRITO | I15: 41276 | K15: 1.2.4.3 OPERACIONAL | L15: OPERADOR MANTENEDOR SENIOR | M15: 3354.5 | N15: 3354.5 | O15: 0 | P15: =N15+O15 -> 3354.5 | Q15: 0 | R15: 0 | S15: 0 | T15: 670.9 | U15: 0 | V15: 0 | W15: 0 | X15: 0 | Y15: 0 | Z15: 0 | AA15: 1849.24 | AB15: 355.62 | AC15: 0 | AD15: 0 | AE15: 0 | AF15: 0 | AG15: 6230.26 | AH15: 0 | AI15: 807.76 | AJ15: 0 | AK15: 0 | AL15: 0 | AM15: 0 | AN15: 0 | AO15: 252.45 | AP15: 0 | AQ15: 0 | AR15: 1060.21 | AS15: 0 | AT15: 0 | AU15: 0 | AV15: 0 | AW15: 0 | AX15: 0 | AY15: 0 | AZ15: 0 | BA15: 0 | BB15: 0 | BC15: 0 | BD15: 0 | BE15: 0 | BF15: 0 | BG15: 0 | BH15: 0 | BI15: 7290.47 | BJ15: 2318.8 | BK15: 4971.67 | BL15: 498.42 | BM15: 1246.05 | BN15: 186.9 | BO15: 361.35 | BP15: 2292.72 | BQ15: 9583.19
A16: RUBENS DE ARAUJO MOTA | B16: 46082 | C16: Empregado – Geral | D16: G S FL 04 - MARINGA | E16: 20.504.237/0004-60 | F16: LOGISTICA | G16: TRANSPORTE | H16: SELETIVA MARINGA DISTRITO | I16: 45664 | J16: 46111 | K16: 1.7.7.4 LOGISTICA | L16: MOTORISTA CARRETEIRO MANTENEDOR SENIOR I | M16: 3345 | N16: 0 | O16: 0 | P16: =N16+O16 -> 0 | Q16: 0 | R16: 0 | S16: 0 | T16: 669 | U16: 0 | V16: 0 | W16: 0 | X16: 0 | Y16: 0 | Z16: 0 | AA16: 1996.66 | AB16: 399.33 | AC16: 0 | AD16: 0 | AE16: 0 | AF16: 0 | AG16: 3064.99 | AH16: 0 | AI16: 0 | AJ16: 914.98 | AK16: 0 | AL16: 0 | AM16: 0 | AN16: 0 | AO16: 252.45 | AP16: 0 | AQ16: 0 | AR16: 1167.43 | AS16: 0 | AT16: 500 | AU16: 0 | AV16: 555.64 | AW16: 0 | AX16: 0 | AY16: 0 | AZ16: 0 | BA16: 0 | BB16: 0 | BC16: 0 | BD16: 0 | BE16: 0 | BF16: 20851.68 | BG16: 1107.57 | BH16: 21959.25 | BI16: 5288.06 | BJ16: 22723.58 | BK16: 0 | BL16: 0 | BM16: 613 | BN16: 91.94 | BO16: 177.76 | BP16: 882.7 | BQ16: 6170.76
A17: WILLIAM CRISTIAN LUPION | B17: 46082 | C17: Empregado – Geral | D17: G S FL 04 - MARINGA | E17: 20.504.237/0004-60 | F17: LOGISTICA | G17: TRANSPORTE | H17: SELETIVA MARINGA DISTRITO | I17: 45117 | K17: 1.7.7.4 LOGISTICA | L17: MOTORISTA CARRETEIRO MANTENEDOR SENIOR I | M17: 3345 | N17: 3345 | O17: 0 | P17: =N17+O17 -> 3345 | Q17: 0 | R17: 0 | S17: 0 | T17: 669 | U17: 0 | V17: 0 | W17: 0 | X17: 0 | Y17: 0 | Z17: 2.97 | AA17: 1235.55 | AB17: 237.61 | AC17: 0 | AD17: 0 | AE17: 0 | AF17: 0 | AG17: 5490.13 | AH17: 0 | AI17: 0 | AJ17: 686.3 | AK17: 0 | AL17: 0 | AM17: 0 | AN17: 0 | AO17: 252.45 | AP17: 0 | AQ17: 0 | AR17: 938.75 | AS17: 0 | AT17: 0 | AU17: 0 | AV17: 776.61 | AW17: 0 | AX17: 0 | AY17: 0 | AZ17: 0 | BA17: 0 | BB17: 0 | BC17: 0 | BD17: 0 | BE17: 0 | BF17: 0 | BG17: 0 | BH17: 0 | BI17: 7205.49 | BJ17: 1941.57 | BK17: 5263.92 | BL17: 439.21 | BM17: 1098.03 | BN17: 164.7 | BO17: 318.42 | BP17: 2020.36 | BQ17: 9225.85
A18: FERNANDO FERRAREZI DOS SANTOS | B18: 46082 | C18: Empregado – Geral | D18: G S FL 04 - MARINGA | E18: 20.504.237/0004-60 | F18: LOGISTICA | G18: TRANSPORTE | H18: SELETIVA MARINGA DISTRITO | I18: 46027 | K18: 1.7.7.4 LOGISTICA | L18: MOTORISTA CARRETEIRO MANTENEDOR SENIOR I | M18: 3345 | N18: 3345 | O18: 0 | P18: =N18+O18 -> 3345 | Q18: 0 | R18: 0 | S18: 0 | T18: 669 | U18: 0 | V18: 0 | W18: 0 | X18: 0 | Y18: 0 | Z18: 0 | AA18: 1316.71 | AB18: 253.21 | AC18: 0 | AD18: 0 | AE18: 0 | AF18: 0 | AG18: 5583.92 | AH18: 0 | AI18: 0 | AJ18: 486.37 | AK18: 0 | AL18: 0 | AM18: 0 | AN18: 0 | AO18: 252.45 | AP18: 0 | AQ18: 0 | AR18: 738.82 | AS18: 0 | AT18: 0 | AU18: 0 | AV18: 181.5 | AW18: 0 | AX18: 0 | AY18: 0 | AZ18: 0 | BA18: 0 | BB18: 0 | BC18: 0 | BD18: 0 | BE18: 0 | BF18: 0 | BG18: 0 | BH18: 0 | BI18: 6504.24 | BJ18: 1954.7 | BK18: 4549.54 | BL18: 446.71 | BM18: 1116.78 | BN18: 167.51 | BO18: 323.86 | BP18: 2054.86 | BQ18: 8559.1
A19: JOHNNIS GUANDALINI SCHIAVON | B19: 46082 | C19: Empregado – Geral | D19: G S FL 04 - MARINGA | E19: 20.504.237/0004-60 | F19: OPERACIONAL | G19: PATIO | H19: SELETIVA MARINGA DISTRITO | I19: 45790 | K19: 1.2.4.3 OPERACIONAL | L19: OPERADOR MANTENEDOR JR | M19: 2610 | N19: 2610 | O19: 0 | P19: =N19+O19 -> 2610 | Q19: 0 | R19: 0 | S19: 0 | T19: 522 | U19: 0 | V19: 0 | W19: 0 | X19: 0 | Y19: 0 | Z19: 0 | AA19: 116.67 | AB19: 22.44 | AC19: 0 | AD19: 0 | AE19: 0 | AF19: 0 | AG19: 3271.11 | AH19: 0 | AI19: 0 | AJ19: 0 | AK19: 0 | AL19: 0 | AM19: 0 | AN19: 0 | AO19: 456.6 | AP19: 0 | AQ19: 0 | AR19: 456.6 | AS19: 0 | AT19: 0 | AU19: 0 | AV19: 0 | AW19: 0 | AX19: 0 | AY19: 0 | AZ19: 0 | BA19: 0 | BB19: 0 | BC19: 0 | BD19: 0 | BE19: 0 | BF19: 0 | BG19: 0 | BH19: 0 | BI19: 3727.71 | BJ19: 2031.99 | BK19: 1695.72 | BL19: 261.68 | BM19: 654.22 | BN19: 98.13 | BO19: 189.72 | BP19: 1203.75 | BQ19: 4931.46
A20: ANTONIO APARECIDO FAQUIANO SOBRINHO | B20: 46082 | C20: Empregado – Geral | D20: G S FL 03 - DOURADOS | E20: 20.504.237/0003-89 | F20: LOGISTICA | G20: TRANSPORTE | H20: SELETIVA DOURADOS | I20: 43521 | K20: 1.7.5.4 LOGISTICA | L20: MOTORISTA CARRETEIRO MANTENEDOR SENIOR I | M20: 2690.66 | N20: 2690.66 | O20: 0 | P20: =N20+O20 -> 2690.66 | Q20: 0 | R20: 0 | S20: 0 | T20: 538.13 | U20: 0 | V20: 0 | W20: 0 | X20: 0 | Y20: 0 | Z20: 0 | AA20: 731.61 | AB20: 140.69 | AC20: 0 | AD20: 0 | AE20: 0 | AF20: 0 | AG20: 4101.09 | AH20: 0 | AI20: 0 | AJ20: 445.29 | AK20: 0 | AL20: 0 | AM20: 0 | AN20: 0 | AO20: 600 | AP20: 0 | AQ20: 0 | AR20: 1045.29 | AS20: 0 | AT20: 0 | AU20: 0 | AV20: 1401 | AW20: 0 | AX20: 0 | AY20: 0 | AZ20: 0 | BA20: 0 | BB20: 0 | BC20: 0 | BD20: 0 | BE20: 0 | BF20: 0 | BG20: 0 | BH20: 0 | BI20: 6547.38 | BJ20: 635.16 | BK20: 5912.22 | BL20: 328.08 | BM20: 820.22 | BN20: 123.03 | BO20: 237.86 | BP20: 1509.19 | BQ20: 8056.57
A21: ERNESTO EUGENIO DA SILVA | B21: 46082 | C21: Empregado – Geral | D21: G S FL 03 - DOURADOS | E21: 20.504.237/0003-89 | F21: LOGISTICA | G21: TRANSPORTE | H21: SELETIVA DOURADOS | I21: 45103 | K21: 1.7.5.4 LOGISTICA | L21: MOTORISTA CARRETEIRO MANTENEDOR SENIOR I | M21: 2690.66 | N21: 2690.66 | O21: 0 | P21: =N21+O21 -> 2690.66 | Q21: 0 | R21: 0 | S21: 0 | T21: 538.13 | U21: 0 | V21: 0 | W21: 0 | X21: 0 | Y21: 0 | Z21: 0 | AA21: 953.96 | AB21: 183.45 | AC21: 0 | AD21: 0 | AE21: 0 | AF21: 0 | AG21: 4366.2 | AH21: 0 | AI21: 0 | AJ21: 366.4 | AK21: 0 | AL21: 0 | AM21: 0 | AN21: 0 | AO21: 600 | AP21: 0 | AQ21: 0 | AR21: 966.4 | AS21: 0 | AT21: 0 | AU21: 0 | AV21: 705 | AW21: 0 | AX21: 0 | AY21: 0 | AZ21: 0 | BA21: 0 | BB21: 0 | BC21: 0 | BD21: 0 | BE21: 0 | BF21: 0 | BG21: 0 | BH21: 0 | BI21: 6037.6 | BJ21: 697.63 | BK21: 5339.97 | BL21: 349.29 | BM21: 873.24 | BN21: 130.98 | BO21: 253.23 | BP21: 1606.74 | BQ21: 7644.34
A22: EVERTON BENITES SOBRINHO | B22: 46082 | C22: Empregado – Geral | D22: G S FL 03 - DOURADOS | E22: 20.504.237/0003-89 | F22: LOGISTICA | G22: TRANSPORTE | H22: SELETIVA DOURADOS | I22: 45440 | J22: 46087 | K22: 1.7.5.4 LOGISTICA | L22: MOTORISTA CARRETEIRO MANTENEDOR SENIOR I | M22: 2690.66 | N22: 0 | O22: 0 | P22: =N22+O22 -> 0 | Q22: 0 | R22: 0 | S22: 0 | T22: 107.63 | U22: 0 | V22: 0 | W22: 0 | X22: 0 | Y22: 0 | Z22: 0 | AA22: 244.36 | AB22: 48.87 | AC22: 0 | AD22: 0 | AE22: 0 | AF22: 0 | AG22: 400.86 | AH22: 0 | AI22: 0 | AJ22: 44.69 | AK22: 0 | AL22: 0 | AM22: 0 | AN22: 0 | AO22: 120 | AP22: 0 | AQ22: 0 | AR22: 164.69 | AS22: 0 | AT22: 500 | AU22: 0 | AV22: 0 | AW22: 0 | AX22: 13.51 | AY22: 0 | AZ22: 0 | BA22: 0 | BB22: 0 | BC22: 0 | BD22: 0 | BE22: 0 | BF22: 10378.53 | BG22: 343.25 | BH22: 10721.78 | BI22: 1079.06 | BJ22: 14575.27 | BK22: 0 | BL22: 0 | BM22: 80.17 | BN22: 12.02 | BO22: 23.24 | BP22: 115.43 | BQ22: 1194.49
A23: JOSE MANOEL DOS SANTOS | B23: 46082 | C23: Empregado – Geral | D23: G S FL 03 - DOURADOS | E23: 20.504.237/0003-89 | F23: OPERACIONAL | G23: PATIO | H23: SELETIVA DOURADOS | I23: 44964 | K23: 1.2.2.3 OPERACIONAL | L23: OPERADOR MANTENEDOR JR | M23: 2610 | N23: 2610 | O23: 0 | P23: =N23+O23 -> 2610 | Q23: 0 | R23: 0 | S23: 0 | T23: 515.67 | U23: 0 | V23: 0 | W23: 0 | X23: 0 | Y23: 0 | Z23: 0 | AA23: 1484.67 | AB23: 285.51 | AC23: 0 | AD23: 0 | AE23: 0 | AF23: 0 | AG23: 4895.85 | AH23: 0 | AI23: 0 | AJ23: 0 | AK23: 0 | AL23: 0 | AM23: 0 | AN23: 0 | AO23: 196.71 | AP23: 0 | AQ23: 0 | AR23: 196.71 | AS23: 0 | AT23: 0 | AU23: 0 | AV23: 0 | AW23: 0 | AX23: 0 | AY23: 0 | AZ23: 0 | BA23: 0 | BB23: 0 | BC23: 0 | BD23: 0 | BE23: 0 | BF23: 0 | BG23: 0 | BH23: 0 | BI23: 5092.56 | BJ23: 1655.41 | BK23: 3437.15 | BL23: 389.13 | BM23: 979.17 | BN23: 146.87 | BO23: 283.95 | BP23: 1799.12 | BQ23: 6891.68
A24: DANIEL JUNIOR SANTOS | B24: 46082 | C24: Empregado – Geral | D24: G S FL 05 - BARUERI | E24: 20.504.237/0005-40 | F24: OPERACIONAL | G24: RESENDE - RJ | H24: EKIPA LOCACOES E SERV G&S | I24: 44617 | K24: 1.7.1.2.1 ARCELOR/ RESENDE/R | L24: MOTORISTA CARRETEIRO MANTENEDOR SENIOR III | M24: 3287.33 | N24: 3287.33 | O24: 0 | P24: =N24+O24 -> 3287.33 | Q24: 0 | R24: 0 | S24: 0 | T24: 657.47 | U24: 0 | V24: 0 | W24: 0 | X24: 0 | Y24: 0 | Z24: 106.82 | AA24: 245.65 | AB24: 47.24 | AC24: 0 | AD24: 0 | AE24: 0 | AF24: 0 | AG24: 4344.51 | AH24: 0 | AI24: 0 | AJ24: 0 | AK24: 692.64 | AL24: 0 | AM24: 0 | AN24: 0 | AO24: 0 | AP24: 0 | AQ24: 0 | AR24: 692.64 | AS24: 0 | AT24: 0 | AU24: 0 | AV24: 2730 | AW24: 0 | AX24: 0 | AY24: 0 | AZ24: 0 | BA24: 0 | BB24: 2000 | BC24: 0 | BD24: 0 | BE24: 0 | BF24: 0 | BG24: 0 | BH24: 0 | BI24: 9767.15 | BJ24: 3824.43 | BK24: 5942.72 | BL24: 347.56 | BM24: 868.9 | BN24: 65.16 | BO24: 251.98 | BP24: 1533.6 | BQ24: 11300.75
A25: CRISTIANO LUCAS BACHIO | B25: 46082 | C25: Empregado – Geral | D25: G S FL 05 - BARUERI | E25: 20.504.237/0005-40 | F25: OPERACIONAL | G25: TUPY/JOINVILLE - SC | H25: EKIPA LOCACOES E SERV G&S | I25: 45026 | K25: 1.7.8.1.1 TUPY - JOINVILLE/S | L25: OPERADOR MANTENEDOR PLENO | M25: 2816.11 | N25: 2816.11 | O25: 0 | P25: =N25+O25 -> 2816.11 | Q25: 0 | R25: 0 | S25: 0 | T25: 563.22 | U25: 0 | V25: 0 | W25: 0 | X25: 0 | Y25: 0 | Z25: 20.45 | AA25: 391.69 | AB25: 75.33 | AC25: 0 | AD25: 0 | AE25: 0 | AF25: 0 | AG25: 3866.8 | AH25: 0 | AI25: 0 | AJ25: 0 | AK25: 0 | AL25: 0 | AM25: 0 | AN25: 975 | AO25: 0 | AP25: 0 | AQ25: 0 | AR25: 975 | AS25: 0 | AT25: 0 | AU25: 0 | AV25: 0 | AW25: 0 | AX25: 0 | AY25: 0 | AZ25: 0 | BA25: 0 | BB25: 0 | BC25: 0 | BD25: 0 | BE25: 0 | BF25: 0 | BG25: 0 | BH25: 0 | BI25: 4841.8 | BJ25: 1479.6 | BK25: 3362.2 | BL25: 309.34 | BM25: 773.36 | BN25: 58 | BO25: 224.27 | BP25: 1364.97 | BQ25: 6206.77
A26: JOAO BATISTA RIBEIRO SILVA | B26: 46082 | C26: Empregado – Geral | D26: G S FL 05 - BARUERI | E26: 20.504.237/0005-40 | F26: OPERACIONAL | G26: PATIO | H26: SELETIVA MARINGA DISTRITO | I26: 42826 | K26: 1.2.4.3 OPERACIONAL | L26: OPERADOR MANTENEDOR PLENO | M26: 2816.11 | N26: 2816.11 | O26: 0 | P26: =N26+O26 -> 2816.11 | Q26: 0 | R26: 0 | S26: 0 | T26: 563.22 | U26: 0 | V26: 0 | W26: 0 | X26: 0 | Y26: 0 | Z26: 0 | AA26: 1568.7 | AB26: 301.67 | AC26: 0 | AD26: 0 | AE26: 0 | AF26: 0 | AG26: 5249.7 | AH26: 0 | AI26: 0 | AJ26: 0 | AK26: 0 | AL26: 0 | AM26: 0 | AN26: 0 | AO26: 252.45 | AP26: 0 | AQ26: 0 | AR26: 252.45 | AS26: 0 | AT26: 0 | AU26: 0 | AV26: 2248 | AW26: 0 | AX26: 0 | AY26: 0 | AZ26: 0 | BA26: 0 | BB26: 0 | BC26: 0 | BD26: 0 | BE26: 0 | BF26: 0 | BG26: 0 | BH26: 0 | BI26: 7750.15 | BJ26: 2723.66 | BK26: 5026.49 | BL26: 419.97 | BM26: 1049.94 | BN26: 78.74 | BO26: 304.48 | BP26: 1853.13 | BQ26: 9603.28
A27: MARCOS ANTONIO CLAUDIO | B27: 46082 | C27: Empregado – Geral | D27: G S FL 05 - BARUERI | E27: 20.504.237/0005-40 | F27: OPERACIONAL | G27: ARCELOR/PIRACICABA - SP | H27: EKIPA LOCACOES E SERV G&S | I27: 45742 | K27: 1.7.1.4.1 ARCELOR/PIRACICABA | L27: OPERADOR MANTENEDOR PLENO | M27: 2816.11 | N27: 2816.11 | O27: 0 | P27: =N27+O27 -> 2816.11 | Q27: 0 | R27: 0 | S27: 0 | T27: 563.22 | U27: 0 | V27: 0 | W27: 0 | X27: 0 | Y27: 0 | Z27: 0 | AA27: 1542.98 | AB27: 296.73 | AC27: 0 | AD27: 0 | AE27: 0 | AF27: 0 | AG27: 5219.04 | AH27: 0 | AI27: 0 | AJ27: 0 | AK27: 1903.5 | AL27: 0 | AM27: 0 | AN27: 0 | AO27: 0 | AP27: 0 | AQ27: 0 | AR27: 1903.5 | AS27: 0 | AT27: 0 | AU27: 0 | AV27: 2016 | AW27: 0 | AX27: 0 | AY27: 0 | AZ27: 0 | BA27: 0 | BB27: 0 | BC27: 0 | BD27: 0 | BE27: 0 | BF27: 0 | BG27: 0 | BH27: 0 | BI27: 9138.54 | BJ27: 3034.85 | BK27: 6103.69 | BL27: 417.52 | BM27: 1043.81 | BN27: 78.28 | BO27: 302.7 | BP27: 1842.31 | BQ27: 10980.85
A28: RIVAEL BARRETO DA SILVA | B28: 46082 | C28: Empregado – Geral | D28: G S FL 05 - BARUERI | E28: 20.504.237/0005-40 | F28: OPERACIONAL | G28: TUPY/JOINVILLE - SC | H28: EKIPA LOCACOES E SERV G&S | I28: 44167 | K28: 1.7.8.1.1 TUPY - JOINVILLE/S | L28: OPERADOR MANTENEDOR SENIOR | M28: 3158.66 | N28: 3158.66 | O28: 0 | P28: =N28+O28 -> 3158.66 | Q28: 0 | R28: 0 | S28: 0 | T28: 631.73 | U28: 0 | V28: 0 | W28: 0 | X28: 0 | Y28: 0 | Z28: 0 | AA28: 279.11 | AB28: 53.68 | AC28: 0 | AD28: 0 | AE28: 0 | AF28: 0 | AG28: 4123.18 | AH28: 0 | AI28: 750 | AJ28: 0 | AK28: 0 | AL28: 0 | AM28: 0 | AN28: 0 | AO28: 0 | AP28: 645 | AQ28: 0 | AR28: 1395 | AS28: 0 | AT28: 50 | AU28: 0 | AV28: 0 | AW28: 0 | AX28: 0 | AY28: 0 | AZ28: 0 | BA28: 0 | BB28: 0 | BC28: 0 | BD28: 0 | BE28: 0 | BF28: 0 | BG28: 0 | BH28: 0 | BI28: 5568.18 | BJ28: 581.25 | BK28: 4986.93 | BL28: 329.85 | BM28: 824.64 | BN28: 61.84 | BO28: 239.14 | BP28: 1455.47 | BQ28: 7023.65
A29: ROBERTT FERNANDO SIQUEIRA | B29: 46082 | C29: Empregado – Geral | D29: G S FL 05 - BARUERI | E29: 20.504.237/0005-40 | F29: OPERACIONAL | G29: ARCELOR/BARRA MANSA - RJ | H29: EKIPA LOCACOES E SERV G&S | I29: 45520 | K29: 1.7.1.3.1 ARCELOR/BARRA MANS | L29: OPERADOR MANTENEDOR PLENO | M29: 2816.11 | N29: 2816.11 | O29: 0 | P29: =N29+O29 -> 2816.11 | Q29: 0 | R29: 0 | S29: 0 | T29: 563.22 | U29: 0 | V29: 0 | W29: 0 | X29: 0 | Y29: 0 | Z29: 50.91 | AA29: 0 | AB29: 0 | AC29: 0 | AD29: 0 | AE29: 0 | AF29: 0 | AG29: 3430.24 | AH29: 0 | AI29: 0 | AJ29: 0 | AK29: 0 | AL29: 0 | AM29: 0 | AN29: 893.2 | AO29: 0 | AP29: 0 | AQ29: 0 | AR29: 893.2 | AS29: 0 | AT29: 250 | AU29: 0 | AV29: 0 | AW29: 0 | AX29: 0 | AY29: 0 | AZ29: 0 | BA29: 0 | BB29: 0 | BC29: 0 | BD29: 0 | BE29: 0 | BF29: 0 | BG29: 0 | BH29: 0 | BI29: 4573.44 | BJ29: 1519.19 | BK29: 3054.25 | BL29: 274.41 | BM29: 686.05 | BN29: 51.45 | BO29: 198.95 | BP29: 1210.86 | BQ29: 5784.3
A30: SANDRILEI MOREIRA JUNIOR | B30: 46082 | C30: Empregado – Geral | D30: G S FL 05 - BARUERI | E30: 20.504.237/0005-40 | F30: OPERACIONAL | G30: ARCELOR/BARRA MANSA - RJ | H30: EKIPA LOCACOES E SERV G&S | I30: 45728 | K30: 1.7.1.3.1 ARCELOR/BARRA MANS | L30: OPERADOR MANTENEDOR PLENO | M30: 2816.11 | N30: 2816.11 | O30: 0 | P30: =N30+O30 -> 2816.11 | Q30: 0 | R30: 0 | S30: 0 | T30: 563.22 | U30: 0 | V30: 0 | W30: 0 | X30: 0 | Y30: 0 | Z30: 85.35 | AA30: 195.85 | AB30: 37.66 | AC30: 0 | AD30: 0 | AE30: 0 | AF30: 0 | AG30: 3698.19 | AH30: 0 | AI30: 0 | AJ30: 0 | AK30: 0 | AL30: 0 | AM30: 0 | AN30: 750.6 | AO30: 0 | AP30: 0 | AQ30: 0 | AR30: 750.6 | AS30: 0 | AT30: 250 | AU30: 0 | AV30: 0 | AW30: 0 | AX30: 0 | AY30: 0 | AZ30: 0 | BA30: 0 | BB30: 0 | BC30: 0 | BD30: 0 | BE30: 0 | BF30: 0 | BG30: 0 | BH30: 0 | BI30: 4698.79 | BJ30: 1831.3 | BK30: 2867.49 | BL30: 295.85 | BM30: 739.64 | BN30: 55.47 | BO30: 214.49 | BP30: 1305.45 | BQ30: 6004.24
A31: SILVANO VIEIRA DE SANTANA | B31: 46082 | C31: Empregado – Geral | D31: G S FL 05 - BARUERI | E31: 20.504.237/0005-40 | F31: LOGISTICA | G31: TRANSPORTE | H31: SELETIVA CORPORATIVO SUCATA | I31: 44238 | K31: 1.7.3.3 OPERACIONAL | L31: MOTORISTA CARRETEIRO MANTENEDOR SENIOR III | M31: 3287.33 | N31: 3287.33 | O31: 0 | P31: =N31+O31 -> 3287.33 | Q31: 0 | R31: 0 | S31: 0 | T31: 657.47 | U31: 0 | V31: 0 | W31: 0 | X31: 0 | Y31: 0 | Z31: 0 | AA31: 313.79 | AB31: 60.34 | AC31: 0 | AD31: 0 | AE31: 0 | AF31: 0 | AG31: 4318.93 | AH31: 0 | AI31: 0 | AJ31: 0 | AK31: 1120 | AL31: 0 | AM31: 0 | AN31: 0 | AO31: 0 | AP31: 0 | AQ31: 0 | AR31: 1120 | AS31: 0 | AT31: 0 | AU31: 0 | AV31: 1502 | AW31: 0 | AX31: 0 | AY31: 0 | AZ31: 0 | BA31: 0 | BB31: 0 | BC31: 0 | BD31: 0 | BE31: 0 | BF31: 0 | BG31: 0 | BH31: 0 | BI31: 6940.93 | BJ31: 671.9 | BK31: 6269.03 | BL31: 345.51 | BM31: 863.79 | BN31: 64.78 | BO31: 250.49 | BP31: 1524.57 | BQ31: 8465.5
A32: WALLANCE ALIEL FURTADO | B32: 46082 | C32: Empregado – Geral | D32: G S FL 05 - BARUERI | E32: 20.504.237/0005-40 | F32: OPERACIONAL | G32: ARCELOR/BARRA MANSA - RJ | H32: EKIPA LOCACOES E SERV G&S | I32: 44876 | K32: 1.7.1.3.1 ARCELOR/BARRA MANS | L32: OPERADOR MANTENEDOR SENIOR | M32: 3158.66 | N32: 3158.66 | O32: 0 | P32: =N32+O32 -> 3158.66 | Q32: 0 | R32: 0 | S32: 0 | T32: 631.73 | U32: 0 | V32: 0 | W32: 0 | X32: 0 | Y32: 0 | Z32: 43.61 | AA32: 0 | AB32: 0 | AC32: 0 | AD32: 0 | AE32: 0 | AF32: 0 | AG32: 3834 | AH32: 0 | AI32: 0 | AJ32: 0 | AK32: 0 | AL32: 0 | AM32: 0 | AN32: 742.5 | AO32: 0 | AP32: 0 | AQ32: 0 | AR32: 742.5 | AS32: 0 | AT32: 250 | AU32: 0 | AV32: 0 | AW32: 0 | AX32: 0 | AY32: 0 | AZ32: 0 | BA32: 0 | BB32: 0 | BC32: 0 | BD32: 0 | BE32: 0 | BF32: 0 | BG32: 0 | BH32: 0 | BI32: 4826.5 | BJ32: 1996.26 | BK32: 2830.24 | BL32: 306.72 | BM32: 766.8 | BN32: 57.51 | BO32: 222.37 | BP32: 1353.4 | BQ32: 6179.9
A33: WAGNER APARECIDO DO NASCIMENTO | B33: 46082 | C33: Empregado – Geral | D33: G S FL 05 - BARUERI | E33: 20.504.237/0005-40 | F33: LOGISTICA | G33: PRENSA MOVEL | H33: SELETIVA CORPORATIVO SUCATA | I33: 43858 | K33: 1.7.3.3 OPERACIONAL | L33: MOTORISTA CARRETEIRO MANTENEDOR SENIOR II | M33: 3091.39 | N33: 3091.39 | O33: 0 | P33: =N33+O33 -> 3091.39 | Q33: 0 | R33: 0 | S33: 0 | T33: 618.28 | U33: 0 | V33: 0 | W33: 0 | X33: 0 | Y33: 0 | Z33: 0 | AA33: 646.94 | AB33: 124.41 | AC33: 0 | AD33: 0 | AE33: 0 | AF33: 0 | AG33: 4481.02 | AH33: 0 | AI33: 2205 | AJ33: 0 | AK33: 0 | AL33: 0 | AM33: 0 | AN33: 0 | AO33: 0 | AP33: 250 | AQ33: 0 | AR33: 2455 | AS33: 0 | AT33: 0 | AU33: 0 | AV33: 2730 | AW33: 0 | AX33: 0 | AY33: 0 | AZ33: 0 | BA33: 0 | BB33: 0 | BC33: 0 | BD33: 0 | BE33: 0 | BF33: 0 | BG33: 0 | BH33: 0 | BI33: 9666.02 | BJ33: 1205.41 | BK33: 8460.61 | BL33: 358.48 | BM33: 896.2 | BN33: 67.21 | BO33: 259.89 | BP33: 1581.78 | BQ33: 11247.8
A34: SERGIO LUIZ RIBEIRO | B34: 46082 | C34: Empregado – Geral | D34: G S FL 05 - BARUERI | E34: 20.504.237/0005-40 | F34: OPERACIONAL | G34: RESENDE - RJ | H34: EKIPA LOCACOES E SERV G&S | I34: 45966 | K34: 1.7.1.2.1 ARCELOR/ RESENDE/R | L34: OPERADOR MANTENEDOR SENIOR | M34: 3158.66 | N34: 3158.66 | O34: 0 | P34: =N34+O34 -> 3158.66 | Q34: 0 | R34: 0 | S34: 0 | T34: 631.73 | U34: 0 | V34: 0 | W34: 0 | X34: 0 | Y34: 0 | Z34: 64.03 | AA34: 0 | AB34: 0 | AC34: 0 | AD34: 0 | AE34: 0 | AF34: 0 | AG34: 3854.42 | AH34: 0 | AI34: 0 | AJ34: 0 | AK34: 812.97 | AL34: 0 | AM34: 0 | AN34: 0 | AO34: 0 | AP34: 0 | AQ34: 0 | AR34: 812.97 | AS34: 0 | AT34: 0 | AU34: 0 | AV34: 0 | AW34: 0 | AX34: 0 | AY34: 0 | AZ34: 0 | BA34: 0 | BB34: 0 | BC34: 0 | BD34: 0 | BE34: 0 | BF34: 0 | BG34: 0 | BH34: 0 | BI34: 4667.39 | BJ34: 1714.61 | BK34: 2952.78 | BL34: 308.35 | BM34: 770.88 | BN34: 57.81 | BO34: 223.55 | BP34: 1360.59 | BQ34: 6027.98
... A55: LAYZA PINHEIRO FRANCESQUETTE | B55: 46082 | C55: Empregado – Geral | D55: G3S FL 10 - PRES PRUD | E55: 20.947.332/0010-86 | F55: COMERCIAL | G55: COMERCIAL | H55: SELETIVA CORPORATIVO SUCATA | I55: 45845 | K55: 1.2.1.1 APOIO | L55: ASSISTENTE COMERCIAL | M55: 2098 | N55: 2098 | O55: 0 | P55: =N55+O55 -> 2098 | Q55: 0 | R55: 0 | S55: 0 | T55: 0 | U55: 0 | V55: 0 | W55: 0 | X55: 0 | Y55: 0 | Z55: 0 | AA55: 0 | AB55: 0 | AC55: 0 | AD55: 0 | AE55: 0 | AF55: 0 | AG55: 2098 | AH55: 0 | AI55: 0 | AJ55: 0 | AK55: 0 | AL55: 929.47 | AM55: 0 | AN55: 0 | AO55: 0 | AP55: 0 | AQ55: 0 | AR55: 929.47 | AS55: 0 | AT55: 0 | AU55: 0 | AV55: 0 | AW55: 0 | AX55: 0 | AY55: 0 | AZ55: 0 | BA55: 165.44 | BB55: 0 | BC55: 0 | BD55: 0 | BE55: 0 | BF55: 0 | BG55: 0 | BH55: 0 | BI55: 3192.91 | BJ55: 164.5 | BK55: 3028.41 | BL55: 167.84 | BM55: 419.6 | BN55: 62.94 | BO55: 121.68 | BP55: 772.06 | BQ55: 3964.97
A56: EDUARDO YUICHI CHINMEI | B56: 46082 | C56: Empregado – Geral | D56: G3S FL 10 - PRES PRUD | E56: 20.947.332/0010-86 | F56: COMERCIAL | G56: COMERCIAL | H56: SELETIVA CORPORATIVO SUCATA | I56: 45748 | J56: 46104 | K56: 1.2.1.1 APOIO | L56: ASSISTENTE COMERCIAL | M56: 2098 | N56: 0 | O56: 0 | P56: =N56+O56 -> 0 | Q56: 0 | R56: 0 | S56: 0 | T56: 0 | U56: 0 | V56: 0 | W56: 0 | X56: 0 | Y56: 0 | Z56: 0 | AA56: 0 | AB56: 8.43 | AC56: 0 | AD56: 0 | AE56: 0 | AF56: 0 | AG56: 8.43 | AH56: 0 | AI56: 0 | AJ56: 0 | AK56: 0 | AL56: 929.47 | AM56: 0 | AN56: 0 | AO56: 0 | AP56: 0 | AQ56: 0 | AR56: 929.47 | AS56: 0 | AT56: 416.67 | AU56: 0 | AV56: 0 | AW56: 0 | AX56: 0 | AY56: 0 | AZ56: 0 | BA56: 165.44 | BB56: 0 | BC56: 0 | BD56: 0 | BE56: 0 | BF56: 6606.85 | BG56: 327.54 | BH56: 6934.39 | BI56: 1520.01 | BJ56: 7625.87 | BK56: 0 | BL56: 0 | BM56: 1.69 | BN56: 0.25 | BO56: 0.48 | BP56: 2.42 | BQ56: 1522.43
A57: MARIANA SIQUEIRA | B57: 46082 | C57: Empregado – Geral | D57: G3S FL 10 - PRES PRUD | E57: 20.947.332/0010-86 | F57: COMERCIAL | G57: COMERCIAL | H57: SELETIVA CORPORATIVO SUCATA | I57: 46055 | K57: 1.2.1.1 APOIO | L57: ASSISTENTE COMERCIAL | M57: 2098 | N57: 2098 | O57: 0 | P57: =N57+O57 -> 2098 | Q57: 0 | R57: 0 | S57: 0 | T57: 0 | U57: 0 | V57: 0 | W57: 0 | X57: 0 | Y57: 0 | Z57: 0 | AA57: 0 | AB57: 0 | AC57: 0 | AD57: 0 | AE57: 0 | AF57: 0 | AG57: 2098 | AH57: 0 | AI57: 0 | AJ57: 0 | AK57: 0 | AL57: 929.47 | AM57: 0 | AN57: 0 | AO57: 0 | AP57: 0 | AQ57: 0 | AR57: 929.47 | AS57: 0 | AT57: 0 | AU57: 0 | AV57: 0 | AW57: 0 | AX57: 0 | AY57: 0 | AZ57: 0 | BA57: 0 | BB57: 0 | BC57: 0 | BD57: 0 | BE57: 0 | BF57: 0 | BG57: 0 | BH57: 0 | BI57: 3027.47 | BJ57: 164.5 | BK57: 2862.97 | BL57: 167.84 | BM57: 419.6 | BN57: 62.94 | BO57: 121.68 | BP57: 772.06 | BQ57: 3799.53
A58: PEDRO MARQUES GUARNIERI | B58: 46082 | C58: Bolsista - Estagiário | D58: G3S FL 10 - PRES PRUD | E58: 20.947.332/0010-86 | F58: ADMINISTRATIVO | G58: QUALIDADE | H58: PILARES | I58: 45790 | J58: 46101 | K58: 1.1.5 QUALIDADE | L58: AUXILIAR ADMINISTRATIVO - ESTAGIARIO(A) | M58: 1000 | N58: 0 | O58: 0 | P58: =N58+O58 -> 0 | Q58: 0 | R58: 0 | S58: 0 | T58: 0 | U58: 0 | V58: 0 | W58: 0 | X58: 0 | Y58: 0 | Z58: 0 | AA58: 0 | AB58: 0 | AC58: 0 | AD58: 0 | AE58: 0 | AF58: 0 | AG58: 0 | AH58: 0 | AI58: 0 | AJ58: 0 | AK58: 0 | AL58: 0 | AM58: 0 | AN58: 0 | AO58: 0 | AP58: 0 | AQ58: 0 | AR58: 0 | AS58: 666.67 | AT58: 0 | AU58: 0 | AV58: 0 | AW58: 0 | AX58: 0 | AY58: 0 | AZ58: 0 | BA58: 0 | BB58: 0 | BC58: 0 | BD58: 0 | BE58: 0 | BF58: 900 | BG58: 0 | BH58: 900 | BI58: 666.67 | BJ58: 900 | BK58: 0 | BL58: 0 | BM58: 0 | BN58: 0 | BO58: 0 | BP58: 0 | BQ58: 666.67
A59: GABRIEL SATOSHI DA SILVA SAKATA | B59: 46082 | C59: Bolsista - Estagiário | D59: G3S FL 10 - PRES PRUD | E59: 20.947.332/0010-86 | F59: ADMINISTRATIVO | G59: SUPRIMENTOS | H59: PILARES | I59: 45810 | K59: 1.1.14 SUPRIMENTOS | L59: AUXILIAR ADMINISTRATIVO - ESTAGIARIO(A) | M59: 1000 | N59: 0 | O59: 0 | P59: =N59+O59 -> 0 | Q59: 0 | R59: 0 | S59: 0 | T59: 0 | U59: 0 | V59: 0 | W59: 0 | X59: 0 | Y59: 0 | Z59: 0 | AA59: 0 | AB59: 0 | AC59: 0 | AD59: 0 | AE59: 0 | AF59: 0 | AG59: 0 | AH59: 0 | AI59: 0 | AJ59: 0 | AK59: 0 | AL59: 0 | AM59: 0 | AN59: 0 | AO59: 0 | AP59: 0 | AQ59: 0 | AR59: 0 | AS59: 1000 | AT59: 0 | AU59: 0 | AV59: 0 | AW59: 0 | AX59: 0 | AY59: 0 | AZ59: 0 | BA59: 0 | BB59: 0 | BC59: 0 | BD59: 0 | BE59: 0 | BF59: 0 | BG59: 0 | BH59: 0 | BI59: 1000 | BJ59: 0 | BK59: 1000 | BL59: 0 | BM59: 0 | BN59: 0 | BO59: 0 | BP59: 0 | BQ59: 1000
A60: MELISSA DE FREITAS ORRIGO | B60: 46082 | C60: Bolsista - Estagiário | D60: G3S FL 10 - PRES PRUD | E60: 20.947.332/0010-86 | F60: COMERCIAL | G60: COMERCIAL | H60: SELETIVA CORPORATIVO SUCATA | I60: 45824 | K60: 1.2.1.1 APOIO | L60: AUXILIAR COMERCIAL - ESTAGIARIO | M60: 1000 | N60: 0 | O60: 0 | P60: =N60+O60 -> 0 | Q60: 0 | R60: 0 | S60: 0 | T60: 0 | U60: 0 | V60: 0 | W60: 0 | X60: 0 | Y60: 0 | Z60: 0 | AA60: 0 | AB60: 0 | AC60: 0 | AD60: 0 | AE60: 0 | AF60: 0 | AG60: 0 | AH60: 0 | AI60: 0 | AJ60: 0 | AK60: 0 | AL60: 0 | AM60: 0 | AN60: 0 | AO60: 0 | AP60: 0 | AQ60: 0 | AR60: 0 | AS60: 1000 | AT60: 0 | AU60: 0 | AV60: 0 | AW60: 0 | AX60: 0 | AY60: 0 | AZ60: 0 | BA60: 0 | BB60: 0 | BC60: 0 | BD60: 0 | BE60: 0 | BF60: 0 | BG60: 0 | BH60: 0 | BI60: 1000 | BJ60: 0 | BK60: 1000 | BL60: 0 | BM60: 0 | BN60: 0 | BO60: 0 | BP60: 0 | BQ60: 1000
A61: JOAO PAULO MARTINS OZORES | B61: 46082 | C61: Bolsista - Estagiário | D61: G3S FL 10 - PRES PRUD | E61: 20.947.332/0010-86 | F61: ADMINISTRATIVO | G61: SUPRIMENTOS | H61: PILARES | I61: 45929 | K61: 1.1.14 SUPRIMENTOS | L61: AUXILIAR ADMINISTRATIVO - ESTAGIARIO(A) | M61: 1000 | N61: 0 | O61: 0 | P61: =N61+O61 -> 0 | Q61: 0 | R61: 0 | S61: 0 | T61: 0 | U61: 0 | V61: 0 | W61: 0 | X61: 0 | Y61: 0 | Z61: 0 | AA61: 0 | AB61: 0 | AC61: 0 | AD61: 0 | AE61: 0 | AF61: 0 | AG61: 0 | AH61: 0 | AI61: 0 | AJ61: 0 | AK61: 0 | AL61: 0 | AM61: 0 | AN61: 0 | AO61: 0 | AP61: 0 | AQ61: 0 | AR61: 0 | AS61: 1000 | AT61: 0 | AU61: 0 | AV61: 0 | AW61: 0 | AX61: 0 | AY61: 0 | AZ61: 0 | BA61: 0 | BB61: 0 | BC61: 0 | BD61: 0 | BE61: 0 | BF61: 0 | BG61: 0 | BH61: 0 | BI61: 1000 | BJ61: 0 | BK61: 1000 | BL61: 0 | BM61: 0 | BN61: 0 | BO61: 0 | BP61: 0 | BQ61: 1000
A62: JOAO EMANUEL SANTOS SILVA | B62: 46082 | C62: Bolsista - Estagiário | D62: G3S FL 10 - PRES PRUD | E62: 20.947.332/0010-86 | F62: ADMINISTRATIVO | G62: FINANCEIRO | H62: PILARES | I62: 45958 | K62: 1.1.3 FINANCEIRO | L62: AUXILIAR FINANCEIRO - ESTAGIARIO | M62: 1000 | N62: 0 | O62: 0 | P62: =N62+O62 -> 0 | Q62: 0 | R62: 0 | S62: 0 | T62: 0 | U62: 0 | V62: 0 | W62: 0 | X62: 0 | Y62: 0 | Z62: 0 | AA62: 0 | AB62: 0 | AC62: 0 | AD62: 0 | AE62: 0 | AF62: 0 | AG62: 0 | AH62: 0 | AI62: 0 | AJ62: 0 | AK62: 0 | AL62: 0 | AM62: 0 | AN62: 0 | AO62: 0 | AP62: 0 | AQ62: 0 | AR62: 0 | AS62: 1000 | AT62: 0 | AU62: 0 | AV62: 0 | AW62: 0 | AX62: 0 | AY62: 0 | AZ62: 0 | BA62: 0 | BB62: 0 | BC62: 0 | BD62: 0 | BE62: 0 | BF62: 0 | BG62: 0 | BH62: 0 | BI62: 1000 | BJ62: 0 | BK62: 1000 | BL62: 0 | BM62: 0 | BN62: 0 | BO62: 0 | BP62: 0 | BQ62: 1000
A63: ISADORA THAYNA VIOTTO DIAS | B63: 46082 | C63: Bolsista - Estagiário | D63: G3S FL 10 - PRES PRUD | E63: 20.947.332/0010-86 | F63: ADMINISTRATIVO | G63: ADMINISTRATIVO | H63: RENDER LOCACOES | I63: 45973 | K63: 1.8.1 ADMINISTRATIVO | L63: AUXILIAR ADMINISTRATIVO - ESTAGIARIO(A) | M63: 1000 | N63: 0 | O63: 0 | P63: =N63+O63 -> 0 | Q63: 0 | R63: 0 | S63: 0 | T63: 0 | U63: 0 | V63: 0 | W63: 0 | X63: 0 | Y63: 0 | Z63: 0 | AA63: 0 | AB63: 0 | AC63: 0 | AD63: 0 | AE63: 0 | AF63: 0 | AG63: 0 | AH63: 0 | AI63: 0 | AJ63: 0 | AK63: 0 | AL63: 0 | AM63: 0 | AN63: 0 | AO63: 0 | AP63: 0 | AQ63: 0 | AR63: 0 | AS63: 1000 | AT63: 0 | AU63: 0 | AV63: 0 | AW63: 0 | AX63: 0 | AY63: 0 | AZ63: 0 | BA63: 0 | BB63: 0 | BC63: 0 | BD63: 0 | BE63: 0 | BF63: 0 | BG63: 0 | BH63: 0 | BI63: 1000 | BJ63: 0 | BK63: 1000 | BL63: 0 | BM63: 0 | BN63: 0 | BO63: 0 | BP63: 0 | BQ63: 1000
A64: CAIO MURILO SPINDOLA DOS SANTOS | B64: 46082 | C64: Bolsista - Estagiário | D64: G3S FL 10 - PRES PRUD | E64: 20.947.332/0010-86 | F64: COMERCIAL | G64: COMERCIAL | H64: SELETIVA CORPORATIVO SUCATA | I64: 45950 | K64: 1.2.1.1 APOIO | L64: AUXILIAR COMERCIAL - ESTAGIARIO | M64: 1000 | N64: 0 | O64: 0 | P64: =N64+O64 -> 0 | Q64: 0 | R64: 0 | S64: 0 | T64: 0 | U64: 0 | V64: 0 | W64: 0 | X64: 0 | Y64: 0 | Z64: 0 | AA64: 0 | AB64: 0 | AC64: 0 | AD64: 0 | AE64: 0 | AF64: 0 | AG64: 0 | AH64: 0 | AI64: 0 | AJ64: 0 | AK64: 0 | AL64: 0 | AM64: 0 | AN64: 0 | AO64: 0 | AP64: 0 | AQ64: 0 | AR64: 0 | AS64: 1000 | AT64: 0 | AU64: 0 | AV64: 0 | AW64: 0 | AX64: 0 | AY64: 0 | AZ64: 0 | BA64: 0 | BB64: 0 | BC64: 0 | BD64: 0 | BE64: 0 | BF64: 0 | BG64: 0 | BH64: 0 | BI64: 1000 | BJ64: 0 | BK64: 1000 | BL64: 0 | BM64: 0 | BN64: 0 | BO64: 0 | BP64: 0 | BQ64: 1000
A65: ESTER TAVARES FERREIRA | B65: 46082 | C65: Bolsista - Estagiário | D65: G3S FL 10 - PRES PRUD | E65: 20.947.332/0010-86 | F65: COMERCIAL | G65: COMERCIAL | H65: SELETIVA CORPORATIVO SUCATA | I65: 46055 | K65: 1.2.1.1 APOIO | L65: AUXILIAR COMERCIAL - ESTAGIARIO | M65: 1000 | N65: 0 | O65: 0 | P65: =N65+O65 -> 0 | Q65: 0 | R65: 0 | S65: 0 | T65: 0 | U65: 0 | V65: 0 | W65: 0 | X65: 0 | Y65: 0 | Z65: 0 | AA65: 0 | AB65: 0 | AC65: 0 | AD65: 0 | AE65: 0 | AF65: 0 | AG65: 0 | AH65: 0 | AI65: 0 | AJ65: 0 | AK65: 0 | AL65: 0 | AM65: 0 | AN65: 0 | AO65: 0 | AP65: 0 | AQ65: 0 | AR65: 0 | AS65: 1500 | AT65: 0 | AU65: 0 | AV65: 0 | AW65: 0 | AX65: 0 | AY65: 0 | AZ65: 0 | BA65: 0 | BB65: 0 | BC65: 0 | BD65: 0 | BE65: 0 | BF65: 0 | BG65: 0 | BH65: 0 | BI65: 1500 | BJ65: 0 | BK65: 1500 | BL65: 0 | BM65: 0 | BN65: 0 | BO65: 0 | BP65: 0 | BQ65: 1500
A66: BRUNA RIBEIRO SANCHEZ | B66: 46082 | C66: Bolsista - Estagiário | D66: G3S FL 10 - PRES PRUD | E66: 20.947.332/0010-86 | F66: GESTÃO DE GENTE | G66: DEPTO PESSOAL | H66: PILARES | I66: 46071 | K66: 1.1.10 PESSOAS | L66: AUXILIAR ADMINISTRATIVO - ESTAGIARIO(A) | M66: 1000 | N66: 0 | O66: 0 | P66: =N66+O66 -> 0 | Q66: 0 | R66: 0 | S66: 0 | T66: 0 | U66: 0 | V66: 0 | W66: 0 | X66: 0 | Y66: 0 | Z66: 0 | AA66: 0 | AB66: 0 | AC66: 0 | AD66: 0 | AE66: 0 | AF66: 0 | AG66: 0 | AH66: 0 | AI66: 0 | AJ66: 0 | AK66: 0 | AL66: 0 | AM66: 0 | AN66: 0 | AO66: 0 | AP66: 0 | AQ66: 0 | AR66: 0 | AS66: 1000 | AT66: 0 | AU66: 0 | AV66: 0 | AW66: 0 | AX66: 0 | AY66: 0 | AZ66: 0 | BA66: 0 | BB66: 0 | BC66: 0 | BD66: 0 | BE66: 0 | BF66: 0 | BG66: 0 | BH66: 0 | BI66: 1000 | BJ66: 100 | BK66: 900 | BL66: 0 | BM66: 0 | BN66: 0 | BO66: 0 | BP66: 0 | BQ66: 1000
A67: MURILO SCHISBELGS DIAS | B67: 46082 | C67: Bolsista - Estagiário | D67: G3S FL 10 - PRES PRUD | E67: 20.947.332/0010-86 | F67: COMERCIAL | G67: COMERCIAL | H67: SELETIVA CORPORATIVO SUCATA | I67: 46083 | K67: 1.2.1.1 APOIO | L67: AUXILIAR COMERCIAL - ESTAGIARIO | M67: 1000 | N67: 0 | O67: 0 | P67: =N67+O67 -> 0 | Q67: 0 | R67: 0 | S67: 0 | T67: 0 | U67: 0 | V67: 0 | W67: 0 | X67: 0 | Y67: 0 | Z67: 0 | AA67: 0 | AB67: 0 | AC67: 0 | AD67: 0 | AE67: 0 | AF67: 0 | AG67: 0 | AH67: 0 | AI67: 0 | AJ67: 0 | AK67: 0 | AL67: 0 | AM67: 0 | AN67: 0 | AO67: 0 | AP67: 0 | AQ67: 0 | AR67: 0 | AS67: 1500 | AT67: 0 | AU67: 0 | AV67: 0 | AW67: 0 | AX67: 0 | AY67: 0 | AZ67: 0 | BA67: 0 | BB67: 0 | BC67: 0 | BD67: 0 | BE67: 0 | BF67: 0 | BG67: 0 | BH67: 0 | BI67: 1500 | BJ67: 250 | BK67: 1250 | BL67: 0 | BM67: 0 | BN67: 0 | BO67: 0 | BP67: 0 | BQ67: 1500
A68: LUCAS VICTOR MENDONÇA RUBIO | B68: 46082 | C68: Bolsista - Estagiário | D68: G3S FL 10 - PRES PRUD | E68: 20.947.332/0010-86 | F68: ADMINISTRATIVO | G68: FISCAL | H68: PILARES | I68: 46083 | K68: 1.1.4 CONTABILIDADE/FISCAL | L68: AUXILIAR CONTABIL - ESTAGIARIO | M68: 1000 | N68: 0 | O68: 0 | P68: =N68+O68 -> 0 | Q68: 0 | R68: 0 | S68: 0 | T68: 0 | U68: 0 | V68: 0 | W68: 0 | X68: 0 | Y68: 0 | Z68: 0 | AA68: 0 | AB68: 0 | AC68: 0 | AD68: 0 | AE68: 0 | AF68: 0 | AG68: 0 | AH68: 0 | AI68: 0 | AJ68: 0 | AK68: 0 | AL68: 0 | AM68: 0 | AN68: 0 | AO68: 0 | AP68: 0 | AQ68: 0 | AR68: 0 | AS68: 1500 | AT68: 0 | AU68: 0 | AV68: 0 | AW68: 0 | AX68: 0 | AY68: 0 | AZ68: 0 | BA68: 0 | BB68: 0 | BC68: 0 | BD68: 0 | BE68: 0 | BF68: 0 | BG68: 0 | BH68: 0 | BI68: 1500 | BJ68: 250 | BK68: 1250 | BL68: 0 | BM68: 0 | BN68: 0 | BO68: 0 | BP68: 0 | BQ68: 1500
A69: JULIO OLIVEIRA SANTANA | B69: 46082 | C69: Bolsista - Estagiário | D69: G3S FL 10 - PRES PRUD | E69: 20.947.332/0010-86 | F69: ADMINISTRATIVO | G69: QUALIDADE | H69: PILARES | I69: 46100 | K69: 1.1.5 QUALIDADE | L69: AUXILIAR DE QUALIDADE - ESTAGIARIO | M69: 1000 | N69: 0 | O69: 0 | P69: =N69+O69 -> 0 | Q69: 0 | R69: 0 | S69: 0 | T69: 0 | U69: 0 | V69: 0 | W69: 0 | X69: 0 | Y69: 0 | Z69: 0 | AA69: 0 | AB69: 0 | AC69: 0 | AD69: 0 | AE69: 0 | AF69: 0 | AG69: 0 | AH69: 0 | AI69: 0 | AJ69: 0 | AK69: 0 | AL69: 0 | AM69: 0 | AN69: 0 | AO69: 0 | AP69: 0 | AQ69: 0 | AR69: 0 | AS69: 650 | AT69: 0 | AU69: 0 | AV69: 0 | AW69: 0 | AX69: 0 | AY69: 0 | AZ69: 0 | BA69: 0 | BB69: 0 | BC69: 0 | BD69: 0 | BE69: 0 | BF69: 0 | BG69: 0 | BH69: 0 | BI69: 650 | BJ69: 216.67 | BK69: 433.33 | BL69: 0 | BM69: 0 | BN69: 0 | BO69: 0 | BP69: 0 | BQ69: 650
A70: ADEMIR DOS SANTOS | B70: 46082 | C70: Empregado – Geral | D70: G3S FL 11 - MARINGA | E70: 20.947.332/0011-67 | F70: OPERACIONAL | G70: PATIO | H70: SELETIVA MARINGA CIDADE ALTA | I70: 45915 | K70: 1.2.8.3. OPERACIONAL | L70: AUXILIAR DE PATIO SENIOR | M70: 2600 | N70: 2600 | O70: 0 | P70: =N70+O70 -> 2600 | Q70: 0 | R70: 0 | S70: 0 | T70: 0 | U70: 0 | V70: 0 | W70: 0 | X70: 0 | Y70: 0 | Z70: 0 | AA70: 79.95 | AB70: 15.38 | AC70: 0 | AD70: 0 | AE70: 0 | AF70: 0 | AG70: 2695.33 | AH70: 0 | AI70: 0 | AJ70: 0 | AK70: 0 | AL70: 0 | AM70: 0 | AN70: 0 | AO70: 456.6 | AP70: 0 | AQ70: 0 | AR70: 456.6 | AS70: 0 | AT70: 0 | AU70: 0 | AV70: 0 | AW70: 0 | AX70: 0 | AY70: 0 | AZ70: 0 | BA70: 0 | BB70: 0 | BC70: 0 | BD70: 0 | BE70: 0 | BF70: 0 | BG70: 0 | BH70: 0 | BI70: 3151.93 | BJ70: 1258.25 | BK70: 1893.68 | BL70: 215.62 | BM70: 539.07 | BN70: 80.85 | BO70: 156.32 | BP70: 991.86 | BQ70: 4143.79
A71: ALEKSANDER APARECIDO GONÇALVES DA SILVA | B71: 46082 | C71: Empregado – Geral | D71: G3S FL 11 - MARINGA | E71: 20.947.332/0011-67 | F71: OPERACIONAL | G71: PATIO | H71: SELETIVA MARINGA CIDADE ALTA | I71: 46050 | J71: 46097 | K71: 1.2.8.3. OPERACIONAL | L71: GERENTE DE PATIO SENIOR | M71: 3679.83 | N71: 0 | O71: 0 | P71: =N71+O71 -> 0 | Q71: 0 | R71: 0 | S71: 0 | T71: 392.52 | U71: 0 | V71: 588.77 | W71: 0 | X71: 0 | Y71: 0 | Z71: 0 | AA71: 0 | AB71: 47.77 | AC71: 0 | AD71: 0 | AE71: 0 | AF71: 0 | AG71: 1029.06 | AH71: 0 | AI71: 0 | AJ71: 0 | AK71: 0 | AL71: 0 | AM71: 0 | AN71: 0 | AO71: 28.92 | AP71: 0 | AQ71: 0 | AR71: 28.92 | AS71: 0 | AT71: 266.67 | AU71: 0 | AV71: 0 | AW71: 0 | AX71: 0 | AY71: 0 | AZ71: 0 | BA71: 0 | BB71: 0 | BC71: 0 | BD71: 0 | BE71: 0 | BF71: 4483.47 | BG71: 0 | BH71: 4483.47 | BI71: 1324.65 | BJ71: 5802.38 | BK71: 0 | BL71: 255.89 | BM71: 205.81 | BN71: 30.87 | BO71: 59.68 | BP71: 552.25 | BQ71: 1876.9
A72: DYESSILA MARY ALVES | B72: 46082 | C72: Empregado – Geral | D72: G3S FL 11 - MARINGA | E72: 20.947.332/0011-67 | F72: ADMINISTRATIVO | G72: ATENDIMENTO | H72: SELETIVA MARINGA CIDADE ALTA | I72: 45323 | K72: 1.2.4.1 ADMINISTRATIVO | L72: AUX ADMINISTRATIVO JUNIOR | M72: 2320 | N72: 2320 | O72: 0 | P72: =N72+O72 -> 2320 | Q72: 0 | R72: 0 | S72: 0 | T72: 0 | U72: 0 | V72: 0 | W72: 0 | X72: 0 | Y72: 0 | Z72: 0 | AA72: 237.8 | AB72: 45.73 | AC72: 0 | AD72: 0 | AE72: 0 | AF72: 0 | AG72: 2603.53 | AH72: 0 | AI72: 0 | AJ72: 0 | AK72: 0 | AL72: 0 | AM72: 0 | AN72: 0 | AO72: 456.6 | AP72: 0 | AQ72: 0 | AR72: 456.6 | AS72: 0 | AT72: 0 | AU72: 0 | AV72: 0 | AW72: 0 | AX72: 0 | AY72: 0 | AZ72: 0 | BA72: 0 | BB72: 0 | BC72: 0 | BD72: 0 | BE72: 0 | BF72: 0 | BG72: 0 | BH72: 0 | BI72: 3060.13 | BJ72: 695.85 | BK72: 2364.28 | BL72: 208.28 | BM72: 520.71 | BN72: 78.1 | BO72: 151 | BP72: 958.09 | BQ72: 4018.22
A73: GUSTAVO LINO DUARTE | B73: 46082 | C73: Empregado – Geral | D73: G3S CMATRIZ - CAMPO GRANDE | E73: 20.947.332/0001-95 | F73: OPERACIONAL | G73: PATIO | H73: SELETIVA C GRANDE | I73: 45237 | J73: 46090 | K73: 1.2.7.3 OPERACIONAL | L73: AUXILIAR DE PATIO JUNIOR | M73: 2305.85 | N73: 0 | O73: 0 | P73: =N73+O73 -> 0 | Q73: 0 | R73: 0 | S73: 0 | T73: 0 | U73: 0 | V73: 0 | W73: 0 | X73: 0 | Y73: 0 | Z73: 0 | AA73: 0 | AB73: 0 | AC73: 0 | AD73: 0 | AE73: 0 | AF73: 0 | AG73: 0 | AH73: 0 | AI73: 0 | AJ73: 0 | AK73: 0 | AL73: 0 | AM73: 0 | AN73: 0 | AO73: 110.84 | AP73: 0 | AQ73: 0 | AR73: 110.84 | AS73: 0 | AT73: 500 | AU73: 0 | AV73: 0 | AW73: 0 | AX73: 0 | AY73: 0 | AZ73: 0 | BA73: 0 | BB73: 0 | BC73: 0 | BD73: 0 | BE73: 0 | BF73: 6369.91 | BG73: 199.81 | BH73: 6569.72 | BI73: 610.84 | BJ73: 7249.09 | BK73: 0 | BL73: 0 | BM73: 0 | BN73: 0 | BO73: 0 | BP73: 0 | BQ73: 610.84
A74: PATRICIA DANIELLE SILVA | B74: 46082 | C74: Empregado – Geral | D74: G3S CMATRIZ - CAMPO GRANDE | E74: 20.947.332/0001-95 | F74: ADMINISTRATIVO | G74: ATENDIMENTO | H74: SELETIVA C GRANDE | I74: 45733 | K74: 1.2.7.1 ADMINISTRATIVO | L74: AUX ADMINISTRATIVO PLENO | M74: 2650 | N74: 2650 | O74: 0 | P74: =N74+O74 -> 2650 | Q74: 0 | R74: 0 | S74: 0 | T74: 0 | U74: 0 | V74: 0 | W74: 0 | X74: 0 | Y74: 0 | Z74: 0 | AA74: 34.91 | AB74: 6.71 | AC74: 0 | AD74: 0 | AE74: 0 | AF74: 265 | AG74: 2956.62 | AH74: 0 | AI74: 0 | AJ74: 0 | AK74: 0 | AL74: 0 | AM74: 0 | AN74: 0 | AO74: 533.04 | AP74: 0 | AQ74: 0 | AR74: 533.04 | AS74: 0 | AT74: 0 | AU74: 0 | AV74: 0 | AW74: 0 | AX74: 0 | AY74: 0 | AZ74: 0 | BA74: 0 | BB74: 0 | BC74: 0 | BD74: 0 | BE74: 0 | BF74: 0 | BG74: 0 | BH74: 0 | BI74: 3489.66 | BJ74: 1303.38 | BK74: 2186.28 | BL74: 236.52 | BM74: 591.32 | BN74: 135.26 | BO74: 171.48 | BP74: 1134.58 | BQ74: 4624.24
A75: LUIZ GUILHERME BRAGHINI | B75: 46082 | C75: Empregado – Geral | D75: G3S CMATRIZ - CAMPO GRANDE | E75: 20.947.332/0001-95 | F75: OPERACIONAL | G75: PATIO | H75: SELETIVA C GRANDE | I75: 44630 | K75: 1.2.7.3 OPERACIONAL | L75: GERENTE DE PATIO SENIOR | M75: 3679.83 | N75: 3679.83 | O75: 0 | P75: =N75+O75 -> 3679.83 | Q75: 0 | R75: 0 | S75: 0 | T75: 735.97 | U75: 0 | V75: 1103.95 | W75: 0 | X75: 0 | Y75: 0 | Z75: 0 | AA75: 0 | AB75: 0 | AC75: 0 | AD75: 0 | AE75: 0 | AF75: 0 | AG75: 5519.75 | AH75: 0 | AI75: 0 | AJ75: 0 | AK75: 0 | AL75: 0 | AM75: 0 | AN75: 0 | AO75: 533.04 | AP75: 0 | AQ75: 0 | AR75: 533.04 | AS75: 0 | AT75: 0 | AU75: 0 | AV75: 160 | AW75: 0 | AX75: 0 | AY75: 0 | AZ75: 0 | BA75: 0 | BB75: 0 | BC75: 0 | BD75: 0 | BE75: 0 | BF75: 0 | BG75: 0 | BH75: 0 | BI75: 6212.79 | BJ75: 2297.76 | BK75: 3915.03 | BL75: 441.58 | BM75: 1103.95 | BN75: 252.52 | BO75: 320.14 | BP75: 2118.19 | BQ75: 8330.98
A76: PEDRO FELIPE PINA DO NASCIMENTO | B76: 46082 | C76: Empregado – Geral | D76: G3S CMATRIZ - CAMPO GRANDE | E76: 20.947.332/0001-95 | F76: OPERACIONAL | G76: PATIO | H76: SELETIVA C GRANDE | I76: 46001 | J76: 46090 | K76: 1.2.7.3 OPERACIONAL | L76: AUXILIAR DE PATIO JUNIOR | M76: 2155 | N76: 0 | O76: 0 | P76: =N76+O76 -> 0 | Q76: 0 | R76: 0 | S76: 0 | T76: 0 | U76: 0 | V76: 0 | W76: 0 | X76: 0 | Y76: 0 | Z76: 0 | AA76: 0 | AB76: 0 | AC76: 0 | AD76: 0 | AE76: 0 | AF76: 0 | AG76: 0 | AH76: 0 | AI76: 0 | AJ76: 0 | AK76: 0 | AL76: 0 | AM76: 0 | AN76: 0 | AO76: 110.84 | AP76: 0 | AQ76: 0 | AR76: 110.84 | AS76: 0 | AT76: 150 | AU76: 0 | AV76: 0 | AW76: 0 | AX76: 0 | AY76: 0 | AZ76: 0 | BA76: 0 | BB76: 0 | BC76: 0 | BD76: 0 | BE76: 0 | BF76: 1776.54 | BG76: 68.95 | BH76: 1845.49 | BI76: 260.84 | BJ76: 1984.84 | BK76: 0 | BL76: 0 | BM76: 0 | BN76: 0 | BO76: 0 | BP76: 0 | BQ76: 260.84
A77: RAFAEL RAMIRES DE ARAUJO | B77: 46082 | C77: Empregado – Geral | D77: G3S CMATRIZ - CAMPO GRANDE | E77: 20.947.332/0001-95 | F77: OPERACIONAL | G77: PATIO | H77: SELETIVA C GRANDE | I77: 46071 | K77: 1.2.7.3 OPERACIONAL | L77: AUXILIAR DE PATIO JUNIOR | M77: 2155 | N77: 2155 | O77: 0 | P77: =N77+O77 -> 2155 | Q77: 0 | R77: 0 | S77: 0 | T77: 0 | U77: 0 | V77: 0 | W77: 0 | X77: 0 | Y77: 0 | Z77: 0 | AA77: 0 | AB77: 0 | AC77: 0 | AD77: 0 | AE77: 0 | AF77: 0 | AG77: 2155 | AH77: 0 | AI77: 0 | AJ77: 0 | AK77: 0 | AL77: 0 | AM77: 0 | AN77: 0 | AO77: 533.04 | AP77: 0 | AQ77: 0 | AR77: 533.04 | AS77: 0 | AT77: 0 | AU77: 0 | AV77: 0 | AW77: 0 | AX77: 0 | AY77: 0 | AZ77: 0 | BA77: 0 | BB77: 0 | BC77: 0 | BD77: 0 | BE77: 0 | BF77: 0 | BG77: 0 | BH77: 0 | BI77: 2688.04 | BJ77: 1031.63 | BK77: 1656.41 | BL77: 172.4 | BM77: 431 | BN77: 98.59 | BO77: 124.99 | BP77: 826.98 | BQ77: 3515.02
A78: VINICIUS LIMA SALDANHA | B78: 46082 | C78: Empregado – Geral | D78: G3S FL 03 - DOURADOS | E78: 20.947.332/0003-57 | F78: OPERACIONAL | G78: PATIO | H78: SELETIVA DOURADOS | I78: 44700 | K78: 1.2.2.3 OPERACIONAL | L78: GERENTE DE PATIO SENIOR | M78: 3679.83 | N78: 1226.61 | O78: 0 | P78: =N78+O78 -> 1226.61 | Q78: 0 | R78: 6114.99 | S78: 3057.49 | T78: 245.32 | U78: 0 | V78: 367.98 | W78: 0 | X78: 0 | Y78: 0 | Z78: 4.5 | AA78: 1625.4 | AB78: 361.2 | AC78: 0 | AD78: 0 | AE78: 0 | AF78: 0 | AG78: 13003.49 | AH78: 0 | AI78: 0 | AJ78: 0 | AK78: 0 | AL78: 0 | AM78: 0 | AN78: 0 | AO78: 196.71 | AP78: 0 | AQ78: 0 | AR78: 196.71 | AS78: 0 | AT78: 0 | AU78: 0 | AV78: 237.5 | AW78: 0 | AX78: 0 | AY78: 0 | AZ78: 3679.83 | BA78: 0 | BB78: 0 | BC78: 0 | BD78: 0 | BE78: 0 | BF78: 0 | BG78: 0 | BH78: 0 | BI78: 17117.53 | BJ78: 2658.97 | BK78: 5286.08 | BL78: 795.68 | BM78: 2600.7 | BN78: 195.05 | BO78: 754.2 | BP78: 4345.63 | BQ78: 21463.16
A79: LAIS VERON TEIXEIRA RIQUELME | B79: 46082 | C79: Empregado – Geral | D79: G3S FL 03 - DOURADOS | E79: 20.947.332/0003-57 | F79: ADMINISTRATIVO | G79: ATENDIMENTO | H79: SELETIVA DOURADOS | I79: 44769 | K79: 1.2.2.1 ADMINISTRATIVO | L79: AUX ADMINISTRATIVO JUNIOR | M79: 2482.4 | N79: 2482.4 | O79: 0 | P79: =N79+O79 -> 2482.4 | Q79: 0 | R79: 0 | S79: 0 | T79: 0 | U79: 0 | V79: 0 | W79: 0 | X79: 0 | Y79: 0 | Z79: 0 | AA79: 192.22 | AB79: 36.97 | AC79: 0 | AD79: 0 | AE79: 0 | AF79: 248.24 | AG79: 2959.83 | AH79: 0 | AI79: 0 | AJ79: 0 | AK79: 0 | AL79: 0 | AM79: 0 | AN79: 0 | AO79: 196.71 | AP79: 0 | AQ79: 0 | AR79: 196.71 | AS79: 0 | AT79: 0 | AU79: 0 | AV79: 0 | AW79: 0 | AX79: 0 | AY79: 0 | AZ79: 0 | BA79: 0 | BB79: 0 | BC79: 0 | BD79: 0 | BE79: 0 | BF79: 0 | BG79: 0 | BH79: 0 | BI79: 3156.54 | BJ79: 1990.93 | BK79: 1165.61 | BL79: 236.78 | BM79: 591.97 | BN79: 44.39 | BO79: 171.67 | BP79: 1044.81 | BQ79: 4201.35
A80: POLIANA CORREA DA SILVA | B80: 46082 | C80: Empregado – Geral | D80: G3S FL 03 - DOURADOS | E80: 20.947.332/0003-57 | F80: ADMINISTRATIVO | G80: ATENDIMENTO | H80: SELETIVA DOURADOS | I80: 45376 | K80: 1.2.2.1 ADMINISTRATIVO | L80: AUX ADMINISTRATIVO JUNIOR | M80: 2482.4 | N80: 2482.4 | O80: 0 | P80: =N80+O80 -> 2482.4 | Q80: 0 | R80: 0 | S80: 0 | T80: 0 | U80: 0 | V80: 0 | W80: 0 | X80: 0 | Y80: 0 | Z80: 1.88 | AA80: 585.54 | AB80: 112.6 | AC80: 0 | AD80: 0 | AE80: 0 | AF80: 0 | AG80: 3182.42 | AH80: 0 | AI80: 0 | AJ80: 0 | AK80: 0 | AL80: 0 | AM80: 0 | AN80: 0 | AO80: 196.71 | AP80: 0 | AQ80: 0 | AR80: 196.71 | AS80: 0 | AT80: 0 | AU80: 0 | AV80: 0 | AW80: 0 | AX80: 0 | AY80: 0 | AZ80: 0 | BA80: 0 | BB80: 0 | BC80: 0 | BD80: 0 | BE80: 0 | BF80: 0 | BG80: 0 | BH80: 0 | BI80: 3379.13 | BJ80: 1263.47 | BK80: 2115.66 | BL80: 254.59 | BM80: 636.48 | BN80: 47.73 | BO80: 184.58 | BP80: 1123.38 | BQ80: 4502.51
A81: RODOLFO SALU DE OLIVEIRA | B81: 46082 | C81: Empregado – Geral | D81: G3S FL 03 - DOURADOS | E81: 20.947.332/0003-57 | F81: OPERACIONAL | G81: PATIO | H81: SELETIVA DOURADOS | I81: 45733 | K81: 1.2.2.3 OPERACIONAL | L81: MACARIQUEIRO PLENO | M81: 2587.5 | N81: 2587.5 | O81: 0 | P81: =N81+O81 -> 2587.5 | Q81: 0 | R81: 0 | S81: 0 | T81: 0 | U81: 0 | V81: 0 | W81: 0 | X81: 0 | Y81: 0 | Z81: 2.05 | AA81: 0 | AB81: 0 | AC81: 0 | AD81: 0 | AE81: 0 | AF81: 0 | AG81: 2589.55 | AH81: 0 | AI81: 0 | AJ81: 0 | AK81: 0 | AL81: 0 | AM81: 0 | AN81: 0 | AO81: 196.71 | AP81: 0 | AQ81: 0 | AR81: 196.71 | AS81: 0 | AT81: 0 | AU81: 0 | AV81: 0 | AW81: 0 | AX81: 0 | AY81: 0 | AZ81: 0 | BA81: 0 | BB81: 0 | BC81: 0 | BD81: 0 | BE81: 0 | BF81: 0 | BG81: 0 | BH81: 0 | BI81: 2786.26 | BJ81: 1773.88 | BK81: 1012.38 | BL81: 207.16 | BM81: 517.91 | BN81: 38.84 | BO81: 150.19 | BP81: 914.1 | BQ81: 3700.36
A82: GEOVANI RODRIGUES DUTRA | B82: 46082 | C82: Empregado – Geral | D82: G3S FL 03 - DOURADOS | E82: 20.947.332/0003-57 | F82: OPERACIONAL | G82: PATIO | H82: SELETIVA DOURADOS | I82: 46048 | K82: 1.2.2.3 OPERACIONAL | L82: MACARIQUEIRO PLENO | M82: 2587.5 | N82: 2587.5 | O82: 0 | P82: =N82+O82 -> 2587.5 | Q82: 0 | R82: 0 | S82: 0 | T82: 0 | U82: 0 | V82: 0 | W82: 0 | X82: 0 | Y82: 0 | Z82: 0 | AA82: 0 | AB82: 0 | AC82: 0 | AD82: 0 | AE82: 0 | AF82: 0 | AG82: 2587.5 | AH82: 0 | AI82: 0 | AJ82: 0 | AK82: 0 | AL82: 0 | AM82: 0 | AN82: 0 | AO82: 196.71 | AP82: 0 | AQ82: 0 | AR82: 196.71 | AS82: 0 | AT82: 0 | AU82: 0 | AV82: 0 | AW82: 0 | AX82: 0 | AY82: 0 | AZ82: 0 | BA82: 0 | BB82: 0 | BC82: 0 | BD82: 0 | BE82: 0 | BF82: 0 | BG82: 0 | BH82: 0 | BI82: 2784.21 | BJ82: 2015.88 | BK82: 768.33 | BL82: 164.15 | BM82: 517.5 | BN82: 38.81 | BO82: 150.07 | BP82: 870.53 | BQ82: 3654.74
A83: WAGNER DARCI DOS SANTOS | B83: 46082 | C83: Empregado – Geral | D83: G3S FL 04 - PRES PRUD | E83: 20.947.332/0004-38 | F83: ADMINISTRATIVO | G83: SERVIÇOS GERAIS | H83: SELETIVA PRESIDENTE PRUDENTE | I83: 40672 | L83: SERVICOS GERAIS (COMERCIO) | M83: 2098 | N83: 0 | O83: 0 | P83: =N83+O83 -> 0 | Q83: 0 | R83: 0 | S83: 0 | T83: 0 | U83: 0 | V83: 0 | W83: 0 | X83: 0 | Y83: 0 | Z83: 0 | AA83: 0 | AB83: 0 | AC83: 0 | AD83: 0 | AE83: 0 | AF83: 0 | AG83: 0 | AH83: 0 | AI83: 0 | AJ83: 0 | AK83: 0 | AL83: 0 | AM83: 0 | AN83: 0 | AO83: 0 | AP83: 0 | AQ83: 0 | AR83: 0 | AS83: 0 | AT83: 0 | AU83: 0 | AV83: 0 | AW83: 0 | AX83: 0 | AY83: 0 | AZ83: 0 | BA83: 0 | BB83: 0 | BC83: 0 | BD83: 0 | BE83: 0 | BF83: 0 | BG83: 0 | BH83: 0 | BI83: 0 | BJ83: 0 | BK83: 0 | BL83: 0 | BM83: 0 | BN83: 0 | BO83: 0 | BP83: 0 | BQ83: 0
A84: MARCELO BARBOSA SARTO | B84: 46082 | C84: Empregado – Geral | D84: G3S FL 04 - PRES PRUD | E84: 20.947.332/0004-38 | F84: LOGISTICA | G84: TRANSPORTE | H84: SELETIVA PRESIDENTE PRUDENTE | I84: 41074 | L84: MOTORISTA CARRETEIRO | M84: 2538.35 | N84: 0 | O84: 0 | P84: =N84+O84 -> 0 | Q84: 0 | R84: 0 | S84: 0 | T84: 0 | U84: 0 | V84: 0 | W84: 0 | X84: 0 | Y84: 0 | Z84: 0 | AA84: 0 | AB84: 0 | AC84: 0 | AD84: 0 | AE84: 0 | AF84: 0 | AG84: 0 | AH84: 0 | AI84: 0 | AJ84: 0 | AK84: 0 | AL84: 0 | AM84: 0 | AN84: 0 | AO84: 0 | AP84: 0 | AQ84: 0 | AR84: 0 | AS84: 0 | AT84: 0 | AU84: 0 | AV84: 0 | AW84: 0 | AX84: 0 | AY84: 0 | AZ84: 0 | BA84: 0 | BB84: 0 | BC84: 0 | BD84: 0 | BE84: 0 | BF84: 0 | BG84: 0 | BH84: 0 | BI84: 0 | BJ84: 59.06 | BK84: 0 | BL84: 0 | BM84: 0 | BN84: 0 | BO84: 0 | BP84: 0 | BQ84: 0
A85: NIVALDO MATEUS | B85: 46082 | C85: Empregado – Geral | D85: G3S FL 04 - PRES PRUD | E85: 20.947.332/0004-38 | F85: OPERACIONAL | G85: PATIO | H85: SELETIVA PRESIDENTE PRUDENTE | I85: 44166 | K85: 1.2.5.3 OPERACIONAL | L85: GERENTE DE PATIO SENIOR PP | M85: 3679.83 | N85: 3679.83 | O85: 0 | P85: =N85+O85 -> 3679.83 | Q85: 0 | R85: 0 | S85: 0 | T85: 735.97 | U85: 0 | V85: 1103.95 | W85: 0 | X85: 0 | Y85: 0 | Z85: 0 | AA85: 176.63 | AB85: 33.97 | AC85: 0 | AD85: 0 | AE85: 0 | AF85: 0 | AG85: 5730.35 | AH85: 0 | AI85: 0 | AJ85: 0 | AK85: 0 | AL85: 0 | AM85: 0 | AN85: 0 | AO85: 579.34 | AP85: 450 | AQ85: 0 | AR85: 1029.34 | AS85: 0 | AT85: 0 | AU85: 0 | AV85: 2016 | AW85: 0 | AX85: 0 | AY85: 0 | AZ85: 0 | BA85: 0 | BB85: 0 | BC85: 0 | BD85: 0 | BE85: 0 | BF85: 0 | BG85: 0 | BH85: 0 | BI85: 8775.69 | BJ85: 4235.55 | BK85: 4540.14 | BL85: 458.42 | BM85: 1146.07 | BN85: 85.95 | BO85: 332.36 | BP85: 2022.8 | BQ85: 10798.49
A86: LUCIMARA PAIZ DE OLIVEIRA | B86: 46082 | C86: Empregado – Geral | D86: G3S FL 04 - PRES PRUD | E86: 20.947.332/0004-38 | F86: ADMINISTRATIVO | G86: ADMINISTRATIVO | H86: SELETIVA PRESIDENTE PRUDENTE | I86: 45600 | K86: 1.2.5.1 ADMINISTRATIVO | L86: FAXINEIRO (EMPRESA) | M86: 1849.8 | N86: 1849.8 | O86: 0 | P86: =N86+O86 -> 1849.8 | Q86: 0 | R86: 0 | S86: 0 | T86: 0 | U86: 0 | V86: 0 | W86: 0 | X86: 0 | Y86: 0 | Z86: 0 | AA86: 0 | AB86: 0 | AC86: 0 | AD86: 0 | AE86: 0 | AF86: 0 | AG86: 1849.8 | AH86: 0 | AI86: 0 | AJ86: 0 | AK86: 0 | AL86: 0 | AM86: 0 | AN86: 0 | AO86: 0 | AP86: 0 | AQ86: 0 | AR86: 0 | AS86: 0 | AT86: 0 | AU86: 0 | AV86: 0 | AW86: 0 | AX86: 0 | AY86: 0 | AZ86: 0 | BA86: 0 | BB86: 0 | BC86: 0 | BD86: 0 | BE86: 0 | BF86: 0 | BG86: 0 | BH86: 0 | BI86: 1849.8 | BJ86: 882.16 | BK86: 967.64 | BL86: 147.98 | BM86: 369.96 | BN86: 27.74 | BO86: 107.28 | BP86: 652.96 | BQ86: 2502.76
A87: ANTONIO ANACLETO DE OLIVEIRA | B87: 46082 | C87: Empregado – Geral | D87: G3S FL 04 - PRES PRUD | E87: 20.947.332/0004-38 | F87: OPERACIONAL | G87: PATIO | H87: SELETIVA PRESIDENTE PRUDENTE | I87: 40118 | K87: 1.2.5.3 OPERACIONAL | L87: AUXILIAR DE PATIO SENIOR | M87: 2600 | N87: 2600 | O87: 0 | P87: =N87+O87 -> 2600 | Q87: 0 | R87: 0 | S87: 0 | T87: 0 | U87: 0 | V87: 0 | W87: 0 | X87: 0 | Y87: 0 | Z87: 0 | AA87: 0 | AB87: 0 | AC87: 0 | AD87: 0 | AE87: 0 | AF87: 0 | AG87: 2600 | AH87: 0 | AI87: 0 | AJ87: 0 | AK87: 0 | AL87: 0 | AM87: 0 | AN87: 0 | AO87: 579.34 | AP87: 1080 | AQ87: 0 | AR87: 1659.34 | AS87: 0 | AT87: 450 | AU87: 0 | AV87: 0 | AW87: 0 | AX87: 0 | AY87: 0 | AZ87: 0 | BA87: 0 | BB87: 0 | BC87: 0 | BD87: 0 | BE87: 0 | BF87: 0 | BG87: 0 | BH87: 0 | BI87: 4709.34 | BJ87: 261.48 | BK87: 4647.86 | BL87: 224 | BM87: 520 | BN87: 39 | BO87: 150.8 | BP87: 933.8 | BQ87: 5643.14
A88: MARCOS MEDEIROS | B88: 46082 | C88: Empregado – Geral | D88: G3S FL 04 - PRES PRUD | E88: 20.947.332/0004-38 | F88: OPERACIONAL | G88: PATIO | H88: SELETIVA PRESIDENTE PRUDENTE | I88: 44228 | K88: 1.2.5.3 OPERACIONAL | L88: SOLDADOR MAÇARIQUEIRO | M88: 2893.8 | N88: 2893.8 | O88: 0 | P88: =N88+O88 -> 2893.8 | Q88: 0 | R88: 0 | S88: 0 | T88: 0 | U88: 324.2 | V88: 0 | W88: 0 | X88: 0 | Y88: 0 | Z88: 0 | AA88: 74.89 | AB88: 14.4 | AC88: 0 | AD88: 0 | AE88: 0 | AF88: 0 | AG88: 3307.29 | AH88: 0 | AI88: 0 | AJ88: 0 | AK88: 0 | AL88: 0 | AM88: 0 | AN88: 0 | AO88: 579.34 | AP88: 515 | AQ88: 0 | AR88: 1094.34 | AS88: 0 | AT88: 0 | AU88: 0 | AV88: 0 | AW88: 0 | AX88: 0 | AY88: 0 | AZ88: 0 | BA88: 0 | BB88: 0 | BC88: 0 | BD88: 0 | BE88: 0 | BF88: 0 | BG88: 0 | BH88: 0 | BI88: 4401.63 | BJ88: 1945.47 | BK88: 2456.16 | BL88: 264.58 | BM88: 661.46 | BN88: 49.6 | BO88: 191.82 | BP88: 1167.46 | BQ88: 5569.09
A89: ANDRESSA MEIRIELLE DE OLIVEIRA TOKAWA | B89: 46082 | C89: Empregado – Geral | D89: G3S FL 04 - PRES PRUD | E89: 20.947.332/0004-38 | F89: ADMINISTRATIVO | G89: ATENDIMENTO | H89: SELETIVA PRESIDENTE PRUDENTE | I89: 44635 | K89: 1.2.5.1 ADMINISTRATIVO | L89: AUX ADMINISTRATIVO SENIOR | M89: 2950 | N89: 2950 | O89: 0 | P89: =N89+O89 -> 2950 | Q89: 0 | R89: 0 | S89: 0 | T89: 0 | U89: 0 | V89: 0 | W89: 0 | X89: 0 | Y89: 0 | Z89: 0 | AA89: 0 | AB89: 0 | AC89: 0 | AD89: 0 | AE89: 0 | AF89: 0 | AG89: 2950 | AH89: 0 | AI89: 0 | AJ89: 0 | AK89: 0 | AL89: 0 | AM89: 0 | AN89: 0 | AO89: 904.34 | AP89: 0 | AQ89: 0 | AR89: 904.34 | AS89: 0 | AT89: 0 | AU89: 0 | AV89: 0 | AW89: 0 | AX89: 0 | AY89: 0 | AZ89: 0 | BA89: 0 | BB89: 0 | BC89: 0 | BD89: 0 | BE89: 0 | BF89: 0 | BG89: 0 | BH89: 0 | BI89: 3854.34 | BJ89: 1463.83 | BK89: 2390.51 | BL89: 236 | BM89: 590 | BN89: 44.25 | BO89: 171.1 | BP89: 1041.35 | BQ89: 4895.69
A90: ALESSANDRA ARAUJO MOURA | B90: 46082 | C90: Empregado – Geral | D90: G3S FL 04 - PRES PRUD | E90: 20.947.332/0004-38 | F90: ADMINISTRATIVO | G90: ATENDIMENTO | H90: SELETIVA CORPORATIVO SUCATA | I90: 44783 | K90: 1.2.1.1 APOIO | L90: SUPERVISOR(A) ADMINISTRATIVO(A) | M90: 3392 | N90: 3392 | O90: 0 | P90: =N90+O90 -> 3392 | Q90: 0 | R90: 0 | S90: 0 | T90: 0 | U90: 0 | V90: 0 | W90: 1356.8 | X90: 0 | Y90: 0 | Z90: 0 | AA90: 0 | AB90: 0 | AC90: 0 | AD90: 0 | AE90: 0 | AF90: 0 | AG90: 4748.8 | AH90: 0 | AI90: 0 | AJ90: 0 | AK90: 0 | AL90: 0 | AM90: 0 | AN90: 0 | AO90: 904.34 | AP90: 0 | AQ90: 0 | AR90: 904.34 | AS90: 0 | AT90: 0 | AU90: 0 | AV90: 0 | AW90: 0 | AX90: 0 | AY90: 0 | AZ90: 0 | BA90: 0 | BB90: 0 | BC90: 0 | BD90: 0 | BE90: 0 | BF90: 0 | BG90: 0 | BH90: 0 | BI90: 5653.14 | BJ90: 1863.33 | BK90: 3789.81 | BL90: 379.9 | BM90: 949.76 | BN90: 71.23 | BO90: 275.43 | BP90: 1676.32 | BQ90: 7329.46
A91: MAURICIO ANTONIO SALETE | B91: 46082 | C91: Empregado – Geral | D91: G3S FL 04 - PRES PRUD | E91: 20.947.332/0004-38 | F91: OPERACIONAL | G91: PATIO | H91: SELETIVA PRESIDENTE PRUDENTE | I91: 44942 | K91: 1.2.5.3 OPERACIONAL | L91: GERENTE DE PATIO SENIOR | M91: 3679.83 | N91: 3679.83 | O91: 0 | P91: =N91+O91 -> 3679.83 | Q91: 0 | R91: 0 | S91: 0 | T91: 0 | U91: 0 | V91: 1103.95 | W91: 0 | X91: 0 | Y91: 0 | Z91: 0 | AA91: 290.51 | AB91: 55.87 | AC91: 0 | AD91: 0 | AE91: 0 | AF91: 0 | AG91: 5130.16 | AH91: 0 | AI91: 0 | AJ91: 0 | AK91: 0 | AL91: 0 | AM91: 0 | AN91: 0 | AO91: 579.34 | AP91: 0 | AQ91: 0 | AR91: 579.34 | AS91: 0 | AT91: 0 | AU91: 0 | AV91: 0 | AW91: 0 | AX91: 0 | AY91: 0 | AZ91: 0 | BA91: 0 | BB91: 0 | BC91: 0 | BD91: 0 | BE91: 0 | BF91: 0 | BG91: 0 | BH91: 0 | BI91: 5709.5 | BJ91: 2031.72 | BK91: 3677.78 | BL91: 410.41 | BM91: 1026.03 | BN91: 76.95 | BO91: 297.54 | BP91: 1810.93 | BQ91: 7520.43
A92: JOSE ANTONIO CAETANO | B92: 46082 | C92: Empregado – Geral | D92: G3S FL 04 - PRES PRUD | E92: 20.947.332/0004-38 | F92: OPERACIONAL | G92: PATIO | H92: SELETIVA PRESIDENTE PRUDENTE | I92: 43906 | K92: 1.2.5.3 OPERACIONAL | L92: CLASSIFICADOR SENIOR | M92: 2967.69 | N92: 2967.69 | O92: 0 | P92: =N92+O92 -> 2967.69 | Q92: 0 | R92: 0 | S92: 0 | T92: 0 | U92: 0 | V92: 0 | W92: 0 | X92: 0 | Y92: 0 | Z92: 0 | AA92: 0 | AB92: 0 | AC92: 0 | AD92: 0 | AE92: 0 | AF92: 0 | AG92: 2967.69 | AH92: 0 | AI92: 0 | AJ92: 0 | AK92: 0 | AL92: 0 | AM92: 0 | AN92: 0 | AO92: 579.34 | AP92: 200 | AQ92: 0 | AR92: 779.34 | AS92: 0 | AT92: 0 | AU92: 0 | AV92: 0 | AW92: 0 | AX92: 0 | AY92: 0 | AZ92: 0 | BA92: 0 | BB92: 0 | BC92: 0 | BD92: 0 | BE92: 0 | BF92: 0 | BG92: 0 | BH92: 0 | BI92: 3747.03 | BJ92: 2422.81 | BK92: 1324.22 | BL92: 237.41 | BM92: 593.54 | BN92: 44.51 | BO92: 172.12 | BP92: 1047.58 | BQ92: 4794.61
A93: ANDERSON RODRIGO FERREIRA DE LIMA | B93: 46082 | C93: Empregado – Geral | D93: G3S FL 04 - PRES PRUD | E93: 20.947.332/0004-38 | F93: OPERACIONAL | G93: PATIO | H93: SELETIVA PRESIDENTE PRUDENTE | I93: 46064 | K93: 1.2.5.3 OPERACIONAL | L93: MACARIQUEIRO PLENO | M93: 2587.5 | N93: 2587.5 | O93: 0 | P93: =N93+O93 -> 2587.5 | Q93: 0 | R93: 0 | S93: 0 | T93: 0 | U93: 0 | V93: 0 | W93: 0 | X93: 0 | Y93: 0 | Z93: 0 | AA93: 0 | AB93: 0 | AC93: 0 | AD93: 0 | AE93: 0 | AF93: 0 | AG93: 2587.5 | AH93: 0 | AI93: 0 | AJ93: 0 | AK93: 0 | AL93: 0 | AM93: 0 | AN93: 0 | AO93: 579.34 | AP93: 0 | AQ93: 0 | AR93: 579.34 | AS93: 0 | AT93: 0 | AU93: 0 | AV93: 0 | AW93: 0 | AX93: 0 | AY93: 0 | AZ93: 0 | BA93: 0 | BB93: 0 | BC93: 0 | BD93: 0 | BE93: 0 | BF93: 0 | BG93: 0 | BH93: 0 | BI93: 3166.84 | BJ93: 1277.19 | BK93: 1889.65 | BL93: 207 | BM93: 517.5 | BN93: 38.81 | BO93: 150.07 | BP93: 913.38 | BQ93: 4080.22
A94: REGINALDO DELA COSTA | B94: 46082 | C94: Empregado – Geral | D94: G3S FL 05 - PRES PRUD | E94: 20.947.332/0005-19 | F94: LOGISTICA | G94: TRANSPORTE | H94: BRACOFER | I94: 43234 | K94: 1.3.1.4 LOGISTICA | L94: MOTORISTA TRUCK MANTENEDOR SENIOR | M94: 2700 | N94: 2700 | O94: 0 | P94: =N94+O94 -> 2700 | Q94: 0 | R94: 0 | S94: 0 | T94: 540 | U94: 0 | V94: 0 | W94: 0 | X94: 0 | Y94: 135 | Z94: 0 | AA94: 838.76 | AB94: 161.3 | AC94: 0 | AD94: 0 | AE94: 0 | AF94: 0 | AG94: 4375.06 | AH94: 0 | AI94: 0 | AJ94: 0 | AK94: 0 | AL94: 0 | AM94: 0 | AN94: 0 | AO94: 0 | AP94: 0 | AQ94: 0 | AR94: 0 | AS94: 0 | AT94: 0 | AU94: 0 | AV94: 0 | AW94: 0 | AX94: 0 | AY94: 0 | AZ94: 0 | BA94: 0 | BB94: 0 | BC94: 0 | BD94: 0 | BE94: 0 | BF94: 0 | BG94: 0 | BH94: 0 | BI94: 4375.06 | BJ94: 1530.46 | BK94: 2844.6 | BL94: 350 | BM94: 875.01 | BN94: 65.62 | BO94: 253.75 | BP94: 1544.38 | BQ94: 5919.44
A95: ROBERTO DOS SANTOS | B95: 46082 | C95: Empregado – Geral | D95: G3S FL 05 - PRES PRUD | E95: 20.947.332/0005-19 | F95: COMERCIAL | G95: VENDAS | H95: BRACOFER | I95: 43761 | K95: 1.3.1.2 COMERCIAL | L95: VENDEDOR(A) | M95: 0 | N95: 0 | O95: 0 | P95: =N95+O95 -> 0 | Q95: 0 | R95: 0 | S95: 0 | T95: 0 | U95: 0 | V95: 0 | W95: 0 | X95: 0 | Y95: 0 | Z95: 0 | AA95: 0 | AB95: 0 | AC95: 5669.28 | AD95: 1090.25 | AE95: 0 | AF95: 0 | AG95: 6759.53 | AH95: 0 | AI95: 0 | AJ95: 0 | AK95: 0 | AL95: 0 | AM95: 0 | AN95: 0 | AO95: 0 | AP95: 0 | AQ95: 0 | AR95: 0 | AS95: 0 | AT95: 0 | AU95: 0 | AV95: 0 | AW95: 0 | AX95: 0 | AY95: 0 | AZ95: 0 | BA95: 0 | BB95: 0 | BC95: 0 | BD95: 0 | BE95: 0 | BF95: 0 | BG95: 0 | BH95: 0 | BI95: 6759.53 | BJ95: 2002.93 | BK95: 4756.6 | BL95: 540.76 | BM95: 1351.91 | BN95: 101.39 | BO95: 392.05 | BP95: 2386.11 | BQ95: 9145.64
A96: PAULO DIAS CORREA | B96: 46082 | C96: Empregado – Geral | D96: G3S FL 05 - PRES PRUD | E96: 20.947.332/0005-19 | F96: LOGISTICA | G96: TRANSPORTE | H96: BRACOFER | I96: 43888 | K96: 1.3.1.4 LOGISTICA | L96: MOTORISTA TRUCK MANTENEDOR SENIOR | M96: 2700 | N96: 2700 | O96: 0 | P96: =N96+O96 -> 2700 | Q96: 0 | R96: 0 | S96: 0 | T96: 540 | U96: 0 | V96: 0 | W96: 0 | X96: 0 | Y96: 135 | Z96: 0 | AA96: 64.82 | AB96: 12.47 | AC96: 0 | AD96: 0 | AE96: 0 | AF96: 0 | AG96: 3452.29 | AH96: 0 | AI96: 0 | AJ96: 0 | AK96: 0 | AL96: 0 | AM96: 0 | AN96: 0 | AO96: 0 | AP96: 612 | AQ96: 0 | AR96: 612 | AS96: 0 | AT96: 0 | AU96: 0 | AV96: 1323 | AW96: 0 | AX96: 0 | AY96: 0 | AZ96: 0 | BA96: 0 | BB96: 0 | BC96: 0 | BD96: 0 | BE96: 0 | BF96: 0 | BG96: 0 | BH96: 0 | BI96: 5387.29 | BJ96: 2449.22 | BK96: 2938.07 | BL96: 276.18 | BM96: 690.46 | BN96: 51.78 | BO96: 200.23 | BP96: 1218.65 | BQ96: 6605.94
... A103: LUIS AUGUSTO DUARTE SILVA | B103: 46082 | C103: Empregado – Geral | D103: G3S FL 05 - PRES PRUD | E103: 20.947.332/0005-19 | F103: COMERCIAL | G103: VENDAS | H103: BRACOFER | I103: 45671 | K103: 1.3.1.2 COMERCIAL | L103: VENDEDOR(A) | M103: 0 | N103: 0 | O103: 0 | P103: =N103+O103 -> 0 | Q103: 0 | R103: 0 | S103: 0 | T103: 0 | U103: 0 | V103: 0 | W103: 0 | X103: 0 | Y103: 0 | Z103: 0 | AA103: 0 | AB103: 0 | AC103: 3877.78 | AD103: 745.73 | AE103: 0 | AF103: 0 | AG103: 4623.51 | AH103: 0 | AI103: 0 | AJ103: 0 | AK103: 0 | AL103: 0 | AM103: 0 | AN103: 0 | AO103: 0 | AP103: 0 | AQ103: 0 | AR103: 0 | AS103: 0 | AT103: 0 | AU103: 0 | AV103: 0 | AW103: 0 | AX103: 0 | AY103: 0 | AZ103: 0 | BA103: 0 | BB103: 0 | BC103: 0 | BD103: 0 | BE103: 0 | BF103: 0 | BG103: 0 | BH103: 0 | BI103: 4623.51 | BJ103: 2734.1 | BK103: 1889.41 | BL103: 369.88 | BM103: 924.7 | BN103: 69.35 | BO103: 268.16 | BP103: 1632.09 | BQ103: 6255.6
A104: MARCOS ROBERTO DA SILVA MARTINS | B104: 46082 | C104: Empregado – Geral | D104: G3S FL 05 - PRES PRUD | E104: 20.947.332/0005-19 | F104: LOGISTICA | G104: TRANSPORTE | H104: BRACOFER | I104: 45701 | J104: 46093 | K104: 1.3.1.4 LOGISTICA | L104: MOTORISTA TRUCK MANTENEDOR JUNIOR | M104: 2308.81 | N104: 0 | O104: 0 | P104: =N104+O104 -> 0 | Q104: 0 | R104: 0 | S104: 0 | T104: 182.92 | U104: 0 | V104: 0 | W104: 0 | X104: 0 | Y104: 0 | Z104: 0 | AA104: 70.52 | AB104: 14.1 | AC104: 0 | AD104: 0 | AE104: 0 | AF104: 0 | AG104: 267.54 | AH104: 0 | AI104: 0 | AJ104: 0 | AK104: 0 | AL104: 0 | AM104: 0 | AN104: 0 | AO104: 0 | AP104: 0 | AQ104: 0 | AR104: 0 | AS104: 0 | AT104: 500 | AU104: 0 | AV104: 0 | AW104: 0 | AX104: 54.03 | AY104: 0 | AZ104: 0 | BA104: 0 | BB104: 0 | BC104: 0 | BD104: 0 | BE104: 0 | BF104: 7656.02 | BG104: 303.64 | BH104: 7959.66 | BI104: 821.57 | BJ104: 8788.28 | BK104: 0 | BL104: 0 | BM104: 53.51 | BN104: 4.01 | BO104: 15.51 | BP104: 73.03 | BQ104: 894.6
A105: LUIS HENRIQUE SEMENSATO | B105: 46082 | C105: Empregado – Geral | D105: G3S FL 05 - PRES PRUD | E105: 20.947.332/0005-19 | F105: OPERACIONAL | G105: CORTE E DOBRA | H105: BRACOFER | I105: 45845 | K105: 1.3.1.5 CORTE E DOBRA | L105: AUXILIAR DE PATIO JUNIOR | M105: 2155 | N105: 2155 | O105: 0 | P105: =N105+O105 -> 2155 | Q105: 0 | R105: 0 | S105: 0 | T105: 0 | U105: 0 | V105: 0 | W105: 0 | X105: 0 | Y105: 0 | Z105: 0 | AA105: 223.07 | AB105: 42.9 | AC105: 0 | AD105: 0 | AE105: 0 | AF105: 0 | AG105: 2420.97 | AH105: 0 | AI105: 0 | AJ105: 0 | AK105: 0 | AL105: 0 | AM105: 0 | AN105: 0 | AO105: 0 | AP105: 350 | AQ105: 0 | AR105: 350 | AS105: 0 | AT105: 0 | AU105: 0 | AV105: 0 | AW105: 0 | AX105: 0 | AY105: 0 | AZ105: 0 | BA105: 0 | BB105: 0 | BC105: 0 | BD105: 0 | BE105: 0 | BF105: 0 | BG105: 0 | BH105: 0 | BI105: 2770.97 | BJ105: 1587.03 | BK105: 1183.94 | BL105: 193.67 | BM105: 484.19 | BN105: 36.31 | BO105: 140.41 | BP105: 854.58 | BQ105: 3625.55
A106: ANDRESSA FRANCINI CRUZ DE SOUZA | B106: 46082 | C106: Empregado – Geral | D106: G3S FL 05 - PRES PRUD | E106: 20.947.332/0005-19 | F106: TRANSMOVE | G106: ADMINISTRATIVO | H106: TRANSMOVE GSL | I106: 45925 | K106: 1.4.1.2 ADMINISTRATIVO | L106: SUPERVISOR(A) DE LOGISTICA | M106: 3500 | N106: 3500 | O106: 0 | P106: =N106+O106 -> 3500 | Q106: 0 | R106: 0 | S106: 0 | T106: 0 | U106: 0 | V106: 0 | W106: 1400 | X106: 0 | Y106: 0 | Z106: 0 | AA106: 0 | AB106: 0 | AC106: 0 | AD106: 0 | AE106: 0 | AF106: 0 | AG106: 4900 | AH106: 0 | AI106: 0 | AJ106: 0 | AK106: 0 | AL106: 0 | AM106: 0 | AN106: 0 | AO106: 0 | AP106: 100 | AQ106: 0 | AR106: 100 | AS106: 0 | AT106: 0 | AU106: 0 | AV106: 0 | AW106: 0 | AX106: 0 | AY106: 0 | AZ106: 0 | BA106: 0 | BB106: 0 | BC106: 0 | BD106: 0 | BE106: 0 | BF106: 0 | BG106: 0 | BH106: 0 | BI106: 5000 | BJ106: 527.5 | BK106: 4472.5 | BL106: 392 | BM106: 980 | BN106: 73.5 | BO106: 284.2 | BP106: 1729.7 | BQ106: 6729.7
A107: MURILO LIMA DE CARVALHO SILVA | B107: 46082 | C107: Empregado – Geral | D107: G3S FL 05 - PRES PRUD | E107: 20.947.332/0005-19 | F107: ADMINISTRATIVO | G107: FINANCEIRO | H107: BRACOFER | I107: 45962 | K107: 1.3.1.1 ADMINISTRATIVO | L107: AUXILIAR FINANCEIRO | M107: 2098 | N107: 2098 | O107: 0 | P107: =N107+O107 -> 2098 | Q107: 0 | R107: 0 | S107: 0 | T107: 0 | U107: 0 | V107: 0 | W107: 0 | X107: 0 | Y107: 0 | Z107: 0 | AA107: 131.48 | AB107: 25.28 | AC107: 0 | AD107: 0 | AE107: 0 | AF107: 0 | AG107: 2254.76 | AH107: 0 | AI107: 0 | AJ107: 0 | AK107: 0 | AL107: 0 | AM107: 0 | AN107: 0 | AO107: 0 | AP107: 0 | AQ107: 0 | AR107: 0 | AS107: 0 | AT107: 0 | AU107: 0 | AV107: 0 | AW107: 0 | AX107: 0 | AY107: 0 | AZ107: 0 | BA107: 0 | BB107: 0 | BC107: 0 | BD107: 0 | BE107: 0 | BF107: 0 | BG107: 0 | BH107: 0 | BI107: 2254.76 | BJ107: 211.33 | BK107: 2043.43 | BL107: 180.07 | BM107: 450.95 | BN107: 33.82 | BO107: 130.77 | BP107: 795.61 | BQ107: 3050.37
A108: LUIS DOUGLAS SANTOS BRAS | B108: 46082 | C108: Empregado – Geral | D108: G3S FL 05 - PRES PRUD | E108: 20.947.332/0005-19 | F108: OPERACIONAL | G108: CORTE E DOBRA | H108: BRACOFER | I108: 45966 | K108: 1.3.1.5 CORTE E DOBRA | L108: AUXILIAR DE PATIO JUNIOR | M108: 2155 | N108: 2155 | O108: 0 | P108: =N108+O108 -> 2155 | Q108: 0 | R108: 0 | S108: 0 | T108: 0 | U108: 0 | V108: 0 | W108: 0 | X108: 0 | Y108: 0 | Z108: 0 | AA108: 173.71 | AB108: 33.41 | AC108: 0 | AD108: 0 | AE108: 0 | AF108: 0 | AG108: 2362.12 | AH108: 0 | AI108: 0 | AJ108: 0 | AK108: 0 | AL108: 0 | AM108: 0 | AN108: 0 | AO108: 0 | AP108: 350 | AQ108: 0 | AR108: 350 | AS108: 0 | AT108: 0 | AU108: 0 | AV108: 0 | AW108: 0 | AX108: 0 | AY108: 0 | AZ108: 0 | BA108: 0 | BB108: 0 | BC108: 0 | BD108: 0 | BE108: 0 | BF108: 0 | BG108: 0 | BH108: 0 | BI108: 2712.12 | BJ108: 1193.28 | BK108: 1518.84 | BL108: 188.96 | BM108: 472.42 | BN108: 35.43 | BO108: 137 | BP108: 833.81 | BQ108: 3545.93
A109: EDUARDO SOARES E SILVA | B109: 46082 | C109: Empregado – Geral | D109: G3S FL 05 - PRES PRUD | E109: 20.947.332/0005-19 | F109: OPERACIONAL | G109: CORTE E DOBRA | H109: BRACOFER | I109: 45979 | K109: 1.3.1.5 CORTE E DOBRA | L109: AUXILIAR DE PATIO JUNIOR | M109: 2155 | N109: 2155 | O109: 0 | P109: =N109+O109 -> 2155 | Q109: 0 | R109: 0 | S109: 0 | T109: 0 | U109: 0 | V109: 0 | W109: 0 | X109: 0 | Y109: 0 | Z109: 0 | AA109: 339.58 | AB109: 65.3 | AC109: 0 | AD109: 0 | AE109: 0 | AF109: 0 | AG109: 2559.88 | AH109: 0 | AI109: 0 | AJ109: 0 | AK109: 0 | AL109: 0 | AM109: 0 | AN109: 0 | AO109: 0 | AP109: 350 | AQ109: 0 | AR109: 350 | AS109: 0 | AT109: 0 | AU109: 0 | AV109: 0 | AW109: 0 | AX109: 0 | AY109: 0 | AZ109: 0 | BA109: 0 | BB109: 0 | BC109: 0 | BD109: 0 | BE109: 0 | BF109: 0 | BG109: 0 | BH109: 0 | BI109: 2909.88 | BJ109: 239.34 | BK109: 2670.54 | BL109: 204.79 | BM109: 511.98 | BN109: 38.39 | BO109: 148.47 | BP109: 903.63 | BQ109: 3813.51
A110: JUNIOR CESAR SOARES | B110: 46082 | C110: Empregado – Geral | D110: G3S FL 05 - PRES PRUD | E110: 20.947.332/0005-19 | F110: COMERCIAL | G110: VENDAS | H110: BRACOFER | I110: 46048 | J110: 46092 | K110: 1.3.1.2 COMERCIAL | L110: VENDEDOR INTERNO SENIOR | M110: 3000 | N110: 0 | O110: 0 | P110: =N110+O110 -> 0 | Q110: 0 | R110: 0 | S110: 0 | T110: 0 | U110: 0 | V110: 0 | W110: 0 | X110: 0 | Y110: 0 | Z110: 0 | AA110: 0 | AB110: 0 | AC110: 0 | AD110: 0 | AE110: 0 | AF110: 0 | AG110: 0 | AH110: 0 | AI110: 0 | AJ110: 0 | AK110: 0 | AL110: 0 | AM110: 0 | AN110: 0 | AO110: 0 | AP110: 0 | AQ110: 0 | AR110: 0 | AS110: 0 | AT110: 183.33 | AU110: 0 | AV110: 0 | AW110: 0 | AX110: 0 | AY110: 0 | AZ110: 0 | BA110: 0 | BB110: 0 | BC110: 0 | BD110: 0 | BE110: 0 | BF110: 1726.41 | BG110: 0 | BH110: 1726.41 | BI110: 183.33 | BJ110: 1866.66 | BK110: 0 | BL110: 88 | BM110: 0 | BN110: 0 | BO110: 0 | BP110: 88 | BQ110: 271.33
A111: GABRIELA BARBOSA FONTE BASSO | B111: 46082 | C111: Empregado – Geral | D111: G3S FL 05 - PRES PRUD | E111: 20.947.332/0005-19 | F111: COMERCIAL | G111: VENDAS | H111: BRACOFER | I111: 46050 | K111: 1.3.1.2 COMERCIAL | L111: VENDEDOR INTERNO PLENO | M111: 2500 | N111: 2250 | O111: 250 | P111: =N111+O111 -> 2500 | Q111: 0 | R111: 0 | S111: 0 | T111: 0 | U111: 0 | V111: 0 | W111: 0 | X111: 0 | Y111: 0 | Z111: 0 | AA111: 0 | AB111: 0 | AC111: 0 | AD111: 0 | AE111: 0 | AF111: 0 | AG111: 2500 | AH111: 0 | AI111: 0 | AJ111: 0 | AK111: 0 | AL111: 0 | AM111: 0 | AN111: 0 | AO111: 0 | AP111: 0 | AQ111: 0 | AR111: 0 | AS111: 0 | AT111: 0 | AU111: 0 | AV111: 0 | AW111: 0 | AX111: 0 | AY111: 0 | AZ111: 0 | BA111: 0 | BB111: 0 | BC111: 0 | BD111: 0 | BE111: 0 | BF111: 0 | BG111: 0 | BH111: 0 | BI111: 2500 | BJ111: 233.18 | BK111: 2266.82 | BL111: 200 | BM111: 500 | BN111: 37.5 | BO111: 145 | BP111: 882.5 | BQ111: 3382.5
A112: JOAO PAULO BENEVENTO NETO | B112: 46082 | C112: Empregado – Geral | D112: G3S FL 05 - PRES PRUD | E112: 20.947.332/0005-19 | F112: OPERACIONAL | G112: CORTE E DOBRA | H112: BRACOFER | I112: 46055 | K112: 1.3.1.5 CORTE E DOBRA | L112: AUXILIAR DE PATIO JUNIOR | M112: 2155 | N112: 2155 | O112: 0 | P112: =N112+O112 -> 2155 | Q112: 0 | R112: 0 | S112: 0 | T112: 0 | U112: 0 | V112: 0 | W112: 0 | X112: 0 | Y112: 0 | Z112: 0 | AA112: 100.83 | AB112: 19.39 | AC112: 0 | AD112: 0 | AE112: 0 | AF112: 0 | AG112: 2275.22 | AH112: 0 | AI112: 0 | AJ112: 0 | AK112: 0 | AL112: 0 | AM112: 0 | AN112: 0 | AO112: 0 | AP112: 350 | AQ112: 0 | AR112: 350 | AS112: 0 | AT112: 0 | AU112: 0 | AV112: 0 | AW112: 0 | AX112: 0 | AY112: 0 | AZ112: 0 | BA112: 0 | BB112: 0 | BC112: 0 | BD112: 0 | BE112: 0 | BF112: 0 | BG112: 0 | BH112: 0 | BI112: 2625.22 | BJ112: 210.02 | BK112: 2415.2 | BL112: 182.01 | BM112: 455.04 | BN112: 34.12 | BO112: 131.96 | BP112: 803.13 | BQ112: 3428.35
A113: NATALIA BAROSSI TREVISAN | B113: 46082 | C113: Empregado – Geral | D113: G3S FL 05 - PRES PRUD | E113: 20.947.332/0005-19 | F113: ADMINISTRATIVO | G113: CONTABILIDADE | H113: BRACOFER | I113: 46083 | K113: 1.3.1.1 ADMINISTRATIVO | L113: AUXILIAR CONTABIL | M113: 2098 | N113: 2098 | O113: 0 | P113: =N113+O113 -> 2098 | Q113: 0 | R113: 0 | S113: 0 | T113: 0 | U113: 0 | V113: 0 | W113: 0 | X113: 0 | Y113: 0 | Z113: 0 | AA113: 0 | AB113: 0 | AC113: 0 | AD113: 0 | AE113: 0 | AF113: 0 | AG113: 2098 | AH113: 0 | AI113: 0 | AJ113: 0 | AK113: 0 | AL113: 0 | AM113: 0 | AN113: 0 | AO113: 0 | AP113: 0 | AQ113: 0 | AR113: 0 | AS113: 0 | AT113: 0 | AU113: 0 | AV113: 0 | AW113: 0 | AX113: 0 | AY113: 0 | AZ113: 0 | BA113: 0 | BB113: 0 | BC113: 0 | BD113: 0 | BE113: 0 | BF113: 0 | BG113: 0 | BH113: 0 | BI113: 2098 | BJ113: 1031.77 | BK113: 1066.23 | BL113: 167.84 | BM113: 419.6 | BN113: 31.47 | BO113: 121.68 | BP113: 740.59 | BQ113: 2838.59
A114: HELENA SOARES GOES DA SILVA | B114: 46082 | C114: Bolsista - Estagiário | D114: G3S FL 05 - PRES PRUD | E114: 20.947.332/0005-19 | F114: COMERCIAL | G114: COMERCIAL | H114: BRACOFER | I114: 45663 | K114: 1.3.1.2 COMERCIAL | L114: AUXILIAR COMERCIAL - ESTAGIARIO | M114: 1000 | N114: 0 | O114: 0 | P114: =N114+O114 -> 0 | Q114: 0 | R114: 0 | S114: 0 | T114: 0 | U114: 0 | V114: 0 | W114: 0 | X114: 0 | Y114: 0 | Z114: 0 | AA114: 0 | AB114: 0 | AC114: 0 | AD114: 0 | AE114: 0 | AF114: 0 | AG114: 0 | AH114: 0 | AI114: 0 | AJ114: 0 | AK114: 0 | AL114: 0 | AM114: 0 | AN114: 0 | AO114: 0 | AP114: 0 | AQ114: 0 | AR114: 0 | AS114: 1000 | AT114: 0 | AU114: 0 | AV114: 0 | AW114: 0 | AX114: 0 | AY114: 0 | AZ114: 0 | BA114: 0 | BB114: 0 | BC114: 0 | BD114: 0 | BE114: 0 | BF114: 0 | BG114: 0 | BH114: 0 | BI114: 1000 | BJ114: 0 | BK114: 1000 | BL114: 0 | BM114: 0 | BN114: 0 | BO114: 0 | BP114: 0 | BQ114: 1000
A115: EDUARDO PEDRETTI ARRUDA RONCHESEL | B115: 46082 | C115: Bolsista - Estagiário | D115: G3S FL 05 - PRES PRUD | E115: 20.947.332/0005-19 | F115: ADMINISTRATIVO | G115: COMERCIAL | H115: BRACOFER | I115: 46071 | K115: 1.3.1.1 ADMINISTRATIVO | L115: AUXILIAR FINANCEIRO - ESTAGIARIO | M115: 1000 | N115: 0 | O115: 0 | P115: =N115+O115 -> 0 | Q115: 0 | R115: 0 | S115: 0 | T115: 0 | U115: 0 | V115: 0 | W115: 0 | X115: 0 | Y115: 0 | Z115: 0 | AA115: 0 | AB115: 0 | AC115: 0 | AD115: 0 | AE115: 0 | AF115: 0 | AG115: 0 | AH115: 0 | AI115: 0 | AJ115: 0 | AK115: 0 | AL115: 0 | AM115: 0 | AN115: 0 | AO115: 0 | AP115: 0 | AQ115: 0 | AR115: 0 | AS115: 1000 | AT115: 0 | AU115: 0 | AV115: 0 | AW115: 0 | AX115: 0 | AY115: 0 | AZ115: 0 | BA115: 0 | BB115: 0 | BC115: 0 | BD115: 0 | BE115: 0 | BF115: 0 | BG115: 0 | BH115: 0 | BI115: 1000 | BJ115: 0 | BK115: 1000 | BL115: 0 | BM115: 0 | BN115: 0 | BO115: 0 | BP115: 0 | BQ115: 1000
A116: VALTER LEITE VIEIRA | B116: 46082 | C116: Empregado – Geral | D116: G3S FL 06 - MARINGA | E116: 20.947.332/0006-08 | F116: OPERACIONAL | G116: PATIO | H116: SELETIVA MARINGA DISTRITO | I116: 44067 | K116: 1.2.4.3 OPERACIONAL | L116: GERENTE DE PATIO SENIOR | M116: 3679.83 | N116: 3679.83 | O116: 0 | P116: =N116+O116 -> 3679.83 | Q116: 0 | R116: 0 | S116: 0 | T116: 735.97 | U116: 0 | V116: 1103.95 | W116: 0 | X116: 0 | Y116: 0 | Z116: 0 | AA116: 198.02 | AB116: 38.08 | AC116: 0 | AD116: 0 | AE116: 0 | AF116: 0 | AG116: 5755.85 | AH116: 0 | AI116: 0 | AJ116: 0 | AK116: 0 | AL116: 0 | AM116: 0 | AN116: 0 | AO116: 781.93 | AP116: 0 | AQ116: 0 | AR116: 781.93 | AS116: 0 | AT116: 0 | AU116: 0 | AV116: 0 | AW116: 0 | AX116: 0 | AY116: 0 | AZ116: 0 | BA116: 0 | BB116: 0 | BC116: 0 | BD116: 0 | BE116: 0 | BF116: 0 | BG116: 0 | BH116: 0 | BI116: 6537.78 | BJ116: 2612.91 | BK116: 3924.87 | BL116: 460.46 | BM116: 1151.17 | BN116: 86.33 | BO116: 333.83 | BP116: 2031.79 | BQ116: 8569.57
A117: PATRICIA CECILIA GUIDOTTI DE FREITAS | B117: 46082 | C117: Empregado – Geral | D117: G3S FL 06 - MARINGA | E117: 20.947.332/0006-08 | F117: ADMINISTRATIVO | G117: ATENDIMENTO | H117: SELETIVA MARINGA DISTRITO | I117: 45880 | K117: 1.2.4.1 ADMINISTRATIVO | L117: AUX ADMINISTRATIVO PLENO | M117: 2650 | N117: 2650 | O117: 0 | P117: =N117+O117 -> 2650 | Q117: 0 | R117: 0 | S117: 0 | T117: 0 | U117: 0 | V117: 0 | W117: 0 | X117: 0 | Y117: 0 | Z117: 0 | AA117: 382.59 | AB117: 73.58 | AC117: 0 | AD117: 0 | AE117: 0 | AF117: 265 | AG117: 3371.17 | AH117: 0 | AI117: 0 | AJ117: 0 | AK117: 0 | AL117: 0 | AM117: 0 | AN117: 0 | AO117: 252.45 | AP117: 0 | AQ117: 0 | AR117: 252.45 | AS117: 0 | AT117: 0 | AU117: 0 | AV117: 0 | AW117: 0 | AX117: 0 | AY117: 0 | AZ117: 0 | BA117: 0 | BB117: 0 | BC117: 0 | BD117: 0 | BE117: 0 | BF117: 0 | BG117: 0 | BH117: 0 | BI117: 3623.62 | BJ117: 293.12 | BK117: 3330.5 | BL117: 269.69 | BM117: 674.23 | BN117: 50.56 | BO117: 195.52 | BP117: 1190 | BQ117: 4813.62
A118: ALIFER BRENO PEREIRA ALMEIDA DE JESUS | B118: 46082 | C118: Empregado – Geral | D118: G3S FL 06 - MARINGA | E118: 20.947.332/0006-08 | F118: ADMINISTRATIVO | G118: ATENDIMENTO | H118: SELETIVA MARINGA DISTRITO | I118: 46034 | K118: 1.2.4.1 ADMINISTRATIVO | L118: AUX ADMINISTRATIVO JUNIOR | M118: 2320 | N118: 2320 | O118: 0 | P118: =N118+O118 -> 2320 | Q118: 0 | R118: 0 | S118: 0 | T118: 0 | U118: 0 | V118: 0 | W118: 0 | X118: 0 | Y118: 0 | Z118: 0 | AA118: 236.35 | AB118: 66.81 | AC118: 0 | AD118: 0 | AE118: 0 | AF118: 0 | AG118: 2623.16 | AH118: 0 | AI118: 0 | AJ118: 0 | AK118: 0 | AL118: 0 | AM118: 0 | AN118: 0 | AO118: 456.6 | AP118: 0 | AQ118: 0 | AR118: 456.6 | AS118: 0 | AT118: 0 | AU118: 0 | AV118: 0 | AW118: 0 | AX118: 0 | AY118: 0 | AZ118: 0 | BA118: 0 | BB118: 0 | BC118: 0 | BD118: 0 | BE118: 0 | BF118: 0 | BG118: 0 | BH118: 0 | BI118: 3079.76 | BJ118: 225.6 | BK118: 2965.23 | BL118: 218.4 | BM118: 524.63 | BN118: 39.34 | BO118: 152.14 | BP118: 934.51 | BQ118: 4014.27
A119: PABLO HENRYQUE BARBOSA DE CASTRO | B119: 46082 | C119: Empregado – Geral | D119: G3S FL 06 - MARINGA | E119: 20.947.332/0006-08 | F119: OPERACIONAL | G119: PATIO | H119: SELETIVA MARINGA DISTRITO | I119: 46076 | K119: 1.2.4.3 OPERACIONAL | L119: CLASSIFICADOR PLENO | M119: 2333.09 | N119: 2333.09 | O119: 0 | P119: =N119+O119 -> 2333.09 | Q119: 0 | R119: 0 | S119: 0 | T119: 0 | U119: 0 | V119: 0 | W119: 0 | X119: 0 | Y119: 0 | Z119: 0 | AA119: 74.95 | AB119: 14.41 | AC119: 0 | AD119: 0 | AE119: 0 | AF119: 0 | AG119: 2422.45 | AH119: 0 | AI119: 0 | AJ119: 0 | AK119: 0 | AL119: 0 | AM119: 0 | AN119: 0 | AO119: 252.45 | AP119: 0 | AQ119: 0 | AR119: 252.45 | AS119: 0 | AT119: 0 | AU119: 0 | AV119: 0 | AW119: 0 | AX119: 0 | AY119: 0 | AZ119: 0 | BA119: 0 | BB119: 0 | BC119: 0 | BD119: 0 | BE119: 0 | BF119: 0 | BG119: 0 | BH119: 0 | BI119: 2674.9 | BJ119: 1127.7 | BK119: 1547.2 | BL119: 193.79 | BM119: 484.49 | BN119: 36.33 | BO119: 140.5 | BP119: 855.11 | BQ119: 3530.01
A120: ANDREW GABRYEL ARCANJO DE SOUZA | B120: 46082 | C120: Empregado – Geral | D120: G3S FL 06 - MARINGA | E120: 20.947.332/0006-08 | F120: OPERACIONAL | G120: PATIO | H120: SELETIVA MARINGA DISTRITO | I120: 46083 | K120: 1.2.4.3 OPERACIONAL | L120: AUXILIAR DE PATIO JUNIOR | M120: 2155 | N120: 2155 | O120: 0 | P120: =N120+O120 -> 2155 | Q120: 0 | R120: 0 | S120: 0 | T120: 0 | U120: 0 | V120: 0 | W120: 0 | X120: 0 | Y120: 0 | Z120: 0 | AA120: 0 | AB120: 0 | AC120: 0 | AD120: 0 | AE120: 0 | AF120: 0 | AG120: 2155 | AH120: 0 | AI120: 0 | AJ120: 0 | AK120: 0 | AL120: 0 | AM120: 0 | AN120: 0 | AO120: 252.45 | AP120: 0 | AQ120: 0 | AR120: 252.45 | AS120: 0 | AT120: 500 | AU120: 0 | AV120: 0 | AW120: 0 | AX120: 0 | AY120: 0 | AZ120: 0 | BA120: 0 | BB120: 0 | BC120: 0 | BD120: 0 | BE120: 0 | BF120: 0 | BG120: 0 | BH120: 0 | BI120: 2907.45 | BJ120: 419.63 | BK120: 2487.82 | BL120: 172.4 | BM120: 431 | BN120: 32.32 | BO120: 124.99 | BP120: 760.71 | BQ120: 3668.16

Sheet BASE+TOMADOR
A1: FUNCIONÁRIO | B1: COMPETÊNCIA | C1: MODALIDADE | D1: EMPRESA | E1: FILIAL | F1: EMPRESA + FILIAL | G1: CNPJ | H1: SETOR | I1: SEÇÃO | J1: TOMADOR | K1: ADMISSÃO | L1: DEMISSÃO | M1: RESPONSÁVEL | N1: CENTRO DE CUSTO | O1: FUNÇÃO | P1: SAL. BASE | Q1: SALÁRIO | R1: AUX. MATERNIDADE | S1: FÉRIAS | T1: AD. FUNÇÃO 20% | U1: AD. INSALUBRIDADE 20% | V1: AD. PERICULOSIDADE 30% | W1: GRATIFICAÇÃO 40% | X1: GRAT(ADRIANA) | Y1: BIÊNIO 5% | Z1: AD. NOTURNO 20% | AA1: HORA EXTRA | AB1: H. EXTRA DSR | AC1: COMISSÃO | AD1: COMISSÃO DSR | AE1: DIF. CONVENÇÃO | AF1: QUEBRA DE CAIXA | AG1: TOTAL EVENTOS COM IMPOSTOS | AH1: ESTAGIARIOS | AI1: AJUDA CUSTO VT | AJ1: CESTA BASICA DINHEIRO | AK1: CESTA BASICA PRODUTO | AL1: PRODUÇÃO FIXO | AM1: PRODUÇÃO CHECK LIST MOTORISTA | AN1: PRODUÇÃO PRENSA | AO1: CAÇAMBA/CONTAINER | AP1: PRÊMIO FIXO | AQ1: PRÊMIO OPERADORES | AR1: PRÊMIO VENDAS UNIDADES | AS1: PRÊMIO PORTA | AT1: PRÊMIO ANUÊNIO | AU1: REFEIÇÃO | AV1: DIÁRIA DIFERENCIADA | AW1: ABONO PECUNIÁRIO FÉRIAS | AX1: SALÁRIO FAMÍLIA | AY1: PLANO DE SAÚDE | AZ1: ASSISTÊNCIA SAÚDE | BA1: AJUDA DE ALUGUEL | BB1: PREMIO GRATIFICAÇÃO | BC1: TOTAL EVENTOS SEM IMPOSTOS | BD1: TOTAL BRUTO | BE1: SALÁRIO PF | BF1: TOTAL BRUTO + PF | BG1: PROV. 13º | BH1: PROV. FÉRIAS | BI1: PROV. 1/3 FERIAS | BJ1: TOTAL PROVISÕES | BK1: INSS | BL1: RAT | BM1: TERCEIROS | BN1: FGTS | BO1: TOTAL ENCARGOS | BP1: TOTAL CUSTO FOLHA (SEM PROVISÕES, COM ENCARGOS) | BQ1: TOTAL GERAL (COM PROVISÕES E ENCARGOS) | BR1: TOTAL RESCISAO | BS1: STATUS
A2: ADEMIR DOS SANTOS | B2: 46082 | C2: CLT | D2: =VLOOKUP(A2,'Custo_Fopag (2)'!A:$BQ,4,0) -> G3S FL 11 - MARINGA | G2: =VLOOKUP(A2,'Custo_Fopag (2)'!$A:$BQ,5,0) -> 20.947.332/0011-67 | H2: =VLOOKUP(A2,'Custo_Fopag (2)'!$A:$BQ,6,0) -> OPERACIONAL | I2: =VLOOKUP(A2,'Custo_Fopag (2)'!$A:$BQ,7,0) -> PATIO | J2: =VLOOKUP(A2,'Custo_Fopag (2)'!$A:$BQ,8,0) -> SELETIVA MARINGA CIDADE ALTA | K2: =VLOOKUP(A2,'Custo_Fopag (2)'!$A:$BQ,9,0) -> 45915 | N2: =VLOOKUP(A2,'Custo_Fopag (2)'!$A:$BQ,11,0) -> 1.2.8.3. OPERACIONAL | O2: =VLOOKUP(A2,'Custo_Fopag (2)'!$A:$BQ,12,0) -> AUXILIAR DE PATIO SENIOR | P2: =VLOOKUP(A2,'Custo_Fopag (2)'!$A:$BQ,13,0) -> 2600 | Q2: =VLOOKUP(A2,'Custo_Fopag (2)'!$A:$BQ,16,0) -> 2600 | R2: =VLOOKUP(A2,'Custo_Fopag (2)'!$A:$BQ,17,0) -> 0 | S2: =VLOOKUP(A2,'Custo_Fopag (2)'!$A:$BP,18,0) -> 0 | T2: =VLOOKUP(A2,'Custo_Fopag (2)'!$A:$BQ,20,0) -> 0 | U2: =VLOOKUP(A2,'Custo_Fopag (2)'!$A:$BQ,21,0) -> 0 | V2: =VLOOKUP(A2,'Custo_Fopag (2)'!$A:$BQ,22,0) -> 0 | W2: =VLOOKUP(A2,'Custo_Fopag (2)'!$A:$BQ,23,0) -> 0 | X2: =VLOOKUP(A2,'Custo_Fopag (2)'!$A:$BQ,24,0) -> 0 | Y2: =VLOOKUP(A2,'Custo_Fopag (2)'!$A:$BQ,25,0) -> 0 | Z2: =VLOOKUP(A2,'Custo_Fopag (2)'!$A:$BQ,26,0) -> 0 | AA2: =VLOOKUP(A2,'Custo_Fopag (2)'!$A:$BQ,27,0) -> 79.95 | AB2: =VLOOKUP(A2,'Custo_Fopag (2)'!$A:$BQ,28,0) -> 15.38 | AC2: =VLOOKUP(A2,'Custo_Fopag (2)'!$A:$BQ,29,0) -> 0 | AD2: =VLOOKUP(A2,'Custo_Fopag (2)'!$A:$BQ,30,0) -> 0 | AE2: =VLOOKUP(A2,'Custo_Fopag (2)'!$A:$BQ,31,0) -> 0 | AF2: =VLOOKUP(A2,'Custo_Fopag (2)'!$A:$BQ,32,0) -> 0 | AG2: =SUM(Q2:AF2) -> 2695.33 | AH2: =VLOOKUP(A2,'Custo_Fopag (2)'!$A:$BQ,45,0) -> 0 | AI2: =_xlfn.XLOOKUP(A2,Beneficios!A:A,Beneficios!B:B,0,0,1) -> 512.87 | AJ2: =VLOOKUP(A2,'Custo_Fopag (2)'!$A:$BQ,47,0) -> 0 | AK2: 0 | AL2: =VLOOKUP(A2,'Custo_Fopag (2)'!$A:$BQ,35,0) -> 0 | AM2: =VLOOKUP(A2,'Custo_Fopag (2)'!$A:$BQ,36,0) -> 0 | AN2: =VLOOKUP(A2,'Custo_Fopag (2)'!$A:$BQ,37,0) -> 0 | AO2: =VLOOKUP(A2,'Custo_Fopag (2)'!$A:$BQ,39,0) -> 0 | AP2: =VLOOKUP(A2,'Custo_Fopag (2)'!$A:$BQ,42,0) -> 0 | AQ2: =VLOOKUP(A2,'Custo_Fopag (2)'!$A:$BQ,40,0) -> 0 | AR2: =VLOOKUP(A2,'Custo_Fopag (2)'!$A:$BQ,41,0) -> 456.6 | AS2: =VLOOKUP(A2,'Custo_Fopag (2)'!$A:$BQ,38,0) -> 0 | AT2: =VLOOKUP(A2,'Custo_Fopag (2)'!$A:$BQ,43,0) -> 0 | AU2: =VLOOKUP(A2,'Custo_Fopag (2)'!$A:$BQ,48,0) -> 0 | AV2: =VLOOKUP(A2,'Custo_Fopag (2)'!$A:$BQ,49,0) -> 0 | AW2: =VLOOKUP(A2,'Custo_Fopag (2)'!$A:$BQ,19,0) -> 0 | AX2: =VLOOKUP(A2,'Custo_Fopag (2)'!$A:$BQ,50,0) -> 0 | AY2: =VLOOKUP(A2,'Custo_Fopag (2)'!$A:$BQ,51,0) -> 0 | AZ2: 0 | BA2: =VLOOKUP(A2,'Custo_Fopag (2)'!$A:$BQ,54,0) -> 0 | BB2: =VLOOKUP(A2,'Custo_Fopag (2)'!$A:$BQ,52,0) -> 0 | BC2: =SUM(AH2:BB2) -> 969.47 | BD2: =BC2+AG2 -> 3664.8 | BF2: =BD2+BE2 -> 3664.8 | BG2: =AG2/12 -> 224.61083 | BH2: =BG2 -> 224.61083 | BI2: =BH2/3 -> 74.870278 | BJ2: =SUM(BG2:BI2) -> 524.09194 | BK2: =VLOOKUP(A2,'Custo_Fopag (2)'!$A:$BQ,65,0) -> 539.07 | BL2: =VLOOKUP(A2,'Custo_Fopag (2)'!$A:$BQP,66,0) -> 80.85 | BM2: =VLOOKUP(A2,'Custo_Fopag (2)'!$A:$BQ,67,0) -> 156.32 | BN2: =VLOOKUP(A2,'Custo_Fopag (2)'!$A:$BQ,64,0) -> 215.62 | BO2: =SUM(BK2:BN2) -> 991.86 | BP2: =BF2+BO2 -> 4656.66 | BQ2: =BF2+BJ2+BO2 -> 5180.7519 | BR2: =VLOOKUP(A2,'Custo_Fopag (2)'!$A:$BQ,60,0) -> 0 | BS2: =IF(ISBLANK(L2),"Ativo","Desligado") -> Ativo
A3: ADRIANA APARECIDA GUABERTO PALANCIO | B3: 46082 | C3: CLT | D3: =VLOOKUP(A3,'Custo_Fopag (2)'!A:$BQ,4,0) -> G3S FL 05 - PRES PRUD | G3: =VLOOKUP(A3,'Custo_Fopag (2)'!$A:$BQ,5,0) -> 20.947.332/0005-19 | H3: =VLOOKUP(A3,'Custo_Fopag (2)'!$A:$BQ,6,0) -> ADMINISTRATIVO | I3: =VLOOKUP(A3,'Custo_Fopag (2)'!$A:$BQ,7,0) -> FINANCEIRO | J3: =VLOOKUP(A3,'Custo_Fopag (2)'!$A:$BQ,8,0) -> SELETIVA CORPORATIVO SUCATA | K3: =VLOOKUP(A3,'Custo_Fopag (2)'!$A:$BQ,9,0) -> 43866 | N3: =VLOOKUP(A3,'Custo_Fopag (2)'!$A:$BQ,11,0) -> 1.2.1.1 APOIO | O3: =VLOOKUP(A3,'Custo_Fopag (2)'!$A:$BQ,12,0) -> ANALISTA FINANCEIRO SENIOR I | P3: =VLOOKUP(A3,'Custo_Fopag (2)'!$A:$BQ,13,0) -> 3500 | Q3: =VLOOKUP(A3,'Custo_Fopag (2)'!$A:$BQ,16,0) -> 3500 | R3: =VLOOKUP(A3,'Custo_Fopag (2)'!$A:$BQ,17,0) -> 0 | S3: =VLOOKUP(A3,'Custo_Fopag (2)'!$A:$BP,18,0) -> 0 | T3: =VLOOKUP(A3,'Custo_Fopag (2)'!$A:$BQ,20,0) -> 0 | U3: =VLOOKUP(A3,'Custo_Fopag (2)'!$A:$BQ,21,0) -> 0 | V3: =VLOOKUP(A3,'Custo_Fopag (2)'!$A:$BQ,22,0) -> 0 | W3: =VLOOKUP(A3,'Custo_Fopag (2)'!$A:$BQ,23,0) -> 0 | X3: =VLOOKUP(A3,'Custo_Fopag (2)'!$A:$BQ,24,0) -> 0 | Y3: =VLOOKUP(A3,'Custo_Fopag (2)'!$A:$BQ,25,0) -> 0 | Z3: =VLOOKUP(A3,'Custo_Fopag (2)'!$A:$BQ,26,0) -> 0 | AA3: =VLOOKUP(A3,'Custo_Fopag (2)'!$A:$BQ,27,0) -> 0 | AB3: =VLOOKUP(A3,'Custo_Fopag (2)'!$A:$BQ,28,0) -> 0 | AC3: =VLOOKUP(A3,'Custo_Fopag (2)'!$A:$BQ,29,0) -> 0 | AD3: =VLOOKUP(A3,'Custo_Fopag (2)'!$A:$BQ,30,0) -> 0 | AE3: =VLOOKUP(A3,'Custo_Fopag (2)'!$A:$BQ,31,0) -> 0 | AF3: =VLOOKUP(A3,'Custo_Fopag (2)'!$A:$BQ,32,0) -> 0 | AG3: =SUM(Q3:AF3) -> 3500 | AH3: =VLOOKUP(A3,'Custo_Fopag (2)'!$A:$BQ,45,0) -> 0 | AI3: =_xlfn.XLOOKUP(A3,Beneficios!A:A,Beneficios!B:B,0,0,1) -> 521.87 | AJ3: =VLOOKUP(A3,'Custo_Fopag (2)'!$A:$BQ,47,0) -> 0 | AK3: 0 | AL3: =VLOOKUP(A3,'Custo_Fopag (2)'!$A:$BQ,35,0) -> 0 | AM3: =VLOOKUP(A3,'Custo_Fopag (2)'!$A:$BQ,36,0) -> 0 | AN3: =VLOOKUP(A3,'Custo_Fopag (2)'!$A:$BQ,37,0) -> 0 | AO3: =VLOOKUP(A3,'Custo_Fopag (2)'!$A:$BQ,39,0) -> 0 | AP3: =VLOOKUP(A3,'Custo_Fopag (2)'!$A:$BQ,42,0) -> 0 | AQ3: =VLOOKUP(A3,'Custo_Fopag (2)'!$A:$BQ,40,0) -> 0 | AR3: =VLOOKUP(A3,'Custo_Fopag (2)'!$A:$BQ,41,0) -> 0 | AS3: =VLOOKUP(A3,'Custo_Fopag (2)'!$A:$BQ,38,0) -> 0 | AT3: =VLOOKUP(A3,'Custo_Fopag (2)'!$A:$BQ,43,0) -> 0 | AU3: =VLOOKUP(A3,'Custo_Fopag (2)'!$A:$BQ,48,0) -> 0 | AV3: =VLOOKUP(A3,'Custo_Fopag (2)'!$A:$BQ,49,0) -> 0 | AW3: =VLOOKUP(A3,'Custo_Fopag (2)'!$A:$BQ,19,0) -> 0 | AX3: =VLOOKUP(A3,'Custo_Fopag (2)'!$A:$BQ,50,0) -> 0 | AY3: =VLOOKUP(A3,'Custo_Fopag (2)'!$A:$BQ,51,0) -> 0 | AZ3: 0 | BA3: =VLOOKUP(A3,'Custo_Fopag (2)'!$A:$BQ,54,0) -> 0 | BB3: =VLOOKUP(A3,'Custo_Fopag (2)'!$A:$BQ,52,0) -> 0 | BC3: =SUM(AH3:BB3) -> 521.87 | BD3: =BC3+AG3 -> 4021.87 | BF3: =BD3+BE3 -> 4021.87 | BG3: =AG3/12 -> 291.66667 | BH3: =BG3 -> 291.66667 | BI3: =BH3/3 -> 97.222222 | BJ3: =SUM(BG3:BI3) -> 680.55556 | BK3: =VLOOKUP(A3,'Custo_Fopag (2)'!$A:$BQ,65,0) -> 700 | BL3: =VLOOKUP(A3,'Custo_Fopag (2)'!$A:$BQP,66,0) -> 52.5 | BM3: =VLOOKUP(A3,'Custo_Fopag (2)'!$A:$BQ,67,0) -> 203 | BN3: =VLOOKUP(A3,'Custo_Fopag (2)'!$A:$BQ,64,0) -> 280 | BO3: =SUM(BK3:BN3) -> 1235.5 | BP3: =BF3+BO3 -> 5257.37 | BQ3: =BF3+BJ3+BO3 -> 5937.9256 | BR3: =VLOOKUP(A3,'Custo_Fopag (2)'!$A:$BQ,60,0) -> 0 | BS3: =IF(ISBLANK(L3),"Ativo","Desligado") -> Ativo
A4: ADRIANA CANDIDO FIGUEIREDO | B4: 46082 | C4: CLT | D4: =VLOOKUP(A4,'Custo_Fopag (2)'!A:$BQ,4,0) -> G3S FL 10 - PRES PRUD | G4: =VLOOKUP(A4,'Custo_Fopag (2)'!$A:$BQ,5,0) -> 20.947.332/0010-86 | H4: =VLOOKUP(A4,'Custo_Fopag (2)'!$A:$BQ,6,0) -> GESTÃO DE GENTE | I4: =VLOOKUP(A4,'Custo_Fopag (2)'!$A:$BQ,7,0) -> DEPTO PESSOAL | J4: =VLOOKUP(A4,'Custo_Fopag (2)'!$A:$BQ,8,0) -> PILARES | K4: =VLOOKUP(A4,'Custo_Fopag (2)'!$A:$BQ,9,0) -> 43692 | N4: =VLOOKUP(A4,'Custo_Fopag (2)'!$A:$BQ,11,0) -> 1.1.10 PESSOAS | O4: =VLOOKUP(A4,'Custo_Fopag (2)'!$A:$BQ,12,0) -> ANALISTA DE DEPTO PESSOAL | P4: =VLOOKUP(A4,'Custo_Fopag (2)'!$A:$BQ,13,0) -> 4568.75 | Q4: =VLOOKUP(A4,'Custo_Fopag (2)'!$A:$BQ,16,0) -> 4568.75 | R4: =VLOOKUP(A4,'Custo_Fopag (2)'!$A:$BQ,17,0) -> 0 | S4: =VLOOKUP(A4,'Custo_Fopag (2)'!$A:$BP,18,0) -> 0 | T4: =VLOOKUP(A4,'Custo_Fopag (2)'!$A:$BQ,20,0) -> 0 | U4: =VLOOKUP(A4,'Custo_Fopag (2)'!$A:$BQ,21,0) -> 0 | V4: =VLOOKUP(A4,'Custo_Fopag (2)'!$A:$BQ,22,0) -> 0 | W4: =VLOOKUP(A4,'Custo_Fopag (2)'!$A:$BQ,23,0) -> 0 | X4: =VLOOKUP(A4,'Custo_Fopag (2)'!$A:$BQ,24,0) -> 0 | Y4: =VLOOKUP(A4,'Custo_Fopag (2)'!$A:$BQ,25,0) -> 0 | Z4: =VLOOKUP(A4,'Custo_Fopag (2)'!$A:$BQ,26,0) -> 0 | AA4: =VLOOKUP(A4,'Custo_Fopag (2)'!$A:$BQ,27,0) -> 0 | AB4: =VLOOKUP(A4,'Custo_Fopag (2)'!$A:$BQ,28,0) -> 0 | AC4: =VLOOKUP(A4,'Custo_Fopag (2)'!$A:$BQ,29,0) -> 0 | AD4: =VLOOKUP(A4,'Custo_Fopag (2)'!$A:$BQ,30,0) -> 0 | AE4: =VLOOKUP(A4,'Custo_Fopag (2)'!$A:$BQ,31,0) -> 0 | AF4: =VLOOKUP(A4,'Custo_Fopag (2)'!$A:$BQ,32,0) -> 0 | AG4: =SUM(Q4:AF4) -> 4568.75 | AH4: =VLOOKUP(A4,'Custo_Fopag (2)'!$A:$BQ,45,0) -> 0 | AI4: =_xlfn.XLOOKUP(A4,Beneficios!A:A,Beneficios!B:B,0,0,1) -> 512.87 | AJ4: =VLOOKUP(A4,'Custo_Fopag (2)'!$A:$BQ,47,0) -> 0 | AK4: 0 | AL4: =VLOOKUP(A4,'Custo_Fopag (2)'!$A:$BQ,35,0) -> 0 | AM4: =VLOOKUP(A4,'Custo_Fopag (2)'!$A:$BQ,36,0) -> 0 | AN4: =VLOOKUP(A4,'Custo_Fopag (2)'!$A:$BQ,37,0) -> 0 | AO4: =VLOOKUP(A4,'Custo_Fopag (2)'!$A:$BQ,39,0) -> 0 | AP4: =VLOOKUP(A4,'Custo_Fopag (2)'!$A:$BQ,42,0) -> 0 | AQ4: =VLOOKUP(A4,'Custo_Fopag (2)'!$A:$BQ,40,0) -> 0 | AR4: =VLOOKUP(A4,'Custo_Fopag (2)'!$A:$BQ,41,0) -> 0 | AS4: =VLOOKUP(A4,'Custo_Fopag (2)'!$A:$BQ,38,0) -> 0 | AT4: =VLOOKUP(A4,'Custo_Fopag (2)'!$A:$BQ,43,0) -> 0 | AU4: =VLOOKUP(A4,'Custo_Fopag (2)'!$A:$BQ,48,0) -> 0 | AV4: =VLOOKUP(A4,'Custo_Fopag (2)'!$A:$BQ,49,0) -> 0 | AW4: =VLOOKUP(A4,'Custo_Fopag (2)'!$A:$BQ,19,0) -> 0 | AX4: =VLOOKUP(A4,'Custo_Fopag (2)'!$A:$BQ,50,0) -> 0 | AY4: =VLOOKUP(A4,'Custo_Fopag (2)'!$A:$BQ,51,0) -> 0 | AZ4: 0 | BA4: =VLOOKUP(A4,'Custo_Fopag (2)'!$A:$BQ,54,0) -> 0 | BB4: =VLOOKUP(A4,'Custo_Fopag (2)'!$A:$BQ,52,0) -> 0 | BC4: =SUM(AH4:BB4) -> 512.87 | BD4: =BC4+AG4 -> 5081.62 | BF4: =BD4+BE4 -> 5081.62 | BG4: =AG4/12 -> 380.72917 | BH4: =BG4 -> 380.72917 | BI4: =BH4/3 -> 126.90972 | BJ4: =SUM(BG4:BI4) -> 888.36806 | BK4: =VLOOKUP(A4,'Custo_Fopag (2)'!$A:$BQ,65,0) -> 913.75 | BL4: =VLOOKUP(A4,'Custo_Fopag (2)'!$A:$BQP,66,0) -> 137.06 | BM4: =VLOOKUP(A4,'Custo_Fopag (2)'!$A:$BQ,67,0) -> 264.98 | BN4: =VLOOKUP(A4,'Custo_Fopag (2)'!$A:$BQ,64,0) -> 365.5 | BO4: =SUM(BK4:BN4) -> 1681.29 | BP4: =BF4+BO4 -> 6762.91 | BQ4: =BF4+BJ4+BO4 -> 7651.2781 | BR4: =VLOOKUP(A4,'Custo_Fopag (2)'!$A:$BQ,60,0) -> 0 | BS4: =IF(ISBLANK(L4),"Ativo","Desligado") -> Ativo
A5: ALEKSANDER APARECIDO GONÇALVES DA SILVA | B5: 46082 | C5: CLT | D5: =VLOOKUP(A5,'Custo_Fopag (2)'!A:$BQ,4,0) -> G3S FL 11 - MARINGA | G5: =VLOOKUP(A5,'Custo_Fopag (2)'!$A:$BQ,5,0) -> 20.947.332/0011-67 | H5: =VLOOKUP(A5,'Custo_Fopag (2)'!$A:$BQ,6,0) -> OPERACIONAL | I5: =VLOOKUP(A5,'Custo_Fopag (2)'!$A:$BQ,7,0) -> PATIO | J5: =VLOOKUP(A5,'Custo_Fopag (2)'!$A:$BQ,8,0) -> SELETIVA MARINGA CIDADE ALTA | K5: =VLOOKUP(A5,'Custo_Fopag (2)'!$A:$BQ,9,0) -> 46050 | L5: =VLOOKUP(A5,'Custo_Fopag (2)'!$A:$BQ,10,0) -> 46097 | N5: =VLOOKUP(A5,'Custo_Fopag (2)'!$A:$BQ,11,0) -> 1.2.8.3. OPERACIONAL | O5: =VLOOKUP(A5,'Custo_Fopag (2)'!$A:$BQ,12,0) -> GERENTE DE PATIO SENIOR | P5: =VLOOKUP(A5,'Custo_Fopag (2)'!$A:$BQ,13,0) -> 3679.83 | Q5: =VLOOKUP(A5,'Custo_Fopag (2)'!$A:$BQ,16,0) -> 0 | R5: =VLOOKUP(A5,'Custo_Fopag (2)'!$A:$BQ,17,0) -> 0 | S5: =VLOOKUP(A5,'Custo_Fopag (2)'!$A:$BP,18,0) -> 0 | T5: =VLOOKUP(A5,'Custo_Fopag (2)'!$A:$BQ,20,0) -> 392.52 | U5: =VLOOKUP(A5,'Custo_Fopag (2)'!$A:$BQ,21,0) -> 0 | V5: =VLOOKUP(A5,'Custo_Fopag (2)'!$A:$BQ,22,0) -> 588.77 | W5: =VLOOKUP(A5,'Custo_Fopag (2)'!$A:$BQ,23,0) -> 0 | X5: =VLOOKUP(A5,'Custo_Fopag (2)'!$A:$BQ,24,0) -> 0 | Y5: =VLOOKUP(A5,'Custo_Fopag (2)'!$A:$BQ,25,0) -> 0 | Z5: =VLOOKUP(A5,'Custo_Fopag (2)'!$A:$BQ,26,0) -> 0 | AA5: =VLOOKUP(A5,'Custo_Fopag (2)'!$A:$BQ,27,0) -> 0 | AB5: =VLOOKUP(A5,'Custo_Fopag (2)'!$A:$BQ,28,0) -> 47.77 | AC5: =VLOOKUP(A5,'Custo_Fopag (2)'!$A:$BQ,29,0) -> 0 | AD5: =VLOOKUP(A5,'Custo_Fopag (2)'!$A:$BQ,30,0) -> 0 | AE5: =VLOOKUP(A5,'Custo_Fopag (2)'!$A:$BQ,31,0) -> 0 | AF5: =VLOOKUP(A5,'Custo_Fopag (2)'!$A:$BQ,32,0) -> 0 | AG5: =SUM(Q5:AF5) -> 1029.06 | AH5: =VLOOKUP(A5,'Custo_Fopag (2)'!$A:$BQ,45,0) -> 0 | AI5: =_xlfn.XLOOKUP(A5,'Custo_Fopag (2)'!A:A,'Custo_Fopag (2)'!AT:AT,0,0,1) -> 266.67 | AJ5: =VLOOKUP(A5,'Custo_Fopag (2)'!$A:$BQ,47,0) -> 0 | AK5: 0 | AL5: =VLOOKUP(A5,'Custo_Fopag (2)'!$A:$BQ,35,0) -> 0 | AM5: =VLOOKUP(A5,'Custo_Fopag (2)'!$A:$BQ,36,0) -> 0 | AN5: =VLOOKUP(A5,'Custo_Fopag (2)'!$A:$BQ,37,0) -> 0 | AO5: =VLOOKUP(A5,'Custo_Fopag (2)'!$A:$BQ,39,0) -> 0 | AP5: =VLOOKUP(A5,'Custo_Fopag (2)'!$A:$BQ,42,0) -> 0 | AQ5: =VLOOKUP(A5,'Custo_Fopag (2)'!$A:$BQ,40,0) -> 0 | AR5: =VLOOKUP(A5,'Custo_Fopag (2)'!$A:$BQ,41,0) -> 28.92 | AS5: =VLOOKUP(A5,'Custo_Fopag (2)'!$A:$BQ,38,0) -> 0 | AT5: =VLOOKUP(A5,'Custo_Fopag (2)'!$A:$BQ,43,0) -> 0 | AU5: =VLOOKUP(A5,'Custo_Fopag (2)'!$A:$BQ,48,0) -> 0 | AV5: =VLOOKUP(A5,'Custo_Fopag (2)'!$A:$BQ,49,0) -> 0 | AW5: =VLOOKUP(A5,'Custo_Fopag (2)'!$A:$BQ,19,0) -> 0 | AX5: =VLOOKUP(A5,'Custo_Fopag (2)'!$A:$BQ,50,0) -> 0 | AY5: =VLOOKUP(A5,'Custo_Fopag (2)'!$A:$BQ,51,0) -> 0 | AZ5: 0 | BA5: =VLOOKUP(A5,'Custo_Fopag (2)'!$A:$BQ,54,0) -> 0 | BB5: =VLOOKUP(A5,'Custo_Fopag (2)'!$A:$BQ,52,0) -> 0 | BC5: =SUM(AH5:BB5) -> 295.59 | BD5: =BC5+AG5 -> 1324.65 | BF5: =BD5+BE5 -> 1324.65 | BG5: =AG5/12 -> 85.755 | BH5: =BG5 -> 85.755 | BI5: =BH5/3 -> 28.585 | BJ5: =SUM(BG5:BI5) -> 200.095 | BK5: =VLOOKUP(A5,'Custo_Fopag (2)'!$A:$BQ,65,0) -> 205.81 | BL5: =VLOOKUP(A5,'Custo_Fopag (2)'!$A:$BQP,66,0) -> 30.87 | BM5: =VLOOKUP(A5,'Custo_Fopag (2)'!$A:$BQ,67,0) -> 59.68 | BN5: =VLOOKUP(A5,'Custo_Fopag (2)'!$A:$BQ,64,0) -> 255.89 | BO5: =SUM(BK5:BN5) -> 552.25 | BP5: =BF5+BO5 -> 1876.9 | BQ5: =BF5+BJ5+BO5 -> 2076.995 | BR5: =VLOOKUP(A5,'Custo_Fopag (2)'!$A:$BQ,60,0) -> 4483.47 | BS5: =IF(ISBLANK(L5),"Ativo","Desligado") -> Desligado
A6: ALESSANDRA ARAUJO MOURA | B6: 46082 | C6: CLT | D6: =VLOOKUP(A6,'Custo_Fopag (2)'!A:$BQ,4,0) -> G3S FL 04 - PRES PRUD | G6: =VLOOKUP(A6,'Custo_Fopag (2)'!$A:$BQ,5,0) -> 20.947.332/0004-38 | H6: =VLOOKUP(A6,'Custo_Fopag (2)'!$A:$BQ,6,0) -> ADMINISTRATIVO | I6: =VLOOKUP(A6,'Custo_Fopag (2)'!$A:$BQ,7,0) -> ATENDIMENTO | J6: =VLOOKUP(A6,'Custo_Fopag (2)'!$A:$BQ,8,0) -> SELETIVA CORPORATIVO SUCATA | K6: =VLOOKUP(A6,'Custo_Fopag (2)'!$A:$BQ,9,0) -> 44783 | N6: =VLOOKUP(A6,'Custo_Fopag (2)'!$A:$BQ,11,0) -> 1.2.1.1 APOIO | O6: =VLOOKUP(A6,'Custo_Fopag (2)'!$A:$BQ,12,0) -> SUPERVISOR(A) ADMINISTRATIVO(A) | P6: =VLOOKUP(A6,'Custo_Fopag (2)'!$A:$BQ,13,0) -> 3392 | Q6: =VLOOKUP(A6,'Custo_Fopag (2)'!$A:$BQ,16,0) -> 3392 | R6: =VLOOKUP(A6,'Custo_Fopag (2)'!$A:$BQ,17,0) -> 0 | S6: =VLOOKUP(A6,'Custo_Fopag (2)'!$A:$BP,18,0) -> 0 | T6: =VLOOKUP(A6,'Custo_Fopag (2)'!$A:$BQ,20,0) -> 0 | U6: =VLOOKUP(A6,'Custo_Fopag (2)'!$A:$BQ,21,0) -> 0 | V6: =VLOOKUP(A6,'Custo_Fopag (2)'!$A:$BQ,22,0) -> 0 | W6: =VLOOKUP(A6,'Custo_Fopag (2)'!$A:$BQ,23,0) -> 1356.8 | X6: =VLOOKUP(A6,'Custo_Fopag (2)'!$A:$BQ,24,0) -> 0 | Y6: =VLOOKUP(A6,'Custo_Fopag (2)'!$A:$BQ,25,0) -> 0 | Z6: =VLOOKUP(A6,'Custo_Fopag (2)'!$A:$BQ,26,0) -> 0 | AA6: =VLOOKUP(A6,'Custo_Fopag (2)'!$A:$BQ,27,0) -> 0 | AB6: =VLOOKUP(A6,'Custo_Fopag (2)'!$A:$BQ,28,0) -> 0 | AC6: =VLOOKUP(A6,'Custo_Fopag (2)'!$A:$BQ,29,0) -> 0 | AD6: =VLOOKUP(A6,'Custo_Fopag (2)'!$A:$BQ,30,0) -> 0 | AE6: =VLOOKUP(A6,'Custo_Fopag (2)'!$A:$BQ,31,0) -> 0 | AF6: =VLOOKUP(A6,'Custo_Fopag (2)'!$A:$BQ,32,0) -> 0 | AG6: =SUM(Q6:AF6) -> 4748.8 | AH6: =VLOOKUP(A6,'Custo_Fopag (2)'!$A:$BQ,45,0) -> 0 | AI6: =_xlfn.XLOOKUP(A6,Beneficios!A:A,Beneficios!B:B,0,0,1) -> 521.87 | AJ6: =VLOOKUP(A6,'Custo_Fopag (2)'!$A:$BQ,47,0) -> 0 | AK6: 0 | AL6: =VLOOKUP(A6,'Custo_Fopag (2)'!$A:$BQ,35,0) -> 0 | AM6: =VLOOKUP(A6,'Custo_Fopag (2)'!$A:$BQ,36,0) -> 0 | AN6: =VLOOKUP(A6,'Custo_Fopag (2)'!$A:$BQ,37,0) -> 0 | AO6: =VLOOKUP(A6,'Custo_Fopag (2)'!$A:$BQ,39,0) -> 0 | AP6: =VLOOKUP(A6,'Custo_Fopag (2)'!$A:$BQ,42,0) -> 0 | AQ6: =VLOOKUP(A6,'Custo_Fopag (2)'!$A:$BQ,40,0) -> 0 | AR6: =VLOOKUP(A6,'Custo_Fopag (2)'!$A:$BQ,41,0) -> 904.34 | AS6: =VLOOKUP(A6,'Custo_Fopag (2)'!$A:$BQ,38,0) -> 0 | AT6: =VLOOKUP(A6,'Custo_Fopag (2)'!$A:$BQ,43,0) -> 0 | AU6: =VLOOKUP(A6,'Custo_Fopag (2)'!$A:$BQ,48,0) -> 0 | AV6: =VLOOKUP(A6,'Custo_Fopag (2)'!$A:$BQ,49,0) -> 0 | AW6: =VLOOKUP(A6,'Custo_Fopag (2)'!$A:$BQ,19,0) -> 0 | AX6: =VLOOKUP(A6,'Custo_Fopag (2)'!$A:$BQ,50,0) -> 0 | AY6: =VLOOKUP(A6,'Custo_Fopag (2)'!$A:$BQ,51,0) -> 0 | AZ6: 0 | BA6: =VLOOKUP(A6,'Custo_Fopag (2)'!$A:$BQ,54,0) -> 0 | BB6: =VLOOKUP(A6,'Custo_Fopag (2)'!$A:$BQ,52,0) -> 0 | BC6: =SUM(AH6:BB6) -> 1426.21 | BD6: =BC6+AG6 -> 6175.01 | BF6: =BD6+BE6 -> 6175.01 | BG6: =AG6/12 -> 395.73333 | BH6: =BG6 -> 395.73333 | BI6: =BH6/3 -> 131.91111 | BJ6: =SUM(BG6:BI6) -> 923.37778 | BK6: =VLOOKUP(A6,'Custo_Fopag (2)'!$A:$BQ,65,0) -> 949.76 | BL6: =VLOOKUP(A6,'Custo_Fopag (2)'!$A:$BQP,66,0) -> 71.23 | BM6: =VLOOKUP(A6,'Custo_Fopag (2)'!$A:$BQ,67,0) -> 275.43 | BN6: =VLOOKUP(A6,'Custo_Fopag (2)'!$A:$BQ,64,0) -> 379.9 | BO6: =SUM(BK6:BN6) -> 1676.32 | BP6: =BF6+BO6 -> 7851.33 | BQ6: =BF6+BJ6+BO6 -> 8774.7078 | BR6: =VLOOKUP(A6,'Custo_Fopag (2)'!$A:$BQ,60,0) -> 0 | BS6: =IF(ISBLANK(L6),"Ativo","Desligado") -> Ativo
A7: ALIFER BRENO PEREIRA ALMEIDA DE JESUS | B7: 46082 | C7: CLT | D7: =VLOOKUP(A7,'Custo_Fopag (2)'!A:$BQ,4,0) -> G3S FL 06 - MARINGA | G7: =VLOOKUP(A7,'Custo_Fopag (2)'!$A:$BQ,5,0) -> 20.947.332/0006-08 | H7: =VLOOKUP(A7,'Custo_Fopag (2)'!$A:$BQ,6,0) -> ADMINISTRATIVO | I7: =VLOOKUP(A7,'Custo_Fopag (2)'!$A:$BQ,7,0) -> ATENDIMENTO | J7: =VLOOKUP(A7,'Custo_Fopag (2)'!$A:$BQ,8,0) -> SELETIVA MARINGA DISTRITO | K7: =VLOOKUP(A7,'Custo_Fopag (2)'!$A:$BQ,9,0) -> 46034 | N7: =VLOOKUP(A7,'Custo_Fopag (2)'!$A:$BQ,11,0) -> 1.2.4.1 ADMINISTRATIVO | O7: =VLOOKUP(A7,'Custo_Fopag (2)'!$A:$BQ,12,0) -> AUX ADMINISTRATIVO JUNIOR | P7: =VLOOKUP(A7,'Custo_Fopag (2)'!$A:$BQ,13,0) -> 2320 | Q7: =VLOOKUP(A7,'Custo_Fopag (2)'!$A:$BQ,16,0) -> 2320 | R7: =VLOOKUP(A7,'Custo_Fopag (2)'!$A:$BQ,17,0) -> 0 | S7: =VLOOKUP(A7,'Custo_Fopag (2)'!$A:$BP,18,0) -> 0 | T7: =VLOOKUP(A7,'Custo_Fopag (2)'!$A:$BQ,20,0) -> 0 | U7: =VLOOKUP(A7,'Custo_Fopag (2)'!$A:$BQ,21,0) -> 0 | V7: =VLOOKUP(A7,'Custo_Fopag (2)'!$A:$BQ,22,0) -> 0 | W7: =VLOOKUP(A7,'Custo_Fopag (2)'!$A:$BQ,23,0) -> 0 | X7: =VLOOKUP(A7,'Custo_Fopag (2)'!$A:$BQ,24,0) -> 0 | Y7: =VLOOKUP(A7,'Custo_Fopag (2)'!$A:$BQ,25,0) -> 0 | Z7: =VLOOKUP(A7,'Custo_Fopag (2)'!$A:$BQ,26,0) -> 0 | AA7: =VLOOKUP(A7,'Custo_Fopag (2)'!$A:$BQ,27,0) -> 236.35 | AB7: =VLOOKUP(A7,'Custo_Fopag (2)'!$A:$BQ,28,0) -> 66.81 | AC7: =VLOOKUP(A7,'Custo_Fopag (2)'!$A:$BQ,29,0) -> 0 | AD7: =VLOOKUP(A7,'Custo_Fopag (2)'!$A:$BQ,30,0) -> 0 | AE7: =VLOOKUP(A7,'Custo_Fopag (2)'!$A:$BQ,31,0) -> 0 | AF7: =VLOOKUP(A7,'Custo_Fopag (2)'!$A:$BQ,32,0) -> 0 | AG7: =SUM(Q7:AF7) -> 2623.16 | AH7: =VLOOKUP(A7,'Custo_Fopag (2)'!$A:$BQ,45,0) -> 0 | AI7: =_xlfn.XLOOKUP(A7,Beneficios!A:A,Beneficios!B:B,0,0,1) -> 0 | AJ7: =VLOOKUP(A7,'Custo_Fopag (2)'!$A:$BQ,47,0) -> 0 | AK7: 0 | AL7: =VLOOKUP(A7,'Custo_Fopag (2)'!$A:$BQ,35,0) -> 0 | AM7: =VLOOKUP(A7,'Custo_Fopag (2)'!$A:$BQ,36,0) -> 0 | AN7: =VLOOKUP(A7,'Custo_Fopag (2)'!$A:$BQ,37,0) -> 0 | AO7: =VLOOKUP(A7,'Custo_Fopag (2)'!$A:$BQ,39,0) -> 0 | AP7: =VLOOKUP(A7,'Custo_Fopag (2)'!$A:$BQ,42,0) -> 0 | AQ7: =VLOOKUP(A7,'Custo_Fopag (2)'!$A:$BQ,40,0) -> 0 | AR7: =VLOOKUP(A7,'Custo_Fopag (2)'!$A:$BQ,41,0) -> 456.6 | AS7: =VLOOKUP(A7,'Custo_Fopag (2)'!$A:$BQ,38,0) -> 0 | AT7: =VLOOKUP(A7,'Custo_Fopag (2)'!$A:$BQ,43,0) -> 0 | AU7: =VLOOKUP(A7,'Custo_Fopag (2)'!$A:$BQ,48,0) -> 0 | AV7: =VLOOKUP(A7,'Custo_Fopag (2)'!$A:$BQ,49,0) -> 0 | AW7: =VLOOKUP(A7,'Custo_Fopag (2)'!$A:$BQ,19,0) -> 0 | AX7: =VLOOKUP(A7,'Custo_Fopag (2)'!$A:$BQ,50,0) -> 0 | AY7: =VLOOKUP(A7,'Custo_Fopag (2)'!$A:$BQ,51,0) -> 0 | AZ7: 0 | BA7: =VLOOKUP(A7,'Custo_Fopag (2)'!$A:$BQ,54,0) -> 0 | BB7: =VLOOKUP(A7,'Custo_Fopag (2)'!$A:$BQ,52,0) -> 0 | BC7: =SUM(AH7:BB7) -> 456.6 | BD7: =BC7+AG7 -> 3079.76 | BF7: =BD7+BE7 -> 3079.76 | BG7: =AG7/12 -> 218.59667 | BH7: =BG7 -> 218.59667 | BI7: =BH7/3 -> 72.865556 | BJ7: =SUM(BG7:BI7) -> 510.05889 | BK7: =VLOOKUP(A7,'Custo_Fopag (2)'!$A:$BQ,65,0) -> 524.63 | BL7: =VLOOKUP(A7,'Custo_Fopag (2)'!$A:$BQP,66,0) -> 39.34 | BM7: =VLOOKUP(A7,'Custo_Fopag (2)'!$A:$BQ,67,0) -> 152.14 | BN7: =VLOOKUP(A7,'Custo_Fopag (2)'!$A:$BQ,64,0) -> 218.4 | BO7: =SUM(BK7:BN7) -> 934.51 | BP7: =BF7+BO7 -> 4014.27 | BQ7: =BF7+BJ7+BO7 -> 4524.3289 | BR7: =VLOOKUP(A7,'Custo_Fopag (2)'!$A:$BQ,60,0) -> 0 | BS7: =IF(ISBLANK(L7),"Ativo","Desligado") -> Ativo
A8: AMANDA DE OLIVEIRA VINCO | B8: 46082 | C8: CLT | D8: =VLOOKUP(A8,'Custo_Fopag (2)'!A:$BQ,4,0) -> G3S FL 10 - PRES PRUD | G8: =VLOOKUP(A8,'Custo_Fopag (2)'!$A:$BQ,5,0) -> 20.947.332/0010-86 | H8: =VLOOKUP(A8,'Custo_Fopag (2)'!$A:$BQ,6,0) -> ADMINISTRATIVO | I8: =VLOOKUP(A8,'Custo_Fopag (2)'!$A:$BQ,7,0) -> CONTABILIDADE | J8: =VLOOKUP(A8,'Custo_Fopag (2)'!$A:$BQ,8,0) -> PILARES | K8: =VLOOKUP(A8,'Custo_Fopag (2)'!$A:$BQ,9,0) -> 45552 | N8: =VLOOKUP(A8,'Custo_Fopag (2)'!$A:$BQ,11,0) -> 1.1.4 CONTABILIDADE/FISCAL | O8: =VLOOKUP(A8,'Custo_Fopag (2)'!$A:$BQ,12,0) -> ANALISTA CONTABIL JUNIOR | P8: =VLOOKUP(A8,'Custo_Fopag (2)'!$A:$BQ,13,0) -> 2656.25 | Q8: =VLOOKUP(A8,'Custo_Fopag (2)'!$A:$BQ,16,0) -> 2656.25 | R8: =VLOOKUP(A8,'Custo_Fopag (2)'!$A:$BQ,17,0) -> 0 | S8: =VLOOKUP(A8,'Custo_Fopag (2)'!$A:$BP,18,0) -> 0 | T8: =VLOOKUP(A8,'Custo_Fopag (2)'!$A:$BQ,20,0) -> 0 | U8: =VLOOKUP(A8,'Custo_Fopag (2)'!$A:$BQ,21,0) -> 0 | V8: =VLOOKUP(A8,'Custo_Fopag (2)'!$A:$BQ,22,0) -> 0 | W8: =VLOOKUP(A8,'Custo_Fopag (2)'!$A:$BQ,23,0) -> 0 | X8: =VLOOKUP(A8,'Custo_Fopag (2)'!$A:$BQ,24,0) -> 0 | Y8: =VLOOKUP(A8,'Custo_Fopag (2)'!$A:$BQ,25,0) -> 0 | Z8: =VLOOKUP(A8,'Custo_Fopag (2)'!$A:$BQ,26,0) -> 0 | AA8: =VLOOKUP(A8,'Custo_Fopag (2)'!$A:$BQ,27,0) -> 0 | AB8: =VLOOKUP(A8,'Custo_Fopag (2)'!$A:$BQ,28,0) -> 0 | AC8: =VLOOKUP(A8,'Custo_Fopag (2)'!$A:$BQ,29,0) -> 0 | AD8: =VLOOKUP(A8,'Custo_Fopag (2)'!$A:$BQ,30,0) -> 0 | AE8: =VLOOKUP(A8,'Custo_Fopag (2)'!$A:$BQ,31,0) -> 0 | AF8: =VLOOKUP(A8,'Custo_Fopag (2)'!$A:$BQ,32,0) -> 0 | AG8: =SUM(Q8:AF8) -> 2656.25 | AH8: =VLOOKUP(A8,'Custo_Fopag (2)'!$A:$BQ,45,0) -> 0 | AI8: =_xlfn.XLOOKUP(A8,Beneficios!A:A,Beneficios!B:B,0,0,1) -> 521.87 | AJ8: =VLOOKUP(A8,'Custo_Fopag (2)'!$A:$BQ,47,0) -> 0 | AK8: 0 | AL8: =VLOOKUP(A8,'Custo_Fopag (2)'!$A:$BQ,35,0) -> 0 | AM8: =VLOOKUP(A8,'Custo_Fopag (2)'!$A:$BQ,36,0) -> 0 | AN8: =VLOOKUP(A8,'Custo_Fopag (2)'!$A:$BQ,37,0) -> 0 | AO8: =VLOOKUP(A8,'Custo_Fopag (2)'!$A:$BQ,39,0) -> 0 | AP8: =VLOOKUP(A8,'Custo_Fopag (2)'!$A:$BQ,42,0) -> 0 | AQ8: =VLOOKUP(A8,'Custo_Fopag (2)'!$A:$BQ,40,0) -> 0 | AR8: =VLOOKUP(A8,'Custo_Fopag (2)'!$A:$BQ,41,0) -> 0 | AS8: =VLOOKUP(A8,'Custo_Fopag (2)'!$A:$BQ,38,0) -> 0 | AT8: =VLOOKUP(A8,'Custo_Fopag (2)'!$A:$BQ,43,0) -> 0 | AU8: =VLOOKUP(A8,'Custo_Fopag (2)'!$A:$BQ,48,0) -> 0 | AV8: =VLOOKUP(A8,'Custo_Fopag (2)'!$A:$BQ,49,0) -> 0 | AW8: =VLOOKUP(A8,'Custo_Fopag (2)'!$A:$BQ,19,0) -> 0 | AX8: =VLOOKUP(A8,'Custo_Fopag (2)'!$A:$BQ,50,0) -> 0 | AY8: =VLOOKUP(A8,'Custo_Fopag (2)'!$A:$BQ,51,0) -> 0 | AZ8: 0 | BA8: =VLOOKUP(A8,'Custo_Fopag (2)'!$A:$BQ,54,0) -> 0 | BB8: =VLOOKUP(A8,'Custo_Fopag (2)'!$A:$BQ,52,0) -> 0 | BC8: =SUM(AH8:BB8) -> 521.87 | BD8: =BC8+AG8 -> 3178.12 | BF8: =BD8+BE8 -> 3178.12 | BG8: =AG8/12 -> 221.35417 | BH8: =BG8 -> 221.35417 | BI8: =BH8/3 -> 73.784722 | BJ8: =SUM(BG8:BI8) -> 516.49306 | BK8: =VLOOKUP(A8,'Custo_Fopag (2)'!$A:$BQ,65,0) -> 531.25 | BL8: =VLOOKUP(A8,'Custo_Fopag (2)'!$A:$BQP,66,0) -> 79.68 | BM8: =VLOOKUP(A8,'Custo_Fopag (2)'!$A:$BQ,67,0) -> 154.06 | BN8: =VLOOKUP(A8,'Custo_Fopag (2)'!$A:$BQ,64,0) -> 212.5 | BO8: =SUM(BK8:BN8) -> 977.49 | BP8: =BF8+BO8 -> 4155.61 | BQ8: =BF8+BJ8+BO8 -> 4672.1031 | BR8: =VLOOKUP(A8,'Custo_Fopag (2)'!$A:$BQ,60,0) -> 0 | BS8: =IF(ISBLANK(L8),"Ativo","Desligado") -> Ativo
A9: ANDERSON RODRIGO FERREIRA DE LIMA | B9: 46082 | C9: CLT | D9: =VLOOKUP(A9,'Custo_Fopag (2)'!A:$BQ,4,0) -> G3S FL 04 - PRES PRUD | G9: =VLOOKUP(A9,'Custo_Fopag (2)'!$A:$BQ,5,0) -> 20.947.332/0004-38 | H9: =VLOOKUP(A9,'Custo_Fopag (2)'!$A:$BQ,6,0) -> OPERACIONAL | I9: =VLOOKUP(A9,'Custo_Fopag (2)'!$A:$BQ,7,0) -> PATIO | J9: =VLOOKUP(A9,'Custo_Fopag (2)'!$A:$BQ,8,0) -> SELETIVA PRESIDENTE PRUDENTE | K9: =VLOOKUP(A9,'Custo_Fopag (2)'!$A:$BQ,9,0) -> 46064 | N9: =VLOOKUP(A9,'Custo_Fopag (2)'!$A:$BQ,11,0) -> 1.2.5.3 OPERACIONAL | O9: =VLOOKUP(A9,'Custo_Fopag (2)'!$A:$BQ,12,0) -> MACARIQUEIRO PLENO | P9: =VLOOKUP(A9,'Custo_Fopag (2)'!$A:$BQ,13,0) -> 2587.5 | Q9: =VLOOKUP(A9,'Custo_Fopag (2)'!$A:$BQ,16,0) -> 2587.5 | R9: =VLOOKUP(A9,'Custo_Fopag (2)'!$A:$BQ,17,0) -> 0 | S9: =VLOOKUP(A9,'Custo_Fopag (2)'!$A:$BP,18,0) -> 0 | T9: =VLOOKUP(A9,'Custo_Fopag (2)'!$A:$BQ,20,0) -> 0 | U9: =VLOOKUP(A9,'Custo_Fopag (2)'!$A:$BQ,21,0) -> 0 | V9: =VLOOKUP(A9,'Custo_Fopag (2)'!$A:$BQ,22,0) -> 0 | W9: =VLOOKUP(A9,'Custo_Fopag (2)'!$A:$BQ,23,0) -> 0 | X9: =VLOOKUP(A9,'Custo_Fopag (2)'!$A:$BQ,24,0) -> 0 | Y9: =VLOOKUP(A9,'Custo_Fopag (2)'!$A:$BQ,25,0) -> 0 | Z9: =VLOOKUP(A9,'Custo_Fopag (2)'!$A:$BQ,26,0) -> 0 | AA9: =VLOOKUP(A9,'Custo_Fopag (2)'!$A:$BQ,27,0) -> 0 | AB9: =VLOOKUP(A9,'Custo_Fopag (2)'!$A:$BQ,28,0) -> 0 | AC9: =VLOOKUP(A9,'Custo_Fopag (2)'!$A:$BQ,29,0) -> 0 | AD9: =VLOOKUP(A9,'Custo_Fopag (2)'!$A:$BQ,30,0) -> 0 | AE9: =VLOOKUP(A9,'Custo_Fopag (2)'!$A:$BQ,31,0) -> 0 | AF9: =VLOOKUP(A9,'Custo_Fopag (2)'!$A:$BQ,32,0) -> 0 | AG9: =SUM(Q9:AF9) -> 2587.5 | AH9: =VLOOKUP(A9,'Custo_Fopag (2)'!$A:$BQ,45,0) -> 0 | AI9: =_xlfn.XLOOKUP(A9,Beneficios!A:A,Beneficios!B:B,0,0,1) -> 512.87 | AJ9: =VLOOKUP(A9,'Custo_Fopag (2)'!$A:$BQ,47,0) -> 0 | AK9: 0 | AL9: =VLOOKUP(A9,'Custo_Fopag (2)'!$A:$BQ,35,0) -> 0 | AM9: =VLOOKUP(A9,'Custo_Fopag (2)'!$A:$BQ,36,0) -> 0 | AN9: =VLOOKUP(A9,'Custo_Fopag (2)'!$A:$BQ,37,0) -> 0 | AO9: =VLOOKUP(A9,'Custo_Fopag (2)'!$A:$BQ,39,0) -> 0 | AP9: =VLOOKUP(A9,'Custo_Fopag (2)'!$A:$BQ,42,0) -> 0 | AQ9: =VLOOKUP(A9,'Custo_Fopag (2)'!$A:$BQ,40,0) -> 0 | AR9: =VLOOKUP(A9,'Custo_Fopag (2)'!$A:$BQ,41,0) -> 579.34 | AS9: =VLOOKUP(A9,'Custo_Fopag (2)'!$A:$BQ,38,0) -> 0 | AT9: =VLOOKUP(A9,'Custo_Fopag (2)'!$A:$BQ,43,0) -> 0 | AU9: =VLOOKUP(A9,'Custo_Fopag (2)'!$A:$BQ,48,0) -> 0 | AV9: =VLOOKUP(A9,'Custo_Fopag (2)'!$A:$BQ,49,0) -> 0 | AW9: =VLOOKUP(A9,'Custo_Fopag (2)'!$A:$BQ,19,0) -> 0 | AX9: =VLOOKUP(A9,'Custo_Fopag (2)'!$A:$BQ,50,0) -> 0 | AY9: =VLOOKUP(A9,'Custo_Fopag (2)'!$A:$BQ,51,0) -> 0 | AZ9: 0 | BA9: =VLOOKUP(A9,'Custo_Fopag (2)'!$A:$BQ,54,0) -> 0 | BB9: =VLOOKUP(A9,'Custo_Fopag (2)'!$A:$BQ,52,0) -> 0 | BC9: =SUM(AH9:BB9) -> 1092.21 | BD9: =BC9+AG9 -> 3679.71 | BF9: =BD9+BE9 -> 3679.71 | BG9: =AG9/12 -> 215.625 | BH9: =BG9 -> 215.625 | BI9: =BH9/3 -> 71.875 | BJ9: =SUM(BG9:BI9) -> 503.125 | BK9: =VLOOKUP(A9,'Custo_Fopag (2)'!$A:$BQ,65,0) -> 517.5 | BL9: =VLOOKUP(A9,'Custo_Fopag (2)'!$A:$BQP,66,0) -> 38.81 | BM9: =VLOOKUP(A9,'Custo_Fopag (2)'!$A:$BQ,67,0) -> 150.07 | BN9: =VLOOKUP(A9,'Custo_Fopag (2)'!$A:$BQ,64,0) -> 207 | BO9: =SUM(BK9:BN9) -> 913.38 | BP9: =BF9+BO9 -> 4593.09 | BQ9: =BF9+BJ9+BO9 -> 5096.215 | BR9: =VLOOKUP(A9,'Custo_Fopag (2)'!$A:$BQ,60,0) -> 0 | BS9: =IF(ISBLANK(L9),"Ativo","Desligado") -> Ativo
A10: ANDRESSA FRANCINI CRUZ DE SOUZA | B10: 46082 | C10: CLT | D10: =VLOOKUP(A10,'Custo_Fopag (2)'!A:$BQ,4,0) -> G3S FL 05 - PRES PRUD | G10: =VLOOKUP(A10,'Custo_Fopag (2)'!$A:$BQ,5,0) -> 20.947.332/0005-19 | H10: =VLOOKUP(A10,'Custo_Fopag (2)'!$A:$BQ,6,0) -> TRANSMOVE | I10: =VLOOKUP(A10,'Custo_Fopag (2)'!$A:$BQ,7,0) -> ADMINISTRATIVO | J10: =VLOOKUP(A10,'Custo_Fopag (2)'!$A:$BQ,8,0) -> TRANSMOVE GSL | K10: =VLOOKUP(A10,'Custo_Fopag (2)'!$A:$BQ,9,0) -> 45925 | N10: =VLOOKUP(A10,'Custo_Fopag (2)'!$A:$BQ,11,0) -> 1.4.1.2 ADMINISTRATIVO | O10: =VLOOKUP(A10,'Custo_Fopag (2)'!$A:$BQ,12,0) -> SUPERVISOR(A) DE LOGISTICA | P10: =VLOOKUP(A10,'Custo_Fopag (2)'!$A:$BQ,13,0) -> 3500 | Q10: =VLOOKUP(A10,'Custo_Fopag (2)'!$A:$BQ,16,0) -> 3500 | R10: =VLOOKUP(A10,'Custo_Fopag (2)'!$A:$BQ,17,0) -> 0 | S10: =VLOOKUP(A10,'Custo_Fopag (2)'!$A:$BP,18,0) -> 0 | T10: =VLOOKUP(A10,'Custo_Fopag (2)'!$A:$BQ,20,0) -> 0 | U10: =VLOOKUP(A10,'Custo_Fopag (2)'!$A:$BQ,21,0) -> 0 | V10: =VLOOKUP(A10,'Custo_Fopag (2)'!$A:$BQ,22,0) -> 0 | W10: =VLOOKUP(A10,'Custo_Fopag (2)'!$A:$BQ,23,0) -> 1400 | X10: =VLOOKUP(A10,'Custo_Fopag (2)'!$A:$BQ,24,0) -> 0 | Y10: =VLOOKUP(A10,'Custo_Fopag (2)'!$A:$BQ,25,0) -> 0 | Z10: =VLOOKUP(A10,'Custo_Fopag (2)'!$A:$BQ,26,0) -> 0 | AA10: =VLOOKUP(A10,'Custo_Fopag (2)'!$A:$BQ,27,0) -> 0 | AB10: =VLOOKUP(A10,'Custo_Fopag (2)'!$A:$BQ,28,0) -> 0 | AC10: =VLOOKUP(A10,'Custo_Fopag (2)'!$A:$BQ,29,0) -> 0 | AD10: =VLOOKUP(A10,'Custo_Fopag (2)'!$A:$BQ,30,0) -> 0 | AE10: =VLOOKUP(A10,'Custo_Fopag (2)'!$A:$BQ,31,0) -> 0 | AF10: =VLOOKUP(A10,'Custo_Fopag (2)'!$A:$BQ,32,0) -> 0 | AG10: =SUM(Q10:AF10) -> 4900 | AH10: =VLOOKUP(A10,'Custo_Fopag (2)'!$A:$BQ,45,0) -> 0 | AI10: =_xlfn.XLOOKUP(A10,Beneficios!A:A,Beneficios!B:B,0,0,1) -> 0 | AJ10: =VLOOKUP(A10,'Custo_Fopag (2)'!$A:$BQ,47,0) -> 0 | AK10: 0 | AL10: =VLOOKUP(A10,'Custo_Fopag (2)'!$A:$BQ,35,0) -> 0 | AM10: =VLOOKUP(A10,'Custo_Fopag (2)'!$A:$BQ,36,0) -> 0 | AN10: =VLOOKUP(A10,'Custo_Fopag (2)'!$A:$BQ,37,0) -> 0 | AO10: =VLOOKUP(A10,'Custo_Fopag (2)'!$A:$BQ,39,0) -> 0 | AP10: =VLOOKUP(A10,'Custo_Fopag (2)'!$A:$BQ,42,0) -> 100 | AQ10: =VLOOKUP(A10,'Custo_Fopag (2)'!$A:$BQ,40,0) -> 0 | AR10: =VLOOKUP(A10,'Custo_Fopag (2)'!$A:$BQ,41,0) -> 0 | AS10: =VLOOKUP(A10,'Custo_Fopag (2)'!$A:$BQ,38,0) -> 0 | AT10: =VLOOKUP(A10,'Custo_Fopag (2)'!$A:$BQ,43,0) -> 0 | AU10: =VLOOKUP(A10,'Custo_Fopag (2)'!$A:$BQ,48,0) -> 0 | AV10: =VLOOKUP(A10,'Custo_Fopag (2)'!$A:$BQ,49,0) -> 0 | AW10: =VLOOKUP(A10,'Custo_Fopag (2)'!$A:$BQ,19,0) -> 0 | AX10: =VLOOKUP(A10,'Custo_Fopag (2)'!$A:$BQ,50,0) -> 0 | AY10: =VLOOKUP(A10,'Custo_Fopag (2)'!$A:$BQ,51,0) -> 0 | AZ10: 0 | BA10: =VLOOKUP(A10,'Custo_Fopag (2)'!$A:$BQ,54,0) -> 0 | BB10: =VLOOKUP(A10,'Custo_Fopag (2)'!$A:$BQ,52,0) -> 0 | BC10: =SUM(AH10:BB10) -> 100 | BD10: =BC10+AG10 -> 5000 | BE10: 4238.33 | BF10: =BD10+BE10 -> 9238.33 | BG10: =AG10/12 -> 408.33333 | BH10: =BG10 -> 408.33333 | BI10: =BH10/3 -> 136.11111 | BJ10: =SUM(BG10:BI10) -> 952.77778 | BK10: =VLOOKUP(A10,'Custo_Fopag (2)'!$A:$BQ,65,0) -> 980 | BL10: =VLOOKUP(A10,'Custo_Fopag (2)'!$A:$BQP,66,0) -> 73.5 | BM10: =VLOOKUP(A10,'Custo_Fopag (2)'!$A:$BQ,67,0) -> 284.2 | BN10: =VLOOKUP(A10,'Custo_Fopag (2)'!$A:$BQ,64,0) -> 392 | BO10: =SUM(BK10:BN10) -> 1729.7 | BP10: =BF10+BO10 -> 10968.03 | BQ10: =BF10+BJ10+BO10 -> 11920.808 | BR10: =VLOOKUP(A10,'Custo_Fopag (2)'!$A:$BQ,60,0) -> 0 | BS10: =IF(ISBLANK(L10),"Ativo","Desligado") -> Ativo
A11: ANDRESSA MEIRIELLE DE OLIVEIRA TOKAWA | B11: 46082 | C11: CLT | D11: =VLOOKUP(A11,'Custo_Fopag (2)'!A:$BQ,4,0) -> G3S FL 04 - PRES PRUD | G11: =VLOOKUP(A11,'Custo_Fopag (2)'!$A:$BQ,5,0) -> 20.947.332/0004-38 | H11: =VLOOKUP(A11,'Custo_Fopag (2)'!$A:$BQ,6,0) -> ADMINISTRATIVO | I11: =VLOOKUP(A11,'Custo_Fopag (2)'!$A:$BQ,7,0) -> ATENDIMENTO | J11: =VLOOKUP(A11,'Custo_Fopag (2)'!$A:$BQ,8,0) -> SELETIVA PRESIDENTE PRUDENTE | K11: =VLOOKUP(A11,'Custo_Fopag (2)'!$A:$BQ,9,0) -> 44635 | N11: =VLOOKUP(A11,'Custo_Fopag (2)'!$A:$BQ,11,0) -> 1.2.5.1 ADMINISTRATIVO | O11: =VLOOKUP(A11,'Custo_Fopag (2)'!$A:$BQ,12,0) -> AUX ADMINISTRATIVO SENIOR | P11: =VLOOKUP(A11,'Custo_Fopag (2)'!$A:$BQ,13,0) -> 2950 | Q11: =VLOOKUP(A11,'Custo_Fopag (2)'!$A:$BQ,16,0) -> 2950 | R11: =VLOOKUP(A11,'Custo_Fopag (2)'!$A:$BQ,17,0) -> 0 | S11: =VLOOKUP(A11,'Custo_Fopag (2)'!$A:$BP,18,0) -> 0 | T11: =VLOOKUP(A11,'Custo_Fopag (2)'!$A:$BQ,20,0) -> 0 | U11: =VLOOKUP(A11,'Custo_Fopag (2)'!$A:$BQ,21,0) -> 0 | V11: =VLOOKUP(A11,'Custo_Fopag (2)'!$A:$BQ,22,0) -> 0 | W11: =VLOOKUP(A11,'Custo_Fopag (2)'!$A:$BQ,23,0) -> 0 | X11: =VLOOKUP(A11,'Custo_Fopag (2)'!$A:$BQ,24,0) -> 0 | Y11: =VLOOKUP(A11,'Custo_Fopag (2)'!$A:$BQ,25,0) -> 0 | Z11: =VLOOKUP(A11,'Custo_Fopag (2)'!$A:$BQ,26,0) -> 0 | AA11: =VLOOKUP(A11,'Custo_Fopag (2)'!$A:$BQ,27,0) -> 0 | AB11: =VLOOKUP(A11,'Custo_Fopag (2)'!$A:$BQ,28,0) -> 0 | AC11: =VLOOKUP(A11,'Custo_Fopag (2)'!$A:$BQ,29,0) -> 0 | AD11: =VLOOKUP(A11,'Custo_Fopag (2)'!$A:$BQ,30,0) -> 0 | AE11: =VLOOKUP(A11,'Custo_Fopag (2)'!$A:$BQ,31,0) -> 0 | AF11: =VLOOKUP(A11,'Custo_Fopag (2)'!$A:$BQ,32,0) -> 0 | AG11: =SUM(Q11:AF11) -> 2950 | AH11: =VLOOKUP(A11,'Custo_Fopag (2)'!$A:$BQ,45,0) -> 0 | AI11: =_xlfn.XLOOKUP(A11,Beneficios!A:A,Beneficios!B:B,0,0,1) -> 512.87 | AJ11: =VLOOKUP(A11,'Custo_Fopag (2)'!$A:$BQ,47,0) -> 0 | AK11: 0 | AL11: =VLOOKUP(A11,'Custo_Fopag (2)'!$A:$BQ,35,0) -> 0 | AM11: =VLOOKUP(A11,'Custo_Fopag (2)'!$A:$BQ,36,0) -> 0 | AN11: =VLOOKUP(A11,'Custo_Fopag (2)'!$A:$BQ,37,0) -> 0 | AO11: =VLOOKUP(A11,'Custo_Fopag (2)'!$A:$BQ,39,0) -> 0 | AP11: =VLOOKUP(A11,'Custo_Fopag (2)'!$A:$BQ,42,0) -> 0 | AQ11: =VLOOKUP(A11,'Custo_Fopag (2)'!$A:$BQ,40,0) -> 0 | AR11: =VLOOKUP(A11,'Custo_Fopag (2)'!$A:$BQ,41,0) -> 904.34 | AS11: =VLOOKUP(A11,'Custo_Fopag (2)'!$A:$BQ,38,0) -> 0 | AT11: =VLOOKUP(A11,'Custo_Fopag (2)'!$A:$BQ,43,0) -> 0 | AU11: =VLOOKUP(A11,'Custo_Fopag (2)'!$A:$BQ,48,0) -> 0 | AV11: =VLOOKUP(A11,'Custo_Fopag (2)'!$A:$BQ,49,0) -> 0 | AW11: =VLOOKUP(A11,'Custo_Fopag (2)'!$A:$BQ,19,0) -> 0 | AX11: =VLOOKUP(A11,'Custo_Fopag (2)'!$A:$BQ,50,0) -> 0 | AY11: =VLOOKUP(A11,'Custo_Fopag (2)'!$A:$BQ,51,0) -> 0 | AZ11: 0 | BA11: =VLOOKUP(A11,'Custo_Fopag (2)'!$A:$BQ,54,0) -> 0 | BB11: =VLOOKUP(A11,'Custo_Fopag (2)'!$A:$BQ,52,0) -> 0 | BC11: =SUM(AH11:BB11) -> 1417.21 | BD11: =BC11+AG11 -> 4367.21 | BF11: =BD11+BE11 -> 4367.21 | BG11: =AG11/12 -> 245.83333 | BH11: =BG11 -> 245.83333 | BI11: =BH11/3 -> 81.944444 | BJ11: =SUM(BG11:BI11) -> 573.61111 | BK11: =VLOOKUP(A11,'Custo_Fopag (2)'!$A:$BQ,65,0) -> 590 | BL11: =VLOOKUP(A11,'Custo_Fopag (2)'!$A:$BQP,66,0) -> 44.25 | BM11: =VLOOKUP(A11,'Custo_Fopag (2)'!$A:$BQ,67,0) -> 171.1 | BN11: =VLOOKUP(A11,'Custo_Fopag (2)'!$A:$BQ,64,0) -> 236 | BO11: =SUM(BK11:BN11) -> 1041.35 | BP11: =BF11+BO11 -> 5408.56 | BQ11: =BF11+BJ11+BO11 -> 5982.1711 | BR11: =VLOOKUP(A11,'Custo_Fopag (2)'!$A:$BQ,60,0) -> 0 | BS11: =IF(ISBLANK(L11),"Ativo","Desligado") -> Ativo
A12: ANTONIO ANACLETO DE OLIVEIRA | B12: 46082 | C12: CLT | D12: =VLOOKUP(A12,'Custo_Fopag (2)'!A:$BQ,4,0) -> G3S FL 04 - PRES PRUD | G12: =VLOOKUP(A12,'Custo_Fopag (2)'!$A:$BQ,5,0) -> 20.947.332/0004-38 | H12: =VLOOKUP(A12,'Custo_Fopag (2)'!$A:$BQ,6,0) -> OPERACIONAL | I12: =VLOOKUP(A12,'Custo_Fopag (2)'!$A:$BQ,7,0) -> PATIO | J12: =VLOOKUP(A12,'Custo_Fopag (2)'!$A:$BQ,8,0) -> SELETIVA PRESIDENTE PRUDENTE | K12: =VLOOKUP(A12,'Custo_Fopag (2)'!$A:$BQ,9,0) -> 40118 | N12: =VLOOKUP(A12,'Custo_Fopag (2)'!$A:$BQ,11,0) -> 1.2.5.3 OPERACIONAL | O12: =VLOOKUP(A12,'Custo_Fopag (2)'!$A:$BQ,12,0) -> AUXILIAR DE PATIO SENIOR | P12: =VLOOKUP(A12,'Custo_Fopag (2)'!$A:$BQ,13,0) -> 2600 | Q12: =VLOOKUP(A12,'Custo_Fopag (2)'!$A:$BQ,16,0) -> 2600 | R12: =VLOOKUP(A12,'Custo_Fopag (2)'!$A:$BQ,17,0) -> 0 | S12: =VLOOKUP(A12,'Custo_Fopag (2)'!$A:$BP,18,0) -> 0 | T12: =VLOOKUP(A12,'Custo_Fopag (2)'!$A:$BQ,20,0) -> 0 | U12: =VLOOKUP(A12,'Custo_Fopag (2)'!$A:$BQ,21,0) -> 0 | V12: =VLOOKUP(A12,'Custo_Fopag (2)'!$A:$BQ,22,0) -> 0 | W12: =VLOOKUP(A12,'Custo_Fopag (2)'!$A:$BQ,23,0) -> 0 | X12: =VLOOKUP(A12,'Custo_Fopag (2)'!$A:$BQ,24,0) -> 0 | Y12: =VLOOKUP(A12,'Custo_Fopag (2)'!$A:$BQ,25,0) -> 0 | Z12: =VLOOKUP(A12,'Custo_Fopag (2)'!$A:$BQ,26,0) -> 0 | AA12: =VLOOKUP(A12,'Custo_Fopag (2)'!$A:$BQ,27,0) -> 0 | AB12: =VLOOKUP(A12,'Custo_Fopag (2)'!$A:$BQ,28,0) -> 0 | AC12: =VLOOKUP(A12,'Custo_Fopag (2)'!$A:$BQ,29,0) -> 0 | AD12: =VLOOKUP(A12,'Custo_Fopag (2)'!$A:$BQ,30,0) -> 0 | AE12: =VLOOKUP(A12,'Custo_Fopag (2)'!$A:$BQ,31,0) -> 0 | AF12: =VLOOKUP(A12,'Custo_Fopag (2)'!$A:$BQ,32,0) -> 0 | AG12: =SUM(Q12:AF12) -> 2600 | AH12: =VLOOKUP(A12,'Custo_Fopag (2)'!$A:$BQ,45,0) -> 0 | AI12: =_xlfn.XLOOKUP(A12,'Custo_Fopag (2)'!A:A,'Custo_Fopag (2)'!AT:AT,0,0,1) -> 450 | AJ12: =VLOOKUP(A12,'Custo_Fopag (2)'!$A:$BQ,47,0) -> 0 | AK12: 0 | AL12: =VLOOKUP(A12,'Custo_Fopag (2)'!$A:$BQ,35,0) -> 0 | AM12: =VLOOKUP(A12,'Custo_Fopag (2)'!$A:$BQ,36,0) -> 0 | AN12: =VLOOKUP(A12,'Custo_Fopag (2)'!$A:$BQ,37,0) -> 0 | AO12: =VLOOKUP(A12,'Custo_Fopag (2)'!$A:$BQ,39,0) -> 0 | AP12: =VLOOKUP(A12,'Custo_Fopag (2)'!$A:$BQ,42,0) -> 1080 | AQ12: =VLOOKUP(A12,'Custo_Fopag (2)'!$A:$BQ,40,0) -> 0 | AR12: =VLOOKUP(A12,'Custo_Fopag (2)'!$A:$BQ,41,0) -> 579.34 | AS12: =VLOOKUP(A12,'Custo_Fopag (2)'!$A:$BQ,38,0) -> 0 | AT12: =VLOOKUP(A12,'Custo_Fopag (2)'!$A:$BQ,43,0) -> 0 | AU12: =VLOOKUP(A12,'Custo_Fopag (2)'!$A:$BQ,48,0) -> 0 | AV12: =VLOOKUP(A12,'Custo_Fopag (2)'!$A:$BQ,49,0) -> 0 | AW12: =VLOOKUP(A12,'Custo_Fopag (2)'!$A:$BQ,19,0) -> 0 | AX12: =VLOOKUP(A12,'Custo_Fopag (2)'!$A:$BQ,50,0) -> 0 | AY12: =VLOOKUP(A12,'Custo_Fopag (2)'!$A:$BQ,51,0) -> 0 | AZ12: 0 | BA12: =VLOOKUP(A12,'Custo_Fopag (2)'!$A:$BQ,54,0) -> 0 | BB12: =VLOOKUP(A12,'Custo_Fopag (2)'!$A:$BQ,52,0) -> 0 | BC12: =SUM(AH12:BB12) -> 2109.34 | BD12: =BC12+AG12 -> 4709.34 | BF12: =BD12+BE12 -> 4709.34 | BG12: =AG12/12 -> 216.66667 | BH12: =BG12 -> 216.66667 | BI12: =BH12/3 -> 72.222222 | BJ12: =SUM(BG12:BI12) -> 505.55556 | BK12: =VLOOKUP(A12,'Custo_Fopag (2)'!$A:$BQ,65,0) -> 520 | BL12: =VLOOKUP(A12,'Custo_Fopag (2)'!$A:$BQP,66,0) -> 39 | BM12: =VLOOKUP(A12,'Custo_Fopag (2)'!$A:$BQ,67,0) -> 150.8 | BN12: =VLOOKUP(A12,'Custo_Fopag (2)'!$A:$BQ,64,0) -> 224 | BO12: =SUM(BK12:BN12) -> 933.8 | BP12: =BF12+BO12 -> 5643.14 | BQ12: =BF12+BJ12+BO12 -> 6148.6956 | BR12: =VLOOKUP(A12,'Custo_Fopag (2)'!$A:$BQ,60,0) -> 0 | BS12: =IF(ISBLANK(L12),"Ativo","Desligado") -> Ativo
A13: ANTONIO APARECIDO FAQUIANO SOBRINHO | B13: 46082 | C13: CLT | D13: =VLOOKUP(A13,'Custo_Fopag (2)'!A:$BQ,4,0) -> G S FL 03 - DOURADOS | G13: =VLOOKUP(A13,'Custo_Fopag (2)'!$A:$BQ,5,0) -> 20.504.237/0003-89 | H13: =VLOOKUP(A13,'Custo_Fopag (2)'!$A:$BQ,6,0) -> LOGISTICA | I13: =VLOOKUP(A13,'Custo_Fopag (2)'!$A:$BQ,7,0) -> TRANSPORTE | J13: =VLOOKUP(A13,'Custo_Fopag (2)'!$A:$BQ,8,0) -> SELETIVA DOURADOS | K13: =VLOOKUP(A13,'Custo_Fopag (2)'!$A:$BQ,9,0) -> 43521 | N13: =VLOOKUP(A13,'Custo_Fopag (2)'!$A:$BQ,11,0) -> 1.7.5.4 LOGISTICA | O13: =VLOOKUP(A13,'Custo_Fopag (2)'!$A:$BQ,12,0) -> MOTORISTA CARRETEIRO MANTENEDOR SENIOR I | P13: =VLOOKUP(A13,'Custo_Fopag (2)'!$A:$BQ,13,0) -> 2690.66 | Q13: =VLOOKUP(A13,'Custo_Fopag (2)'!$A:$BQ,16,0) -> 2690.66 | R13: =VLOOKUP(A13,'Custo_Fopag (2)'!$A:$BQ,17,0) -> 0 | S13: =VLOOKUP(A13,'Custo_Fopag (2)'!$A:$BP,18,0) -> 0 | T13: =VLOOKUP(A13,'Custo_Fopag (2)'!$A:$BQ,20,0) -> 538.13 | U13: =VLOOKUP(A13,'Custo_Fopag (2)'!$A:$BQ,21,0) -> 0 | V13: =VLOOKUP(A13,'Custo_Fopag (2)'!$A:$BQ,22,0) -> 0 | W13: =VLOOKUP(A13,'Custo_Fopag (2)'!$A:$BQ,23,0) -> 0 | X13: =VLOOKUP(A13,'Custo_Fopag (2)'!$A:$BQ,24,0) -> 0 | Y13: =VLOOKUP(A13,'Custo_Fopag (2)'!$A:$BQ,25,0) -> 0 | Z13: =VLOOKUP(A13,'Custo_Fopag (2)'!$A:$BQ,26,0) -> 0 | AA13: =VLOOKUP(A13,'Custo_Fopag (2)'!$A:$BQ,27,0) -> 731.61 | AB13: =VLOOKUP(A13,'Custo_Fopag (2)'!$A:$BQ,28,0) -> 140.69 | AC13: =VLOOKUP(A13,'Custo_Fopag (2)'!$A:$BQ,29,0) -> 0 | AD13: =VLOOKUP(A13,'Custo_Fopag (2)'!$A:$BQ,30,0) -> 0 | AE13: =VLOOKUP(A13,'Custo_Fopag (2)'!$A:$BQ,31,0) -> 0 | AF13: =VLOOKUP(A13,'Custo_Fopag (2)'!$A:$BQ,32,0) -> 0 | AG13: =SUM(Q13:AF13) -> 4101.09 | AH13: =VLOOKUP(A13,'Custo_Fopag (2)'!$A:$BQ,45,0) -> 0 | AI13: =_xlfn.XLOOKUP(A13,Beneficios!A:A,Beneficios!B:B,0,0,1) -> 512.87 | AJ13: =VLOOKUP(A13,'Custo_Fopag (2)'!$A:$BQ,47,0) -> 0 | AK13: 0 | AL13: =VLOOKUP(A13,'Custo_Fopag (2)'!$A:$BQ,35,0) -> 0 | AM13: =VLOOKUP(A13,'Custo_Fopag (2)'!$A:$BQ,36,0) -> 445.29 | AN13: =VLOOKUP(A13,'Custo_Fopag (2)'!$A:$BQ,37,0) -> 0 | AO13: =VLOOKUP(A13,'Custo_Fopag (2)'!$A:$BQ,39,0) -> 0 | AP13: =VLOOKUP(A13,'Custo_Fopag (2)'!$A:$BQ,42,0) -> 0 | AQ13: =VLOOKUP(A13,'Custo_Fopag (2)'!$A:$BQ,40,0) -> 0 | AR13: =VLOOKUP(A13,'Custo_Fopag (2)'!$A:$BQ,41,0) -> 600 | AS13: =VLOOKUP(A13,'Custo_Fopag (2)'!$A:$BQ,38,0) -> 0 | AT13: =VLOOKUP(A13,'Custo_Fopag (2)'!$A:$BQ,43,0) -> 0 | AU13: =VLOOKUP(A13,'Custo_Fopag (2)'!$A:$BQ,48,0) -> 1401 | AV13: =VLOOKUP(A13,'Custo_Fopag (2)'!$A:$BQ,49,0) -> 0 | AW13: =VLOOKUP(A13,'Custo_Fopag (2)'!$A:$BQ,19,0) -> 0 | AX13: =VLOOKUP(A13,'Custo_Fopag (2)'!$A:$BQ,50,0) -> 0 | AY13: 96.2 | AZ13: 0 | BA13: =VLOOKUP(A13,'Custo_Fopag (2)'!$A:$BQ,54,0) -> 0 | BB13: =VLOOKUP(A13,'Custo_Fopag (2)'!$A:$BQ,52,0) -> 0 | BC13: =SUM(AH13:BB13) -> 3055.36 | BD13: =BC13+AG13 -> 7156.45 | BF13: =BD13+BE13 -> 7156.45 | BG13: =AG13/12 -> 341.7575 | BH13: =BG13 -> 341.7575 | BI13: =BH13/3 -> 113.91917 | BJ13: =SUM(BG13:BI13) -> 797.43417 | BK13: =VLOOKUP(A13,'Custo_Fopag (2)'!$A:$BQ,65,0) -> 820.22 | BL13: =VLOOKUP(A13,'Custo_Fopag (2)'!$A:$BQP,66,0) -> 123.03 | BM13: =VLOOKUP(A13,'Custo_Fopag (2)'!$A:$BQ,67,0) -> 237.86 | BN13: =VLOOKUP(A13,'Custo_Fopag (2)'!$A:$BQ,64,0) -> 328.08 | BO13: =SUM(BK13:BN13) -> 1509.19 | BP13: =BF13+BO13 -> 8665.64 | BQ13: =BF13+BJ13+BO13 -> 9463.0742 | BR13: =VLOOKUP(A13,'Custo_Fopag (2)'!$A:$BQ,60,0) -> 0 | BS13: =IF(ISBLANK(L13),"Ativo","Desligado") -> Ativo
A14: ANTONIO BATISTA DA SILVA | B14: 46082 | C14: CLT | D14: =VLOOKUP(A14,'Custo_Fopag (2)'!A:$BQ,4,0) -> G S FL 06 - CAMPO GRANDE | G14: =VLOOKUP(A14,'Custo_Fopag (2)'!$A:$BQ,5,0) -> 20.504.237/0006-21 | H14: =VLOOKUP(A14,'Custo_Fopag (2)'!$A:$BQ,6,0) -> LOGISTICA | I14: =VLOOKUP(A14,'Custo_Fopag (2)'!$A:$BQ,7,0) -> TRANSPORTE | J14: =VLOOKUP(A14,'Custo_Fopag (2)'!$A:$BQ,8,0) -> SELETIVA C GRANDE | K14: =VLOOKUP(A14,'Custo_Fopag (2)'!$A:$BQ,9,0) -> 45597 | N14: =VLOOKUP(A14,'Custo_Fopag (2)'!$A:$BQ,11,0) -> 1.7.4.4 LOGISTICA | O14: =VLOOKUP(A14,'Custo_Fopag (2)'!$A:$BQ,12,0) -> MOTORISTA CARRETEIRO MANTENEDOR PLENO | P14: =VLOOKUP(A14,'Custo_Fopag (2)'!$A:$BQ,13,0) -> 2591 | Q14: =VLOOKUP(A14,'Custo_Fopag (2)'!$A:$BQ,16,0) -> 2591 | R14: =VLOOKUP(A14,'Custo_Fopag (2)'!$A:$BQ,17,0) -> 0 | S14: =VLOOKUP(A14,'Custo_Fopag (2)'!$A:$BP,18,0) -> 0 | T14: =VLOOKUP(A14,'Custo_Fopag (2)'!$A:$BQ,20,0) -> 516.24 | U14: =VLOOKUP(A14,'Custo_Fopag (2)'!$A:$BQ,21,0) -> 0 | V14: =VLOOKUP(A14,'Custo_Fopag (2)'!$A:$BQ,22,0) -> 0 | W14: =VLOOKUP(A14,'Custo_Fopag (2)'!$A:$BQ,23,0) -> 0 | X14: =VLOOKUP(A14,'Custo_Fopag (2)'!$A:$BQ,24,0) -> 0 | Y14: =VLOOKUP(A14,'Custo_Fopag (2)'!$A:$BQ,25,0) -> 0 | Z14: =VLOOKUP(A14,'Custo_Fopag (2)'!$A:$BQ,26,0) -> 0 | AA14: =VLOOKUP(A14,'Custo_Fopag (2)'!$A:$BQ,27,0) -> 395.36 | AB14: =VLOOKUP(A14,'Custo_Fopag (2)'!$A:$BQ,28,0) -> 76.03 | AC14: =VLOOKUP(A14,'Custo_Fopag (2)'!$A:$BQ,29,0) -> 0 | AD14: =VLOOKUP(A14,'Custo_Fopag (2)'!$A:$BQ,30,0) -> 0 | AE14: =VLOOKUP(A14,'Custo_Fopag (2)'!$A:$BQ,31,0) -> 0 | AF14: =VLOOKUP(A14,'Custo_Fopag (2)'!$A:$BQ,32,0) -> 0 | AG14: =SUM(Q14:AF14) -> 3578.63 | AH14: =VLOOKUP(A14,'Custo_Fopag (2)'!$A:$BQ,45,0) -> 0 | AI14: =_xlfn.XLOOKUP(A14,Beneficios!A:A,Beneficios!B:B,0,0,1) -> 512.87 | AJ14: =VLOOKUP(A14,'Custo_Fopag (2)'!$A:$BQ,47,0) -> 0 | AK14: 0 | AL14: =VLOOKUP(A14,'Custo_Fopag (2)'!$A:$BQ,35,0) -> 0 | AM14: =VLOOKUP(A14,'Custo_Fopag (2)'!$A:$BQ,36,0) -> 290.52 | AN14: =VLOOKUP(A14,'Custo_Fopag (2)'!$A:$BQ,37,0) -> 0 | AO14: =VLOOKUP(A14,'Custo_Fopag (2)'!$A:$BQ,39,0) -> 0 | AP14: =VLOOKUP(A14,'Custo_Fopag (2)'!$A:$BQ,42,0) -> 0 | AQ14: =VLOOKUP(A14,'Custo_Fopag (2)'!$A:$BQ,40,0) -> 0 | AR14: =VLOOKUP(A14,'Custo_Fopag (2)'!$A:$BQ,41,0) -> 533.04 | AS14: =VLOOKUP(A14,'Custo_Fopag (2)'!$A:$BQ,38,0) -> 0 | AT14: =VLOOKUP(A14,'Custo_Fopag (2)'!$A:$BQ,43,0) -> 0 | AU14: =VLOOKUP(A14,'Custo_Fopag (2)'!$A:$BQ,48,0) -> 650 | AV14: =VLOOKUP(A14,'Custo_Fopag (2)'!$A:$BQ,49,0) -> 0 | AW14: =VLOOKUP(A14,'Custo_Fopag (2)'!$A:$BQ,19,0) -> 0 | AX14: =VLOOKUP(A14,'Custo_Fopag (2)'!$A:$BQ,50,0) -> 0 | AY14: 96.2 | AZ14: 0 | BA14: =VLOOKUP(A14,'Custo_Fopag (2)'!$A:$BQ,54,0) -> 0 | BB14: =VLOOKUP(A14,'Custo_Fopag (2)'!$A:$BQ,52,0) -> 0 | BC14: =SUM(AH14:BB14) -> 2082.63 | BD14: =BC14+AG14 -> 5661.26 | BF14: =BD14+BE14 -> 5661.26 | BG14: =AG14/12 -> 298.21917 | BH14: =BG14 -> 298.21917 | BI14: =BH14/3 -> 99.406389 | BJ14: =SUM(BG14:BI14) -> 695.84472 | BK14: =VLOOKUP(A14,'Custo_Fopag (2)'!$A:$BQ,65,0) -> 715.73 | BL14: =VLOOKUP(A14,'Custo_Fopag (2)'!$A:$BQP,66,0) -> 107.35 | BM14: =VLOOKUP(A14,'Custo_Fopag (2)'!$A:$BQ,67,0) -> 207.56 | BN14: =VLOOKUP(A14,'Custo_Fopag (2)'!$A:$BQ,64,0) -> 285.5 | BO14: =SUM(BK14:BN14) -> 1316.14 | BP14: =BF14+BO14 -> 6977.4 | BQ14: =BF14+BJ14+BO14 -> 7673.2447 | BR14: =VLOOKUP(A14,'Custo_Fopag (2)'!$A:$BQ,60,0) -> 0 | BS14: =IF(ISBLANK(L14),"Ativo","Desligado") -> Ativo
A15: BEATRIZ FERREIRA DE SOUZA | B15: 46082 | C15: CLT | D15: =VLOOKUP(A15,'Custo_Fopag (2)'!A:$BQ,4,0) -> G3S FL 10 - PRES PRUD | G15: =VLOOKUP(A15,'Custo_Fopag (2)'!$A:$BQ,5,0) -> 20.947.332/0010-86 | H15: =VLOOKUP(A15,'Custo_Fopag (2)'!$A:$BQ,6,0) -> COMERCIAL | I15: =VLOOKUP(A15,'Custo_Fopag (2)'!$A:$BQ,7,0) -> COMERCIAL | J15: =VLOOKUP(A15,'Custo_Fopag (2)'!$A:$BQ,8,0) -> SELETIVA CORPORATIVO SUCATA | K15: =VLOOKUP(A15,'Custo_Fopag (2)'!$A:$BQ,9,0) -> 45628 | N15: =VLOOKUP(A15,'Custo_Fopag (2)'!$A:$BQ,11,0) -> 1.2.1.1 APOIO | O15: =VLOOKUP(A15,'Custo_Fopag (2)'!$A:$BQ,12,0) -> ASSISTENTE COMERCIAL | P15: =VLOOKUP(A15,'Custo_Fopag (2)'!$A:$BQ,13,0) -> 2098 | Q15: =VLOOKUP(A15,'Custo_Fopag (2)'!$A:$BQ,16,0) -> 2098 | R15: =VLOOKUP(A15,'Custo_Fopag (2)'!$A:$BQ,17,0) -> 0 | S15: =VLOOKUP(A15,'Custo_Fopag (2)'!$A:$BP,18,0) -> 0 | T15: =VLOOKUP(A15,'Custo_Fopag (2)'!$A:$BQ,20,0) -> 0 | U15: =VLOOKUP(A15,'Custo_Fopag (2)'!$A:$BQ,21,0) -> 0 | V15: =VLOOKUP(A15,'Custo_Fopag (2)'!$A:$BQ,22,0) -> 0 | W15: =VLOOKUP(A15,'Custo_Fopag (2)'!$A:$BQ,23,0) -> 0 | X15: =VLOOKUP(A15,'Custo_Fopag (2)'!$A:$BQ,24,0) -> 0 | Y15: =VLOOKUP(A15,'Custo_Fopag (2)'!$A:$BQ,25,0) -> 0 | Z15: =VLOOKUP(A15,'Custo_Fopag (2)'!$A:$BQ,26,0) -> 0 | AA15: =VLOOKUP(A15,'Custo_Fopag (2)'!$A:$BQ,27,0) -> 0 | AB15: =VLOOKUP(A15,'Custo_Fopag (2)'!$A:$BQ,28,0) -> 0 | AC15: =VLOOKUP(A15,'Custo_Fopag (2)'!$A:$BQ,29,0) -> 0 | AD15: =VLOOKUP(A15,'Custo_Fopag (2)'!$A:$BQ,30,0) -> 0 | AE15: =VLOOKUP(A15,'Custo_Fopag (2)'!$A:$BQ,31,0) -> 0 | AF15: =VLOOKUP(A15,'Custo_Fopag (2)'!$A:$BQ,32,0) -> 0 | AG15: =SUM(Q15:AF15) -> 2098 | AH15: =VLOOKUP(A15,'Custo_Fopag (2)'!$A:$BQ,45,0) -> 0 | AI15: =_xlfn.XLOOKUP(A15,Beneficios!A:A,Beneficios!B:B,0,0,1) -> 521.87 | AJ15: =VLOOKUP(A15,'Custo_Fopag (2)'!$A:$BQ,47,0) -> 0 | AK15: 0 | AL15: =VLOOKUP(A15,'Custo_Fopag (2)'!$A:$BQ,35,0) -> 0 | AM15: =VLOOKUP(A15,'Custo_Fopag (2)'!$A:$BQ,36,0) -> 0 | AN15: =VLOOKUP(A15,'Custo_Fopag (2)'!$A:$BQ,37,0) -> 0 | AO15: =VLOOKUP(A15,'Custo_Fopag (2)'!$A:$BQ,39,0) -> 0 | AP15: =VLOOKUP(A15,'Custo_Fopag (2)'!$A:$BQ,42,0) -> 0 | AQ15: =VLOOKUP(A15,'Custo_Fopag (2)'!$A:$BQ,40,0) -> 0 | AR15: =VLOOKUP(A15,'Custo_Fopag (2)'!$A:$BQ,41,0) -> 0 | AS15: =VLOOKUP(A15,'Custo_Fopag (2)'!$A:$BQ,38,0) -> 929.47 | AT15: =VLOOKUP(A15,'Custo_Fopag (2)'!$A:$BQ,43,0) -> 0 | AU15: =VLOOKUP(A15,'Custo_Fopag (2)'!$A:$BQ,48,0) -> 0 | AV15: =VLOOKUP(A15,'Custo_Fopag (2)'!$A:$BQ,49,0) -> 0 | AW15: =VLOOKUP(A15,'Custo_Fopag (2)'!$A:$BQ,19,0) -> 0 | AX15: =VLOOKUP(A15,'Custo_Fopag (2)'!$A:$BQ,50,0) -> 0 | AY15: =VLOOKUP(A15,'Custo_Fopag (2)'!$A:$BQ,51,0) -> 0 | AZ15: 0 | BA15: =VLOOKUP(A15,'Custo_Fopag (2)'!$A:$BQ,54,0) -> 0 | BB15: =VLOOKUP(A15,'Custo_Fopag (2)'!$A:$BQ,52,0) -> 0 | BC15: =SUM(AH15:BB15) -> 1451.34 | BD15: =BC15+AG15 -> 3549.34 | BF15: =BD15+BE15 -> 3549.34 | BG15: =AG15/12 -> 174.83333 | BH15: =BG15 -> 174.83333 | BI15: =BH15/3 -> 58.277778 | BJ15: =SUM(BG15:BI15) -> 407.94444 | BK15: =VLOOKUP(A15,'Custo_Fopag (2)'!$A:$BQ,65,0) -> 419.6 | BL15: =VLOOKUP(A15,'Custo_Fopag (2)'!$A:$BQP,66,0) -> 62.94 | BM15: =VLOOKUP(A15,'Custo_Fopag (2)'!$A:$BQ,67,0) -> 121.68 | BN15: =VLOOKUP(A15,'Custo_Fopag (2)'!$A:$BQ,64,0) -> 167.84 | BO15: =SUM(BK15:BN15) -> 772.06 | BP15: =BF15+BO15 -> 4321.4 | BQ15: =BF15+BJ15+BO15 -> 4729.3444 | BR15: =VLOOKUP(A15,'Custo_Fopag (2)'!$A:$BQ,60,0) -> 0 | BS15: =IF(ISBLANK(L15),"Ativo","Desligado") -> Ativo
A16: BRUNO RUANI SCARFONI | B16: 46082 | C16: CLT | D16: =VLOOKUP(A16,'Custo_Fopag (2)'!A:$BQ,4,0) -> RSE COM DE FERRO,ACO E LOCA | G16: =VLOOKUP(A16,'Custo_Fopag (2)'!$A:$BQ,5,0) -> 6.916.551/0001-86 | H16: =VLOOKUP(A16,'Custo_Fopag (2)'!$A:$BQ,6,0) -> COMERCIAL | I16: =VLOOKUP(A16,'Custo_Fopag (2)'!$A:$BQ,7,0) -> ADMINISTRATIVO | J16: =VLOOKUP(A16,'Custo_Fopag (2)'!$A:$BQ,8,0) -> EKIPA LOCACOES E SERV G&S | K16: =VLOOKUP(A16,'Custo_Fopag (2)'!$A:$BQ,9,0) -> 46055 | N16: =VLOOKUP(A16,'Custo_Fopag (2)'!$A:$BQ,11,0) -> 1.5.1.2 COMERCIAL | O16: =VLOOKUP(A16,'Custo_Fopag (2)'!$A:$BQ,12,0) -> VENDEDOR (A) | P16: =VLOOKUP(A16,'Custo_Fopag (2)'!$A:$BQ,13,0) -> 2500 | Q16: =VLOOKUP(A16,'Custo_Fopag (2)'!$A:$BQ,16,0) -> 2500 | R16: =VLOOKUP(A16,'Custo_Fopag (2)'!$A:$BQ,17,0) -> 0 | S16: =VLOOKUP(A16,'Custo_Fopag (2)'!$A:$BP,18,0) -> 0 | T16: =VLOOKUP(A16,'Custo_Fopag (2)'!$A:$BQ,20,0) -> 0 | U16: =VLOOKUP(A16,'Custo_Fopag (2)'!$A:$BQ,21,0) -> 0 | V16: =VLOOKUP(A16,'Custo_Fopag (2)'!$A:$BQ,22,0) -> 0 | W16: =VLOOKUP(A16,'Custo_Fopag (2)'!$A:$BQ,23,0) -> 0 | X16: =VLOOKUP(A16,'Custo_Fopag (2)'!$A:$BQ,24,0) -> 0 | Y16: =VLOOKUP(A16,'Custo_Fopag (2)'!$A:$BQ,25,0) -> 0 | Z16: =VLOOKUP(A16,'Custo_Fopag (2)'!$A:$BQ,26,0) -> 0 | AA16: =VLOOKUP(A16,'Custo_Fopag (2)'!$A:$BQ,27,0) -> 0 | AB16: =VLOOKUP(A16,'Custo_Fopag (2)'!$A:$BQ,28,0) -> 0 | AC16: =VLOOKUP(A16,'Custo_Fopag (2)'!$A:$BQ,29,0) -> 0 | AD16: =VLOOKUP(A16,'Custo_Fopag (2)'!$A:$BQ,30,0) -> 0 | AE16: =VLOOKUP(A16,'Custo_Fopag (2)'!$A:$BQ,31,0) -> 0 | AF16: =VLOOKUP(A16,'Custo_Fopag (2)'!$A:$BQ,32,0) -> 0 | AG16: =SUM(Q16:AF16) -> 2500 | AH16: =VLOOKUP(A16,'Custo_Fopag (2)'!$A:$BQ,45,0) -> 0 | AI16: =_xlfn.XLOOKUP(A16,Beneficios!A:A,Beneficios!B:B,0,0,1) -> 521.87 | AJ16: =VLOOKUP(A16,'Custo_Fopag (2)'!$A:$BQ,47,0) -> 0 | AK16: 0 | AL16: =VLOOKUP(A16,'Custo_Fopag (2)'!$A:$BQ,35,0) -> 0 | AM16: =VLOOKUP(A16,'Custo_Fopag (2)'!$A:$BQ,36,0) -> 0 | AN16: =VLOOKUP(A16,'Custo_Fopag (2)'!$A:$BQ,37,0) -> 0 | AO16: =VLOOKUP(A16,'Custo_Fopag (2)'!$A:$BQ,39,0) -> 400 | AP16: =VLOOKUP(A16,'Custo_Fopag (2)'!$A:$BQ,42,0) -> 0 | AQ16: =VLOOKUP(A16,'Custo_Fopag (2)'!$A:$BQ,40,0) -> 0 | AR16: =VLOOKUP(A16,'Custo_Fopag (2)'!$A:$BQ,41,0) -> 0 | AS16: =VLOOKUP(A16,'Custo_Fopag (2)'!$A:$BQ,38,0) -> 0 | AT16: =VLOOKUP(A16,'Custo_Fopag (2)'!$A:$BQ,43,0) -> 0 | AU16: =VLOOKUP(A16,'Custo_Fopag (2)'!$A:$BQ,48,0) -> 0 | AV16: =VLOOKUP(A16,'Custo_Fopag (2)'!$A:$BQ,49,0) -> 0 | AW16: =VLOOKUP(A16,'Custo_Fopag (2)'!$A:$BQ,19,0) -> 0 | AX16: =VLOOKUP(A16,'Custo_Fopag (2)'!$A:$BQ,50,0) -> 0 | AY16: =VLOOKUP(A16,'Custo_Fopag (2)'!$A:$BQ,51,0) -> 0 | AZ16: 0 | BA16: =VLOOKUP(A16,'Custo_Fopag (2)'!$A:$BQ,54,0) -> 0 | BB16: =VLOOKUP(A16,'Custo_Fopag (2)'!$A:$BQ,52,0) -> 0 | BC16: =SUM(AH16:BB16) -> 921.87 | BD16: =BC16+AG16 -> 3421.87 | BF16: =BD16+BE16 -> 3421.87 | BG16: =AG16/12 -> 208.33333 | BH16: =BG16 -> 208.33333 | BI16: =BH16/3 -> 69.444444 | BJ16: =SUM(BG16:BI16) -> 486.11111 | BK16: =VLOOKUP(A16,'Custo_Fopag (2)'!$A:$BQ,65,0) -> 500 | BL16: =VLOOKUP(A16,'Custo_Fopag (2)'!$A:$BQP,66,0) -> 37.5 | BM16: =VLOOKUP(A16,'Custo_Fopag (2)'!$A:$BQ,67,0) -> 145 | BN16: =VLOOKUP(A16,'Custo_Fopag (2)'!$A:$BQ,64,0) -> 200 | BO16: =SUM(BK16:BN16) -> 882.5 | BP16: =BF16+BO16 -> 4304.37 | BQ16: =BF16+BJ16+BO16 -> 4790.4811 | BR16: =VLOOKUP(A16,'Custo_Fopag (2)'!$A:$BQ,60,0) -> 0 | BS16: =IF(ISBLANK(L16),"Ativo","Desligado") -> Ativo
A17: CELIO MATEUS | B17: 46082 | C17: CLT | D17: =VLOOKUP(A17,'Custo_Fopag (2)'!A:$BQ,4,0) -> G S MATRIZ - PRES PRUD | G17: =VLOOKUP(A17,'Custo_Fopag (2)'!$A:$BQ,5,0) -> 20.504.237/0001-17 | H17: =VLOOKUP(A17,'Custo_Fopag (2)'!$A:$BQ,6,0) -> OPERACIONAL | I17: =VLOOKUP(A17,'Custo_Fopag (2)'!$A:$BQ,7,0) -> PATIO | J17: =VLOOKUP(A17,'Custo_Fopag (2)'!$A:$BQ,8,0) -> SELETIVA PRESIDENTE PRUDENTE | K17: =VLOOKUP(A17,'Custo_Fopag (2)'!$A:$BQ,9,0) -> 40269 | N17: =VLOOKUP(A17,'Custo_Fopag (2)'!$A:$BQ,11,0) -> 1.2.5.3 OPERACIONAL | O17: =VLOOKUP(A17,'Custo_Fopag (2)'!$A:$BQ,12,0) -> OPERADOR MANTENEDOR JR | P17: =VLOOKUP(A17,'Custo_Fopag (2)'!$A:$BQ,13,0) -> 2610 | Q17: =VLOOKUP(A17,'Custo_Fopag (2)'!$A:$BQ,16,0) -> 870 | R17: =VLOOKUP(A17,'Custo_Fopag (2)'!$A:$BQ,17,0) -> 0 | S17: =VLOOKUP(A17,'Custo_Fopag (2)'!$A:$BP,18,0) -> 3784.63 | T17: =VLOOKUP(A17,'Custo_Fopag (2)'!$A:$BQ,20,0) -> 174 | U17: =VLOOKUP(A17,'Custo_Fopag (2)'!$A:$BQ,21,0) -> 0 | V17: =VLOOKUP(A17,'Custo_Fopag (2)'!$A:$BQ,22,0) -> 0 | W17: =VLOOKUP(A17,'Custo_Fopag (2)'!$A:$BQ,23,0) -> 0 | X17: =VLOOKUP(A17,'Custo_Fopag (2)'!$A:$BQ,24,0) -> 0 | Y17: =VLOOKUP(A17,'Custo_Fopag (2)'!$A:$BQ,25,0) -> 43.5 | Z17: =VLOOKUP(A17,'Custo_Fopag (2)'!$A:$BQ,26,0) -> 0 | AA17: =VLOOKUP(A17,'Custo_Fopag (2)'!$A:$BQ,27,0) -> 88.98 | AB17: =VLOOKUP(A17,'Custo_Fopag (2)'!$A:$BQ,28,0) -> 19.77 | AC17: =VLOOKUP(A17,'Custo_Fopag (2)'!$A:$BQ,29,0) -> 0 | AD17: =VLOOKUP(A17,'Custo_Fopag (2)'!$A:$BQ,30,0) -> 0 | AE17: =VLOOKUP(A17,'Custo_Fopag (2)'!$A:$BQ,31,0) -> 0 | AF17: =VLOOKUP(A17,'Custo_Fopag (2)'!$A:$BQ,32,0) -> 0 | AG17: =SUM(Q17:AF17) -> 4980.88 | AH17: =VLOOKUP(A17,'Custo_Fopag (2)'!$A:$BQ,45,0) -> 0 | AI17: =_xlfn.XLOOKUP(A17,Beneficios!A:A,Beneficios!B:B,0,0,1) -> 512.87 | AJ17: =VLOOKUP(A17,'Custo_Fopag (2)'!$A:$BQ,47,0) -> 0 | AK17: 0 | AL17: =VLOOKUP(A17,'Custo_Fopag (2)'!$A:$BQ,35,0) -> 0 | AM17: =VLOOKUP(A17,'Custo_Fopag (2)'!$A:$BQ,36,0) -> 0 | AN17: =VLOOKUP(A17,'Custo_Fopag (2)'!$A:$BQ,37,0) -> 0 | AO17: =VLOOKUP(A17,'Custo_Fopag (2)'!$A:$BQ,39,0) -> 0 | AP17: =VLOOKUP(A17,'Custo_Fopag (2)'!$A:$BQ,42,0) -> 0 | AQ17: =VLOOKUP(A17,'Custo_Fopag (2)'!$A:$BQ,40,0) -> 0 | AR17: =VLOOKUP(A17,'Custo_Fopag (2)'!$A:$BQ,41,0) -> 579.34 | AS17: =VLOOKUP(A17,'Custo_Fopag (2)'!$A:$BQ,38,0) -> 0 | AT17: =VLOOKUP(A17,'Custo_Fopag (2)'!$A:$BQ,43,0) -> 0 | AU17: =VLOOKUP(A17,'Custo_Fopag (2)'!$A:$BQ,48,0) -> 2520 | AV17: =VLOOKUP(A17,'Custo_Fopag (2)'!$A:$BQ,49,0) -> 0 | AW17: =VLOOKUP(A17,'Custo_Fopag (2)'!$A:$BQ,19,0) -> 1892.32 | AX17: =VLOOKUP(A17,'Custo_Fopag (2)'!$A:$BQ,50,0) -> 0 | AY17: =VLOOKUP(A17,'Custo_Fopag (2)'!$A:$BQ,51,0) -> 0 | AZ17: 0 | BA17: =VLOOKUP(A17,'Custo_Fopag (2)'!$A:$BQ,54,0) -> 0 | BB17: =VLOOKUP(A17,'Custo_Fopag (2)'!$A:$BQ,52,0) -> 2175 | BC17: =SUM(AH17:BB17) -> 7679.53 | BD17: =BC17+AG17 -> 12660.41 | BF17: =BD17+BE17 -> 12660.41 | BG17: =AG17/12 -> 415.07333 | BH17: =BG17 -> 415.07333 | BI17: =BH17/3 -> 138.35778 | BJ17: =SUM(BG17:BI17) -> 968.50444 | BK17: =VLOOKUP(A17,'Custo_Fopag (2)'!$A:$BQ,65,0) -> 1374.64 | BL17: =VLOOKUP(A17,'Custo_Fopag (2)'!$A:$BQP,66,0) -> 103.09 | BM17: =VLOOKUP(A17,'Custo_Fopag (2)'!$A:$BQ,67,0) -> 398.64 | BN17: =VLOOKUP(A17,'Custo_Fopag (2)'!$A:$BQ,64,0) -> 398.47 | BO17: =SUM(BK17:BN17) -> 2274.84 | BP17: =BF17+BO17 -> 14935.25 | BQ17: =BF17+BJ17+BO17 -> 15903.754 | BR17: =VLOOKUP(A17,'Custo_Fopag (2)'!$A:$BQ,60,0) -> 0 | BS17: =IF(ISBLANK(L17),"Ativo","Desligado") -> Ativo
A18: CRISTIANO LUCAS BACHIO | B18: 46082 | C18: CLT | D18: =VLOOKUP(A18,'Custo_Fopag (2)'!A:$BQ,4,0) -> G S FL 05 - BARUERI | G18: =VLOOKUP(A18,'Custo_Fopag (2)'!$A:$BQ,5,0) -> 20.504.237/0005-40 | H18: =VLOOKUP(A18,'Custo_Fopag (2)'!$A:$BQ,6,0) -> OPERACIONAL | I18: =VLOOKUP(A18,'Custo_Fopag (2)'!$A:$BQ,7,0) -> TUPY/JOINVILLE - SC | J18: =VLOOKUP(A18,'Custo_Fopag (2)'!$A:$BQ,8,0) -> EKIPA LOCACOES E SERV G&S | K18: =VLOOKUP(A18,'Custo_Fopag (2)'!$A:$BQ,9,0) -> 45026 | N18: =VLOOKUP(A18,'Custo_Fopag (2)'!$A:$BQ,11,0) -> 1.7.8.1.1 TUPY - JOINVILLE/S | O18: =VLOOKUP(A18,'Custo_Fopag (2)'!$A:$BQ,12,0) -> OPERADOR MANTENEDOR PLENO | P18: =VLOOKUP(A18,'Custo_Fopag (2)'!$A:$BQ,13,0) -> 2816.11 | Q18: =VLOOKUP(A18,'Custo_Fopag (2)'!$A:$BQ,16,0) -> 2816.11 | R18: =VLOOKUP(A18,'Custo_Fopag (2)'!$A:$BQ,17,0) -> 0 | S18: =VLOOKUP(A18,'Custo_Fopag (2)'!$A:$BP,18,0) -> 0 | T18: =VLOOKUP(A18,'Custo_Fopag (2)'!$A:$BQ,20,0) -> 563.22 | U18: =VLOOKUP(A18,'Custo_Fopag (2)'!$A:$BQ,21,0) -> 0 | V18: =VLOOKUP(A18,'Custo_Fopag (2)'!$A:$BQ,22,0) -> 0 | W18: =VLOOKUP(A18,'Custo_Fopag (2)'!$A:$BQ,23,0) -> 0 | X18: =VLOOKUP(A18,'Custo_Fopag (2)'!$A:$BQ,24,0) -> 0 | Y18: =VLOOKUP(A18,'Custo_Fopag (2)'!$A:$BQ,25,0) -> 0 | Z18: =VLOOKUP(A18,'Custo_Fopag (2)'!$A:$BQ,26,0) -> 20.45 | AA18: =VLOOKUP(A18,'Custo_Fopag (2)'!$A:$BQ,27,0) -> 391.69 | AB18: =VLOOKUP(A18,'Custo_Fopag (2)'!$A:$BQ,28,0) -> 75.33 | AC18: =VLOOKUP(A18,'Custo_Fopag (2)'!$A:$BQ,29,0) -> 0 | AD18: =VLOOKUP(A18,'Custo_Fopag (2)'!$A:$BQ,30,0) -> 0 | AE18: =VLOOKUP(A18,'Custo_Fopag (2)'!$A:$BQ,31,0) -> 0 | AF18: =VLOOKUP(A18,'Custo_Fopag (2)'!$A:$BQ,32,0) -> 0 | AG18: =SUM(Q18:AF18) -> 3866.8 | AH18: =VLOOKUP(A18,'Custo_Fopag (2)'!$A:$BQ,45,0) -> 0 | AI18: =_xlfn.XLOOKUP(A18,Beneficios!A:A,Beneficios!B:B,0,0,1) -> 512.87 | AJ18: =VLOOKUP(A18,'Custo_Fopag (2)'!$A:$BQ,47,0) -> 0 | AK18: 0 | AL18: =VLOOKUP(A18,'Custo_Fopag (2)'!$A:$BQ,35,0) -> 0 | AM18: =VLOOKUP(A18,'Custo_Fopag (2)'!$A:$BQ,36,0) -> 0 | AN18: =VLOOKUP(A18,'Custo_Fopag (2)'!$A:$BQ,37,0) -> 0 | AO18: =VLOOKUP(A18,'Custo_Fopag (2)'!$A:$BQ,39,0) -> 0 | AP18: =VLOOKUP(A18,'Custo_Fopag (2)'!$A:$BQ,42,0) -> 0 | AQ18: =VLOOKUP(A18,'Custo_Fopag (2)'!$A:$BQ,40,0) -> 975 | AR18: =VLOOKUP(A18,'Custo_Fopag (2)'!$A:$BQ,41,0) -> 0 | AS18: =VLOOKUP(A18,'Custo_Fopag (2)'!$A:$BQ,38,0) -> 0 | AT18: =VLOOKUP(A18,'Custo_Fopag (2)'!$A:$BQ,43,0) -> 0 | AU18: =VLOOKUP(A18,'Custo_Fopag (2)'!$A:$BQ,48,0) -> 0 | AV18: =VLOOKUP(A18,'Custo_Fopag (2)'!$A:$BQ,49,0) -> 0 | AW18: =VLOOKUP(A18,'Custo_Fopag (2)'!$A:$BQ,19,0) -> 0 | AX18: =VLOOKUP(A18,'Custo_Fopag (2)'!$A:$BQ,50,0) -> 0 | AY18: =VLOOKUP(A18,'Custo_Fopag (2)'!$A:$BQ,51,0) -> 0 | AZ18: 0 | BA18: =VLOOKUP(A18,'Custo_Fopag (2)'!$A:$BQ,54,0) -> 0 | BB18: =VLOOKUP(A18,'Custo_Fopag (2)'!$A:$BQ,52,0) -> 0 | BC18: =SUM(AH18:BB18) -> 1487.87 | BD18: =BC18+AG18 -> 5354.67 | BF18: =BD18+BE18 -> 5354.67 | BG18: =AG18/12 -> 322.23333 | BH18: =BG18 -> 322.23333 | BI18: =BH18/3 -> 107.41111 | BJ18: =SUM(BG18:BI18) -> 751.87778 | BK18: =VLOOKUP(A18,'Custo_Fopag (2)'!$A:$BQ,65,0) -> 773.36 | BL18: =VLOOKUP(A18,'Custo_Fopag (2)'!$A:$BQP,66,0) -> 58 | BM18: =VLOOKUP(A18,'Custo_Fopag (2)'!$A:$BQ,67,0) -> 224.27 | BN18: =VLOOKUP(A18,'Custo_Fopag (2)'!$A:$BQ,64,0) -> 309.34 | BO18: =SUM(BK18:BN18) -> 1364.97 | BP18: =BF18+BO18 -> 6719.64 | BQ18: =BF18+BJ18+BO18 -> 7471.5178 | BR18: =VLOOKUP(A18,'Custo_Fopag (2)'!$A:$BQ,60,0) -> 0 | BS18: =IF(ISBLANK(L18),"Ativo","Desligado") -> Ativo
A19: DANIEL JUNIOR SANTOS | B19: 46082 | C19: CLT | D19: =VLOOKUP(A19,'Custo_Fopag (2)'!A:$BQ,4,0) -> G S FL 05 - BARUERI | G19: =VLOOKUP(A19,'Custo_Fopag (2)'!$A:$BQ,5,0) -> 20.504.237/0005-40 | H19: =VLOOKUP(A19,'Custo_Fopag (2)'!$A:$BQ,6,0) -> OPERACIONAL | I19: =VLOOKUP(A19,'Custo_Fopag (2)'!$A:$BQ,7,0) -> RESENDE - RJ | J19: =VLOOKUP(A19,'Custo_Fopag (2)'!$A:$BQ,8,0) -> EKIPA LOCACOES E SERV G&S | K19: =VLOOKUP(A19,'Custo_Fopag (2)'!$A:$BQ,9,0) -> 44617 | N19: =VLOOKUP(A19,'Custo_Fopag (2)'!$A:$BQ,11,0) -> 1.7.1.2.1 ARCELOR/ RESENDE/R | O19: =VLOOKUP(A19,'Custo_Fopag (2)'!$A:$BQ,12,0) -> MOTORISTA CARRETEIRO MANTENEDOR SENIOR III | P19: =VLOOKUP(A19,'Custo_Fopag (2)'!$A:$BQ,13,0) -> 3287.33 | Q19: =VLOOKUP(A19,'Custo_Fopag (2)'!$A:$BQ,16,0) -> 3287.33 | R19: =VLOOKUP(A19,'Custo_Fopag (2)'!$A:$BQ,17,0) -> 0 | S19: =VLOOKUP(A19,'Custo_Fopag (2)'!$A:$BP,18,0) -> 0 | T19: =VLOOKUP(A19,'Custo_Fopag (2)'!$A:$BQ,20,0) -> 657.47 | U19: =VLOOKUP(A19,'Custo_Fopag (2)'!$A:$BQ,21,0) -> 0 | V19: =VLOOKUP(A19,'Custo_Fopag (2)'!$A:$BQ,22,0) -> 0 | W19: =VLOOKUP(A19,'Custo_Fopag (2)'!$A:$BQ,23,0) -> 0 | X19: =VLOOKUP(A19,'Custo_Fopag (2)'!$A:$BQ,24,0) -> 0 | Y19: =VLOOKUP(A19,'Custo_Fopag (2)'!$A:$BQ,25,0) -> 0 | Z19: =VLOOKUP(A19,'Custo_Fopag (2)'!$A:$BQ,26,0) -> 106.82 | AA19: =VLOOKUP(A19,'Custo_Fopag (2)'!$A:$BQ,27,0) -> 245.65 | AB19: =VLOOKUP(A19,'Custo_Fopag (2)'!$A:$BQ,28,0) -> 47.24 | AC19: =VLOOKUP(A19,'Custo_Fopag (2)'!$A:$BQ,29,0) -> 0 | AD19: =VLOOKUP(A19,'Custo_Fopag (2)'!$A:$BQ,30,0) -> 0 | AE19: =VLOOKUP(A19,'Custo_Fopag (2)'!$A:$BQ,31,0) -> 0 | AF19: =VLOOKUP(A19,'Custo_Fopag (2)'!$A:$BQ,32,0) -> 0 | AG19: =SUM(Q19:AF19) -> 4344.51 | AH19: =VLOOKUP(A19,'Custo_Fopag (2)'!$A:$BQ,45,0) -> 0 | AI19: =_xlfn.XLOOKUP(A19,Beneficios!A:A,Beneficios!B:B,0,0,1) -> 512.87 | AJ19: =VLOOKUP(A19,'Custo_Fopag (2)'!$A:$BQ,47,0) -> 0 | AK19: 0 | AL19: =VLOOKUP(A19,'Custo_Fopag (2)'!$A:$BQ,35,0) -> 0 | AM19: =VLOOKUP(A19,'Custo_Fopag (2)'!$A:$BQ,36,0) -> 0 | AN19: =VLOOKUP(A19,'Custo_Fopag (2)'!$A:$BQ,37,0) -> 692.64 | AO19: =VLOOKUP(A19,'Custo_Fopag (2)'!$A:$BQ,39,0) -> 0 | AP19: =VLOOKUP(A19,'Custo_Fopag (2)'!$A:$BQ,42,0) -> 0 | AQ19: =VLOOKUP(A19,'Custo_Fopag (2)'!$A:$BQ,40,0) -> 0 | AR19: =VLOOKUP(A19,'Custo_Fopag (2)'!$A:$BQ,41,0) -> 0 | AS19: =VLOOKUP(A19,'Custo_Fopag (2)'!$A:$BQ,38,0) -> 0 | AT19: =VLOOKUP(A19,'Custo_Fopag (2)'!$A:$BQ,43,0) -> 0 | AU19: =VLOOKUP(A19,'Custo_Fopag (2)'!$A:$BQ,48,0) -> 2730 | AV19: =VLOOKUP(A19,'Custo_Fopag (2)'!$A:$BQ,49,0) -> 0 | AW19: =VLOOKUP(A19,'Custo_Fopag (2)'!$A:$BQ,19,0) -> 0 | AX19: =VLOOKUP(A19,'Custo_Fopag (2)'!$A:$BQ,50,0) -> 0 | AY19: =VLOOKUP(A19,'Custo_Fopag (2)'!$A:$BQ,51,0) -> 0 | AZ19: 0 | BA19: 0 | BB19: =VLOOKUP(A19,'Custo_Fopag (2)'!$A:$BQ,52,0) -> 0 | BC19: =SUM(AH19:BB19) -> 3935.51 | BD19: =BC19+AG19 -> 8280.02 | BF19: =BD19+BE19 -> 8280.02 | BG19: =AG19/12 -> 362.0425 | BH19: =BG19 -> 362.0425 | BI19: =BH19/3 -> 120.68083 | BJ19: =SUM(BG19:BI19) -> 844.76583 | BK19: =VLOOKUP(A19,'Custo_Fopag (2)'!$A:$BQ,65,0) -> 868.9 | BL19: =VLOOKUP(A19,'Custo_Fopag (2)'!$A:$BQP,66,0) -> 65.16 | BM19: =VLOOKUP(A19,'Custo_Fopag (2)'!$A:$BQ,67,0) -> 251.98 | BN19: =VLOOKUP(A19,'Custo_Fopag (2)'!$A:$BQ,64,0) -> 347.56 | BO19: =SUM(BK19:BN19) -> 1533.6 | BP19: =BF19+BO19 -> 9813.62 | BQ19: =BF19+BJ19+BO19 -> 10658.386 | BR19: =VLOOKUP(A19,'Custo_Fopag (2)'!$A:$BQ,60,0) -> 0 | BS19: =IF(ISBLANK(L19),"Ativo","Desligado") -> Ativo
A20: DANIELA SANTOS MORAES | B20: 46082 | C20: CLT | D20: =VLOOKUP(A20,'Custo_Fopag (2)'!A:$BQ,4,0) -> G3S FL 10 - PRES PRUD | G20: =VLOOKUP(A20,'Custo_Fopag (2)'!$A:$BQ,5,0) -> 20.947.332/0010-86 | H20: =VLOOKUP(A20,'Custo_Fopag (2)'!$A:$BQ,6,0) -> ADMINISTRATIVO | I20: =VLOOKUP(A20,'Custo_Fopag (2)'!$A:$BQ,7,0) -> CONTABILIDADE | J20: =VLOOKUP(A20,'Custo_Fopag (2)'!$A:$BQ,8,0) -> PILARES | K20: =VLOOKUP(A20,'Custo_Fopag (2)'!$A:$BQ,9,0) -> 43678 | N20: =VLOOKUP(A20,'Custo_Fopag (2)'!$A:$BQ,11,0) -> 1.1.4 CONTABILIDADE/FISCAL | O20: =VLOOKUP(A20,'Custo_Fopag (2)'!$A:$BQ,12,0) -> ANALISTA CONTABIL SENIOR | P20: =VLOOKUP(A20,'Custo_Fopag (2)'!$A:$BQ,13,0) -> 3718.75 | Q20: =VLOOKUP(A20,'Custo_Fopag (2)'!$A:$BQ,16,0) -> 3718.75 | R20: =VLOOKUP(A20,'Custo_Fopag (2)'!$A:$BQ,17,0) -> 0 | S20: =VLOOKUP(A20,'Custo_Fopag (2)'!$A:$BP,18,0) -> 0 | T20: =VLOOKUP(A20,'Custo_Fopag (2)'!$A:$BQ,20,0) -> 0 | U20: =VLOOKUP(A20,'Custo_Fopag (2)'!$A:$BQ,21,0) -> 0 | V20: =VLOOKUP(A20,'Custo_Fopag (2)'!$A:$BQ,22,0) -> 0 | W20: =VLOOKUP(A20,'Custo_Fopag (2)'!$A:$BQ,23,0) -> 0 | X20: =VLOOKUP(A20,'Custo_Fopag (2)'!$A:$BQ,24,0) -> 0 | Y20: =VLOOKUP(A20,'Custo_Fopag (2)'!$A:$BQ,25,0) -> 0 | Z20: =VLOOKUP(A20,'Custo_Fopag (2)'!$A:$BQ,26,0) -> 0 | AA20: =VLOOKUP(A20,'Custo_Fopag (2)'!$A:$BQ,27,0) -> 0 | AB20: =VLOOKUP(A20,'Custo_Fopag (2)'!$A:$BQ,28,0) -> 0 | AC20: =VLOOKUP(A20,'Custo_Fopag (2)'!$A:$BQ,29,0) -> 0 | AD20: =VLOOKUP(A20,'Custo_Fopag (2)'!$A:$BQ,30,0) -> 0 | AE20: =VLOOKUP(A20,'Custo_Fopag (2)'!$A:$BQ,31,0) -> 0 | AF20: =VLOOKUP(A20,'Custo_Fopag (2)'!$A:$BQ,32,0) -> 0 | AG20: =SUM(Q20:AF20) -> 3718.75 | AH20: =VLOOKUP(A20,'Custo_Fopag (2)'!$A:$BQ,45,0) -> 0 | AI20: =_xlfn.XLOOKUP(A20,Beneficios!A:A,Beneficios!B:B,0,0,1) -> 521.87 | AJ20: =VLOOKUP(A20,'Custo_Fopag (2)'!$A:$BQ,47,0) -> 0 | AK20: 0 | AL20: =VLOOKUP(A20,'Custo_Fopag (2)'!$A:$BQ,35,0) -> 0 | AM20: =VLOOKUP(A20,'Custo_Fopag (2)'!$A:$BQ,36,0) -> 0 | AN20: =VLOOKUP(A20,'Custo_Fopag (2)'!$A:$BQ,37,0) -> 0 | AO20: =VLOOKUP(A20,'Custo_Fopag (2)'!$A:$BQ,39,0) -> 0 | AP20: =VLOOKUP(A20,'Custo_Fopag (2)'!$A:$BQ,42,0) -> 100 | AQ20: =VLOOKUP(A20,'Custo_Fopag (2)'!$A:$BQ,40,0) -> 0 | AR20: =VLOOKUP(A20,'Custo_Fopag (2)'!$A:$BQ,41,0) -> 0 | AS20: =VLOOKUP(A20,'Custo_Fopag (2)'!$A:$BQ,38,0) -> 0 | AT20: =VLOOKUP(A20,'Custo_Fopag (2)'!$A:$BQ,43,0) -> 0 | AU20: =VLOOKUP(A20,'Custo_Fopag (2)'!$A:$BQ,48,0) -> 0 | AV20: =VLOOKUP(A20,'Custo_Fopag (2)'!$A:$BQ,49,0) -> 0 | AW20: =VLOOKUP(A20,'Custo_Fopag (2)'!$A:$BQ,19,0) -> 0 | AX20: =VLOOKUP(A20,'Custo_Fopag (2)'!$A:$BQ,50,0) -> 0 | AY20: =VLOOKUP(A20,'Custo_Fopag (2)'!$A:$BQ,51,0) -> 0 | AZ20: 0 | BA20: =VLOOKUP(A20,'Custo_Fopag (2)'!$A:$BQ,54,0) -> 0 | BB20: =VLOOKUP(A20,'Custo_Fopag (2)'!$A:$BQ,52,0) -> 0 | BC20: =SUM(AH20:BB20) -> 621.87 | BD20: =BC20+AG20 -> 4340.62 | BF20: =BD20+BE20 -> 4340.62 | BG20: =AG20/12 -> 309.89583 | BH20: =BG20 -> 309.89583 | BI20: =BH20/3 -> 103.29861 | BJ20: =SUM(BG20:BI20) -> 723.09028 | BK20: =VLOOKUP(A20,'Custo_Fopag (2)'!$A:$BQ,65,0) -> 743.75 | BL20: =VLOOKUP(A20,'Custo_Fopag (2)'!$A:$BQP,66,0) -> 111.56 | BM20: =VLOOKUP(A20,'Custo_Fopag (2)'!$A:$BQ,67,0) -> 215.68 | BN20: =VLOOKUP(A20,'Custo_Fopag (2)'!$A:$BQ,64,0) -> 297.5 | BO20: =SUM(BK20:BN20) -> 1368.49 | BP20: =BF20+BO20 -> 5709.11 | BQ20: =BF20+BJ20+BO20 -> 6432.2003 | BR20: =VLOOKUP(A20,'Custo_Fopag (2)'!$A:$BQ,60,0) -> 0 | BS20: =IF(ISBLANK(L20),"Ativo","Desligado") -> Ativo
A21: DIEGO LEANDRO DE OLIVEIRA | B21: 46082 | C21: CLT | D21: =VLOOKUP(A21,'Custo_Fopag (2)'!A:$BQ,4,0) -> G3S FL 05 - PRES PRUD | G21: =VLOOKUP(A21,'Custo_Fopag (2)'!$A:$BQ,5,0) -> 20.947.332/0005-19 | H21: =VLOOKUP(A21,'Custo_Fopag (2)'!$A:$BQ,6,0) -> OPERACIONAL | I21: =VLOOKUP(A21,'Custo_Fopag (2)'!$A:$BQ,7,0) -> CORTE E DOBRA | J21: =VLOOKUP(A21,'Custo_Fopag (2)'!$A:$BQ,8,0) -> BRACOFER | K21: =VLOOKUP(A21,'Custo_Fopag (2)'!$A:$BQ,9,0) -> 45021 | N21: =VLOOKUP(A21,'Custo_Fopag (2)'!$A:$BQ,11,0) -> 1.3.1.5 CORTE E DOBRA | O21: =VLOOKUP(A21,'Custo_Fopag (2)'!$A:$BQ,12,0) -> AUXILIAR DE PATIO PLENO | P21: =VLOOKUP(A21,'Custo_Fopag (2)'!$A:$BQ,13,0) -> 2350 | Q21: =VLOOKUP(A21,'Custo_Fopag (2)'!$A:$BQ,16,0) -> 2350 | R21: =VLOOKUP(A21,'Custo_Fopag (2)'!$A:$BQ,17,0) -> 0 | S21: =VLOOKUP(A21,'Custo_Fopag (2)'!$A:$BP,18,0) -> 0 | T21: =VLOOKUP(A21,'Custo_Fopag (2)'!$A:$BQ,20,0) -> 0 | U21: =VLOOKUP(A21,'Custo_Fopag (2)'!$A:$BQ,21,0) -> 0 | V21: =VLOOKUP(A21,'Custo_Fopag (2)'!$A:$BQ,22,0) -> 0 | W21: =VLOOKUP(A21,'Custo_Fopag (2)'!$A:$BQ,23,0) -> 0 | X21: =VLOOKUP(A21,'Custo_Fopag (2)'!$A:$BQ,24,0) -> 0 | Y21: =VLOOKUP(A21,'Custo_Fopag (2)'!$A:$BQ,25,0) -> 0 | Z21: =VLOOKUP(A21,'Custo_Fopag (2)'!$A:$BQ,26,0) -> 0 | AA21: =VLOOKUP(A21,'Custo_Fopag (2)'!$A:$BQ,27,0) -> 385.69 | AB21: =VLOOKUP(A21,'Custo_Fopag (2)'!$A:$BQ,28,0) -> 74.17 | AC21: =VLOOKUP(A21,'Custo_Fopag (2)'!$A:$BQ,29,0) -> 0 | AD21: =VLOOKUP(A21,'Custo_Fopag (2)'!$A:$BQ,30,0) -> 0 | AE21: =VLOOKUP(A21,'Custo_Fopag (2)'!$A:$BQ,31,0) -> 0 | AF21: =VLOOKUP(A21,'Custo_Fopag (2)'!$A:$BQ,32,0) -> 0 | AG21: =SUM(Q21:AF21) -> 2809.86 | AH21: =VLOOKUP(A21,'Custo_Fopag (2)'!$A:$BQ,45,0) -> 0 | AI21: =_xlfn.XLOOKUP(A21,Beneficios!A:A,Beneficios!B:B,0,0,1) -> 521.87 | AJ21: =VLOOKUP(A21,'Custo_Fopag (2)'!$A:$BQ,47,0) -> 0 | AK21: 0 | AL21: =VLOOKUP(A21,'Custo_Fopag (2)'!$A:$BQ,35,0) -> 0 | AM21: =VLOOKUP(A21,'Custo_Fopag (2)'!$A:$BQ,36,0) -> 0 | AN21: =VLOOKUP(A21,'Custo_Fopag (2)'!$A:$BQ,37,0) -> 0 | AO21: =VLOOKUP(A21,'Custo_Fopag (2)'!$A:$BQ,39,0) -> 0 | AP21: =VLOOKUP(A21,'Custo_Fopag (2)'!$A:$BQ,42,0) -> 350 | AQ21: =VLOOKUP(A21,'Custo_Fopag (2)'!$A:$BQ,40,0) -> 0 | AR21: =VLOOKUP(A21,'Custo_Fopag (2)'!$A:$BQ,41,0) -> 0 | AS21: =VLOOKUP(A21,'Custo_Fopag (2)'!$A:$BQ,38,0) -> 0 | AT21: =VLOOKUP(A21,'Custo_Fopag (2)'!$A:$BQ,43,0) -> 0 | AU21: =VLOOKUP(A21,'Custo_Fopag (2)'!$A:$BQ,48,0) -> 0 | AV21: =VLOOKUP(A21,'Custo_Fopag (2)'!$A:$BQ,49,0) -> 0 | AW21: =VLOOKUP(A21,'Custo_Fopag (2)'!$A:$BQ,19,0) -> 0 | AX21: =VLOOKUP(A21,'Custo_Fopag (2)'!$A:$BQ,50,0) -> 0 | AY21: =VLOOKUP(A21,'Custo_Fopag (2)'!$A:$BQ,51,0) -> 0 | AZ21: 0 | BA21: =VLOOKUP(A21,'Custo_Fopag (2)'!$A:$BQ,54,0) -> 0 | BB21: =VLOOKUP(A21,'Custo_Fopag (2)'!$A:$BQ,52,0) -> 0 | BC21: =SUM(AH21:BB21) -> 871.87 | BD21: =BC21+AG21 -> 3681.73 | BF21: =BD21+BE21 -> 3681.73 | BG21: =AG21/12 -> 234.155 | BH21: =BG21 -> 234.155 | BI21: =BH21/3 -> 78.051667 | BJ21: =SUM(BG21:BI21) -> 546.36167 | BK21: =VLOOKUP(A21,'Custo_Fopag (2)'!$A:$BQ,65,0) -> 561.97 | BL21: =VLOOKUP(A21,'Custo_Fopag (2)'!$A:$BQP,66,0) -> 42.14 | BM21: =VLOOKUP(A21,'Custo_Fopag (2)'!$A:$BQ,67,0) -> 162.97 | BN21: =VLOOKUP(A21,'Custo_Fopag (2)'!$A:$BQ,64,0) -> 224.78 | BO21: =SUM(BK21:BN21) -> 991.86 | BP21: =BF21+BO21 -> 4673.59 | BQ21: =BF21+BJ21+BO21 -> 5219.9517 | BR21: =VLOOKUP(A21,'Custo_Fopag (2)'!$A:$BQ,60,0) -> 0 | BS21: =IF(ISBLANK(L21),"Ativo","Desligado") -> Ativo
A22: DYESSILA MARY ALVES | B22: 46082 | C22: CLT | D22: =VLOOKUP(A22,'Custo_Fopag (2)'!A:$BQ,4,0) -> G3S FL 11 - MARINGA | G22: =VLOOKUP(A22,'Custo_Fopag (2)'!$A:$BQ,5,0) -> 20.947.332/0011-67 | H22: =VLOOKUP(A22,'Custo_Fopag (2)'!$A:$BQ,6,0) -> ADMINISTRATIVO | I22: =VLOOKUP(A22,'Custo_Fopag (2)'!$A:$BQ,7,0) -> ATENDIMENTO | J22: =VLOOKUP(A22,'Custo_Fopag (2)'!$A:$BQ,8,0) -> SELETIVA MARINGA CIDADE ALTA | K22: =VLOOKUP(A22,'Custo_Fopag (2)'!$A:$BQ,9,0) -> 45323 | N22: =VLOOKUP(A22,'Custo_Fopag (2)'!$A:$BQ,11,0) -> 1.2.4.1 ADMINISTRATIVO | O22: =VLOOKUP(A22,'Custo_Fopag (2)'!$A:$BQ,12,0) -> AUX ADMINISTRATIVO JUNIOR | P22: =VLOOKUP(A22,'Custo_Fopag (2)'!$A:$BQ,13,0) -> 2320 | Q22: =VLOOKUP(A22,'Custo_Fopag (2)'!$A:$BQ,16,0) -> 2320 | R22: =VLOOKUP(A22,'Custo_Fopag (2)'!$A:$BQ,17,0) -> 0 | S22: =VLOOKUP(A22,'Custo_Fopag (2)'!$A:$BP,18,0) -> 0 | T22: =VLOOKUP(A22,'Custo_Fopag (2)'!$A:$BQ,20,0) -> 0 | U22: =VLOOKUP(A22,'Custo_Fopag (2)'!$A:$BQ,21,0) -> 0 | V22: =VLOOKUP(A22,'Custo_Fopag (2)'!$A:$BQ,22,0) -> 0 | W22: =VLOOKUP(A22,'Custo_Fopag (2)'!$A:$BQ,23,0) -> 0 | X22: =VLOOKUP(A22,'Custo_Fopag (2)'!$A:$BQ,24,0) -> 0 | Y22: =VLOOKUP(A22,'Custo_Fopag (2)'!$A:$BQ,25,0) -> 0 | Z22: =VLOOKUP(A22,'Custo_Fopag (2)'!$A:$BQ,26,0) -> 0 | AA22: =VLOOKUP(A22,'Custo_Fopag (2)'!$A:$BQ,27,0) -> 237.8 | AB22: =VLOOKUP(A22,'Custo_Fopag (2)'!$A:$BQ,28,0) -> 45.73 | AC22: =VLOOKUP(A22,'Custo_Fopag (2)'!$A:$BQ,29,0) -> 0 | AD22: =VLOOKUP(A22,'Custo_Fopag (2)'!$A:$BQ,30,0) -> 0 | AE22: =VLOOKUP(A22,'Custo_Fopag (2)'!$A:$BQ,31,0) -> 0 | AF22: =VLOOKUP(A22,'Custo_Fopag (2)'!$A:$BQ,32,0) -> 0 | AG22: =SUM(Q22:AF22) -> 2603.53 | AH22: =VLOOKUP(A22,'Custo_Fopag (2)'!$A:$BQ,45,0) -> 0 | AI22: =_xlfn.XLOOKUP(A22,Beneficios!A:A,Beneficios!B:B,0,0,1) -> 0 | AJ22: =VLOOKUP(A22,'Custo_Fopag (2)'!$A:$BQ,47,0) -> 0 | AK22: 0 | AL22: =VLOOKUP(A22,'Custo_Fopag (2)'!$A:$BQ,35,0) -> 0 | AM22: =VLOOKUP(A22,'Custo_Fopag (2)'!$A:$BQ,36,0) -> 0 | AN22: =VLOOKUP(A22,'Custo_Fopag (2)'!$A:$BQ,37,0) -> 0 | AO22: =VLOOKUP(A22,'Custo_Fopag (2)'!$A:$BQ,39,0) -> 0 | AP22: =VLOOKUP(A22,'Custo_Fopag (2)'!$A:$BQ,42,0) -> 0 | AQ22: =VLOOKUP(A22,'Custo_Fopag (2)'!$A:$BQ,40,0) -> 0 | AR22: =VLOOKUP(A22,'Custo_Fopag (2)'!$A:$BQ,41,0) -> 456.6 | AS22: =VLOOKUP(A22,'Custo_Fopag (2)'!$A:$BQ,38,0) -> 0 | AT22: =VLOOKUP(A22,'Custo_Fopag (2)'!$A:$BQ,43,0) -> 0 | AU22: =VLOOKUP(A22,'Custo_Fopag (2)'!$A:$BQ,48,0) -> 0 | AV22: =VLOOKUP(A22,'Custo_Fopag (2)'!$A:$BQ,49,0) -> 0 | AW22: =VLOOKUP(A22,'Custo_Fopag (2)'!$A:$BQ,19,0) -> 0 | AX22: =VLOOKUP(A22,'Custo_Fopag (2)'!$A:$BQ,50,0) -> 0 | AY22: =VLOOKUP(A22,'Custo_Fopag (2)'!$A:$BQ,51,0) -> 0 | AZ22: 0 | BA22: =VLOOKUP(A22,'Custo_Fopag (2)'!$A:$BQ,54,0) -> 0 | BB22: =VLOOKUP(A22,'Custo_Fopag (2)'!$A:$BQ,52,0) -> 0 | BC22: =SUM(AH22:BB22) -> 456.6 | BD22: =BC22+AG22 -> 3060.13 | BF22: =BD22+BE22 -> 3060.13 | BG22: =AG22/12 -> 216.96083 | BH22: =BG22 -> 216.96083 | BI22: =BH22/3 -> 72.320278 | BJ22: =SUM(BG22:BI22) -> 506.24194 | BK22: =VLOOKUP(A22,'Custo_Fopag (2)'!$A:$BQ,65,0) -> 520.71 | BL22: =VLOOKUP(A22,'Custo_Fopag (2)'!$A:$BQP,66,0) -> 78.1 | BM22: =VLOOKUP(A22,'Custo_Fopag (2)'!$A:$BQ,67,0) -> 151 | BN22: =VLOOKUP(A22,'Custo_Fopag (2)'!$A:$BQ,64,0) -> 208.28 | BO22: =SUM(BK22:BN22) -> 958.09 | BP22: =BF22+BO22 -> 4018.22 | BQ22: =BF22+BJ22+BO22 -> 4524.4619 | BR22: =VLOOKUP(A22,'Custo_Fopag (2)'!$A:$BQ,60,0) -> 0 | BS22: =IF(ISBLANK(L22),"Ativo","Desligado") -> Ativo
A23: EDILEUSA PEREIRA LISBOA | B23: 46082 | C23: CLT | D23: =VLOOKUP(A23,'Custo_Fopag (2)'!A:$BQ,4,0) -> G S MATRIZ - PRES PRUD | G23: =VLOOKUP(A23,'Custo_Fopag (2)'!$A:$BQ,5,0) -> 20.504.237/0001-17 | H23: =VLOOKUP(A23,'Custo_Fopag (2)'!$A:$BQ,6,0) -> OPERACIONAL | I23: =VLOOKUP(A23,'Custo_Fopag (2)'!$A:$BQ,7,0) -> PATIO | J23: =VLOOKUP(A23,'Custo_Fopag (2)'!$A:$BQ,8,0) -> SELETIVA PRESIDENTE PRUDENTE | K23: =VLOOKUP(A23,'Custo_Fopag (2)'!$A:$BQ,9,0) -> 46043 | N23: =VLOOKUP(A23,'Custo_Fopag (2)'!$A:$BQ,11,0) -> 1.2.5.3 OPERACIONAL | O23: =VLOOKUP(A23,'Custo_Fopag (2)'!$A:$BQ,12,0) -> OPERADOR MANTENEDOR JR | P23: =VLOOKUP(A23,'Custo_Fopag (2)'!$A:$BQ,13,0) -> 2610 | Q23: =VLOOKUP(A23,'Custo_Fopag (2)'!$A:$BQ,16,0) -> 2610 | R23: =VLOOKUP(A23,'Custo_Fopag (2)'!$A:$BQ,17,0) -> 0 | S23: =VLOOKUP(A23,'Custo_Fopag (2)'!$A:$BP,18,0) -> 0 | T23: =VLOOKUP(A23,'Custo_Fopag (2)'!$A:$BQ,20,0) -> 522 | U23: =VLOOKUP(A23,'Custo_Fopag (2)'!$A:$BQ,21,0) -> 0 | V23: =VLOOKUP(A23,'Custo_Fopag (2)'!$A:$BQ,22,0) -> 0 | W23: =VLOOKUP(A23,'Custo_Fopag (2)'!$A:$BQ,23,0) -> 0 | X23: =VLOOKUP(A23,'Custo_Fopag (2)'!$A:$BQ,24,0) -> 0 | Y23: =VLOOKUP(A23,'Custo_Fopag (2)'!$A:$BQ,25,0) -> 0 | Z23: =VLOOKUP(A23,'Custo_Fopag (2)'!$A:$BQ,26,0) -> 0 | AA23: =VLOOKUP(A23,'Custo_Fopag (2)'!$A:$BQ,27,0) -> 750.61 | AB23: =VLOOKUP(A23,'Custo_Fopag (2)'!$A:$BQ,28,0) -> 144.35 | AC23: =VLOOKUP(A23,'Custo_Fopag (2)'!$A:$BQ,29,0) -> 0 | AD23: =VLOOKUP(A23,'Custo_Fopag (2)'!$A:$BQ,30,0) -> 0 | AE23: =VLOOKUP(A23,'Custo_Fopag (2)'!$A:$BQ,31,0) -> 0 | AF23: =VLOOKUP(A23,'Custo_Fopag (2)'!$A:$BQ,32,0) -> 0 | AG23: =SUM(Q23:AF23) -> 4026.96 | AH23: =VLOOKUP(A23,'Custo_Fopag (2)'!$A:$BQ,45,0) -> 0 | AI23: =_xlfn.XLOOKUP(A23,Beneficios!A:A,Beneficios!B:B,0,0,1) -> 512.87 | AJ23: =VLOOKUP(A23,'Custo_Fopag (2)'!$A:$BQ,47,0) -> 0 | AK23: 0 | AL23: =VLOOKUP(A23,'Custo_Fopag (2)'!$A:$BQ,35,0) -> 0 | AM23: =VLOOKUP(A23,'Custo_Fopag (2)'!$A:$BQ,36,0) -> 0 | AN23: =VLOOKUP(A23,'Custo_Fopag (2)'!$A:$BQ,37,0) -> 0 | AO23: =VLOOKUP(A23,'Custo_Fopag (2)'!$A:$BQ,39,0) -> 0 | AP23: =VLOOKUP(A23,'Custo_Fopag (2)'!$A:$BQ,42,0) -> 0 | AQ23: =VLOOKUP(A23,'Custo_Fopag (2)'!$A:$BQ,40,0) -> 0 | AR23: =VLOOKUP(A23,'Custo_Fopag (2)'!$A:$BQ,41,0) -> 579.34 | AS23: =VLOOKUP(A23,'Custo_Fopag (2)'!$A:$BQ,38,0) -> 0 | AT23: =VLOOKUP(A23,'Custo_Fopag (2)'!$A:$BQ,43,0) -> 0 | AU23: =VLOOKUP(A23,'Custo_Fopag (2)'!$A:$BQ,48,0) -> 0 | AV23: =VLOOKUP(A23,'Custo_Fopag (2)'!$A:$BQ,49,0) -> 0 | AW23: =VLOOKUP(A23,'Custo_Fopag (2)'!$A:$BQ,19,0) -> 0 | AX23: =VLOOKUP(A23,'Custo_Fopag (2)'!$A:$BQ,50,0) -> 0 | AY23: =VLOOKUP(A23,'Custo_Fopag (2)'!$A:$BQ,51,0) -> 0 | AZ23: 0 | BA23: =VLOOKUP(A23,'Custo_Fopag (2)'!$A:$BQ,54,0) -> 0 | BB23: =VLOOKUP(A23,'Custo_Fopag (2)'!$A:$BQ,52,0) -> 0 | BC23: =SUM(AH23:BB23) -> 1092.21 | BD23: =BC23+AG23 -> 5119.17 | BF23: =BD23+BE23 -> 5119.17 | BG23: =AG23/12 -> 335.58 | BH23: =BG23 -> 335.58 | BI23: =BH23/3 -> 111.86 | BJ23: =SUM(BG23:BI23) -> 783.02 | BK23: =VLOOKUP(A23,'Custo_Fopag (2)'!$A:$BQ,65,0) -> 805.39 | BL23: =VLOOKUP(A23,'Custo_Fopag (2)'!$A:$BQP,66,0) -> 60.4 | BM23: =VLOOKUP(A23,'Custo_Fopag (2)'!$A:$BQ,67,0) -> 233.56 | BN23: =VLOOKUP(A23,'Custo_Fopag (2)'!$A:$BQ,64,0) -> 322.15 | BO23: =SUM(BK23:BN23) -> 1421.5 | BP23: =BF23+BO23 -> 6540.67 | BQ23: =BF23+BJ23+BO23 -> 7323.69 | BR23: =VLOOKUP(A23,'Custo_Fopag (2)'!$A:$BQ,60,0) -> 0 | BS23: =IF(ISBLANK(L23),"Ativo","Desligado") -> Ativo
A24: EDUARDO SOARES E SILVA | B24: 46082 | C24: CLT | D24: =VLOOKUP(A24,'Custo_Fopag (2)'!A:$BQ,4,0) -> G3S FL 05 - PRES PRUD | G24: =VLOOKUP(A24,'Custo_Fopag (2)'!$A:$BQ,5,0) -> 20.947.332/0005-19 | H24: =VLOOKUP(A24,'Custo_Fopag (2)'!$A:$BQ,6,0) -> OPERACIONAL | I24: =VLOOKUP(A24,'Custo_Fopag (2)'!$A:$BQ,7,0) -> CORTE E DOBRA | J24: =VLOOKUP(A24,'Custo_Fopag (2)'!$A:$BQ,8,0) -> BRACOFER | K24: =VLOOKUP(A24,'Custo_Fopag (2)'!$A:$BQ,9,0) -> 45979 | N24: =VLOOKUP(A24,'Custo_Fopag (2)'!$A:$BQ,11,0) -> 1.3.1.5 CORTE E DOBRA | O24: =VLOOKUP(A24,'Custo_Fopag (2)'!$A:$BQ,12,0) -> AUXILIAR DE PATIO JUNIOR | P24: =VLOOKUP(A24,'Custo_Fopag (2)'!$A:$BQ,13,0) -> 2155 | Q24: =VLOOKUP(A24,'Custo_Fopag (2)'!$A:$BQ,16,0) -> 2155 | R24: =VLOOKUP(A24,'Custo_Fopag (2)'!$A:$BQ,17,0) -> 0 | S24: =VLOOKUP(A24,'Custo_Fopag (2)'!$A:$BP,18,0) -> 0 | T24: =VLOOKUP(A24,'Custo_Fopag (2)'!$A:$BQ,20,0) -> 0 | U24: =VLOOKUP(A24,'Custo_Fopag (2)'!$A:$BQ,21,0) -> 0 | V24: =VLOOKUP(A24,'Custo_Fopag (2)'!$A:$BQ,22,0) -> 0 | W24: =VLOOKUP(A24,'Custo_Fopag (2)'!$A:$BQ,23,0) -> 0 | X24: =VLOOKUP(A24,'Custo_Fopag (2)'!$A:$BQ,24,0) -> 0 | Y24: =VLOOKUP(A24,'Custo_Fopag (2)'!$A:$BQ,25,0) -> 0 | Z24: =VLOOKUP(A24,'Custo_Fopag (2)'!$A:$BQ,26,0) -> 0 | AA24: =VLOOKUP(A24,'Custo_Fopag (2)'!$A:$BQ,27,0) -> 339.58 | AB24: =VLOOKUP(A24,'Custo_Fopag (2)'!$A:$BQ,28,0) -> 65.3 | AC24: =VLOOKUP(A24,'Custo_Fopag (2)'!$A:$BQ,29,0) -> 0 | AD24: =VLOOKUP(A24,'Custo_Fopag (2)'!$A:$BQ,30,0) -> 0 | AE24: =VLOOKUP(A24,'Custo_Fopag (2)'!$A:$BQ,31,0) -> 0 | AF24: =VLOOKUP(A24,'Custo_Fopag (2)'!$A:$BQ,32,0) -> 0 | AG24: =SUM(Q24:AF24) -> 2559.88 | AH24: =VLOOKUP(A24,'Custo_Fopag (2)'!$A:$BQ,45,0) -> 0 | AI24: =_xlfn.XLOOKUP(A24,Beneficios!A:A,Beneficios!B:B,0,0,1) -> 521.87 | AJ24: =VLOOKUP(A24,'Custo_Fopag (2)'!$A:$BQ,47,0) -> 0 | AK24: 0 | AL24: =VLOOKUP(A24,'Custo_Fopag (2)'!$A:$BQ,35,0) -> 0 | AM24: =VLOOKUP(A24,'Custo_Fopag (2)'!$A:$BQ,36,0) -> 0 | AN24: =VLOOKUP(A24,'Custo_Fopag (2)'!$A:$BQ,37,0) -> 0 | AO24: =VLOOKUP(A24,'Custo_Fopag (2)'!$A:$BQ,39,0) -> 0 | AP24: =VLOOKUP(A24,'Custo_Fopag (2)'!$A:$BQ,42,0) -> 350 | AQ24: =VLOOKUP(A24,'Custo_Fopag (2)'!$A:$BQ,40,0) -> 0 | AR24: =VLOOKUP(A24,'Custo_Fopag (2)'!$A:$BQ,41,0) -> 0 | AS24: =VLOOKUP(A24,'Custo_Fopag (2)'!$A:$BQ,38,0) -> 0 | AT24: =VLOOKUP(A24,'Custo_Fopag (2)'!$A:$BQ,43,0) -> 0 | AU24: =VLOOKUP(A24,'Custo_Fopag (2)'!$A:$BQ,48,0) -> 0 | AV24: =VLOOKUP(A24,'Custo_Fopag (2)'!$A:$BQ,49,0) -> 0 | AW24: =VLOOKUP(A24,'Custo_Fopag (2)'!$A:$BQ,19,0) -> 0 | AX24: =VLOOKUP(A24,'Custo_Fopag (2)'!$A:$BQ,50,0) -> 0 | AY24: =VLOOKUP(A24,'Custo_Fopag (2)'!$A:$BQ,51,0) -> 0 | AZ24: 0 | BA24: =VLOOKUP(A24,'Custo_Fopag (2)'!$A:$BQ,54,0) -> 0 | BB24: =VLOOKUP(A24,'Custo_Fopag (2)'!$A:$BQ,52,0) -> 0 | BC24: =SUM(AH24:BB24) -> 871.87 | BD24: =BC24+AG24 -> 3431.75 | BF24: =BD24+BE24 -> 3431.75 | BG24: =AG24/12 -> 213.32333 | BH24: =BG24 -> 213.32333 | BI24: =BH24/3 -> 71.107778 | BJ24: =SUM(BG24:BI24) -> 497.75444 | BK24: =VLOOKUP(A24,'Custo_Fopag (2)'!$A:$BQ,65,0) -> 511.98 | BL24: =VLOOKUP(A24,'Custo_Fopag (2)'!$A:$BQP,66,0) -> 38.39 | BM24: =VLOOKUP(A24,'Custo_Fopag (2)'!$A:$BQ,67,0) -> 148.47 | BN24: =VLOOKUP(A24,'Custo_Fopag (2)'!$A:$BQ,64,0) -> 204.79 | BO24: =SUM(BK24:BN24) -> 903.63 | BP24: =BF24+BO24 -> 4335.38 | BQ24: =BF24+BJ24+BO24 -> 4833.1344 | BR24: =VLOOKUP(A24,'Custo_Fopag (2)'!$A:$BQ,60,0) -> 0 | BS24: =IF(ISBLANK(L24),"Ativo","Desligado") -> Ativo
A25: EDUARDO YUICHI CHINMEI | B25: 46082 | C25: CLT | D25: =VLOOKUP(A25,'Custo_Fopag (2)'!A:$BQ,4,0) -> G3S FL 10 - PRES PRUD | E25: 4 | G25: =VLOOKUP(A25,'Custo_Fopag (2)'!$A:$BQ,5,0) -> 20.947.332/0010-86 | H25: =VLOOKUP(A25,'Custo_Fopag (2)'!$A:$BQ,6,0) -> COMERCIAL | I25: =VLOOKUP(A25,'Custo_Fopag (2)'!$A:$BQ,7,0) -> COMERCIAL | J25: =VLOOKUP(A25,'Custo_Fopag (2)'!$A:$BQ,8,0) -> SELETIVA CORPORATIVO SUCATA | K25: =VLOOKUP(A25,'Custo_Fopag (2)'!$A:$BQ,9,0) -> 45748 | L25: =VLOOKUP(A25,'Custo_Fopag (2)'!$A:$BQ,10,0) -> 46104 | M25: MARCONDES | N25: =VLOOKUP(A25,'Custo_Fopag (2)'!$A:$BQ,11,0) -> 1.2.1.1 APOIO | O25: =VLOOKUP(A25,'Custo_Fopag (2)'!$A:$BQ,12,0) -> ASSISTENTE COMERCIAL | P25: =VLOOKUP(A25,'Custo_Fopag (2)'!$A:$BQ,13,0) -> 2098 | Q25: =VLOOKUP(A25,'Custo_Fopag (2)'!$A:$BQ,16,0) -> 0 | R25: =VLOOKUP(A25,'Custo_Fopag (2)'!$A:$BQ,17,0) -> 0 | S25: =VLOOKUP(A25,'Custo_Fopag (2)'!$A:$BP,18,0) -> 0 | T25: =VLOOKUP(A25,'Custo_Fopag (2)'!$A:$BQ,20,0) -> 0 | U25: =VLOOKUP(A25,'Custo_Fopag (2)'!$A:$BQ,21,0) -> 0 | V25: =VLOOKUP(A25,'Custo_Fopag (2)'!$A:$BQ,22,0) -> 0 | W25: =VLOOKUP(A25,'Custo_Fopag (2)'!$A:$BQ,23,0) -> 0 | X25: =VLOOKUP(A25,'Custo_Fopag (2)'!$A:$BQ,24,0) -> 0 | Y25: =VLOOKUP(A25,'Custo_Fopag (2)'!$A:$BQ,25,0) -> 0 | Z25: =VLOOKUP(A25,'Custo_Fopag (2)'!$A:$BQ,26,0) -> 0 | AA25: =VLOOKUP(A25,'Custo_Fopag (2)'!$A:$BQ,27,0) -> 0 | AB25: =VLOOKUP(A25,'Custo_Fopag (2)'!$A:$BQ,28,0) -> 8.43 | AC25: =VLOOKUP(A25,'Custo_Fopag (2)'!$A:$BQ,29,0) -> 0 | AD25: =VLOOKUP(A25,'Custo_Fopag (2)'!$A:$BQ,30,0) -> 0 | AE25: =VLOOKUP(A25,'Custo_Fopag (2)'!$A:$BQ,31,0) -> 0 | AF25: =VLOOKUP(A25,'Custo_Fopag (2)'!$A:$BQ,32,0) -> 0 | AG25: =SUM(Q25:AF25) -> 8.43 | AH25: =VLOOKUP(A25,'Custo_Fopag (2)'!$A:$BQ,45,0) -> 0 | AI25: =_xlfn.XLOOKUP(A25,'Custo_Fopag (2)'!A:A,'Custo_Fopag (2)'!AT:AT,0,0,1) -> 416.67 | AJ25: =VLOOKUP(A25,'Custo_Fopag (2)'!$A:$BQ,47,0) -> 0 | AK25: 0 | AL25: =VLOOKUP(A25,'Custo_Fopag (2)'!$A:$BQ,35,0) -> 0 | AM25: =VLOOKUP(A25,'Custo_Fopag (2)'!$A:$BQ,36,0) -> 0 | AN25: =VLOOKUP(A25,'Custo_Fopag (2)'!$A:$BQ,37,0) -> 0 | AO25: =VLOOKUP(A25,'Custo_Fopag (2)'!$A:$BQ,39,0) -> 0 | AP25: =VLOOKUP(A25,'Custo_Fopag (2)'!$A:$BQ,42,0) -> 0 | AQ25: =VLOOKUP(A25,'Custo_Fopag (2)'!$A:$BQ,40,0) -> 0 | AR25: =VLOOKUP(A25,'Custo_Fopag (2)'!$A:$BQ,41,0) -> 0 | AS25: =VLOOKUP(A25,'Custo_Fopag (2)'!$A:$BQ,38,0) -> 929.47 | AT25: =VLOOKUP(A25,'Custo_Fopag (2)'!$A:$BQ,43,0) -> 0 | AU25: =VLOOKUP(A25,'Custo_Fopag (2)'!$A:$BQ,48,0) -> 0 | AV25: =VLOOKUP(A25,'Custo_Fopag (2)'!$A:$BQ,49,0) -> 0 | AW25: =VLOOKUP(A25,'Custo_Fopag (2)'!$A:$BQ,19,0) -> 0 | AX25: =VLOOKUP(A25,'Custo_Fopag (2)'!$A:$BQ,50,0) -> 0 | AY25: =VLOOKUP(A25,'Custo_Fopag (2)'!$A:$BQ,51,0) -> 0 | AZ25: 0 | BA25: =VLOOKUP(A25,'Custo_Fopag (2)'!$A:$BQ,54,0) -> 0 | BB25: =VLOOKUP(A25,'Custo_Fopag (2)'!$A:$BQ,52,0) -> 0 | BC25: =SUM(AH25:BB25) -> 1346.14 | BD25: =BC25+AG25 -> 1354.57 | BF25: =BD25+BE25 -> 1354.57 | BG25: =AG25/12 -> 0.7025 | BH25: =BG25 -> 0.7025 | BI25: =BH25/3 -> 0.23416667 | BJ25: =SUM(BG25:BI25) -> 1.6391667 | BK25: =VLOOKUP(A25,'Custo_Fopag (2)'!$A:$BQ,65,0) -> 1.69 | BL25: =VLOOKUP(A25,'Custo_Fopag (2)'!$A:$BQP,66,0) -> 0.25 | BM25: =VLOOKUP(A25,'Custo_Fopag (2)'!$A:$BQ,67,0) -> 0.48 | BN25: =VLOOKUP(A25,'Custo_Fopag (2)'!$A:$BQ,64,0) -> 0 | BO25: =SUM(BK25:BN25) -> 2.42 | BP25: =BF25+BO25 -> 1356.99 | BQ25: =BF25+BJ25+BO25 -> 1358.6292 | BR25: =VLOOKUP(A25,'Custo_Fopag (2)'!$A:$BQ,60,0) -> 6934.39 | BS25: =IF(ISBLANK(L25),"Ativo","Desligado") -> Desligado
A26: ELAINE CRISTINA PANIZZA SILVA | B26: 46082 | C26: CLT | D26: =VLOOKUP(A26,'Custo_Fopag (2)'!A:$BQ,4,0) -> G3S FL 10 - PRES PRUD | G26: =VLOOKUP(A26,'Custo_Fopag (2)'!$A:$BQ,5,0) -> 20.947.332/0010-86 | H26: =VLOOKUP(A26,'Custo_Fopag (2)'!$A:$BQ,6,0) -> GESTÃO DE GENTE | I26: =VLOOKUP(A26,'Custo_Fopag (2)'!$A:$BQ,7,0) -> RECURSOS HUMANOS | J26: =VLOOKUP(A26,'Custo_Fopag (2)'!$A:$BQ,8,0) -> PILARES | K26: =VLOOKUP(A26,'Custo_Fopag (2)'!$A:$BQ,9,0) -> 45825 | N26: =VLOOKUP(A26,'Custo_Fopag (2)'!$A:$BQ,11,0) -> 1.1.9 RECURSOS HUMANOS | O26: =VLOOKUP(A26,'Custo_Fopag (2)'!$A:$BQ,12,0) -> ANALISTA DE RECURSOS HUMANOS SENIOR | P26: =VLOOKUP(A26,'Custo_Fopag (2)'!$A:$BQ,13,0) -> 4250 | Q26: =VLOOKUP(A26,'Custo_Fopag (2)'!$A:$BQ,16,0) -> 4250 | R26: =VLOOKUP(A26,'Custo_Fopag (2)'!$A:$BQ,17,0) -> 0 | S26: =VLOOKUP(A26,'Custo_Fopag (2)'!$A:$BP,18,0) -> 0 | T26: =VLOOKUP(A26,'Custo_Fopag (2)'!$A:$BQ,20,0) -> 0 | U26: =VLOOKUP(A26,'Custo_Fopag (2)'!$A:$BQ,21,0) -> 0 | V26: =VLOOKUP(A26,'Custo_Fopag (2)'!$A:$BQ,22,0) -> 0 | W26: =VLOOKUP(A26,'Custo_Fopag (2)'!$A:$BQ,23,0) -> 0 | X26: =VLOOKUP(A26,'Custo_Fopag (2)'!$A:$BQ,24,0) -> 0 | Y26: =VLOOKUP(A26,'Custo_Fopag (2)'!$A:$BQ,25,0) -> 0 | Z26: =VLOOKUP(A26,'Custo_Fopag (2)'!$A:$BQ,26,0) -> 0 | AA26: =VLOOKUP(A26,'Custo_Fopag (2)'!$A:$BQ,27,0) -> 0 | AB26: =VLOOKUP(A26,'Custo_Fopag (2)'!$A:$BQ,28,0) -> 0 | AC26: =VLOOKUP(A26,'Custo_Fopag (2)'!$A:$BQ,29,0) -> 0 | AD26: =VLOOKUP(A26,'Custo_Fopag (2)'!$A:$BQ,30,0) -> 0 | AE26: =VLOOKUP(A26,'Custo_Fopag (2)'!$A:$BQ,31,0) -> 0 | AF26: =VLOOKUP(A26,'Custo_Fopag (2)'!$A:$BQ,32,0) -> 0 | AG26: =SUM(Q26:AF26) -> 4250 | AH26: =VLOOKUP(A26,'Custo_Fopag (2)'!$A:$BQ,45,0) -> 0 | AI26: =_xlfn.XLOOKUP(A26,Beneficios!A:A,Beneficios!B:B,0,0,1) -> 521.87 | AJ26: =VLOOKUP(A26,'Custo_Fopag (2)'!$A:$BQ,47,0) -> 0 | AK26: 0 | AL26: =VLOOKUP(A26,'Custo_Fopag (2)'!$A:$BQ,35,0) -> 0 | AM26: =VLOOKUP(A26,'Custo_Fopag (2)'!$A:$BQ,36,0) -> 0 | AN26: =VLOOKUP(A26,'Custo_Fopag (2)'!$A:$BQ,37,0) -> 0 | AO26: =VLOOKUP(A26,'Custo_Fopag (2)'!$A:$BQ,39,0) -> 0 | AP26: =VLOOKUP(A26,'Custo_Fopag (2)'!$A:$BQ,42,0) -> 0 | AQ26: =VLOOKUP(A26,'Custo_Fopag (2)'!$A:$BQ,40,0) -> 0 | AR26: =VLOOKUP(A26,'Custo_Fopag (2)'!$A:$BQ,41,0) -> 0 | AS26: =VLOOKUP(A26,'Custo_Fopag (2)'!$A:$BQ,38,0) -> 0 | AT26: =VLOOKUP(A26,'Custo_Fopag (2)'!$A:$BQ,43,0) -> 0 | AU26: =VLOOKUP(A26,'Custo_Fopag (2)'!$A:$BQ,48,0) -> 0 | AV26: =VLOOKUP(A26,'Custo_Fopag (2)'!$A:$BQ,49,0) -> 0 | AW26: =VLOOKUP(A26,'Custo_Fopag (2)'!$A:$BQ,19,0) -> 0 | AX26: =VLOOKUP(A26,'Custo_Fopag (2)'!$A:$BQ,50,0) -> 0 | AY26: =VLOOKUP(A26,'Custo_Fopag (2)'!$A:$BQ,51,0) -> 0 | AZ26: 0 | BA26: =VLOOKUP(A26,'Custo_Fopag (2)'!$A:$BQ,54,0) -> 0 | BB26: =VLOOKUP(A26,'Custo_Fopag (2)'!$A:$BQ,52,0) -> 0 | BC26: =SUM(AH26:BB26) -> 521.87 | BD26: =BC26+AG26 -> 4771.87 | BF26: =BD26+BE26 -> 4771.87 | BG26: =AG26/12 -> 354.16667 | BH26: =BG26 -> 354.16667 | BI26: =BH26/3 -> 118.05556 | BJ26: =SUM(BG26:BI26) -> 826.38889 | BK26: =VLOOKUP(A26,'Custo_Fopag (2)'!$A:$BQ,65,0) -> 850 | BL26: =VLOOKUP(A26,'Custo_Fopag (2)'!$A:$BQP,66,0) -> 127.5 | BM26: =VLOOKUP(A26,'Custo_Fopag (2)'!$A:$BQ,67,0) -> 246.5 | BN26: =VLOOKUP(A26,'Custo_Fopag (2)'!$A:$BQ,64,0) -> 340 | BO26: =SUM(BK26:BN26) -> 1564 | BP26: =BF26+BO26 -> 6335.87 | BQ26: =BF26+BJ26+BO26 -> 7162.2589 | BR26: =VLOOKUP(A26,'Custo_Fopag (2)'!$A:$BQ,60,0) -> 0 | BS26: =IF(ISBLANK(L26),"Ativo","Desligado") -> Ativo
A27: ELISMAR FERREIRA MEDEIROS | B27: 46082 | C27: CLT | D27: =VLOOKUP(A27,'Custo_Fopag (2)'!A:$BQ,4,0) -> G3S FL 05 - PRES PRUD | G27: =VLOOKUP(A27,'Custo_Fopag (2)'!$A:$BQ,5,0) -> 20.947.332/0005-19 | H27: =VLOOKUP(A27,'Custo_Fopag (2)'!$A:$BQ,6,0) -> OPERACIONAL | I27: =VLOOKUP(A27,'Custo_Fopag (2)'!$A:$BQ,7,0) -> PATIO | J27: =VLOOKUP(A27,'Custo_Fopag (2)'!$A:$BQ,8,0) -> BRACOFER | K27: =VLOOKUP(A27,'Custo_Fopag (2)'!$A:$BQ,9,0) -> 45238 | N27: =VLOOKUP(A27,'Custo_Fopag (2)'!$A:$BQ,11,0) -> 1.3.1.3 OPERACIONAL | O27: =VLOOKUP(A27,'Custo_Fopag (2)'!$A:$BQ,12,0) -> AUXILIAR DE PATIO PLENO | P27: =VLOOKUP(A27,'Custo_Fopag (2)'!$A:$BQ,13,0) -> 2350 | Q27: =VLOOKUP(A27,'Custo_Fopag (2)'!$A:$BQ,16,0) -> 2350 | R27: =VLOOKUP(A27,'Custo_Fopag (2)'!$A:$BQ,17,0) -> 0 | S27: =VLOOKUP(A27,'Custo_Fopag (2)'!$A:$BP,18,0) -> 0 | T27: =VLOOKUP(A27,'Custo_Fopag (2)'!$A:$BQ,20,0) -> 0 | U27: =VLOOKUP(A27,'Custo_Fopag (2)'!$A:$BQ,21,0) -> 0 | V27: =VLOOKUP(A27,'Custo_Fopag (2)'!$A:$BQ,22,0) -> 0 | W27: =VLOOKUP(A27,'Custo_Fopag (2)'!$A:$BQ,23,0) -> 0 | X27: =VLOOKUP(A27,'Custo_Fopag (2)'!$A:$BQ,24,0) -> 0 | Y27: =VLOOKUP(A27,'Custo_Fopag (2)'!$A:$BQ,25,0) -> 0 | Z27: =VLOOKUP(A27,'Custo_Fopag (2)'!$A:$BQ,26,0) -> 0 | AA27: =VLOOKUP(A27,'Custo_Fopag (2)'!$A:$BQ,27,0) -> 69.22 | AB27: =VLOOKUP(A27,'Custo_Fopag (2)'!$A:$BQ,28,0) -> 13.31 | AC27: =VLOOKUP(A27,'Custo_Fopag (2)'!$A:$BQ,29,0) -> 0 | AD27: =VLOOKUP(A27,'Custo_Fopag (2)'!$A:$BQ,30,0) -> 0 | AE27: =VLOOKUP(A27,'Custo_Fopag (2)'!$A:$BQ,31,0) -> 0 | AF27: =VLOOKUP(A27,'Custo_Fopag (2)'!$A:$BQ,32,0) -> 0 | AG27: =SUM(Q27:AF27) -> 2432.53 | AH27: =VLOOKUP(A27,'Custo_Fopag (2)'!$A:$BQ,45,0) -> 0 | AI27: =_xlfn.XLOOKUP(A27,Beneficios!A:A,Beneficios!B:B,0,0,1) -> 512.87 | AJ27: =VLOOKUP(A27,'Custo_Fopag (2)'!$A:$BQ,47,0) -> 0 | AK27: 0 | AL27: =VLOOKUP(A27,'Custo_Fopag (2)'!$A:$BQ,35,0) -> 0 | AM27: =VLOOKUP(A27,'Custo_Fopag (2)'!$A:$BQ,36,0) -> 0 | AN27: =VLOOKUP(A27,'Custo_Fopag (2)'!$A:$BQ,37,0) -> 0 | AO27: =VLOOKUP(A27,'Custo_Fopag (2)'!$A:$BQ,39,0) -> 0 | AP27: =VLOOKUP(A27,'Custo_Fopag (2)'!$A:$BQ,42,0) -> 350 | AQ27: =VLOOKUP(A27,'Custo_Fopag (2)'!$A:$BQ,40,0) -> 0 | AR27: =VLOOKUP(A27,'Custo_Fopag (2)'!$A:$BQ,41,0) -> 0 | AS27: =VLOOKUP(A27,'Custo_Fopag (2)'!$A:$BQ,38,0) -> 0 | AT27: =VLOOKUP(A27,'Custo_Fopag (2)'!$A:$BQ,43,0) -> 0 | AU27: =VLOOKUP(A27,'Custo_Fopag (2)'!$A:$BQ,48,0) -> 0 | AV27: =VLOOKUP(A27,'Custo_Fopag (2)'!$A:$BQ,49,0) -> 0 | AW27: =VLOOKUP(A27,'Custo_Fopag (2)'!$A:$BQ,19,0) -> 0 | AX27: =VLOOKUP(A27,'Custo_Fopag (2)'!$A:$BQ,50,0) -> 0 | AY27: =VLOOKUP(A27,'Custo_Fopag (2)'!$A:$BQ,51,0) -> 0 | AZ27: 0 | BA27: =VLOOKUP(A27,'Custo_Fopag (2)'!$A:$BQ,54,0) -> 0 | BB27: =VLOOKUP(A27,'Custo_Fopag (2)'!$A:$BQ,52,0) -> 0 | BC27: =SUM(AH27:BB27) -> 862.87 | BD27: =BC27+AG27 -> 3295.4 | BF27: =BD27+BE27 -> 3295.4 | BG27: =AG27/12 -> 202.71083 | BH27: =BG27 -> 202.71083 | BI27: =BH27/3 -> 67.570278 | BJ27: =SUM(BG27:BI27) -> 472.99194 | BK27: =VLOOKUP(A27,'Custo_Fopag (2)'!$A:$BQ,65,0) -> 486.51 | BL27: =VLOOKUP(A27,'Custo_Fopag (2)'!$A:$BQP,66,0) -> 36.48 | BM27: =VLOOKUP(A27,'Custo_Fopag (2)'!$A:$BQ,67,0) -> 141.08 | BN27: =VLOOKUP(A27,'Custo_Fopag (2)'!$A:$BQ,64,0) -> 194.6 | BO27: =SUM(BK27:BN27) -> 858.67 | BP27: =BF27+BO27 -> 4154.07 | BQ27: =BF27+BJ27+BO27 -> 4627.0619 | BR27: =VLOOKUP(A27,'Custo_Fopag (2)'!$A:$BQ,60,0) -> 0 | BS27: =IF(ISBLANK(L27),"Ativo","Desligado") -> Ativo
A28: ERNESTO EUGENIO DA SILVA | B28: 46082 | C28: CLT | D28: =VLOOKUP(A28,'Custo_Fopag (2)'!A:$BQ,4,0) -> G S FL 03 - DOURADOS | G28: =VLOOKUP(A28,'Custo_Fopag (2)'!$A:$BQ,5,0) -> 20.504.237/0003-89 | H28: =VLOOKUP(A28,'Custo_Fopag (2)'!$A:$BQ,6,0) -> LOGISTICA | I28: =VLOOKUP(A28,'Custo_Fopag (2)'!$A:$BQ,7,0) -> TRANSPORTE | J28: =VLOOKUP(A28,'Custo_Fopag (2)'!$A:$BQ,8,0) -> SELETIVA DOURADOS | K28: =VLOOKUP(A28,'Custo_Fopag (2)'!$A:$BQ,9,0) -> 45103 | N28: =VLOOKUP(A28,'Custo_Fopag (2)'!$A:$BQ,11,0) -> 1.7.5.4 LOGISTICA | O28: =VLOOKUP(A28,'Custo_Fopag (2)'!$A:$BQ,12,0) -> MOTORISTA CARRETEIRO MANTENEDOR SENIOR I | P28: =VLOOKUP(A28,'Custo_Fopag (2)'!$A:$BQ,13,0) -> 2690.66 | Q28: =VLOOKUP(A28,'Custo_Fopag (2)'!$A:$BQ,16,0) -> 2690.66 | R28: =VLOOKUP(A28,'Custo_Fopag (2)'!$A:$BQ,17,0) -> 0 | S28: =VLOOKUP(A28,'Custo_Fopag (2)'!$A:$BP,18,0) -> 0 | T28: =VLOOKUP(A28,'Custo_Fopag (2)'!$A:$BQ,20,0) -> 538.13 | U28: =VLOOKUP(A28,'Custo_Fopag (2)'!$A:$BQ,21,0) -> 0 | V28: =VLOOKUP(A28,'Custo_Fopag (2)'!$A:$BQ,22,0) -> 0 | W28: =VLOOKUP(A28,'Custo_Fopag (2)'!$A:$BQ,23,0) -> 0 | X28: =VLOOKUP(A28,'Custo_Fopag (2)'!$A:$BQ,24,0) -> 0 | Y28: =VLOOKUP(A28,'Custo_Fopag (2)'!$A:$BQ,25,0) -> 0 | Z28: =VLOOKUP(A28,'Custo_Fopag (2)'!$A:$BQ,26,0) -> 0 | AA28: =VLOOKUP(A28,'Custo_Fopag (2)'!$A:$BQ,27,0) -> 953.96 | AB28: =VLOOKUP(A28,'Custo_Fopag (2)'!$A:$BQ,28,0) -> 183.45 | AC28: =VLOOKUP(A28,'Custo_Fopag (2)'!$A:$BQ,29,0) -> 0 | AD28: =VLOOKUP(A28,'Custo_Fopag (2)'!$A:$BQ,30,0) -> 0 | AE28: =VLOOKUP(A28,'Custo_Fopag (2)'!$A:$BQ,31,0) -> 0 | AF28: =VLOOKUP(A28,'Custo_Fopag (2)'!$A:$BQ,32,0) -> 0 | AG28: =SUM(Q28:AF28) -> 4366.2 | AH28: =VLOOKUP(A28,'Custo_Fopag (2)'!$A:$BQ,45,0) -> 0 | AI28: =_xlfn.XLOOKUP(A28,Beneficios!A:A,Beneficios!B:B,0,0,1) -> 521.87 | AJ28: =VLOOKUP(A28,'Custo_Fopag (2)'!$A:$BQ,47,0) -> 0 | AK28: 0 | AL28: =VLOOKUP(A28,'Custo_Fopag (2)'!$A:$BQ,35,0) -> 0 | AM28: =VLOOKUP(A28,'Custo_Fopag (2)'!$A:$BQ,36,0) -> 366.4 | AN28: =VLOOKUP(A28,'Custo_Fopag (2)'!$A:$BQ,37,0) -> 0 | AO28: =VLOOKUP(A28,'Custo_Fopag (2)'!$A:$BQ,39,0) -> 0 | AP28: =VLOOKUP(A28,'Custo_Fopag (2)'!$A:$BQ,42,0) -> 0 | AQ28: =VLOOKUP(A28,'Custo_Fopag (2)'!$A:$BQ,40,0) -> 0 | AR28: =VLOOKUP(A28,'Custo_Fopag (2)'!$A:$BQ,41,0) -> 600 | AS28: =VLOOKUP(A28,'Custo_Fopag (2)'!$A:$BQ,38,0) -> 0 | AT28: =VLOOKUP(A28,'Custo_Fopag (2)'!$A:$BQ,43,0) -> 0 | AU28: =VLOOKUP(A28,'Custo_Fopag (2)'!$A:$BQ,48,0) -> 705 | AV28: =VLOOKUP(A28,'Custo_Fopag (2)'!$A:$BQ,49,0) -> 0 | AW28: =VLOOKUP(A28,'Custo_Fopag (2)'!$A:$BQ,19,0) -> 0 | AX28: =VLOOKUP(A28,'Custo_Fopag (2)'!$A:$BQ,50,0) -> 0 | AY28: 96.2 | AZ28: 0 | BA28: =VLOOKUP(A28,'Custo_Fopag (2)'!$A:$BQ,54,0) -> 0 | BB28: =VLOOKUP(A28,'Custo_Fopag (2)'!$A:$BQ,52,0) -> 0 | BC28: =SUM(AH28:BB28) -> 2289.47 | BD28: =BC28+AG28 -> 6655.67 | BF28: =BD28+BE28 -> 6655.67 | BG28: =AG28/12 -> 363.85 | BH28: =BG28 -> 363.85 | BI28: =BH28/3 -> 121.28333 | BJ28: =SUM(BG28:BI28) -> 848.98333 | BK28: =VLOOKUP(A28,'Custo_Fopag (2)'!$A:$BQ,65,0) -> 873.24 | BL28: =VLOOKUP(A28,'Custo_Fopag (2)'!$A:$BQP,66,0) -> 130.98 | BM28: =VLOOKUP(A28,'Custo_Fopag (2)'!$A:$BQ,67,0) -> 253.23 | BN28: =VLOOKUP(A28,'Custo_Fopag (2)'!$A:$BQ,64,0) -> 349.29 | BO28: =SUM(BK28:BN28) -> 1606.74 | BP28: =BF28+BO28 -> 8262.41 | BQ28: =BF28+BJ28+BO28 -> 9111.3933 | BR28: =VLOOKUP(A28,'Custo_Fopag (2)'!$A:$BQ,60,0) -> 0 | BS28: =IF(ISBLANK(L28),"Ativo","Desligado") -> Ativo
A29: EVERTON BENITES SOBRINHO | B29: 46082 | C29: CLT | D29: =VLOOKUP(A29,'Custo_Fopag (2)'!A:$BQ,4,0) -> G S FL 03 - DOURADOS | G29: =VLOOKUP(A29,'Custo_Fopag (2)'!$A:$BQ,5,0) -> 20.504.237/0003-89 | H29: =VLOOKUP(A29,'Custo_Fopag (2)'!$A:$BQ,6,0) -> LOGISTICA | I29: =VLOOKUP(A29,'Custo_Fopag (2)'!$A:$BQ,7,0) -> TRANSPORTE | J29: =VLOOKUP(A29,'Custo_Fopag (2)'!$A:$BQ,8,0) -> SELETIVA DOURADOS | K29: =VLOOKUP(A29,'Custo_Fopag (2)'!$A:$BQ,9,0) -> 45440 | L29: =VLOOKUP(A29,'Custo_Fopag (2)'!$A:$BQ,10,0) -> 46087 | N29: =VLOOKUP(A29,'Custo_Fopag (2)'!$A:$BQ,11,0) -> 1.7.5.4 LOGISTICA | O29: =VLOOKUP(A29,'Custo_Fopag (2)'!$A:$BQ,12,0) -> MOTORISTA CARRETEIRO MANTENEDOR SENIOR I | P29: =VLOOKUP(A29,'Custo_Fopag (2)'!$A:$BQ,13,0) -> 2690.66 | Q29: =VLOOKUP(A29,'Custo_Fopag (2)'!$A:$BQ,16,0) -> 0 | R29: =VLOOKUP(A29,'Custo_Fopag (2)'!$A:$BQ,17,0) -> 0 | S29: =VLOOKUP(A29,'Custo_Fopag (2)'!$A:$BP,18,0) -> 0 | T29: =VLOOKUP(A29,'Custo_Fopag (2)'!$A:$BQ,20,0) -> 107.63 | U29: =VLOOKUP(A29,'Custo_Fopag (2)'!$A:$BQ,21,0) -> 0 | V29: =VLOOKUP(A29,'Custo_Fopag (2)'!$A:$BQ,22,0) -> 0 | W29: =VLOOKUP(A29,'Custo_Fopag (2)'!$A:$BQ,23,0) -> 0 | X29: =VLOOKUP(A29,'Custo_Fopag (2)'!$A:$BQ,24,0) -> 0 | Y29: =VLOOKUP(A29,'Custo_Fopag (2)'!$A:$BQ,25,0) -> 0 | Z29: =VLOOKUP(A29,'Custo_Fopag (2)'!$A:$BQ,26,0) -> 0 | AA29: =VLOOKUP(A29,'Custo_Fopag (2)'!$A:$BQ,27,0) -> 244.36 | AB29: =VLOOKUP(A29,'Custo_Fopag (2)'!$A:$BQ,28,0) -> 48.87 | AC29: =VLOOKUP(A29,'Custo_Fopag (2)'!$A:$BQ,29,0) -> 0 | AD29: =VLOOKUP(A29,'Custo_Fopag (2)'!$A:$BQ,30,0) -> 0 | AE29: =VLOOKUP(A29,'Custo_Fopag (2)'!$A:$BQ,31,0) -> 0 | AF29: =VLOOKUP(A29,'Custo_Fopag (2)'!$A:$BQ,32,0) -> 0 | AG29: =SUM(Q29:AF29) -> 400.86 | AH29: =VLOOKUP(A29,'Custo_Fopag (2)'!$A:$BQ,45,0) -> 0 | AI29: =_xlfn.XLOOKUP(A29,'Custo_Fopag (2)'!A:A,'Custo_Fopag (2)'!AT:AT,0,0,1) -> 500 | AJ29: =VLOOKUP(A29,'Custo_Fopag (2)'!$A:$BQ,47,0) -> 0 | AK29: 0 | AL29: =VLOOKUP(A29,'Custo_Fopag (2)'!$A:$BQ,35,0) -> 0 | AM29: =VLOOKUP(A29,'Custo_Fopag (2)'!$A:$BQ,36,0) -> 44.69 | AN29: =VLOOKUP(A29,'Custo_Fopag (2)'!$A:$BQ,37,0) -> 0 | AO29: =VLOOKUP(A29,'Custo_Fopag (2)'!$A:$BQ,39,0) -> 0 | AP29: =VLOOKUP(A29,'Custo_Fopag (2)'!$A:$BQ,42,0) -> 0 | AQ29: =VLOOKUP(A29,'Custo_Fopag (2)'!$A:$BQ,40,0) -> 0 | AR29: =VLOOKUP(A29,'Custo_Fopag (2)'!$A:$BQ,41,0) -> 120 | AS29: =VLOOKUP(A29,'Custo_Fopag (2)'!$A:$BQ,38,0) -> 0 | AT29: =VLOOKUP(A29,'Custo_Fopag (2)'!$A:$BQ,43,0) -> 0 | AU29: =VLOOKUP(A29,'Custo_Fopag (2)'!$A:$BQ,48,0) -> 0 | AV29: =VLOOKUP(A29,'Custo_Fopag (2)'!$A:$BQ,49,0) -> 0 | AW29: =VLOOKUP(A29,'Custo_Fopag (2)'!$A:$BQ,19,0) -> 0 | AX29: =VLOOKUP(A29,'Custo_Fopag (2)'!$A:$BQ,50,0) -> 13.51 | AY29: 96.2 | AZ29: 0 | BA29: =VLOOKUP(A29,'Custo_Fopag (2)'!$A:$BQ,54,0) -> 0 | BB29: =VLOOKUP(A29,'Custo_Fopag (2)'!$A:$BQ,52,0) -> 0 | BC29: =SUM(AH29:BB29) -> 774.4 | BD29: =BC29+AG29 -> 1175.26 | BF29: =BD29+BE29 -> 1175.26 | BG29: =AG29/12 -> 33.405 | BH29: =BG29 -> 33.405 | BI29: =BH29/3 -> 11.135 | BJ29: =SUM(BG29:BI29) -> 77.945 | BK29: =VLOOKUP(A29,'Custo_Fopag (2)'!$A:$BQ,65,0) -> 80.17 | BL29: =VLOOKUP(A29,'Custo_Fopag (2)'!$A:$BQP,66,0) -> 12.02 | BM29: =VLOOKUP(A29,'Custo_Fopag (2)'!$A:$BQ,67,0) -> 23.24 | BN29: =VLOOKUP(A29,'Custo_Fopag (2)'!$A:$BQ,64,0) -> 0 | BO29: =SUM(BK29:BN29) -> 115.43 | BP29: =BF29+BO29 -> 1290.69 | BQ29: =BF29+BJ29+BO29 -> 1368.635 | BR29: =VLOOKUP(A29,'Custo_Fopag (2)'!$A:$BQ,60,0) -> 10721.78 | BS29: =IF(ISBLANK(L29),"Ativo","Desligado") -> Desligado
A30: FERNANDA OLIVEIRA SILVA CARDOSO | B30: 46082 | C30: CLT | D30: =VLOOKUP(A30,'Custo_Fopag (2)'!A:$BQ,4,0) -> G3S FL 10 - PRES PRUD | G30: =VLOOKUP(A30,'Custo_Fopag (2)'!$A:$BQ,5,0) -> 20.947.332/0010-86 | H30: =VLOOKUP(A30,'Custo_Fopag (2)'!$A:$BQ,6,0) -> ADMINISTRATIVO | I30: =VLOOKUP(A30,'Custo_Fopag (2)'!$A:$BQ,7,0) -> FISCAL | J30: =VLOOKUP(A30,'Custo_Fopag (2)'!$A:$BQ,8,0) -> PILARES | K30: =VLOOKUP(A30,'Custo_Fopag (2)'!$A:$BQ,9,0) -> 45812 | N30: =VLOOKUP(A30,'Custo_Fopag (2)'!$A:$BQ,11,0) -> 1.1.4 CONTABILIDADE/FISCAL | O30: =VLOOKUP(A30,'Custo_Fopag (2)'!$A:$BQ,12,0) -> ANALISTA FISCAL SENIOR I | P30: =VLOOKUP(A30,'Custo_Fopag (2)'!$A:$BQ,13,0) -> 3500 | Q30: =VLOOKUP(A30,'Custo_Fopag (2)'!$A:$BQ,16,0) -> 3500 | R30: =VLOOKUP(A30,'Custo_Fopag (2)'!$A:$BQ,17,0) -> 0 | S30: =VLOOKUP(A30,'Custo_Fopag (2)'!$A:$BP,18,0) -> 0 | T30: =VLOOKUP(A30,'Custo_Fopag (2)'!$A:$BQ,20,0) -> 0 | U30: =VLOOKUP(A30,'Custo_Fopag (2)'!$A:$BQ,21,0) -> 0 | V30: =VLOOKUP(A30,'Custo_Fopag (2)'!$A:$BQ,22,0) -> 0 | W30: =VLOOKUP(A30,'Custo_Fopag (2)'!$A:$BQ,23,0) -> 0 | X30: =VLOOKUP(A30,'Custo_Fopag (2)'!$A:$BQ,24,0) -> 0 | Y30: =VLOOKUP(A30,'Custo_Fopag (2)'!$A:$BQ,25,0) -> 0 | Z30: =VLOOKUP(A30,'Custo_Fopag (2)'!$A:$BQ,26,0) -> 0 | AA30: =VLOOKUP(A30,'Custo_Fopag (2)'!$A:$BQ,27,0) -> 0 | AB30: =VLOOKUP(A30,'Custo_Fopag (2)'!$A:$BQ,28,0) -> 0 | AC30: =VLOOKUP(A30,'Custo_Fopag (2)'!$A:$BQ,29,0) -> 0 | AD30: =VLOOKUP(A30,'Custo_Fopag (2)'!$A:$BQ,30,0) -> 0 | AE30: =VLOOKUP(A30,'Custo_Fopag (2)'!$A:$BQ,31,0) -> 0 | AF30: =VLOOKUP(A30,'Custo_Fopag (2)'!$A:$BQ,32,0) -> 0 | AG30: =SUM(Q30:AF30) -> 3500 | AH30: =VLOOKUP(A30,'Custo_Fopag (2)'!$A:$BQ,45,0) -> 0 | AI30: =_xlfn.XLOOKUP(A30,Beneficios!A:A,Beneficios!B:B,0,0,1) -> 521.87 | AJ30: =VLOOKUP(A30,'Custo_Fopag (2)'!$A:$BQ,47,0) -> 0 | AK30: 0 | AL30: =VLOOKUP(A30,'Custo_Fopag (2)'!$A:$BQ,35,0) -> 0 | AM30: =VLOOKUP(A30,'Custo_Fopag (2)'!$A:$BQ,36,0) -> 0 | AN30: =VLOOKUP(A30,'Custo_Fopag (2)'!$A:$BQ,37,0) -> 0 | AO30: =VLOOKUP(A30,'Custo_Fopag (2)'!$A:$BQ,39,0) -> 0 | AP30: =VLOOKUP(A30,'Custo_Fopag (2)'!$A:$BQ,42,0) -> 0 | AQ30: =VLOOKUP(A30,'Custo_Fopag (2)'!$A:$BQ,40,0) -> 0 | AR30: =VLOOKUP(A30,'Custo_Fopag (2)'!$A:$BQ,41,0) -> 0 | AS30: =VLOOKUP(A30,'Custo_Fopag (2)'!$A:$BQ,38,0) -> 0 | AT30: =VLOOKUP(A30,'Custo_Fopag (2)'!$A:$BQ,43,0) -> 0 | AU30: =VLOOKUP(A30,'Custo_Fopag (2)'!$A:$BQ,48,0) -> 0 | AV30: =VLOOKUP(A30,'Custo_Fopag (2)'!$A:$BQ,49,0) -> 0 | AW30: =VLOOKUP(A30,'Custo_Fopag (2)'!$A:$BQ,19,0) -> 0 | AX30: =VLOOKUP(A30,'Custo_Fopag (2)'!$A:$BQ,50,0) -> 0 | AY30: =VLOOKUP(A30,'Custo_Fopag (2)'!$A:$BQ,51,0) -> 0 | AZ30: 0 | BA30: =VLOOKUP(A30,'Custo_Fopag (2)'!$A:$BQ,54,0) -> 0 | BB30: =VLOOKUP(A30,'Custo_Fopag (2)'!$A:$BQ,52,0) -> 0 | BC30: =SUM(AH30:BB30) -> 521.87 | BD30: =BC30+AG30 -> 4021.87 | BF30: =BD30+BE30 -> 4021.87 | BG30: =AG30/12 -> 291.66667 | BH30: =BG30 -> 291.66667 | BI30: =BH30/3 -> 97.222222 | BJ30: =SUM(BG30:BI30) -> 680.55556 | BK30: =VLOOKUP(A30,'Custo_Fopag (2)'!$A:$BQ,65,0) -> 700 | BL30: =VLOOKUP(A30,'Custo_Fopag (2)'!$A:$BQP,66,0) -> 105 | BM30: =VLOOKUP(A30,'Custo_Fopag (2)'!$A:$BQ,67,0) -> 203 | BN30: =VLOOKUP(A30,'Custo_Fopag (2)'!$A:$BQ,64,0) -> 280 | BO30: =SUM(BK30:BN30) -> 1288 | BP30: =BF30+BO30 -> 5309.87 | BQ30: =BF30+BJ30+BO30 -> 5990.4256 | BR30: =VLOOKUP(A30,'Custo_Fopag (2)'!$A:$BQ,60,0) -> 0 | BS30: =IF(ISBLANK(L30),"Ativo","Desligado") -> Ativo
A31: FERNANDO FERRAREZI DOS SANTOS | B31: 46082 | C31: CLT | D31: =VLOOKUP(A31,'Custo_Fopag (2)'!A:$BQ,4,0) -> G S FL 04 - MARINGA | G31: =VLOOKUP(A31,'Custo_Fopag (2)'!$A:$BQ,5,0) -> 20.504.237/0004-60 | H31: =VLOOKUP(A31,'Custo_Fopag (2)'!$A:$BQ,6,0) -> LOGISTICA | I31: =VLOOKUP(A31,'Custo_Fopag (2)'!$A:$BQ,7,0) -> TRANSPORTE | J31: =VLOOKUP(A31,'Custo_Fopag (2)'!$A:$BQ,8,0) -> SELETIVA MARINGA DISTRITO | K31: =VLOOKUP(A31,'Custo_Fopag (2)'!$A:$BQ,9,0) -> 46027 | N31: =VLOOKUP(A31,'Custo_Fopag (2)'!$A:$BQ,11,0) -> 1.7.7.4 LOGISTICA | O31: =VLOOKUP(A31,'Custo_Fopag (2)'!$A:$BQ,12,0) -> MOTORISTA CARRETEIRO MANTENEDOR SENIOR I | P31: =VLOOKUP(A31,'Custo_Fopag (2)'!$A:$BQ,13,0) -> 3345 | Q31: =VLOOKUP(A31,'Custo_Fopag (2)'!$A:$BQ,16,0) -> 3345 | R31: =VLOOKUP(A31,'Custo_Fopag (2)'!$A:$BQ,17,0) -> 0 | S31: =VLOOKUP(A31,'Custo_Fopag (2)'!$A:$BP,18,0) -> 0 | T31: =VLOOKUP(A31,'Custo_Fopag (2)'!$A:$BQ,20,0) -> 669 | U31: =VLOOKUP(A31,'Custo_Fopag (2)'!$A:$BQ,21,0) -> 0 | V31: =VLOOKUP(A31,'Custo_Fopag (2)'!$A:$BQ,22,0) -> 0 | W31: =VLOOKUP(A31,'Custo_Fopag (2)'!$A:$BQ,23,0) -> 0 | X31: =VLOOKUP(A31,'Custo_Fopag (2)'!$A:$BQ,24,0) -> 0 | Y31: =VLOOKUP(A31,'Custo_Fopag (2)'!$A:$BQ,25,0) -> 0 | Z31: =VLOOKUP(A31,'Custo_Fopag (2)'!$A:$BQ,26,0) -> 0 | AA31: =VLOOKUP(A31,'Custo_Fopag (2)'!$A:$BQ,27,0) -> 1316.71 | AB31: =VLOOKUP(A31,'Custo_Fopag (2)'!$A:$BQ,28,0) -> 253.21 | AC31: =VLOOKUP(A31,'Custo_Fopag (2)'!$A:$BQ,29,0) -> 0 | AD31: =VLOOKUP(A31,'Custo_Fopag (2)'!$A:$BQ,30,0) -> 0 | AE31: =VLOOKUP(A31,'Custo_Fopag (2)'!$A:$BQ,31,0) -> 0 | AF31: =VLOOKUP(A31,'Custo_Fopag (2)'!$A:$BQ,32,0) -> 0 | AG31: =SUM(Q31:AF31) -> 5583.92 | AH31: =VLOOKUP(A31,'Custo_Fopag (2)'!$A:$BQ,45,0) -> 0 | AI31: =_xlfn.XLOOKUP(A31,Beneficios!A:A,Beneficios!B:B,0,0,1) -> 512.87 | AJ31: =VLOOKUP(A31,'Custo_Fopag (2)'!$A:$BQ,47,0) -> 0 | AK31: 0 | AL31: =VLOOKUP(A31,'Custo_Fopag (2)'!$A:$BQ,35,0) -> 0 | AM31: =VLOOKUP(A31,'Custo_Fopag (2)'!$A:$BQ,36,0) -> 486.37 | AN31: =VLOOKUP(A31,'Custo_Fopag (2)'!$A:$BQ,37,0) -> 0 | AO31: =VLOOKUP(A31,'Custo_Fopag (2)'!$A:$BQ,39,0) -> 0 | AP31: =VLOOKUP(A31,'Custo_Fopag (2)'!$A:$BQ,42,0) -> 0 | AQ31: =VLOOKUP(A31,'Custo_Fopag (2)'!$A:$BQ,40,0) -> 0 | AR31: =VLOOKUP(A31,'Custo_Fopag (2)'!$A:$BQ,41,0) -> 252.45 | AS31: =VLOOKUP(A31,'Custo_Fopag (2)'!$A:$BQ,38,0) -> 0 | AT31: =VLOOKUP(A31,'Custo_Fopag (2)'!$A:$BQ,43,0) -> 0 | AU31: =VLOOKUP(A31,'Custo_Fopag (2)'!$A:$BQ,48,0) -> 181.5 | AV31: =VLOOKUP(A31,'Custo_Fopag (2)'!$A:$BQ,49,0) -> 0 | AW31: =VLOOKUP(A31,'Custo_Fopag (2)'!$A:$BQ,19,0) -> 0 | AX31: =VLOOKUP(A31,'Custo_Fopag (2)'!$A:$BQ,50,0) -> 0 | AY31: =VLOOKUP(A31,'Custo_Fopag (2)'!$A:$BQ,51,0) -> 0 | AZ31: 0 | BA31: =VLOOKUP(A31,'Custo_Fopag (2)'!$A:$BQ,54,0) -> 0 | BB31: =VLOOKUP(A31,'Custo_Fopag (2)'!$A:$BQ,52,0) -> 0 | BC31: =SUM(AH31:BB31) -> 1433.19 | BD31: =BC31+AG31 -> 7017.11 | BF31: =BD31+BE31 -> 7017.11 | BG31: =AG31/12 -> 465.32667 | BH31: =BG31 -> 465.32667 | BI31: =BH31/3 -> 155.10889 | BJ31: =SUM(BG31:BI31) -> 1085.7622 | BK31: =VLOOKUP(A31,'Custo_Fopag (2)'!$A:$BQ,65,0) -> 1116.78 | BL31: =VLOOKUP(A31,'Custo_Fopag (2)'!$A:$BQP,66,0) -> 167.51 | BM31: =VLOOKUP(A31,'Custo_Fopag (2)'!$A:$BQ,67,0) -> 323.86 | BN31: =VLOOKUP(A31,'Custo_Fopag (2)'!$A:$BQ,64,0) -> 446.71 | BO31: =SUM(BK31:BN31) -> 2054.86 | BP31: =BF31+BO31 -> 9071.97 | BQ31: =BF31+BJ31+BO31 -> 10157.732 | BR31: =VLOOKUP(A31,'Custo_Fopag (2)'!$A:$BQ,60,0) -> 0 | BS31: =IF(ISBLANK(L31),"Ativo","Desligado") -> Ativo
A32: GABRIELA BARBOSA FONTE BASSO | B32: 46082 | C32: CLT | D32: =VLOOKUP(A32,'Custo_Fopag (2)'!A:$BQ,4,0) -> G3S FL 05 - PRES PRUD | G32: =VLOOKUP(A32,'Custo_Fopag (2)'!$A:$BQ,5,0) -> 20.947.332/0005-19 | H32: =VLOOKUP(A32,'Custo_Fopag (2)'!$A:$BQ,6,0) -> COMERCIAL | I32: =VLOOKUP(A32,'Custo_Fopag (2)'!$A:$BQ,7,0) -> VENDAS | J32: =VLOOKUP(A32,'Custo_Fopag (2)'!$A:$BQ,8,0) -> BRACOFER | K32: =VLOOKUP(A32,'Custo_Fopag (2)'!$A:$BQ,9,0) -> 46050 | N32: =VLOOKUP(A32,'Custo_Fopag (2)'!$A:$BQ,11,0) -> 1.3.1.2 COMERCIAL | O32: =VLOOKUP(A32,'Custo_Fopag (2)'!$A:$BQ,12,0) -> VENDEDOR INTERNO PLENO | P32: =VLOOKUP(A32,'Custo_Fopag (2)'!$A:$BQ,13,0) -> 2500 | Q32: =VLOOKUP(A32,'Custo_Fopag (2)'!$A:$BQ,16,0) -> 2500 | R32: =VLOOKUP(A32,'Custo_Fopag (2)'!$A:$BQ,17,0) -> 0 | S32: =VLOOKUP(A32,'Custo_Fopag (2)'!$A:$BP,18,0) -> 0 | T32: =VLOOKUP(A32,'Custo_Fopag (2)'!$A:$BQ,20,0) -> 0 | U32: =VLOOKUP(A32,'Custo_Fopag (2)'!$A:$BQ,21,0) -> 0 | V32: =VLOOKUP(A32,'Custo_Fopag (2)'!$A:$BQ,22,0) -> 0 | W32: =VLOOKUP(A32,'Custo_Fopag (2)'!$A:$BQ,23,0) -> 0 | X32: =VLOOKUP(A32,'Custo_Fopag (2)'!$A:$BQ,24,0) -> 0 | Y32: =VLOOKUP(A32,'Custo_Fopag (2)'!$A:$BQ,25,0) -> 0 | Z32: =VLOOKUP(A32,'Custo_Fopag (2)'!$A:$BQ,26,0) -> 0 | AA32: =VLOOKUP(A32,'Custo_Fopag (2)'!$A:$BQ,27,0) -> 0 | AB32: =VLOOKUP(A32,'Custo_Fopag (2)'!$A:$BQ,28,0) -> 0 | AC32: =VLOOKUP(A32,'Custo_Fopag (2)'!$A:$BQ,29,0) -> 0 | AD32: =VLOOKUP(A32,'Custo_Fopag (2)'!$A:$BQ,30,0) -> 0 | AE32: =VLOOKUP(A32,'Custo_Fopag (2)'!$A:$BQ,31,0) -> 0 | AF32: =VLOOKUP(A32,'Custo_Fopag (2)'!$A:$BQ,32,0) -> 0 | AG32: =SUM(Q32:AF32) -> 2500 | AH32: =VLOOKUP(A32,'Custo_Fopag (2)'!$A:$BQ,45,0) -> 0 | AI32: =_xlfn.XLOOKUP(A32,Beneficios!A:A,Beneficios!B:B,0,0,1) -> 512.87 | AJ32: =VLOOKUP(A32,'Custo_Fopag (2)'!$A:$BQ,47,0) -> 0 | AK32: 0 | AL32: =VLOOKUP(A32,'Custo_Fopag (2)'!$A:$BQ,35,0) -> 0 | AM32: =VLOOKUP(A32,'Custo_Fopag (2)'!$A:$BQ,36,0) -> 0 | AN32: =VLOOKUP(A32,'Custo_Fopag (2)'!$A:$BQ,37,0) -> 0 | AO32: =VLOOKUP(A32,'Custo_Fopag (2)'!$A:$BQ,39,0) -> 0 | AP32: =VLOOKUP(A32,'Custo_Fopag (2)'!$A:$BQ,42,0) -> 0 | AQ32: =VLOOKUP(A32,'Custo_Fopag (2)'!$A:$BQ,40,0) -> 0 | AR32: =VLOOKUP(A32,'Custo_Fopag (2)'!$A:$BQ,41,0) -> 0 | AS32: =VLOOKUP(A32,'Custo_Fopag (2)'!$A:$BQ,38,0) -> 0 | AT32: =VLOOKUP(A32,'Custo_Fopag (2)'!$A:$BQ,43,0) -> 0 | AU32: =VLOOKUP(A32,'Custo_Fopag (2)'!$A:$BQ,48,0) -> 0 | AV32: =VLOOKUP(A32,'Custo_Fopag (2)'!$A:$BQ,49,0) -> 0 | AW32: =VLOOKUP(A32,'Custo_Fopag (2)'!$A:$BQ,19,0) -> 0 | AX32: =VLOOKUP(A32,'Custo_Fopag (2)'!$A:$BQ,50,0) -> 0 | AY32: =VLOOKUP(A32,'Custo_Fopag (2)'!$A:$BQ,51,0) -> 0 | AZ32: 0 | BA32: =VLOOKUP(A32,'Custo_Fopag (2)'!$A:$BQ,54,0) -> 0 | BB32: =VLOOKUP(A32,'Custo_Fopag (2)'!$A:$BQ,52,0) -> 0 | BC32: =SUM(AH32:BB32) -> 512.87 | BD32: =BC32+AG32 -> 3012.87 | BF32: =BD32+BE32 -> 3012.87 | BG32: =AG32/12 -> 208.33333 | BH32: =BG32 -> 208.33333 | BI32: =BH32/3 -> 69.444444 | BJ32: =SUM(BG32:BI32) -> 486.11111 | BK32: =VLOOKUP(A32,'Custo_Fopag (2)'!$A:$BQ,65,0) -> 500 | BL32: =VLOOKUP(A32,'Custo_Fopag (2)'!$A:$BQP,66,0) -> 37.5 | BM32: =VLOOKUP(A32,'Custo_Fopag (2)'!$A:$BQ,67,0) -> 145 | BN32: =VLOOKUP(A32,'Custo_Fopag (2)'!$A:$BQ,64,0) -> 200 | BO32: =SUM(BK32:BN32) -> 882.5 | BP32: =BF32+BO32 -> 3895.37 | BQ32: =BF32+BJ32+BO32 -> 4381.4811 | BR32: =VLOOKUP(A32,'Custo_Fopag (2)'!$A:$BQ,60,0) -> 0 | BS32: =IF(ISBLANK(L32),"Ativo","Desligado") -> Ativo
A33: GEOVANI RODRIGUES DUTRA | B33: 46082 | C33: CLT | D33: =VLOOKUP(A33,'Custo_Fopag (2)'!A:$BQ,4,0) -> G3S FL 03 - DOURADOS | G33: =VLOOKUP(A33,'Custo_Fopag (2)'!$A:$BQ,5,0) -> 20.947.332/0003-57 | H33: =VLOOKUP(A33,'Custo_Fopag (2)'!$A:$BQ,6,0) -> OPERACIONAL | I33: =VLOOKUP(A33,'Custo_Fopag (2)'!$A:$BQ,7,0) -> PATIO | J33: =VLOOKUP(A33,'Custo_Fopag (2)'!$A:$BQ,8,0) -> SELETIVA DOURADOS | K33: =VLOOKUP(A33,'Custo_Fopag (2)'!$A:$BQ,9,0) -> 46048 | N33: =VLOOKUP(A33,'Custo_Fopag (2)'!$A:$BQ,11,0) -> 1.2.2.3 OPERACIONAL | O33: =VLOOKUP(A33,'Custo_Fopag (2)'!$A:$BQ,12,0) -> MACARIQUEIRO PLENO | P33: =VLOOKUP(A33,'Custo_Fopag (2)'!$A:$BQ,13,0) -> 2587.5 | Q33: =VLOOKUP(A33,'Custo_Fopag (2)'!$A:$BQ,16,0) -> 2587.5 | R33: =VLOOKUP(A33,'Custo_Fopag (2)'!$A:$BQ,17,0) -> 0 | S33: =VLOOKUP(A33,'Custo_Fopag (2)'!$A:$BP,18,0) -> 0 | T33: =VLOOKUP(A33,'Custo_Fopag (2)'!$A:$BQ,20,0) -> 0 | U33: =VLOOKUP(A33,'Custo_Fopag (2)'!$A:$BQ,21,0) -> 0 | V33: =VLOOKUP(A33,'Custo_Fopag (2)'!$A:$BQ,22,0) -> 0 | W33: =VLOOKUP(A33,'Custo_Fopag (2)'!$A:$BQ,23,0) -> 0 | X33: =VLOOKUP(A33,'Custo_Fopag (2)'!$A:$BQ,24,0) -> 0 | Y33: =VLOOKUP(A33,'Custo_Fopag (2)'!$A:$BQ,25,0) -> 0 | Z33: =VLOOKUP(A33,'Custo_Fopag (2)'!$A:$BQ,26,0) -> 0 | AA33: =VLOOKUP(A33,'Custo_Fopag (2)'!$A:$BQ,27,0) -> 0 | AB33: =VLOOKUP(A33,'Custo_Fopag (2)'!$A:$BQ,28,0) -> 0 | AC33: =VLOOKUP(A33,'Custo_Fopag (2)'!$A:$BQ,29,0) -> 0 | AD33: =VLOOKUP(A33,'Custo_Fopag (2)'!$A:$BQ,30,0) -> 0 | AE33: =VLOOKUP(A33,'Custo_Fopag (2)'!$A:$BQ,31,0) -> 0 | AF33: =VLOOKUP(A33,'Custo_Fopag (2)'!$A:$BQ,32,0) -> 0 | AG33: =SUM(Q33:AF33) -> 2587.5 | AH33: =VLOOKUP(A33,'Custo_Fopag (2)'!$A:$BQ,45,0) -> 0 | AI33: =_xlfn.XLOOKUP(A33,Beneficios!A:A,Beneficios!B:B,0,0,1) -> 0 | AJ33: =VLOOKUP(A33,'Custo_Fopag (2)'!$A:$BQ,47,0) -> 0 | AK33: 0 | AL33: =VLOOKUP(A33,'Custo_Fopag (2)'!$A:$BQ,35,0) -> 0 | AM33: =VLOOKUP(A33,'Custo_Fopag (2)'!$A:$BQ,36,0) -> 0 | AN33: =VLOOKUP(A33,'Custo_Fopag (2)'!$A:$BQ,37,0) -> 0 | AO33: =VLOOKUP(A33,'Custo_Fopag (2)'!$A:$BQ,39,0) -> 0 | AP33: =VLOOKUP(A33,'Custo_Fopag (2)'!$A:$BQ,42,0) -> 0 | AQ33: =VLOOKUP(A33,'Custo_Fopag (2)'!$A:$BQ,40,0) -> 0 | AR33: =VLOOKUP(A33,'Custo_Fopag (2)'!$A:$BQ,41,0) -> 196.71 | AS33: =VLOOKUP(A33,'Custo_Fopag (2)'!$A:$BQ,38,0) -> 0 | AT33: =VLOOKUP(A33,'Custo_Fopag (2)'!$A:$BQ,43,0) -> 0 | AU33: =VLOOKUP(A33,'Custo_Fopag (2)'!$A:$BQ,48,0) -> 0 | AV33: =VLOOKUP(A33,'Custo_Fopag (2)'!$A:$BQ,49,0) -> 0 | AW33: =VLOOKUP(A33,'Custo_Fopag (2)'!$A:$BQ,19,0) -> 0 | AX33: =VLOOKUP(A33,'Custo_Fopag (2)'!$A:$BQ,50,0) -> 0 | AY33: =VLOOKUP(A33,'Custo_Fopag (2)'!$A:$BQ,51,0) -> 0 | AZ33: 0 | BA33: =VLOOKUP(A33,'Custo_Fopag (2)'!$A:$BQ,54,0) -> 0 | BB33: =VLOOKUP(A33,'Custo_Fopag (2)'!$A:$BQ,52,0) -> 0 | BC33: =SUM(AH33:BB33) -> 196.71 | BD33: =BC33+AG33 -> 2784.21 | BF33: =BD33+BE33 -> 2784.21 | BG33: =AG33/12 -> 215.625 | BH33: =BG33 -> 215.625 | BI33: =BH33/3 -> 71.875 | BJ33: =SUM(BG33:BI33) -> 503.125 | BK33: =VLOOKUP(A33,'Custo_Fopag (2)'!$A:$BQ,65,0) -> 517.5 | BL33: =VLOOKUP(A33,'Custo_Fopag (2)'!$A:$BQP,66,0) -> 38.81 | BM33: =VLOOKUP(A33,'Custo_Fopag (2)'!$A:$BQ,67,0) -> 150.07 | BN33: =VLOOKUP(A33,'Custo_Fopag (2)'!$A:$BQ,64,0) -> 164.15 | BO33: =SUM(BK33:BN33) -> 870.53 | BP33: =BF33+BO33 -> 3654.74 | BQ33: =BF33+BJ33+BO33 -> 4157.865 | BR33: =VLOOKUP(A33,'Custo_Fopag (2)'!$A:$BQ,60,0) -> 0 | BS33: =IF(ISBLANK(L33),"Ativo","Desligado") -> Ativo
A34: GIOVANNA SILVA DE OLIVEIRA | B34: 46082 | C34: CLT | D34: =VLOOKUP(A34,'Custo_Fopag (2)'!A:$BQ,4,0) -> G3S FL 10 - PRES PRUD | G34: =VLOOKUP(A34,'Custo_Fopag (2)'!$A:$BQ,5,0) -> 20.947.332/0010-86 | H34: =VLOOKUP(A34,'Custo_Fopag (2)'!$A:$BQ,6,0) -> COMERCIAL | I34: =VLOOKUP(A34,'Custo_Fopag (2)'!$A:$BQ,7,0) -> COMERCIAL | J34: =VLOOKUP(A34,'Custo_Fopag (2)'!$A:$BQ,8,0) -> SELETIVA CORPORATIVO SUCATA | K34: =VLOOKUP(A34,'Custo_Fopag (2)'!$A:$BQ,9,0) -> 44397 | N34: =VLOOKUP(A34,'Custo_Fopag (2)'!$A:$BQ,11,0) -> 1.2.1.1 APOIO | O34: =VLOOKUP(A34,'Custo_Fopag (2)'!$A:$BQ,12,0) -> ANALISTA COMERCIAL SENIOR | P34: =VLOOKUP(A34,'Custo_Fopag (2)'!$A:$BQ,13,0) -> 3570 | Q34: =VLOOKUP(A34,'Custo_Fopag (2)'!$A:$BQ,16,0) -> 3570 | R34: =VLOOKUP(A34,'Custo_Fopag (2)'!$A:$BQ,17,0) -> 0 | S34: =VLOOKUP(A34,'Custo_Fopag (2)'!$A:$BP,18,0) -> 0 | T34: =VLOOKUP(A34,'Custo_Fopag (2)'!$A:$BQ,20,0) -> 0 | U34: =VLOOKUP(A34,'Custo_Fopag (2)'!$A:$BQ,21,0) -> 0 | V34: =VLOOKUP(A34,'Custo_Fopag (2)'!$A:$BQ,22,0) -> 0 | W34: =VLOOKUP(A34,'Custo_Fopag (2)'!$A:$BQ,23,0) -> 0 | X34: =VLOOKUP(A34,'Custo_Fopag (2)'!$A:$BQ,24,0) -> 0 | Y34: =VLOOKUP(A34,'Custo_Fopag (2)'!$A:$BQ,25,0) -> 0 | Z34: =VLOOKUP(A34,'Custo_Fopag (2)'!$A:$BQ,26,0) -> 0 | AA34: =VLOOKUP(A34,'Custo_Fopag (2)'!$A:$BQ,27,0) -> 0 | AB34: =VLOOKUP(A34,'Custo_Fopag (2)'!$A:$BQ,28,0) -> 0 | AC34: =VLOOKUP(A34,'Custo_Fopag (2)'!$A:$BQ,29,0) -> 0 | AD34: =VLOOKUP(A34,'Custo_Fopag (2)'!$A:$BQ,30,0) -> 0 | AE34: =VLOOKUP(A34,'Custo_Fopag (2)'!$A:$BQ,31,0) -> 0 | AF34: =VLOOKUP(A34,'Custo_Fopag (2)'!$A:$BQ,32,0) -> 0 | AG34: =SUM(Q34:AF34) -> 3570 | AH34: =VLOOKUP(A34,'Custo_Fopag (2)'!$A:$BQ,45,0) -> 0 | AI34: =_xlfn.XLOOKUP(A34,Beneficios!A:A,Beneficios!B:B,0,0,1) -> 512.87 | AJ34: =VLOOKUP(A34,'Custo_Fopag (2)'!$A:$BQ,47,0) -> 0 | AK34: 0 | AL34: =VLOOKUP(A34,'Custo_Fopag (2)'!$A:$BQ,35,0) -> 0 | AM34: =VLOOKUP(A34,'Custo_Fopag (2)'!$A:$BQ,36,0) -> 0 | AN34: =VLOOKUP(A34,'Custo_Fopag (2)'!$A:$BQ,37,0) -> 0 | AO34: =VLOOKUP(A34,'Custo_Fopag (2)'!$A:$BQ,39,0) -> 0 | AP34: =VLOOKUP(A34,'Custo_Fopag (2)'!$A:$BQ,42,0) -> 0 | AQ34: =VLOOKUP(A34,'Custo_Fopag (2)'!$A:$BQ,40,0) -> 0 | AR34: =VLOOKUP(A34,'Custo_Fopag (2)'!$A:$BQ,41,0) -> 0 | AS34: =VLOOKUP(A34,'Custo_Fopag (2)'!$A:$BQ,38,0) -> 929.47 | AT34: =VLOOKUP(A34,'Custo_Fopag (2)'!$A:$BQ,43,0) -> 0 | AU34: =VLOOKUP(A34,'Custo_Fopag (2)'!$A:$BQ,48,0) -> 0 | AV34: =VLOOKUP(A34,'Custo_Fopag (2)'!$A:$BQ,49,0) -> 0 | AW34: =VLOOKUP(A34,'Custo_Fopag (2)'!$A:$BQ,19,0) -> 0 | AX34: =VLOOKUP(A34,'Custo_Fopag (2)'!$A:$BQ,50,0) -> 0 | AY34: =VLOOKUP(A34,'Custo_Fopag (2)'!$A:$BQ,51,0) -> 0 | AZ34: 0 | BA34: =VLOOKUP(A34,'Custo_Fopag (2)'!$A:$BQ,54,0) -> 0 | BB34: =VLOOKUP(A34,'Custo_Fopag (2)'!$A:$BQ,52,0) -> 0 | BC34: =SUM(AH34:BB34) -> 1442.34 | BD34: =BC34+AG34 -> 5012.34 | BF34: =BD34+BE34 -> 5012.34 | BG34: =AG34/12 -> 297.5 | BH34: =BG34 -> 297.5 | BI34: =BH34/3 -> 99.166667 | BJ34: =SUM(BG34:BI34) -> 694.16667 | BK34: =VLOOKUP(A34,'Custo_Fopag (2)'!$A:$BQ,65,0) -> 714 | BL34: =VLOOKUP(A34,'Custo_Fopag (2)'!$A:$BQP,66,0) -> 107.1 | BM34: =VLOOKUP(A34,'Custo_Fopag (2)'!$A:$BQ,67,0) -> 207.06 | BN34: =VLOOKUP(A34,'Custo_Fopag (2)'!$A:$BQ,64,0) -> 285.6 | BO34: =SUM(BK34:BN34) -> 1313.76 | BP34: =BF34+BO34 -> 6326.1 | BQ34: =BF34+BJ34+BO34 -> 7020.2667 | BR34: =VLOOKUP(A34,'Custo_Fopag (2)'!$A:$BQ,60,0) -> 0 | BS34: =IF(ISBLANK(L34),"Ativo","Desligado") -> Ativo
