Workbook

Sheet Atividades
A1: DATA | B1: EMPRESA | C1: RESUMO ATIV. | D1: DESCRIÇÃO DA ATIV. | E1: INICIAL | F1: FINAL | G1: QTDE DE HORAS
A2: 23/05/2026 | B2: G3S 10 | C2: BCBI Seletiva | D2: Operação assistida do sistema de BI da seletiva, acompanhamento e checagem de erros no sistema | E2: 0.32291667 | F2: 0.41666667 | G2: 0.09375
A3: 20/05/2026 | B3: G3S 10 | C3: BCBI Seletiva | D3: Operação assistida do sistema de BI da seletiva, acompanhamento e checagem de erros no sistema | E3: 0.32430556 | F3: 0.4375 | G3: 0.11319444
A4: 21/05/2026 | B4: G3S 10 | C4: BCBI Seletiva | D4: Operação assistida do sistema de BI da seletiva, acompanhamento e checagem de erros no sistema | E4: 0.32430556 | F4: 0.35416667 | G4: 0.029861111
A5: 14/05/2026 | B5: G3S 10 | C5: BCBI Seletiva | D5: Operação assistida do sistema de BI da seletiva | E5: 0.32638889 | F5: 0.35416667 | G5: 0.027777778
A6: 22/05/2026 | B6: G3S 10 | C6: BCBI Seletiva | D6: Atualização do ODBC e verificação de integridade dos dados | E6: 0.32708333 | F6: 0.4375 | G6: 0.11041667
A7: 15/05/2026 | B7: G3S 10 | C7: BCBI Seletiva | D7: Operação assistida do sistema de BI da seletiva, acompanhamento e checagem de erros no sistema | E7: 0.32777778 | F7: 0.4375 | G7: 0.10972222
A8: 24/05/2026 | B8: G3S 10 | C8: Fechamento | D8: Tratamento dos dados de fechamento abril pré carga | E8: 0.32777778 | F8: 0.41666667 | G8: 0.088888889
A9: 16/05/2026 | B9: G3S 10 | C9: Fechamento | D9: Tratamento dos dados de fechamento abril pré carga | E9: 0.32916667 | F9: 0.41666667 | G9: 0.0875
A10: 26/05/2026 | B10: G3S 10 | C10: BCBI Seletiva | D10: Auditoria entre relatórios do SAGI e dados do BCBI | E10: 0.32986111 | F10: 0.41666667 | G10: 0.086805556
A11: 27/05/2026 | B11: G3S 10 | C11: BCBI Seletiva | D11: Operação assistida do sistema de BI da seletiva, acompanhamento e checagem de erros no sistema | E11: 0.32986111 | F11: 0.41666667 | G11: 0.086805556
A12: 19/05/2026 | B12: G3S 10 | C12: BCBI Seletiva | D12: Auditoria entre relatórios do SAGI e dados do BCBI | E12: 0.33194444 | F12: 0.4375 | G12: 0.10555556
A13: 13/04/2026 | B13: G3S 10 | C13: BCBI Seletiva | D13: Operação assistida do sistema de BI da seletiva, acompanhamento e checagem de erros no sistema | E13: 0.33333333 | F13: 0.4375 | G13: 0.10416667
... A88: 27/04/2026 | B88: G3S 10 | C88: Fechamento | D88: Finalização e validação dos dados de fechamento | E88: 0.66666667 | F88: 0.75 | G88: 0.083333333
A89: 45992 | B89: G3S | C89: Suporte Áreas | D89: relatório Horas extras marcondes 24-25 | E89: 0.5 | F89: 0.65277778 | G89: 0.15277778
A90: 45992 | B90: EKIPA | C90: Centro de custo | D90: Adequação de centro de custo da máquina phh0044(atual gbl8h44) | E90: 0.65277778 | F90: 0.67708333 | G90: 0.024305556
A91: 45992 | B91: G3S 10 | C91: Fechamento | D91: Tratamento dos dados de fechamento pré carga | E91: 0.67708333 | F91: 0.75 | G91: 0.072916667
A92: 45993 | B92: G3S 10 | C92: Fechamento | D92: Tratamento dos dados de fechamento pré carga | E92: 0.5 | F92: 0.625 | G92: 0.125
A93: 45993 | B93: G3S 10 | C93: Suporte Áreas | D93: Criação arquivo "cola" de rateio de centro de custo estagiários para a Elaine do RH | E93: 0.625 | F93: 0.63888889 | G93: 0.013888889
A94: 45993 | B94: G3S 10 | C94: Fechamento | D94: Tratamento dos dados de fechamento pré carga | E94: 0.63888889 | F94: 0.75 | G94: 0.11111111
A95: 45994 | B95: G3S 10 | C95: Fechamento | D95: Tratamento dos dados de fechamento pré carga | E95: 0.33333333 | F95: 0.375 | G95: 0.041666667
A96: 45994 | B96: G3S 10 | C96: Sagi | D96: Abertura de chamado no SAGI para solução de troca do tipo de centro de custo, mas não foi resolvido, iremos acionar o Leonardo | E96: 0.375 | F96: 0.40763889 | G96: 0.032638889
A97: 45994 | B97: G3S 10 | C97: Fechamento | D97: Tratamento dos dados de fechamento pré carga | E97: 0.40763889 | F97: 0.48958333 | G97: 0.081944444
A98: 45994 | B98: G3S 10 | C98: Fechamento | D98: Tratamento dos dados de fechamento pré carga | E98: 0.53125 | F98: 0.58333333 | G98: 0.052083333
A99: 45994 | B99: G3S 10 | C99: Suporte Áreas | D99: Cálculo/definição dos rateios a serem feitos para cada empresa | E99: 0.58333333 | F99: 0.625 | G99: 0.041666667
A100: 45995 | B100: G3S | C100: BCBI Seletiva | D100: Operação assistida do sistema de BI da seletiva, acompanhamento e checagem de erros no sistema | E100: 0.33333333 | F100: 0.36111111 | G100: 0.027777778
... A355: 46098 | B355: G3S 10 | C355: BCBI Seletiva | D355: Checagens BCBI solicitadas por Luciano | E355: 0.59375 | F355: 0.625 | G355: 0.03125
A356: 46099 | B356: G3S 10 | C356: LEONARDO | D356: Translado leonardo Comfort X Seletiva' | E356: - | F356: - | G356: -
A357: 46099 | B357: G3S 10 | C357: Fechamento | D357: Correção de lançamentos SAGI | E357: 0.33333333 | F357: 0.375 | G357: 0.041666667
A358: 46099 | B358: G3S 10 | C358: Rh | D358: treinamento estagiários | E358: 0.375 | F358: 0.4375 | G358: 0.0625
A359: 46099 | B359: G&S | C359: Suporte Áreas | D359: Geração de relatório de custos ekipa intralogística e ECO EXPO | E359: 0.4375 | F359: 0.45833333 | G359: 0.020833333
A360: 46099 | B360: G3S 10 | C360: Fechamento | D360: fechamento dados abastecimentos | E360: 0.45833333 | F360: 0.51736111 | G360: 0.059027778
A361: 46099 | B361: G3S 10 | C361: Fechamento | D361: fechamento dados abastecimentos | E361: 0.55902778 | F361: 0.625 | G361: 0.065972222
A362: 46100 | B362: G3S 10 | C362: Qualidade | D362: Overview Pedro X Julio | E362: 0.33333333 | F362: 0.51041667 | G362: 0.17708333
A363: 46100 | B363: G3S 10 | C363: Qualidade | D363: Overview Pedro X Julio | E363: 0.55208333 | F363: 0.625 | G363: 0.072916667
A364: 46101 | B364: G3S 10 | C364: Qualidade | D364: Overview Pedro X Julio | E364: 0.33333333 | F364: 0.35416667 | G364: 0.020833333
A365: 46101 | B365: G3S 10 | C365: BCBI Seletiva | D365: Reunião Leonardo, Luciano, Júlio, Caíque, Matheus para alinharmos integração FOPA x BCBI | E365: 0.35416667 | F365: 0.375 | G365: 0.020833333
A366: 46101 | B366: G3S 10 | C366: Qualidade | D366: Overview Pedro X Julio | E366: 0.375 | F366: 0.51736111 | G366: 0.14236111
A367: 46101 | B367: G3S 10 | C367: Qualidade | D367: Overview Pedro X Julio | E367: 0.55902778 | F367: 0.625 | G367: 0.065972222
A368: 46104 | B368: G3S 10 | C368: Qualidade | D368: Cadastro nos sistemas | E368: 0.33333333 | F368: 0.5 | G368: 0.16666667
... A380: 46113 | B380: G3S 10 | C380: Consulti | D380: Atualização do wsl | E380: 0.54166667 | F380: 0.625 | G380: 0.083333333
A381: 46114 | D381: Realização de Auditoria BCBI x Relatórios SAGI | E381: 0.33333333 | F381: 0.52083333 | G381: 0.1875
A382: 46114 | B382: G3S 10 | C382: Fechamento | D382: Adequação de relatórios de sistemas externos para formato de Fechamento | E382: 0.54166667 | F382: 0.625 | G382: 0.083333333
A383: 46115 | B383: G3S 10 | C383: BCBI Seletiva | D383: Auditoria entre relatórios do SAGI e dados do BCBI | E383: 0.33333333 | F383: 0.45833333 | G383: 0.125
A384: 46115 | B384: G3S 10 | C384: Qualidade | D384: Alinhamento de demandas e atividades | E384: 0.45833333 | F384: 0.5 | G384: 0.041666667
A385: 46115 | B385: G3S 10 | C385: Fechamento | D385: Tratamento dos dados de fechamento março pré carga | E385: 0.54166667 | F385: 0.625 | G385: 0.083333333
A386: 46116 | B386: G3S 10 | C386: BCBI Seletiva | D386: Atualização do ODBC e verificação de integridade dos dados | E386: 0.33333333 | F386: 0.41666667 | G386: 0.083333333
A387: 46116 | B387: G3S 10 | C387: BCBI Seletiva | D387: Auditoria entre relatórios do SAGI e dados do BCBI | E387: 0.41666667 | F387: 0.5 | G387: 0.083333333
A388: 46116 | B388: G3S 10 | C388: Fechamento | D388: Tratamento dos dados de fechamento março pré carga | E388: 0.54166667 | F388: 0.625 | G388: 0.083333333
A389: 46116 | B389: G3S 10 | C389: Fechamento | D389: Finalização e validação dos dados de fechamento | E389: 0.66666667 | F389: 0.75 | G389: 0.083333333
A390: 46117 | B390: G3S 10 | C390: BCBI Seletiva | D390: Operação assistida do sistema de BI da seletiva | E390: 0.33333333 | F390: 0.35416667 | G390: 0.020833333
A391: 46117 | B391: RH | C391: Ginástica Laboral | D391: Ginástica Laboral | E391: 0.35416667 | F391: 0.375 | G391: 0.020833333
A392: 46117 | B392: G3S 10 | C392: BCBI Seletiva | D392: Auditoria entre relatórios do SAGI e dados do BCBI | E392: 0.375 | F392: 0.5 | G392: 0.125
A393: 46117 | B393: G3S 10 | C393: BCBI Seletiva | D393: Auditoria entre relatórios do SAGI e dados do BCBI | E393: 0.54166667 | F393: 0.62708333 | G393: 0.085416667
... A539: 46169 | B539: G3S 10 | C539: Fechamento | D539: Finalização e validação dos dados de fechamento | E539: 0.66666667 | F539: 0.75 | G539: 0.083333333
A540: 28/05/2026 | B540: G3S 10 | C540: BCBI Seletiva | D540: Operação assistida do sistema de BI da seletiva, acompanhamento e checagem de erros no sistema | E540: 0.32777778 | F540: 0.35416667 | G540: =F540-E540
A541: 28/05/2026 | B541: RH | C541: Ginástica Laboral | D541: Ginástica Laboral | E541: 0.35416667 | F541: 0.375 | G541: =F541-E541
A542: 28/05/2026 | B542: G3S 10 | C542: BCBI Seletiva | D542: Auditoria entre relatórios do SAGI e dados do BCBI | E542: 0.375 | F542: 0.47916667 | G542: =F542-E542
A543: 28/05/2026 | B543: G3S 10 | C543: Qualidade | D543: Alinhamento de demandas e atividades | E543: 0.47916667 | F543: 0.5 | G543: =F543-E543
A544: 28/05/2026 | B544: G3S 10 | C544: Fechamento | D544: Tratamento dos dados de fechamento abril pré carga | E544: 0.54166667 | F544: 0.62986111 | G544: =F544-E544
A545: 46028 | B545: G3S 10 | C545: BCBI Seletiva | D545: Operação assistida do sistema de BI da seletiva, acompanhamento e checagem de erros no sistema | E545: 0.33194444 | F545: 0.4375 | G545: 0.10555556
A546: 46028 | B546: G3S 10 | C546: Qualidade | D546: Alinhamento com o Matheus e abertura de chamado para Validação de Valores de Bônus de Compra - Registros sem Filial | E546: 0.4375 | F546: 0.47916667 | G546: 0.041666667
A547: 46028 | B547: G3S 10 | C547: Fechamento | D547: Tratamento dos dados de fechamento maio pré carga | E547: 0.52083333 | F547: 0.625 | G547: 0.10416667
A548: 46059 | B548: G3S 10 | C548: BCBI Seletiva | D548: Operação assistida do sistema de BI da seletiva, acompanhamento e checagem de erros no sistema | E548: 0.32291667 | F548: 0.41666667 | G548: =F548-E548
A549: 46059 | B549: G3S 10 | C549: Fechamento | D549: Conferência e correção de dados da planilha '2026_02_27 - Custo de Coleta Própria' com a Base Financeira | E549: 0.41666667 | F549: 0.47916667 | G549: =F549-E549
A550: 46059 | B550: G3S 10 | C550: Fechamento | D550: Conferência e correção de dados da planilha '2026_02_27 - Custo de Coleta Própria' com a Base Financeira | E550: 0.52083333 | F550: 0.62847222 | G550: =F550-E550
A551: 46087 | B551: G3S 10 | C551: BCBI Seletiva | D551: Auditoria do BCBI | E551: 0.33263889 | F551: 0.41666667 | G551: 0.084027778
A552: 46087 | B552: G3S 10 | C552: Fechamento | D552: Filtragem e categorização de placas especificadas pela Andressa a partir dos relatórios de fechamento | E552: 0.41666667 | F552: 0.43819444 | G552: 0.021527778
A553: =DATE(2026,6,8) | B553: G3S 10 | C553: BCBI Seletiva | D553: Operação assistida do sistema de BI da seletiva, acompanhamento e checagem de erros no sistema | E553: 0.33263889 | F553: 0.39583333 | G553: =F553-E553
A554: =DATE(2026,6,8) | B554: G3S 10 | C554: Suporte Áreas | D554: Análise comparativa de custos de máquinas Liebherr × Hyundai - Levantamento inicial e estruturação da base de dados de custos | E554: 0.39583333 | F554: 0.47916667 | G554: =F554-E554
A555: =DATE(2026,6,8) | B555: G3S 10 | C555: Suporte Áreas | D555: Análise comparativa Liebherr × Hyundai - Definição de metodologia para comparativo justo entre marcas (custo médio por máquina) | E555: 0.52083333 | F555: 0.62777778 | G555: =F555-E555
A556: =DATE(2026,6,9) | B556: G3S 10 | C556: BCBI Seletiva | D556: Operação assistida do sistema de BI da seletiva, acompanhamento e checagem de erros no sistema | E556: 0.325 | F556: 0.375 | G556: =F556-E556
A557: =DATE(2026,6,9) | B557: G3S 10 | C557: Suporte Áreas | D557: Análise comparativa de custos de máquinas Liebherr × Hyundai - Carga e higienização dos dados da base consolidada 2025+2026 | E557: 0.375 | F557: 0.47916667 | G557: =F557-E557
A558: =DATE(2026,6,9) | B558: G3S 10 | C558: Suporte Áreas | D558: Análise comparativa Liebherr × Hyundai - Construção do painel executivo com KPIs (volume, ticket médio, custo por máquina) | E558: 0.52083333 | F558: 0.62916667 | G558: =F558-E558
A559: =DATE(2026,6,10) | B559: G3S 10 | C559: Suporte Áreas | D559: Análise comparativa Liebherr × Hyundai - Composição por conta (plano de contas e DE-PARA de custeio) e ranking por máquina/divisão | E559: 0.32777778 | F559: 0.4 | G559: =F559-E559
A635: =DATE(2026,6,10) | B635: G3S 10 | C635: Fechamento | D635: Conferencia e ajuste de base para fechamento de custos de combustivel e folha (preparacao dos arquivos de fechamento).
A636: =DATE(2026,6,11) | B636: G3S 10 | C636: Suporte areas | D636: Analise comparativa Liebherr x Hyundai com refinamento de metodologia e consolidacao de insumos para relatorio executivo.
A637: =DATE(2026,6,12) | B637: G3S 10 | C637: Suporte areas | D637: Tratamento de dados de consumo de diesel e geracao de analises de contratos para maquinas, com validacoes auxiliares de apoio ao fechamento.
A638: =DATE(2026,6,13) | B638: G3S 10 | C638: Organizacao tecnica | D638: Organizacao e revisao tecnica de artefatos de analise e documentacao de apoio do projeto.
A639: =DATE(2026,6,14) | B639: G3S 10 | C639: Organizacao tecnica | D639: Consolidacao de pendencias e preparacao de material para continuidade das entregas da semana seguinte.
A640: =DATE(2026,6,15) | B640: G3S 10 | C640: Suporte areas | D640: Atualizacao do dashboard comparativo Liebherr x Hyundai, sincronizacao de figuras e ajustes de scripts de exportacao e auditoria.
A641: =DATE(2026,6,16) | B641: G3S 10 | C641: Governanca de dados | D641: Atualizacao de referencias de Plano de Contas e revisao de apontamentos de auditoria analitica para suporte a classificacao contabil.

Sheet Banco de Horas
A1: DATA | B1: HORA INICIAL | C1: HORA FINAL | D1: HORAS TRABALHADAS | E1: HORAS ESPERADAS | F1: BANCO DO DIA | G1: COMPENSAÇÃO | H1: BANCO FINAL | I1: BANCO ACUMULADO
A2: 45992 | B2: =_xlfn.MINIFS(Atividades!$E:$E,Atividades!$A:$A, A2) | C2: =_xlfn.MAXIFS(Atividades!$F:$F, Atividades!$A:$A, A2) | D2: =IF(C2-B2>TIME(6,0,0), (C2-B2)-TIME(1,0,0), C2-B2) | E2: =IF(OR(D2<=0, B2="", C2=""), 0, TIME(6,0,0)) | F2: =D2-E2 | G2: 0 | H2: =F2-G2 | I2: =H2
A3: 45993 | B3: =_xlfn.MINIFS(Atividades!$E:$E,Atividades!$A:$A, A3) | C3: =_xlfn.MAXIFS(Atividades!$F:$F, Atividades!$A:$A, A3) | D3: =IF(C3-B3>TIME(6,0,0), (C3-B3)-TIME(1,0,0), C3-B3) | E3: =IF(OR(D3<=0, B3="", C3=""), 0, TIME(6,0,0)) | F3: =D3-E3 | G3: 0 | H3: =F3-G3 | I3: =I2+H3
A4: 45994 | B4: =_xlfn.MINIFS(Atividades!$E:$E,Atividades!$A:$A, A4) | C4: =_xlfn.MAXIFS(Atividades!$F:$F, Atividades!$A:$A, A4) | D4: =IF(C4-B4>TIME(6,0,0), (C4-B4)-TIME(1,0,0), C4-B4) | E4: =IF(OR(D4<=0, B4="", C4=""), 0, TIME(6,0,0)) | F4: =D4-E4 | G4: 0 | H4: =F4-G4 | I4: =I3+H4
A5: 45995 | B5: =_xlfn.MINIFS(Atividades!$E:$E,Atividades!$A:$A, A5) | C5: =_xlfn.MAXIFS(Atividades!$F:$F, Atividades!$A:$A, A5) | D5: =IF(C5-B5>TIME(6,0,0), (C5-B5)-TIME(1,0,0), C5-B5) | E5: =IF(OR(D5<=0, B5="", C5=""), 0, TIME(6,0,0)) | F5: =D5-E5 | G5: 0 | H5: =F5-G5 | I5: =I4+H5
A6: 45996 | B6: =_xlfn.MINIFS(Atividades!$E:$E,Atividades!$A:$A, A6) | C6: =_xlfn.MAXIFS(Atividades!$F:$F, Atividades!$A:$A, A6) | D6: =IF(C6-B6>TIME(6,0,0), (C6-B6)-TIME(1,0,0), C6-B6) | E6: =IF(OR(D6<=0, B6="", C6=""), 0, TIME(6,0,0)) | F6: =D6-E6 | G6: 0 | H6: =F6-G6 | I6: =I5+H6
A7: 45999 | B7: =_xlfn.MINIFS(Atividades!$E:$E,Atividades!$A:$A, A7) | C7: =_xlfn.MAXIFS(Atividades!$F:$F, Atividades!$A:$A, A7) | D7: =IF(C7-B7>TIME(6,0,0), (C7-B7)-TIME(1,0,0), C7-B7) | E7: =IF(OR(D7<=0, B7="", C7=""), 0, TIME(6,0,0)) | F7: =D7-E7 | G7: 0 | H7: =F7-G7 | I7: =I6+H7
A8: 46000 | B8: =_xlfn.MINIFS(Atividades!$E:$E,Atividades!$A:$A, A8) | C8: 0.62847222 | D8: =IF(C8-B8>TIME(6,0,0), (C8-B8)-TIME(1,0,0), C8-B8) | E8: =IF(OR(D8<=0, B8="", C8=""), 0, TIME(6,0,0)) | F8: =D8-E8 | G8: 0 | H8: =F8-G8 | I8: =I7+H8
A9: 46001 | B9: =_xlfn.MINIFS(Atividades!$E:$E,Atividades!$A:$A, A9) | C9: =_xlfn.MAXIFS(Atividades!$F:$F, Atividades!$A:$A, A9) | D9: =IF(C9-B9>TIME(6,0,0), (C9-B9)-TIME(1,0,0), C9-B9) | E9: =IF(OR(D9<=0, B9="", C9=""), 0, TIME(6,0,0)) | F9: =D9-E9 | G9: 0 | H9: =F9-G9 | I9: =I8+H9
A10: 46002 | B10: =_xlfn.MINIFS(Atividades!$E:$E,Atividades!$A:$A, A10) | C10: =_xlfn.MAXIFS(Atividades!$F:$F, Atividades!$A:$A, A10) | D10: =IF(C10-B10>TIME(6,0,0), (C10-B10)-TIME(1,0,0), C10-B10) | E10: =IF(OR(D10<=0, B10="", C10=""), 0, TIME(6,0,0)) | F10: =D10-E10 | G10: 0 | H10: =F10-G10 | I10: =I9+H10
A11: 46003 | B11: =_xlfn.MINIFS(Atividades!$E:$E,Atividades!$A:$A, A11) | C11: =_xlfn.MAXIFS(Atividades!$F:$F, Atividades!$A:$A, A11) | D11: =IF(C11-B11>TIME(6,0,0), (C11-B11)-TIME(1,0,0), C11-B11) | E11: =IF(OR(D11<=0, B11="", C11=""), 0, TIME(6,0,0)) | F11: =D11-E11 | G11: 0 | H11: =F11-G11 | I11: =I10+H11
A12: 46006 | B12: =_xlfn.MINIFS(Atividades!$E:$E,Atividades!$A:$A, A12) | C12: =_xlfn.MAXIFS(Atividades!$F:$F, Atividades!$A:$A, A12) | D12: =IF(C12-B12>TIME(6,0,0), (C12-B12)-TIME(1,0,0), C12-B12) | E12: =IF(OR(D12<=0, B12="", C12=""), 0, TIME(6,0,0)) | F12: =D12-E12 | G12: 0 | H12: =F12-G12 | I12: =I11+H12
A13: 46007 | B13: =_xlfn.MINIFS(Atividades!$E:$E,Atividades!$A:$A, A13) | C13: =_xlfn.MAXIFS(Atividades!$F:$F, Atividades!$A:$A, A13) | D13: =IF(C13-B13>TIME(6,0,0), (C13-B13)-TIME(1,0,0), C13-B13) | E13: =IF(OR(D13<=0, B13="", C13=""), 0, TIME(6,0,0)) | F13: =D13-E13 | G13: 0 | H13: =F13-G13 | I13: =I12+H13
A14: 46008 | B14: =_xlfn.MINIFS(Atividades!$E:$E,Atividades!$A:$A, A14) | C14: =_xlfn.MAXIFS(Atividades!$F:$F, Atividades!$A:$A, A14) | D14: =IF(C14-B14>TIME(6,0,0), (C14-B14)-TIME(1,0,0), C14-B14) | E14: =IF(OR(D14<=0, B14="", C14=""), 0, TIME(6,0,0)) | F14: =D14-E14 | G14: 0 | H14: =F14-G14 | I14: =I13+H14
A15: 46027 | B15: =_xlfn.MINIFS(Atividades!$E:$E,Atividades!$A:$A, A15) | C15: 0.62986111 | D15: 0.26388889 | E15: =IF(OR(D15<=0, B15="", C15=""), 0, TIME(6,0,0)) | F15: =D15-E15 | G15: 0 | H15: =F15-G15 | I15: =I14+H15
A16: 46028 | B16: =_xlfn.MINIFS(Atividades!$E:$E,Atividades!$A:$A, A16) | C16: =_xlfn.MAXIFS(Atividades!$F:$F, Atividades!$A:$A, A16) | D16: =IF(C16-B16>TIME(6,0,0), (C16-B16)-TIME(1,0,0), C16-B16) | E16: =IF(OR(D16<=0, B16="", C16=""), 0, TIME(6,0,0)) | F16: =D16-E16 | G16: 0 | H16: =F16-G16 | I16: =I15+H16
A17: 46029 | B17: =_xlfn.MINIFS(Atividades!$E:$E,Atividades!$A:$A, A17) | C17: =_xlfn.MAXIFS(Atividades!$F:$F, Atividades!$A:$A, A17) | D17: =IF(C17-B17>TIME(6,0,0), (C17-B17)-TIME(1,0,0), C17-B17) | E17: =IF(OR(D17<=0, B17="", C17=""), 0, TIME(6,0,0)) | F17: =D17-E17 | G17: 0 | H17: =F17-G17 | I17: =I16+H17
A18: 46030 | B18: =_xlfn.MINIFS(Atividades!$E:$E,Atividades!$A:$A, A18) | C18: =_xlfn.MAXIFS(Atividades!$F:$F, Atividades!$A:$A, A18) | D18: =IF(C18-B18>TIME(6,0,0), (C18-B18)-TIME(1,0,0), C18-B18) | E18: =IF(OR(D18<=0, B18="", C18=""), 0, TIME(6,0,0)) | F18: =D18-E18 | G18: 0 | H18: =F18-G18 | I18: =I17+H18
A19: 46031 | B19: =_xlfn.MINIFS(Atividades!$E:$E,Atividades!$A:$A, A19) | C19: =_xlfn.MAXIFS(Atividades!$F:$F, Atividades!$A:$A, A19) | D19: =IF(C19-B19>TIME(6,0,0), (C19-B19)-TIME(1,0,0), C19-B19) | E19: =IF(OR(D19<=0, B19="", C19=""), 0, TIME(6,0,0)) | F19: =D19-E19 | G19: 0 | H19: =F19-G19 | I19: =I18+H19
A20: 46034 | B20: =_xlfn.MINIFS(Atividades!$E:$E,Atividades!$A:$A, A20) | C20: =_xlfn.MAXIFS(Atividades!$F:$F, Atividades!$A:$A, A20) | D20: =IF(C20-B20>TIME(6,0,0), (C20-B20)-TIME(1,0,0), C20-B20) | E20: =IF(OR(D20<=0, B20="", C20=""), 0, TIME(6,0,0)) | F20: =D20-E20 | G20: 0 | H20: =F20-G20 | I20: =I19+H20
A21: 46035 | B21: =_xlfn.MINIFS(Atividades!$E:$E,Atividades!$A:$A, A21) | C21: =_xlfn.MAXIFS(Atividades!$F:$F, Atividades!$A:$A, A21) | D21: =IF(C21-B21>TIME(6,0,0), (C21-B21)-TIME(1,0,0), C21-B21) | E21: =IF(OR(D21<=0, B21="", C21=""), 0, TIME(6,0,0)) | F21: =D21-E21 | G21: 0 | H21: =F21-G21 | I21: =I20+H21
A22: 46036 | B22: =_xlfn.MINIFS(Atividades!$E:$E,Atividades!$A:$A, A22) | C22: =_xlfn.MAXIFS(Atividades!$F:$F, Atividades!$A:$A, A22) | D22: =IF(C22-B22>TIME(6,0,0), (C22-B22)-TIME(1,0,0), C22-B22) | E22: =IF(OR(D22<=0, B22="", C22=""), 0, TIME(6,0,0)) | F22: =D22-E22 | G22: 0 | H22: =F22-G22 | I22: =I21+H22
A23: 46037 | B23: =_xlfn.MINIFS(Atividades!$E:$E,Atividades!$A:$A, A23) | C23: =_xlfn.MAXIFS(Atividades!$F:$F, Atividades!$A:$A, A23) | D23: =IF(C23-B23>TIME(6,0,0), (C23-B23)-TIME(1,0,0), C23-B23) | E23: =IF(OR(D23<=0, B23="", C23=""), 0, TIME(6,0,0)) | F23: =D23-E23 | G23: 0 | H23: =F23-G23 | I23: =I22+H23
A24: 46038 | B24: =_xlfn.MINIFS(Atividades!$E:$E,Atividades!$A:$A, A24) | C24: =_xlfn.MAXIFS(Atividades!$F:$F, Atividades!$A:$A, A24) | D24: =IF(C24-B24>TIME(6,0,0), (C24-B24)-TIME(1,0,0), C24-B24) | E24: =IF(OR(D24<=0, B24="", C24=""), 0, TIME(6,0,0)) | F24: =D24-E24 | G24: 0 | H24: =F24-G24 | I24: =I23+H24
A25: 46041 | B25: =_xlfn.MINIFS(Atividades!$E:$E,Atividades!$A:$A, A25) | C25: =_xlfn.MAXIFS(Atividades!$F:$F, Atividades!$A:$A, A25) | D25: =IF(C25-B25>TIME(6,0,0), (C25-B25)-TIME(1,0,0), C25-B25) | E25: =IF(OR(D25<=0, B25="", C25=""), 0, TIME(6,0,0)) | F25: =D25-E25 | G25: 0 | H25: =F25-G25 | I25: =I24+H25
A26: 46043 | B26: =_xlfn.MINIFS(Atividades!$E:$E,Atividades!$A:$A, A26) | C26: =_xlfn.MAXIFS(Atividades!$F:$F, Atividades!$A:$A, A26) | D26: =IF(C26-B26>TIME(6,0,0), (C26-B26)-TIME(1,0,0), C26-B26) | E26: =IF(OR(D26<=0, B26="", C26=""), 0, TIME(6,0,0)) | F26: =D26-E26 | G26: 0 | H26: =F26-G26 | I26: =I25+H26
A27: 46044 | B27: =_xlfn.MINIFS(Atividades!$E:$E,Atividades!$A:$A, A27) | C27: =_xlfn.MAXIFS(Atividades!$F:$F, Atividades!$A:$A, A27) | D27: =IF(C27-B27>TIME(6,0,0), (C27-B27)-TIME(1,0,0), C27-B27) | E27: =IF(OR(D27<=0, B27="", C27=""), 0, TIME(6,0,0)) | F27: =D27-E27 | G27: 0 | H27: =F27-G27 | I27: =I26+H27
A28: 46045 | B28: =_xlfn.MINIFS(Atividades!$E:$E,Atividades!$A:$A, A28) | C28: =_xlfn.MAXIFS(Atividades!$F:$F, Atividades!$A:$A, A28) | D28: =IF(C28-B28>TIME(6,0,0), (C28-B28)-TIME(1,0,0), C28-B28) | E28: =IF(OR(D28<=0, B28="", C28=""), 0, TIME(6,0,0)) | F28: 0 | G28: 0.083333333 | H28: =F28-G28 | I28: =I27+H28
A29: 46048 | B29: =_xlfn.MINIFS(Atividades!$E:$E,Atividades!$A:$A, A29) | C29: =_xlfn.MAXIFS(Atividades!$F:$F, Atividades!$A:$A, A29) | D29: =IF(C29-B29>TIME(6,0,0), (C29-B29)-TIME(1,0,0), C29-B29) | E29: =IF(OR(D29<=0, B29="", C29=""), 0, TIME(6,0,0)) | F29: =D29-E29 | G29: 0 | H29: =F29-G29 | I29: =I28+H29
A30: 46049 | B30: =_xlfn.MINIFS(Atividades!$E:$E,Atividades!$A:$A, A30) | C30: =_xlfn.MAXIFS(Atividades!$F:$F, Atividades!$A:$A, A30) | D30: =IF(C30-B30>TIME(6,0,0), (C30-B30)-TIME(1,0,0), C30-B30) | E30: =IF(OR(D30<=0, B30="", C30=""), 0, TIME(6,0,0)) | F30: =D30-E30 | G30: 0 | H30: =F30-G30 | I30: =I29+H30
A31: 46050 | B31: =_xlfn.MINIFS(Atividades!$E:$E,Atividades!$A:$A, A31) | C31: =_xlfn.MAXIFS(Atividades!$F:$F, Atividades!$A:$A, A31) | D31: =IF(C31-B31>TIME(6,0,0), (C31-B31)-TIME(1,0,0), C31-B31) | E31: =IF(OR(D31<=0, B31="", C31=""), 0, TIME(6,0,0)) | F31: =D31-E31 | G31: 0 | H31: =F31-G31 | I31: =I30+H31
A32: 46051 | B32: =_xlfn.MINIFS(Atividades!$E:$E,Atividades!$A:$A, A32) | C32: =_xlfn.MAXIFS(Atividades!$F:$F, Atividades!$A:$A, A32) | D32: =IF(C32-B32>TIME(6,0,0), (C32-B32)-TIME(1,0,0), C32-B32) | E32: =IF(OR(D32<=0, B32="", C32=""), 0, TIME(6,0,0)) | F32: =D32-E32 | G32: 0 | H32: =F32-G32 | I32: =I31+H32
A33: 46052 | B33: =_xlfn.MINIFS(Atividades!$E:$E,Atividades!$A:$A, A33) | C33: =_xlfn.MAXIFS(Atividades!$F:$F, Atividades!$A:$A, A33) | D33: =IF(C33-B33>TIME(6,0,0), (C33-B33)-TIME(1,0,0), C33-B33) | E33: =IF(OR(D33<=0, B33="", C33=""), 0, TIME(6,0,0)) | F33: =D33-E33 | G33: 0 | H33: =F33-G33 | I33: =I32+H33
A34: 46055 | B34: =_xlfn.MINIFS(Atividades!$E:$E,Atividades!$A:$A, A34) | C34: =_xlfn.MAXIFS(Atividades!$F:$F, Atividades!$A:$A, A34) | D34: =IF(C34-B34>TIME(6,0,0), (C34-B34)-TIME(1,0,0), C34-B34) | E34: =IF(OR(D34<=0, B34="", C34=""), 0, TIME(6,0,0)) | F34: =D34-E34 | G34: 0 | H34: =F34-G34 | I34: =I33+H34
A35: 46056 | B35: =_xlfn.MINIFS(Atividades!$E:$E,Atividades!$A:$A, A35) | C35: =_xlfn.MAXIFS(Atividades!$F:$F, Atividades!$A:$A, A35) | D35: =IF(C35-B35>TIME(6,0,0), (C35-B35)-TIME(1,0,0), C35-B35) | E35: =IF(OR(D35<=0, B35="", C35=""), 0, TIME(6,0,0)) | F35: =D35-E35 | G35: 0 | H35: =F35-G35 | I35: =I34+H35
A36: 46057 | B36: =_xlfn.MINIFS(Atividades!$E:$E,Atividades!$A:$A, A36) | C36: =_xlfn.MAXIFS(Atividades!$F:$F, Atividades!$A:$A, A36) | D36: =IF(C36-B36>TIME(6,0,0), (C36-B36)-TIME(1,0,0), C36-B36) | E36: =IF(OR(D36<=0, B36="", C36=""), 0, TIME(6,0,0)) | F36: =D36-E36 | G36: 0 | H36: =F36-G36 | I36: =I35+H36
A37: 46058 | B37: =_xlfn.MINIFS(Atividades!$E:$E,Atividades!$A:$A, A37) | C37: =_xlfn.MAXIFS(Atividades!$F:$F, Atividades!$A:$A, A37) | D37: =IF(C37-B37>TIME(6,0,0), (C37-B37)-TIME(1,0,0), C37-B37) | E37: =IF(OR(D37<=0, B37="", C37=""), 0, TIME(6,0,0)) | F37: =D37-E37 | G37: 0 | H37: =F37-G37 | I37: =I36+H37
A38: 46059 | B38: =_xlfn.MINIFS(Atividades!$E:$E,Atividades!$A:$A, A38) | C38: =_xlfn.MAXIFS(Atividades!$F:$F, Atividades!$A:$A, A38) | D38: =IF(C38-B38>TIME(6,0,0), (C38-B38)-TIME(1,0,0), C38-B38) | E38: =IF(OR(D38<=0, B38="", C38=""), 0, TIME(6,0,0)) | F38: 0 | G38: 0.083333333 | H38: =F38-G38 | I38: =I37+H38
A39: 46064 | B39: =_xlfn.MINIFS(Atividades!$E:$E,Atividades!$A:$A, A39) | C39: =_xlfn.MAXIFS(Atividades!$F:$F, Atividades!$A:$A, A39) | D39: =IF(C39-B39>TIME(6,0,0), (C39-B39)-TIME(1,0,0), C39-B39) | E39: =IF(OR(D39<=0, B39="", C39=""), 0, TIME(6,0,0)) | F39: =D39-E39 | G39: 0 | H39: =F39-G39 | I39: =I38+H39
A40: 46065 | B40: =_xlfn.MINIFS(Atividades!$E:$E,Atividades!$A:$A, A40) | C40: =_xlfn.MAXIFS(Atividades!$F:$F, Atividades!$A:$A, A40) | D40: =IF(C40-B40>TIME(6,0,0), (C40-B40)-TIME(1,0,0), C40-B40) | E40: =IF(OR(D40<=0, B40="", C40=""), 0, TIME(6,0,0)) | F40: =D40-E40 | G40: 0 | H40: =F40-G40 | I40: =I39+H40
A41: 46066 | B41: =_xlfn.MINIFS(Atividades!$E:$E,Atividades!$A:$A, A41) | C41: =_xlfn.MAXIFS(Atividades!$F:$F, Atividades!$A:$A, A41) | D41: =IF(C41-B41>TIME(6,0,0), (C41-B41)-TIME(1,0,0), C41-B41) | E41: =IF(OR(D41<=0, B41="", C41=""), 0, TIME(6,0,0)) | F41: =D41-E41 | G41: 0 | H41: =F41-G41 | I41: =I40+H41
A42: 46071 | B42: =_xlfn.MINIFS(Atividades!$E:$E,Atividades!$A:$A, A42) | C42: =_xlfn.MAXIFS(Atividades!$F:$F, Atividades!$A:$A, A42) | D42: =IF(C42-B42>TIME(6,0,0), (C42-B42)-TIME(1,0,0), C42-B42) | E42: =IF(OR(D42<=0, B42="", C42=""), 0, TIME(6,0,0)) | F42: =D42-E42 | G42: 0 | H42: =F42-G42 | I42: =I41+H42
A43: 46072 | B43: =_xlfn.MINIFS(Atividades!$E:$E,Atividades!$A:$A, A43) | C43: =_xlfn.MAXIFS(Atividades!$F:$F, Atividades!$A:$A, A43) | D43: =IF(C43-B43>TIME(6,0,0), (C43-B43)-TIME(1,0,0), C43-B43) | E43: =IF(OR(D43<=0, B43="", C43=""), 0, TIME(6,0,0)) | F43: =D43-E43 | G43: 0 | H43: =F43-G43 | I43: =I42+H43
A44: 46073 | B44: =_xlfn.MINIFS(Atividades!$E:$E,Atividades!$A:$A, A44) | C44: =_xlfn.MAXIFS(Atividades!$F:$F, Atividades!$A:$A, A44) | D44: =IF(C44-B44>TIME(6,0,0), (C44-B44)-TIME(1,0,0), C44-B44) | E44: =IF(OR(D44<=0, B44="", C44=""), 0, TIME(6,0,0)) | F44: =D44-E44 | G44: 0 | H44: =F44-G44 | I44: =I43+H44
A45: 46076 | B45: =_xlfn.MINIFS(Atividades!$E:$E,Atividades!$A:$A, A45) | C45: =_xlfn.MAXIFS(Atividades!$F:$F, Atividades!$A:$A, A45) | D45: =IF(C45-B45>TIME(6,0,0), (C45-B45)-TIME(1,0,0), C45-B45) | E45: =IF(OR(D45<=0, B45="", C45=""), 0, TIME(6,0,0)) | F45: =D45-E45 | G45: 0 | H45: =F45-G45 | I45: =I44+H45
A46: 46077 | B46: =_xlfn.MINIFS(Atividades!$E:$E,Atividades!$A:$A, A46) | C46: =_xlfn.MAXIFS(Atividades!$F:$F, Atividades!$A:$A, A46) | D46: =IF(C46-B46>TIME(6,0,0), (C46-B46)-TIME(1,0,0), C46-B46) | E46: =IF(OR(D46<=0, B46="", C46=""), 0, TIME(6,0,0)) | F46: =D46-E46 | G46: 0 | H46: =F46-G46 | I46: =I45+H46
A47: 46078 | B47: =_xlfn.MINIFS(Atividades!$E:$E,Atividades!$A:$A, A47) | C47: =_xlfn.MAXIFS(Atividades!$F:$F, Atividades!$A:$A, A47) | D47: =IF(C47-B47>TIME(6,0,0), (C47-B47)-TIME(1,0,0), C47-B47) | E47: =IF(OR(D47<=0, B47="", C47=""), 0, TIME(6,0,0)) | F47: =D47-E47 | G47: 0 | H47: =F47-G47 | I47: =I46+H47
A48: 46079 | B48: =_xlfn.MINIFS(Atividades!$E:$E,Atividades!$A:$A, A48) | C48: =_xlfn.MAXIFS(Atividades!$F:$F, Atividades!$A:$A, A48) | D48: =IF(C48-B48>TIME(6,0,0), (C48-B48)-TIME(1,0,0), C48-B48) | E48: =IF(OR(D48<=0, B48="", C48=""), 0, TIME(6,0,0)) | F48: =D48-E48 | G48: 0 | H48: =F48-G48 | I48: =I47+H48
A49: 46080 | B49: =_xlfn.MINIFS(Atividades!$E:$E,Atividades!$A:$A, A49) | C49: =_xlfn.MAXIFS(Atividades!$F:$F, Atividades!$A:$A, A49) | D49: =IF(C49-B49>TIME(6,0,0), (C49-B49)-TIME(1,0,0), C49-B49) | E49: =IF(OR(D49<=0, B49="", C49=""), 0, TIME(6,0,0)) | F49: =D49-E49 | G49: 0 | H49: =F49-G49 | I49: =I48+H49
A50: 46083 | B50: =_xlfn.MINIFS(Atividades!$E:$E,Atividades!$A:$A, A50) | C50: 0.62916667 | D50: =IF(C50-B50>TIME(6,0,0), (C50-B50)-TIME(1,0,0), C50-B50) | E50: =IF(OR(D50<=0, B50="", C50=""), 0, TIME(6,0,0)) | F50: =D50-E50 | G50: 0 | H50: =F50-G50 | I50: =I49+H50
A51: 46084 | B51: =_xlfn.MINIFS(Atividades!$E:$E,Atividades!$A:$A, A51) | C51: =_xlfn.MAXIFS(Atividades!$F:$F, Atividades!$A:$A, A51) | D51: =IF(C51-B51>TIME(6,0,0), (C51-B51)-TIME(1,0,0), C51-B51) | E51: =IF(OR(D51<=0, B51="", C51=""), 0, TIME(6,0,0)) | F51: =D51-E51 | G51: 0 | H51: =F51-G51 | I51: =I50+H51
A52: 46085 | B52: =_xlfn.MINIFS(Atividades!$E:$E,Atividades!$A:$A, A52) | C52: =_xlfn.MAXIFS(Atividades!$F:$F, Atividades!$A:$A, A52) | D52: =IF(C52-B52>TIME(6,0,0), (C52-B52)-TIME(1,0,0), C52-B52) | E52: =IF(OR(D52<=0, B52="", C52=""), 0, TIME(6,0,0)) | F52: =D52-E52 | G52: 0 | H52: =F52-G52 | I52: =I51+H52
A53: 46086 | B53: =_xlfn.MINIFS(Atividades!$E:$E,Atividades!$A:$A, A53) | C53: =_xlfn.MAXIFS(Atividades!$F:$F, Atividades!$A:$A, A53) | D53: =IF(C53-B53>TIME(6,0,0), (C53-B53)-TIME(1,0,0), C53-B53) | E53: =IF(OR(D53<=0, B53="", C53=""), 0, TIME(6,0,0)) | F53: =D53-E53 | G53: 0 | H53: =F53-G53 | I53: =I52+H53
A54: 46087 | B54: =_xlfn.MINIFS(Atividades!$E:$E,Atividades!$A:$A, A54) | C54: 0.63055556 | D54: =IF(C54-B54>TIME(6,0,0), (C54-B54)-TIME(1,0,0), C54-B54) | E54: =IF(OR(D54<=0, B54="", C54=""), 0, TIME(6,0,0)) | F54: =D54-E54 | G54: 0 | H54: =F54-G54 | I54: =I53+H54
A55: 46090 | B55: =_xlfn.MINIFS(Atividades!$E:$E,Atividades!$A:$A, A55) | C55: =_xlfn.MAXIFS(Atividades!$F:$F, Atividades!$A:$A, A55) | D55: =IF(C55-B55>TIME(6,0,0), (C55-B55)-TIME(1,0,0), C55-B55) | E55: =IF(OR(D55<=0, B55="", C55=""), 0, TIME(6,0,0)) | F55: =D55-E55 | G55: 0 | H55: =F55-G55 | I55: =I54+H55
A56: 46091 | B56: =_xlfn.MINIFS(Atividades!$E:$E,Atividades!$A:$A, A56) | C56: =_xlfn.MAXIFS(Atividades!$F:$F, Atividades!$A:$A, A56) | D56: =IF(C56-B56>TIME(6,0,0), (C56-B56)-TIME(1,0,0), C56-B56) | E56: =IF(OR(D56<=0, B56="", C56=""), 0, TIME(6,0,0)) | F56: =D56-E56 | G56: 0 | H56: =F56-G56 | I56: =I55+H56
A57: 46092 | B57: =_xlfn.MINIFS(Atividades!$E:$E,Atividades!$A:$A, A57) | C57: =_xlfn.MAXIFS(Atividades!$F:$F, Atividades!$A:$A, A57) | D57: =IF(C57-B57>TIME(6,0,0), (C57-B57)-TIME(1,0,0), C57-B57) | E57: =IF(OR(D57<=0, B57="", C57=""), 0, TIME(6,0,0)) | F57: =D57-E57 | G57: 0 | H57: =F57-G57 | I57: =I56+H57
A58: 46093 | B58: =_xlfn.MINIFS(Atividades!$E:$E,Atividades!$A:$A, A58) | C58: =_xlfn.MAXIFS(Atividades!$F:$F, Atividades!$A:$A, A58) | D58: =IF(C58-B58>TIME(6,0,0), (C58-B58)-TIME(1,0,0), C58-B58) | E58: =IF(OR(D58<=0, B58="", C58=""), 0, TIME(6,0,0)) | F58: =D58-E58 | G58: 0 | H58: =F58-G58 | I58: =I57+H58
A59: 46094 | B59: =_xlfn.MINIFS(Atividades!$E:$E,Atividades!$A:$A, A59) | C59: =_xlfn.MAXIFS(Atividades!$F:$F, Atividades!$A:$A, A59) | D59: =IF(C59-B59>TIME(6,0,0), (C59-B59)-TIME(1,0,0), C59-B59) | E59: =IF(OR(D59<=0, B59="", C59=""), 0, TIME(6,0,0)) | F59: =D59-E59 | G59: 0 | H59: =F59-G59 | I59: =I58+H59
A60: 46097 | B60: =_xlfn.MINIFS(Atividades!$E:$E,Atividades!$A:$A, A60) | C60: =_xlfn.MAXIFS(Atividades!$F:$F, Atividades!$A:$A, A60) | D60: =IF(C60-B60>TIME(6,0,0), (C60-B60)-TIME(1,0,0), C60-B60) | E60: =IF(OR(D60<=0, B60="", C60=""), 0, TIME(6,0,0)) | F60: =D60-E60 | G60: 0 | H60: =F60-G60 | I60: =I59+H60
A61: 46098 | B61: =_xlfn.MINIFS(Atividades!$E:$E,Atividades!$A:$A, A61) | C61: =_xlfn.MAXIFS(Atividades!$F:$F, Atividades!$A:$A, A61) | D61: =IF(C61-B61>TIME(6,0,0), (C61-B61)-TIME(1,0,0), C61-B61) | E61: =IF(OR(D61<=0, B61="", C61=""), 0, TIME(6,0,0)) | F61: =D61-E61 | G61: 0 | H61: =F61-G61 | I61: =I60+H61
A62: 46099 | B62: =_xlfn.MINIFS(Atividades!$E:$E,Atividades!$A:$A, A62) | C62: =_xlfn.MAXIFS(Atividades!$F:$F, Atividades!$A:$A, A62) | D62: =IF(C62-B62>TIME(6,0,0), (C62-B62)-TIME(1,0,0), C62-B62) | E62: =IF(OR(D62<=0, B62="", C62=""), 0, TIME(6,0,0)) | F62: =D62-E62 | G62: 0 | H62: =F62-G62 | I62: =I61+H62
A63: 46100 | B63: =_xlfn.MINIFS(Atividades!$E:$E,Atividades!$A:$A, A63) | C63: =_xlfn.MAXIFS(Atividades!$F:$F, Atividades!$A:$A, A63) | D63: =IF(C63-B63>TIME(6,0,0), (C63-B63)-TIME(1,0,0), C63-B63) | E63: =IF(OR(D63<=0, B63="", C63=""), 0, TIME(6,0,0)) | F63: =D63-E63 | G63: 0 | H63: =F63-G63 | I63: =H63 | K63: <- Comecei a Somar minhas horas a partir dessa linha
A64: 46101 | B64: =_xlfn.MINIFS(Atividades!$E:$E,Atividades!$A:$A, A64) | C64: =_xlfn.MAXIFS(Atividades!$F:$F, Atividades!$A:$A, A64) | D64: =IF(C64-B64>TIME(6,0,0), (C64-B64)-TIME(1,0,0), C64-B64) | E64: =IF(OR(D64<=0, B64="", C64=""), 0, TIME(6,0,0)) | F64: =D64-E64 | G64: 0 | H64: =F64-G64 | I64: =I63+H64
A65: 46102 | B65: 0.33333333 | C65: 0.625 | D65: =IF(C65-B65>TIME(6,0,0), (C65-B65)-TIME(1,0,0), C65-B65) | E65: =IF(OR(D65<=0, B65="", C65=""), 0, TIME(6,0,0)) | F65: =D65-E65 | G65: 0 | H65: =F65-G65 | I65: =I64+H65
A66: 46103 | B66: 0.33333333 | C66: 0.625 | D66: =IF(C66-B66>TIME(6,0,0), (C66-B66)-TIME(1,0,0), C66-B66) | E66: =IF(OR(D66<=0, B66="", C66=""), 0, TIME(6,0,0)) | F66: =D66-E66 | G66: 0 | H66: =F66-G66 | I66: =I65+H66
A67: 46104 | B67: 0.33333333 | C67: 0.625 | D67: =IF(C67-B67>TIME(6,0,0), (C67-B67)-TIME(1,0,0), C67-B67) | E67: =IF(OR(D67<=0, B67="", C67=""), 0, TIME(6,0,0)) | F67: =D67-E67 | G67: 0 | H67: =F67-G67 | I67: =I66+H67
A68: 46105 | B68: 0.33333333 | C68: 0.625 | D68: =IF(C68-B68>TIME(6,0,0), (C68-B68)-TIME(1,0,0), C68-B68) | E68: =IF(OR(D68<=0, B68="", C68=""), 0, TIME(6,0,0)) | F68: =D68-E68 | G68: 0 | H68: =F68-G68 | I68: =I67+H68
A69: 46106 | B69: 0.33333333 | C69: 0.625 | D69: =IF(C69-B69>TIME(6,0,0), (C69-B69)-TIME(1,0,0), C69-B69) | E69: =IF(OR(D69<=0, B69="", C69=""), 0, TIME(6,0,0)) | F69: =D69-E69 | G69: 0 | H69: =F69-G69 | I69: =I68+H69
A70: 46107 | B70: 0.33333333 | C70: 0.625 | D70: =IF(C70-B70>TIME(6,0,0), (C70-B70)-TIME(1,0,0), C70-B70) | E70: =IF(OR(D70<=0, B70="", C70=""), 0, TIME(6,0,0)) | F70: =D70-E70 | G70: 0 | H70: =F70-G70 | I70: =I69+H70
A71: 46108 | B71: 0.33333333 | C71: 0.625 | D71: =IF(C71-B71>TIME(6,0,0), (C71-B71)-TIME(1,0,0), C71-B71) | E71: =IF(OR(D71<=0, B71="", C71=""), 0, TIME(6,0,0)) | F71: =D71-E71 | G71: 0 | H71: =F71-G71 | I71: =I70+H71
A72: 46109 | B72: 0.33333333 | C72: 0.625 | D72: =IF(C72-B72>TIME(6,0,0), (C72-B72)-TIME(1,0,0), C72-B72) | E72: =IF(OR(D72<=0, B72="", C72=""), 0, TIME(6,0,0)) | F72: =D72-E72 | G72: 0 | H72: =F72-G72 | I72: =I71+H72
A73: 46110 | B73: 0.33333333 | C73: 0.625 | D73: =IF(C73-B73>TIME(6,0,0), (C73-B73)-TIME(1,0,0), C73-B73) | E73: =IF(OR(D73<=0, B73="", C73=""), 0, TIME(6,0,0)) | F73: =D73-E73 | G73: 0 | H73: =F73-G73 | I73: =I72+H73
A74: 46111 | B74: 0.33333333 | C74: 0.625 | D74: =IF(C74-B74>TIME(6,0,0), (C74-B74)-TIME(1,0,0), C74-B74) | E74: =IF(OR(D74<=0, B74="", C74=""), 0, TIME(6,0,0)) | F74: =D74-E74 | G74: 0 | H74: =F74-G74 | I74: =I73+H74
A75: 46112 | B75: 0.33333333 | C75: 0.625 | D75: =IF(C75-B75>TIME(6,0,0), (C75-B75)-TIME(1,0,0), C75-B75) | E75: =IF(OR(D75<=0, B75="", C75=""), 0, TIME(6,0,0)) | F75: =D75-E75 | G75: 0 | H75: =F75-G75 | I75: =I74+H75
A76: 46113 | B76: 0.33333333 | C76: 0.625 | D76: =IF(C76-B76>TIME(6,0,0), (C76-B76)-TIME(1,0,0), C76-B76) | E76: =IF(OR(D76<=0, B76="", C76=""), 0, TIME(6,0,0)) | F76: =D76-E76 | G76: 0 | H76: =F76-G76 | I76: =I75+H76
... A91: 46128 | B91: 0.33333333 | C91: 0.625 | D91: =IF(C91-B91>TIME(6,0,0), (C91-B91)-TIME(1,0,0), C91-B91) | E91: =IF(OR(D91<=0, B91="", C91=""), 0, TIME(6,0,0)) | F91: =D91-E91 | G91: 0 | H91: =F91-G91 | I91: =I90+H91
A92: 46129 | B92: 0.33333333 | C92: 0.625 | D92: =IF(C92-B92>TIME(6,0,0), (C92-B92)-TIME(1,0,0), C92-B92) | E92: =IF(OR(D92<=0, B92="", C92=""), 0, TIME(6,0,0)) | F92: =D92-E92 | G92: 0 | H92: =F92-G92 | I92: =I91+H92 | K92: ← Levei o Notebook pra casa para dar continuidade no fechamento da Bracofer
A93: 46132 | B93: 0.33333333 | C93: 0.625 | D93: =IF(C93-B93>TIME(6,0,0), (C93-B93)-TIME(1,0,0), C93-B93) | E93: =IF(OR(D93<=0, B93="", C93=""), 0, TIME(6,0,0)) | F93: =D93-E93 | G93: 0 | H93: =F93-G93 | I93: =I92+H93
A94: 46134 | B94: 0.33333333 | C94: 0.625 | D94: =IF(C94-B94>TIME(6,0,0), (C94-B94)-TIME(1,0,0), C94-B94) | E94: =IF(OR(D94<=0, B94="", C94=""), 0, TIME(6,0,0)) | F94: =D94-E94 | G94: 0 | H94: =F94-G94 | I94: =I93+H94
A95: 46135 | B95: 0.33333333 | C95: 0.625 | D95: =IF(C95-B95>TIME(6,0,0), (C95-B95)-TIME(1,0,0), C95-B95) | E95: =IF(OR(D95<=0, B95="", C95=""), 0, TIME(6,0,0)) | F95: =D95-E95 | G95: 0 | H95: =F95-G95 | I95: =I94+H95
A96: 46136 | B96: 0.33333333 | C96: 0.625 | D96: =IF(C96-B96>TIME(6,0,0), (C96-B96)-TIME(1,0,0), C96-B96) | E96: =IF(OR(D96<=0, B96="", C96=""), 0, TIME(6,0,0)) | F96: =D96-E96 | G96: 0 | H96: =F96-G96 | I96: =I95+H96
A97: 46139 | B97: 0.33333333 | C97: 0.625 | D97: =IF(C97-B97>TIME(6,0,0), (C97-B97)-TIME(1,0,0), C97-B97) | E97: =IF(OR(D97<=0, B97="", C97=""), 0, TIME(6,0,0)) | F97: =D97-E97 | G97: 0 | H97: =F97-G97 | I97: =I96+H97
A98: 46140 | B98: 0.33333333 | C98: 0.75 | D98: =IF(C98-B98>TIME(6,0,0), (C98-B98)-TIME(1,0,0), C98-B98) | E98: =IF(OR(D98<=0, B98="", C98=""), 0, TIME(6,0,0)) | F98: =D98-E98 | G98: 0 | H98: =F98-G98 | I98: =I97+H98
A99: 46141 | B99: 0.33333333 | C99: 0.625 | D99: =IF(C99-B99>TIME(6,0,0), (C99-B99)-TIME(1,0,0), C99-B99) | E99: =IF(OR(D99<=0, B99="", C99=""), 0, TIME(6,0,0)) | F99: =D99-E99 | G99: 0 | H99: =F99-G99 | I99: =I98+H99
A100: 46142 | B100: 0.33333333 | C100: 0.5 | D100: =IF(C100-B100>TIME(6,0,0), (C100-B100)-TIME(1,0,0), C100-B100) | E100: =IF(OR(D100<=0, B100="", C100=""), 0, TIME(6,0,0)) | F100: =D100-E100 | G100: 0 | H100: =F100-G100 | I100: =I99+H100
A101: 46146 | B101: 0.33333333 | C101: 0.625 | D101: =IF(C101-B101>TIME(6,0,0), (C101-B101)-TIME(1,0,0), C101-B101) | E101: =IF(OR(D101<=0, B101="", C101=""), 0, TIME(6,0,0)) | F101: =D101-E101 | G101: 0 | H101: =F101-G101 | I101: =I100+H101
A102: 46147 | B102: 0.33472222 | C102: 0.62708333 | D102: =IF(C102-B102>TIME(6,0,0), (C102-B102)-TIME(1,0,0), C102-B102) | E102: =IF(OR(D102<=0, B102="", C102=""), 0, TIME(6,0,0)) | F102: =D102-E102 | G102: 0 | H102: =F102-G102 | I102: =I101+H102
A103: 46148 | B103: 0.33194444 | C103: 0.625 | D103: =IF(C103-B103>TIME(6,0,0), (C103-B103)-TIME(1,0,0), C103-B103) | E103: =IF(OR(D103<=0, B103="", C103=""), 0, TIME(6,0,0)) | F103: =D103-E103 | G103: 0 | H103: =F103-G103 | I103: =I102+H103
A104: 46149 | B104: 0.33055556 | C104: 0.625 | D104: =IF(C104-B104>TIME(6,0,0), (C104-B104)-TIME(1,0,0), C104-B104) | E104: =IF(OR(D104<=0, B104="", C104=""), 0, TIME(6,0,0)) | F104: =D104-E104 | G104: 0 | H104: =F104-G104 | I104: =I103+H104
A105: 46150 | B105: 0.32638889 | C105: =_xlfn.MAXIFS(Atividades!$F:$F, Atividades!$A:$A, A105) | D105: =IF(C105-B105>TIME(6,0,0), (C105-B105)-TIME(1,0,0), C105-B105) | E105: =IF(OR(D105<=0, B105="", C105=""), 0, TIME(6,0,0)) | F105: =D105-E105 | G105: 0 | H105: =F105-G105 | I105: =I104+H105
A106: 46151 | B106: 0.32986111 | C106: 0.62847222 | D106: =IF(C106-B106>TIME(6,0,0),C106-B106-TIME(1,0,0),C106-B106) | E106: =IF(D106>0,TIME(6,0,0),0) | F106: =D106-E106 | G106: 0 | H106: =F106+G106 | I106: =I105+H106
A107: 46152 | B107: 0.32708333 | C107: 0.62916667 | D107: =IF(C107-B107>TIME(6,0,0),C107-B107-TIME(1,0,0),C107-B107) | E107: =IF(D107>0,TIME(6,0,0),0) | F107: =D107-E107 | G107: 0 | H107: =F107+G107 | I107: =I106+H107
A108: 46153 | B108: =_xlfn.MINIFS(Atividades!$E:$E,Atividades!$A:$A, A108) | C108: =_xlfn.MAXIFS(Atividades!$F:$F, Atividades!$A:$A, A108) | D108: =IF(C108-B108>TIME(6,0,0), (C108-B108)-TIME(1,0,0), C108-B108) | E108: =IF(OR(D108<=0, B108="", C108=""), 0, TIME(6,0,0)) | F108: =D108-E108 | G108: 0 | H108: =F108-G108 | I108: =I107+H108
A109: 46154 | B109: =_xlfn.MINIFS(Atividades!$E:$E,Atividades!$A:$A, A109) | C109: =_xlfn.MAXIFS(Atividades!$F:$F, Atividades!$A:$A, A109) | D109: =IF(C109-B109>TIME(6,0,0), (C109-B109)-TIME(1,0,0), C109-B109) | E109: =IF(OR(D109<=0, B109="", C109=""), 0, TIME(6,0,0)) | F109: =D109-E109 | G109: 0 | H109: =F109-G109 | I109: =I108+H109
A110: 46155 | B110: =_xlfn.MINIFS(Atividades!$E:$E,Atividades!$A:$A, A110) | C110: 0.625 | D110: =IF(C110-B110>TIME(6,0,0), (C110-B110)-TIME(1,0,0), C110-B110) | E110: =IF(OR(D110<=0, B110="", C110=""), 0, TIME(6,0,0)) | F110: =D110-E110 | G110: 0 | H110: =F110-G110 | I110: =I109+H110
A111: 46156 | B111: =_xlfn.MINIFS(Atividades!$E:$E,Atividades!$A:$A, A111) | C111: =_xlfn.MAXIFS(Atividades!$F:$F, Atividades!$A:$A, A111) | D111: =IF(C111-B111>TIME(6,0,0), (C111-B111)-TIME(1,0,0), C111-B111) | E111: =IF(OR(D111<=0, B111="", C111=""), 0, TIME(6,0,0)) | F111: =D111-E111 | G111: 0 | H111: =F111-G111 | I111: =I110+H111
A112: 46157 | B112: =_xlfn.MINIFS(Atividades!$E:$E,Atividades!$A:$A, A112) | C112: =_xlfn.MAXIFS(Atividades!$F:$F, Atividades!$A:$A, A112) | D112: =IF(C112-B112>TIME(6,0,0), (C112-B112)-TIME(1,0,0), C112-B112) | E112: =IF(OR(D112<=0, B112="", C112=""), 0, TIME(6,0,0)) | F112: =D112-E112 | G112: 0 | H112: =F112-G112 | I112: =I111+H112
A113: 46158 | B113: 0.32777778 | C113: 0.62986111 | D113: =IF(C113-B113>TIME(6,0,0),C113-B113-TIME(1,0,0),C113-B113) | E113: =IF(D113>0,TIME(6,0,0),0) | F113: =D113-E113 | G113: 0 | H113: =F113+G113 | I113: =I112+H113
A114: 46159 | B114: 0.32916667 | C114: 0.62847222 | D114: =IF(C114-B114>TIME(6,0,0),C114-B114-TIME(1,0,0),C114-B114) | E114: =IF(D114>0,TIME(6,0,0),0) | F114: =D114-E114 | G114: 0 | H114: =F114+G114 | I114: =I113+H114
...
